Workbook

Sheet Cover
B3: StartPad
B4: Operational Financial Model
B5: Thirty-six months · October 2026 to September 2029 · Egypt and Saudi Arabia · USD
B8: WHAT THIS IS
B9: A monthly operating model for three years, built directly on the volumes and the establishment in the StartPad business plan and on the channel structure in the go-to-market strategy.
B10: Every figure in the workbook is a formula. The only typed numbers are the inputs on the Assumptions, HR Model and Actuals sheets, which are shown in blue on a yellow fill.
B11: Change an input and the acquisition funnel, the revenue streams, the expense base, the three statements and every analysis sheet move with it.
B13: CONVENTIONS
B14: Blue figure on a yellow fill | C14: A typed input. Change these.
B15: Black figure | C15: A formula on this sheet.
B16: Green figure | C16: A link to another sheet.
B17: Red figure | C17: A check that must read nil.
B18: Lime band | C18: A headline result.
B20: CONTENTS
B21: 01 Cover | C21: This page — what the model is and how to read it
B22: 02 Dashboard | C22: The whole model on one page, with charts
B23: 03 Assumptions | C23: INPUT · every typed number: volumes, prices, acquisition, cost, revenue share, working capital
B24: 04 HR Model | C24: INPUT · eighteen roles, salaries and start months, monthly and annual
B25: 05 Actuals | C25: INPUT · the opening position and a grid to record each month as it closes
B26: 06 Capex | C26: INPUT · assets driven by new hires, plus shared and intangible assets
B27: 07 Acquisition | C27: PROCESS · offline and online channels, both funnels, 36 months
B28: 08 Revenue | C28: PROCESS · thirteen revenue lines across eight engines, 36 months
B29: 09 Expenses | C29: PROCESS · direct cost, revenue share to three parties, operating cost, 36 months
B30: 10 Depreciation | C30: PROCESS · straight-line depreciation and amortisation by asset class
B31: 11 Income Statement | C31: OUTPUT · three years to 30 September
B32: 12 Balance Sheet | C32: OUTPUT · three years, with the balance check
... B39: 19 Exit Strategy | C39: ANALYSIS · angel and venture returns, and the routes out
B41: Built from business_plan/model.py. Rebuild with: python scripts/build_financial_model_xlsx.py

Sheet Dashboard
A1: Dashboard
A2: The whole model on one page. Every figure is a link; nothing here is typed.
A5: HEADLINES
C6: Year 1 | D6: Year 2 | E6: Year 3
A7: Total revenue | C7: =Income_Statement!$C$9 -> 614990.61 | D7: =Income_Statement!$D$9 -> 2786041.1 | E7: =Income_Statement!$E$9 -> 6112588
A8: Gross profit | C8: =Income_Statement!$C$11 -> 388814.79 | D8: =Income_Statement!$D$11 -> 1856297 | E8: =Income_Statement!$E$11 -> 4043811.6
A9: EBITDA | C9: =Income_Statement!$C$13 -> -163865.33 | D9: =Income_Statement!$D$13 -> 641579.38 | E9: =Income_Statement!$E$13 -> 1869599.3
A10: Net profit | C10: =Income_Statement!$C$22 -> -215248.86 | D10: =Income_Statement!$D$22 -> 499107.71 | E10: =Income_Statement!$E$22 -> 1400468
A11: Cash at year end | C11: =KPIs!$C$39 -> 120154.62 | D11: =KPIs!$D$39 -> 511419.66 | E11: =KPIs!$E$39 -> 1903484.2
A12: Lowest cash in the year | C12: =KPIs!$C$40 -> 91108.322 | D12: =KPIs!$D$40 -> 113684.97 | E12: =KPIs!$E$40 -> 573923.8
A13: Employees at year end | C13: =KPIs!$C$13 -> 6 | D13: =KPIs!$D$13 -> 9 | E13: =KPIs!$E$13 -> 12
A14: Learners reached | C14: =KPIs!$C$11 -> 27014.11 | D14: =KPIs!$D$11 -> 83235.956 | E14: =KPIs!$E$11 -> 179961.34
A16: BALANCE SHEET AND CHECK
C17: At inception | D17: Year 1 | E17: Year 2 | F17: Year 3
A18: Total assets | C18: =Balance_Sheet!$C$11 -> 50000 | D18: =Balance_Sheet!$D$11 -> 585936.93 | E18: =Balance_Sheet!$E$11 -> 1394400 | F18: =Balance_Sheet!$F$11 -> 3551860.9
A19: CHECK — must be nil | C19: =Balance_Sheet!$C$24 -> 0 | D19: =Balance_Sheet!$D$24 -> 0 | E19: =Balance_Sheet!$E$24 -> 0 | F19: =Balance_Sheet!$F$24 -> 0
A41: HOW TO USE THIS WORKBOOK
A42: · Blue figures on a yellow fill are inputs. Change those and the whole model moves. Everything else is a formula.
A43: · The Assumptions sheet holds every typed number in the model. Nothing is typed on any process or output sheet.
A44: · Volume comes from the twelve-quarter plan in the business plan, split into months by the phasing weights on the Assumptions sheet.
A45: · The check line on the balance sheet must read nil in every column. If it does not, something upstream has been broken.

Sheet Assumptions
A1: Assumptions
A2: Every typed input in the model. Blue on yellow is an input you may change; black is a formula. Nothing elsewhere in the workbook is typed.
A5: 1 · TIMELINE AND BASIS
A6: Month 1 is October 2026, the Land quarter in the business plan. Year 1 runs Oct 2026 - Sep 2029 in three twelve-month blocks.
A7: Reporting currency | C7: USD
A8: Corporate tax rate (Egypt) | B8: Egyptian corporate income tax | C8: 0.225
A9: Tax paid in month of the following year | B9: Month 4 of the next financial year | C9: 4
A11: 2 · VOLUME DRIVERS — QUARTERLY, FROM THE BUSINESS PLAN
A12: These twelve quarters are the delivery plan. Monthly figures everywhere else are this quarter's volume split by the phasing weights below, so an annual total always ties back to the plan.
A13: Driver | B13: Unit | C13: Q4 2026 | D13: Q1 2027 | E13: Q2 2027 | F13: Q3 2027 | G13: Q4 2027 | H13: Q1 2028 | I13: Q2 2028 | J13: Q3 2028 | K13: Q4 2028 | L13: Q1 2029 | M13: Q2 2029 | N13: Q3 2029
A14: University cohorts — Egypt | B14: cohorts | C14: 0 | D14: 4 | E14: 7 | F14: 9 | G14: 11 | H14: 13 | I14: 15 | J14: 17 | K14: 20 | L14: 23 | M14: 25 | N14: 28
A15: University cohorts — Saudi Arabia | B15: cohorts | C15: 1 | D15: 2 | E15: 3 | F15: 4 | G15: 5 | H15: 5 | I15: 6 | J15: 6 | K15: 8 | L15: 9 | M15: 10 | N15: 11
A16: University pilot cohorts (unpaid) | B16: cohorts | C16: 4 | D16: 2 | E16: 1 | F16: 1 | G16: 1 | H16: 1 | I16: 1 | J16: 1 | K16: 1 | L16: 1 | M16: 1 | N16: 1
A17: Faculty licences sold | B17: licences | C17: 0 | D17: 0 | E17: 0 | F17: 1 | G17: 1 | H17: 1 | I17: 2 | J17: 2 | K17: 3 | L17: 3 | M17: 4 | N17: 4
A18: School cohorts | B18: cohorts | C18: 0 | D18: 0 | E18: 3 | F18: 6 | G18: 9 | H18: 12 | I18: 14 | J18: 16 | K18: 20 | L18: 24 | M18: 26 | N18: 30
A19: School licences sold | B19: licences | C19: 0 | D19: 0 | E19: 0 | F19: 0 | G19: 1 | H19: 1 | I19: 2 | J19: 2 | K19: 3 | L19: 3 | M19: 4 | N19: 4
A20: Technical and vocational cohorts | B20: cohorts | C20: 0 | D20: 0 | E20: 0 | F20: 2 | G20: 4 | H20: 5 | I20: 7 | J20: 8 | K20: 10 | L20: 12 | M20: 13 | N20: 15
A21: National initiative seats | B21: seats | C21: 0 | D21: 0 | E21: 0 | F21: 2000 | G21: 3000 | H21: 4000 | I21: 6000 | J21: 8000 | K21: 12000 | L21: 15000 | M21: 18000 | N21: 20000
A22: Train-the-trainer cohorts | B22: cohorts | C22: 0 | D22: 0 | E22: 0 | F22: 1 | G22: 1 | H22: 2 | I22: 2 | J22: 3 | K22: 4 | L22: 5 | M22: 5 | N22: 6
A23: NGO and donor programmes | B23: programmes | C23: 0 | D23: 0 | E23: 1 | F23: 1 | G23: 2 | H23: 2 | I23: 3 | J23: 3 | K23: 4 | L23: 4 | M23: 5 | N23: 5
A24: Sponsored competitions | B24: competitions | C24: 0 | D24: 1 | E24: 1 | F24: 2 | G24: 2 | H24: 2 | I24: 3 | J24: 3 | K24: 4 | L24: 4 | M24: 5 | N24: 5
A25: Corporate and CSR programmes | B25: programmes | C25: 0 | D25: 0 | E25: 0 | F25: 1 | G25: 1 | H25: 1 | I25: 1 | J25: 1 | K25: 2 | L25: 2 | M25: 2 | N25: 3
... A29: Certified delivery partner organisations | B29: cumulative at quarter end | C29: 0 | D29: 1 | E29: 2 | F29: 3 | G29: 5 | H29: 6 | I29: 8 | J29: 9 | K29: 10 | L29: 11 | M29: 12 | N29: 13
A31: Monthly phasing within a quarter | B31: month 1 / month 2 / month 3 of each quarter | C31: 0.3 | D31: 0.33 | E31: 0.37 | F31: =SUM(C31:E31) -> 1 | G31: must be 100%
A33: 3 · PRICING — BY YEAR
A34: University cohort — all-in programme fee | B34: 6 bootcamp days, seats, judging, cohort report | C34: 7500 | D34: 7900 | E34: 8300
A35: Faculty licence — annual | B35: faculty-wide, per year | C35: 25000 | D35: 25000 | E35: 25000
A36: School cohort | B36: 4 days, larger groups, employability frame | C36: 4500 | D36: 4700 | E36: 4900
A37: School licence — annual | C37: 12000 | D37: 12000 | E37: 12000
A38: Technical and vocational cohort | B38: 5 days | C38: 5000 | D38: 5200 | E38: 5400
A39: National initiative seat | B39: per participant, bulk provisioned | C39: 22 | D39: 20 | E39: 18
A40: Train-the-trainer cohort | C40: 12000 | D40: 12500 | E40: 13000
A41: NGO and donor programme | B41: multi-site, logframe reporting | C41: 35000 | D41: 38000 | E41: 40000
A42: Sponsored competition | B42: paid by the sponsor, not the organiser | C42: 28000 | D42: 32000 | E42: 36000
A43: Corporate and CSR programme | C43: 45000 | D43: 55000 | E43: 60000
A44: Programme and incubator seat | C44: 40 | D44: 42 | E44: 44
A45: Subscription — Pro, annual | C45: 59
A46: Subscription — Team, annual | C46: 179
A47: Share of new subscribers taking Team | C47: 0.25
A48: Subscription monthly churn | B48: of the active base, monthly | C48: 0.045
A49: Cohort size — university | C49: 25
A50: Cohort size — school and technical | C50: 30
A52: 4 · ACQUISITION — OFFLINE CHANNELS (they create sign-ups)
A53: Five offline channels, from the go-to-market strategy. Activities per month is the lever; cost, sign-ups and institutional leads follow from it.
A54: Offline channel | C54: Activities / month — Y1 | D54: Y2 | E54: Y3 | F54: Cost per activity | G54: Sign-ups per activity | H54: Institutional leads per activity
A55: Campus workshops | B55: Mission 01 completed live in an hour | C55: 2 | D55: 6 | E55: 11 | F55: 420 | G55: 45 | H55: 0.9
A56: Ambassador campus activity | B56: run by the stipended ambassador network | C56: 3 | D56: 8 | E56: 14 | F56: 180 | G56: 38 | H56: 0.6
A57: Competitions and qualifying rounds | B57: a sponsor pays; entry is a free account | C57: 0.5 | D57: 1.2 | E57: 2 | F57: 2600 | G57: 320 | H57: 2.4
A58: Events, fairs and conferences | B58: judged on meetings booked, not stand traffic | C58: 1 | D58: 2 | E58: 3.5 | F58: 1900 | G58: 150 | H58: 3.2
A59: Partner sessions inside NGO and programme cohorts | B59: talks inside somebody else's cohort | C59: 1 | D59: 3 | E59: 5 | F59: 350 | G59: 60 | H59: 1.4
A60: Direct outreach by the partnership heads | B60: their own prospecting; the cost sits in payroll, not marketing | C60: 4 | D60: 7 | E60: 9 | F60: 0 | G60: 0 | H60: 6
A62: 5 · ACQUISITION — ONLINE CHANNELS (they create reach)
A63: Monthly spend is the lever. Reach, clicks and sign-ups follow. There is no cold paid-acquisition line beyond the budget shown: digital retargets people the engines already reached.
A64: Online channel | C64: Spend / month — Y1 | D64: Y2 | E64: Y3 | F64: Cost per 1,000 reached | G64: Reach to click | H64: Click to free account
A65: Short video — TikTok, Instagram, Facebook | B65: organic-first, boosted selectively | C65: 900 | D65: 2200 | E65: 4200 | F65: 3.5 | G65: 0.012 | H65: 0.09
A66: Paid social — targeted by age, city, university | B66: retargeting and event fill only | C66: 850 | D66: 2000 | E66: 4000 | F66: 6.5 | G66: 0.009 | H66: 0.11
A67: Influencers and student creators | B67: Arabic student and founder voices | C67: 700 | D67: 1700 | E67: 3200 | F67: 5.5 | G67: 0.011 | H67: 0.1
A68: Mission Zero — the founder podcast | B68: its real return is institutional, not sign-ups | C68: 2100 | D68: 4000 | E68: 8000 | F68: 14 | G68: 0.012 | H68: 0.1
A69: Webinars — live Mission 01 sessions | B69: highest intent, smallest reach | C69: 260 | D69: 600 | E69: 1150 | F69: 25 | G69: 0.05 | H69: 0.25
A70: SEO and organic search | B70: content and the annual readiness report | C70: 500 | D70: 1150 | E70: 2100 | F70: 3 | G70: 0.018 | H70: 0.08
A72: 6 · FUNNEL CONVERSION
A73: Two funnels. The institutional one ends in a signed contract; the learner one ends at Mission 01 and then a paid plan.
A74: Institutional lead to first meeting | C74: 0.4 | D74: 0.44 | E74: 0.48
A75: Meeting to proposal, pilot or bid | C75: 0.5 | D75: 0.54 | E75: 0.58
A76: Proposal to signed contract | C76: 0.38 | D76: 0.44 | E76: 0.5
A77: Sales cycle — months from lead to signature | B77: the lag applied between leads and wins | C77: 4
A78: Free account to Mission 01 activation | B78: activation is finishing Mission 01 | C78: 0.42 | D78: 0.46 | E78: 0.5
A79: Activation to engaged (Discovery complete) | C79: 0.55 | D79: 0.58 | E79: 0.61
A80: Engaged to paid — reached through an institution | C80: 0.075 | D80: 0.085 | E80: 0.095
A81: Engaged to paid — reached online | C81: 0.03 | D81: 0.034 | E81: 0.038
A82: Inbound institutional enquiries per 1,000 online sign-ups | B82: content and the podcast, working as pipeline rather than brand | C82: 14
A83: Share of online spend serving institutional demand | B83: splits marketing cost between the two funnels for the CAC calculations | C83: 0.35
A84: Deliveries per signed contract | B84: land and expand: one agreement covers more cohorts each year | C84: 1.8 | D84: 2.2 | E84: 2.6
A85: Entrants per sponsored competition | C85: 700
A86: Participants per NGO or donor programme | C86: 140
A87: Participants per corporate programme | C87: 60
A89: 7 · DIRECT COST OF DELIVERY
A90: Facilitator day rate | C90: 120
A91: Facilitators per cohort | C91: 2
A92: Delivery days — university cohort | C92: 6
A93: Delivery days — school cohort | C93: 4
A94: Delivery days — technical cohort | C94: 5
A95: Materials and showcase — university cohort | C95: 750
A96: Materials and showcase — school cohort | C96: 550
A97: Materials and showcase — technical cohort | C97: 600
A98: Delivery cost — train-the-trainer cohort | C98: 3200
A99: Delivery cost — NGO and donor programme | C99: 9000
A100: Delivery cost — sponsored competition | C100: 11000
A101: Delivery cost — corporate programme | C101: 13000
A102: Support cost per national initiative seat | B102: provisioning, bilingual support, partner reporting | C102: 5.2
A103: Support cost per programme seat | C103: 4.6
A104: Subscription hosting and inference, per paid user per month | C104: 0.72
A106: 8 · REVENUE SHARING WITH THIRD PARTIES
A107: Three counterparties take a share. Each is margin deliberately surrendered to buy delivery capacity, distribution or access that would otherwise have to be hired for.
A108: Party 1 · share of cohorts delivered by certified partners | B108: certified delivery partner organisations | C108: 0.1 | D108: 0.35 | E108: 0.55
A109: Party 1 · partner's share of the cohort fee | B109: they deliver, StartPad audits | C109: 0.4
A110: Party 2 · share of competition revenue | B110: youth and channel organisations — Enactus, INJAZ, chapters | C110: 0.15 | D110: 0.15 | E110: 0.14
A111: Party 2 · share of programme and incubator seat revenue | C111: 0.1 | D111: 0.1 | E111: 0.1
A112: Party 3 · share of national initiative seat revenue | B112: government aggregators and local distributors | C112: 0.08 | D112: 0.08 | E112: 0.07
A113: Party 3 · payment processing on subscriptions | C113: 0.035
...

Sheet HR_Model
A1: HR Model
A2: Eighteen roles, each with a start month and a headcount per year. Payroll is computed monthly and summed annually; new hires drive the asset purchases on the Capex sheet.
A5: ESTABLISHMENT — INPUTS
A6: Role | B6: Function | C6: Start month | D6: Base monthly gross | E6: Headcount Y1 | F6: Headcount Y2 | G6: Headcount Y3
A7: Chief Executive Officer | B7: Leadership | C7: 1 | D7: 3000 | E7: 1 | F7: 1 | G7: 1
A8: Chief Technology Officer | B8: Leadership | C8: 1 | D8: 3000 | E8: 1 | F8: 1 | G8: 1
A9: Chief Operating Officer | B9: Leadership | C9: 25 | D9: 3200 | E9: 0 | F9: 0 | G9: 0
A10: Senior full-stack engineer | B10: Product and Engineering | C10: 1 | D10: 2400 | E10: 1 | F10: 2 | G10: 2
A11: AI and data engineer | B11: Product and Engineering | C11: 25 | D11: 2800 | E11: 0 | F11: 0 | G11: 0
A12: Product designer | B12: Product and Engineering | C12: 25 | D12: 1800 | E12: 0 | F12: 0 | G12: 0
A13: Head of Curriculum and Certification | B13: Curriculum and Delivery | C13: 1 | D13: 2400 | E13: 1 | F13: 1 | G13: 1
A14: Partner network manager | B14: Curriculum and Delivery | C14: 13 | D14: 2000 | E14: 0 | F14: 1 | G14: 1
A15: Programme delivery coordinator | B15: Curriculum and Delivery | C15: 25 | D15: 1500 | E15: 0 | F15: 0 | G15: 1
A16: Bilingual curriculum producer | B16: Curriculum and Delivery | C16: 25 | D16: 1300 | E16: 0 | F16: 0 | G16: 0
A17: Head of Partnerships — Egypt | B17: Institutional Partnerships | C17: 1 | D17: 2200 | E17: 1 | F17: 1 | G17: 1
A18: Country Manager — KSA (Riyadh) | B18: Institutional Partnerships | C18: 13 | D18: 5000 | E18: 0 | F18: 1 | G18: 1
... A24: Student success (bilingual) | B24: Growth and Content | C24: 25 | D24: 900 | E24: 0 | F24: 0 | G24: 0
A25: Total establishment | B25: the cap the business plan commits to | E25: =SUM(E7:E24) -> 6 | F25: =SUM(F7:F24) -> 9 | G25: =SUM(G7:G24) -> 12
A27: Employer burden on gross salary | B27: social insurance, end-of-service, medical | C27: 0.155
A28: Annual salary increment | B28: applied from year two | C28: 0.08
A30: MONTHLY PAYROLL — FULLY LOADED
A31: Line item | B31: Driver / source | C31: Oct 26 | D31: Nov 26 | E31: Dec 26 | F31: Jan 26 | G31: Feb 26 | H31: Mar 26 | I31: Apr 26 | J31: May 26 | K31: Jun 26 | L31: Jul 27 | M31: Aug 27 | N31: Sep 27 | O31: Oct 27 | P31: Nov 27 | Q31: Dec 27 | R31: Jan 27 | S31: Feb 27 | T31: Mar 27 | U31: Apr 27 | V31: May 27 | W31: Jun 27 | X31: Jul 28 | Y31: Aug 28 | Z31: Sep 28 | AA31: Oct 28 | AB31: Nov 28 | AC31: Dec 28 | AD31: Jan 28 | AE31: Feb 28 | AF31: Mar 28 | AG31: Apr 28 | AH31: May 28 | AI31: Jun 28 | AJ31: Jul 29 | AK31: Aug 29 | AL31: Sep 29 | AN31: YEAR 1 | AO31: YEAR 2 | AP31: YEAR 3
A32: Chief Executive Officer | B32: Leadership | C32: =IF(1<$C$7,0,$E$7*$D$7*(1+$C$27)*(1+$C$28)^0) -> 3465 | D32: =IF(2<$C$7,0,$E$7*$D$7*(1+$C$27)*(1+$C$28)^0) -> 3465 | E32: =IF(3<$C$7,0,$E$7*$D$7*(1+$C$27)*(1+$C$28)^0) -> 3465 | F32: =IF(4<$C$7,0,$E$7*$D$7*(1+$C$27)*(1+$C$28)^0) -> 3465 | G32: =IF(5<$C$7,0,$E$7*$D$7*(1+$C$27)*(1+$C$28)^0) -> 3465 | H32: =IF(6<$C$7,0,$E$7*$D$7*(1+$C$27)*(1+$C$28)^0) -> 3465 | I32: =IF(7<$C$7,0,$E$7*$D$7*(1+$C$27)*(1+$C$28)^0) -> 3465 | J32: =IF(8<$C$7,0,$E$7*$D$7*(1+$C$27)*(1+$C$28)^0) -> 3465 | K32: =IF(9<$C$7,0,$E$7*$D$7*(1+$C$27)*(1+$C$28)^0) -> 3465 | L32: =IF(10<$C$7,0,$E$7*$D$7*(1+$C$27)*(1+$C$28)^0) -> 3465 | M32: =IF(11<$C$7,0,$E$7*$D$7*(1+$C$27)*(1+$C$28)^0) -> 3465 | N32: =IF(12<$C$7,0,$E$7*$D$7*(1+$C$27)*(1+$C$28)^0) -> 3465 | O32: =IF(13<$C$7,0,$F$7*$D$7*(1+$C$27)*(1+$C$28)^1) -> 3742.2 | P32: =IF(14<$C$7,0,$F$7*$D$7*(1+$C$27)*(1+$C$28)^1) -> 3742.2 | Q32: =IF(15<$C$7,0,$F$7*$D$7*(1+$C$27)*(1+$C$28)^1) -> 3742.2 | R32: =IF(16<$C$7,0,$F$7*$D$7*(1+$C$27)*(1+$C$28)^1) -> 3742.2 | S32: =IF(17<$C$7,0,$F$7*$D$7*(1+$C$27)*(1+$C$28)^1) -> 3742.2 | T32: =IF(18<$C$7,0,$F$7*$D$7*(1+$C$27)*(1+$C$28)^1) -> 3742.2 | U32: =IF(19<$C$7,0,$F$7*$D$7*(1+$C$27)*(1+$C$28)^1) -> 3742.2 | V32: =IF(20<$C$7,0,$F$7*$D$7*(1+$C$27)*(1+$C$28)^1) -> 3742.2 | W32: =IF(21<$C$7,0,$F$7*$D$7*(1+$C$27)*(1+$C$28)^1) -> 3742.2 | X32: =IF(22<$C$7,0,$F$7*$D$7*(1+$C$27)*(1+$C$28)^1) -> 3742.2 | Y32: =IF(23<$C$7,0,$F$7*$D$7*(1+$C$27)*(1+$C$28)^1) -> 3742.2 | Z32: =IF(24<$C$7,0,$F$7*$D$7*(1+$C$27)*(1+$C$28)^1) -> 3742.2 | AA32: =IF(25<$C$7,0,$G$7*$D$7*(1+$C$27)*(1+$C$28)^2) -> 4041.576 | AB32: =IF(26<$C$7,0,$G$7*$D$7*(1+$C$27)*(1+$C$28)^2) -> 4041.576 | AC32: =IF(27<$C$7,0,$G$7*$D$7*(1+$C$27)*(1+$C$28)^2) -> 4041.576 | AD32: =IF(28<$C$7,0,$G$7*$D$7*(1+$C$27)*(1+$C$28)^2) -> 4041.576 | AE32: =IF(29<$C$7,0,$G$7*$D$7*(1+$C$27)*(1+$C$28)^2) -> 4041.576 | AF32: =IF(30<$C$7,0,$G$7*$D$7*(1+$C$27)*(1+$C$28)^2) -> 4041.576 | AG32: =IF(31<$C$7,0,$G$7*$D$7*(1+$C$27)*(1+$C$28)^2) -> 4041.576 | AH32: =IF(32<$C$7,0,$G$7*$D$7*(1+$C$27)*(1+$C$28)^2) -> 4041.576 | AI32: =IF(33<$C$7,0,$G$7*$D$7*(1+$C$27)*(1+$C$28)^2) -> 4041.576 | AJ32: =IF(34<$C$7,0,$G$7*$D$7*(1+$C$27)*(1+$C$28)^2) -> 4041.576 | AK32: =IF(35<$C$7,0,$G$7*$D$7*(1+$C$27)*(1+$C$28)^2) -> 4041.576 | AL32: =IF(36<$C$7,0,$G$7*$D$7*(1+$C$27)*(1+$C$28)^2) -> 4041.576 | AN32: =SUM(C32:N32) -> 41580 | AO32: =SUM(O32:Z32) -> 44906.4 | AP32: =SUM(AA32:AL32) -> 48498.912
A33: Chief Technology Officer | B33: Leadership | C33: =IF(1<$C$8,0,$E$8*$D$8*(1+$C$27)*(1+$C$28)^0) -> 3465 | D33: =IF(2<$C$8,0,$E$8*$D$8*(1+$C$27)*(1+$C$28)^0) -> 3465 | E33: =IF(3<$C$8,0,$E$8*$D$8*(1+$C$27)*(1+$C$28)^0) -> 3465 | F33: =IF(4<$C$8,0,$E$8*$D$8*(1+$C$27)*(1+$C$28)^0) -> 3465 | G33: =IF(5<$C$8,0,$E$8*$D$8*(1+$C$27)*(1+$C$28)^0) -> 3465 | H33: =IF(6<$C$8,0,$E$8*$D$8*(1+$C$27)*(1+$C$28)^0) -> 3465 | I33: =IF(7<$C$8,0,$E$8*$D$8*(1+$C$27)*(1+$C$28)^0) -> 3465 | J33: =IF(8<$C$8,0,$E$8*$D$8*(1+$C$27)*(1+$C$28)^0) -> 3465 | K33: =IF(9<$C$8,0,$E$8*$D$8*(1+$C$27)*(1+$C$28)^0) -> 3465 | L33: =IF(10<$C$8,0,$E$8*$D$8*(1+$C$27)*(1+$C$28)^0) -> 3465 | M33: =IF(11<$C$8,0,$E$8*$D$8*(1+$C$27)*(1+$C$28)^0) -> 3465 | N33: =IF(12<$C$8,0,$E$8*$D$8*(1+$C$27)*(1+$C$28)^0) -> 3465 | O33: =IF(13<$C$8,0,$F$8*$D$8*(1+$C$27)*(1+$C$28)^1) -> 3742.2 | P33: =IF(14<$C$8,0,$F$8*$D$8*(1+$C$27)*(1+$C$28)^1) -> 3742.2 | Q33: =IF(15<$C$8,0,$F$8*$D$8*(1+$C$27)*(1+$C$28)^1) -> 3742.2 | R33: =IF(16<$C$8,0,$F$8*$D$8*(1+$C$27)*(1+$C$28)^1) -> 3742.2 | S33: =IF(17<$C$8,0,$F$8*$D$8*(1+$C$27)*(1+$C$28)^1) -> 3742.2 | T33: =IF(18<$C$8,0,$F$8*$D$8*(1+$C$27)*(1+$C$28)^1) -> 3742.2 | U33: =IF(19<$C$8,0,$F$8*$D$8*(1+$C$27)*(1+$C$28)^1) -> 3742.2 | V33: =IF(20<$C$8,0,$F$8*$D$8*(1+$C$27)*(1+$C$28)^1) -> 3742.2 | W33: =IF(21<$C$8,0,$F$8*$D$8*(1+$C$27)*(1+$C$28)^1) -> 3742.2 | X33: =IF(22<$C$8,0,$F$8*$D$8*(1+$C$27)*(1+$C$28)^1) -> 3742.2 | Y33: =IF(23<$C$8,0,$F$8*$D$8*(1+$C$27)*(1+$C$28)^1) -> 3742.2 | Z33: =IF(24<$C$8,0,$F$8*$D$8*(1+$C$27)*(1+$C$28)^1) -> 3742.2 | AA33: =IF(25<$C$8,0,$G$8*$D$8*(1+$C$27)*(1+$C$28)^2) -> 4041.576 | AB33: =IF(26<$C$8,0,$G$8*$D$8*(1+$C$27)*(1+$C$28)^2) -> 4041.576 | AC33: =IF(27<$C$8,0,$G$8*$D$8*(1+$C$27)*(1+$C$28)^2) -> 4041.576 | AD33: =IF(28<$C$8,0,$G$8*$D$8*(1+$C$27)*(1+$C$28)^2) -> 4041.576 | AE33: =IF(29<$C$8,0,$G$8*$D$8*(1+$C$27)*(1+$C$28)^2) -> 4041.576 | AF33: =IF(30<$C$8,0,$G$8*$D$8*(1+$C$27)*(1+$C$28)^2) -> 4041.576 | AG33: =IF(31<$C$8,0,$G$8*$D$8*(1+$C$27)*(1+$C$28)^2) -> 4041.576 | AH33: =IF(32<$C$8,0,$G$8*$D$8*(1+$C$27)*(1+$C$28)^2) -> 4041.576 | AI33: =IF(33<$C$8,0,$G$8*$D$8*(1+$C$27)*(1+$C$28)^2) -> 4041.576 | AJ33: =IF(34<$C$8,0,$G$8*$D$8*(1+$C$27)*(1+$C$28)^2) -> 4041.576 | AK33: =IF(35<$C$8,0,$G$8*$D$8*(1+$C$27)*(1+$C$28)^2) -> 4041.576 | AL33: =IF(36<$C$8,0,$G$8*$D$8*(1+$C$27)*(1+$C$28)^2) -> 4041.576 | AN33: =SUM(C33:N33) -> 41580 | AO33: =SUM(O33:Z33) -> 44906.4 | AP33: =SUM(AA33:AL33) -> 48498.912
A34: Chief Operating Officer | B34: Leadership | C34: =IF(1<$C$9,0,$E$9*$D$9*(1+$C$27)*(1+$C$28)^0) -> 0 | D34: =IF(2<$C$9,0,$E$9*$D$9*(1+$C$27)*(1+$C$28)^0) -> 0 | E34: =IF(3<$C$9,0,$E$9*$D$9*(1+$C$27)*(1+$C$28)^0) -> 0 | F34: =IF(4<$C$9,0,$E$9*$D$9*(1+$C$27)*(1+$C$28)^0) -> 0 | G34: =IF(5<$C$9,0,$E$9*$D$9*(1+$C$27)*(1+$C$28)^0) -> 0 | H34: =IF(6<$C$9,0,$E$9*$D$9*(1+$C$27)*(1+$C$28)^0) -> 0 | I34: =IF(7<$C$9,0,$E$9*$D$9*(1+$C$27)*(1+$C$28)^0) -> 0 | J34: =IF(8<$C$9,0,$E$9*$D$9*(1+$C$27)*(1+$C$28)^0) -> 0 | K34: =IF(9<$C$9,0,$E$9*$D$9*(1+$C$27)*(1+$C$28)^0) -> 0 | L34: =IF(10<$C$9,0,$E$9*$D$9*(1+$C$27)*(1+$C$28)^0) -> 0 | M34: =IF(11<$C$9,0,$E$9*$D$9*(1+$C$27)*(1+$C$28)^0) -> 0 | N34: =IF(12<$C$9,0,$E$9*$D$9*(1+$C$27)*(1+$C$28)^0) -> 0 | O34: =IF(13<$C$9,0,$F$9*$D$9*(1+$C$27)*(1+$C$28)^1) -> 0 | P34: =IF(14<$C$9,0,$F$9*$D$9*(1+$C$27)*(1+$C$28)^1) -> 0 | Q34: =IF(15<$C$9,0,$F$9*$D$9*(1+$C$27)*(1+$C$28)^1) -> 0 | R34: =IF(16<$C$9,0,$F$9*$D$9*(1+$C$27)*(1+$C$28)^1) -> 0 | S34: =IF(17<$C$9,0,$F$9*$D$9*(1+$C$27)*(1+$C$28)^1) -> 0 | T34: =IF(18<$C$9,0,$F$9*$D$9*(1+$C$27)*(1+$C$28)^1) -> 0 | U34: =IF(19<$C$9,0,$F$9*$D$9*(1+$C$27)*(1+$C$28)^1) -> 0 | V34: =IF(20<$C$9,0,$F$9*$D$9*(1+$C$27)*(1+$C$28)^1) -> 0 | W34: =IF(21<$C$9,0,$F$9*$D$9*(1+$C$27)*(1+$C$28)^1) -> 0 | X34: =IF(22<$C$9,0,$F$9*$D$9*(1+$C$27)*(1+$C$28)^1) -> 0 | Y34: =IF(23<$C$9,0,$F$9*$D$9*(1+$C$27)*(1+$C$28)^1) -> 0 | Z34: =IF(24<$C$9,0,$F$9*$D$9*(1+$C$27)*(1+$C$28)^1) -> 0 | AA34: =IF(25<$C$9,0,$G$9*$D$9*(1+$C$27)*(1+$C$28)^2) -> 0 | AB34: =IF(26<$C$9,0,$G$9*$D$9*(1+$C$27)*(1+$C$28)^2) -> 0 | AC34: =IF(27<$C$9,0,$G$9*$D$9*(1+$C$27)*(1+$C$28)^2) -> 0 | AD34: =IF(28<$C$9,0,$G$9*$D$9*(1+$C$27)*(1+$C$28)^2) -> 0 | AE34: =IF(29<$C$9,0,$G$9*$D$9*(1+$C$27)*(1+$C$28)^2) -> 0 | AF34: =IF(30<$C$9,0,$G$9*$D$9*(1+$C$27)*(1+$C$28)^2) -> 0 | AG34: =IF(31<$C$9,0,$G$9*$D$9*(1+$C$27)*(1+$C$28)^2) -> 0 | AH34: =IF(32<$C$9,0,$G$9*$D$9*(1+$C$27)*(1+$C$28)^2) -> 0 | AI34: =IF(33<$C$9,0,$G$9*$D$9*(1+$C$27)*(1+$C$28)^2) -> 0 | AJ34: =IF(34<$C$9,0,$G$9*$D$9*(1+$C$27)*(1+$C$28)^2) -> 0 | AK34: =IF(35<$C$9,0,$G$9*$D$9*(1+$C$27)*(1+$C$28)^2) -> 0 | AL34: =IF(36<$C$9,0,$G$9*$D$9*(1+$C$27)*(1+$C$28)^2) -> 0 | AN34: =SUM(C34:N34) -> 0 | AO34: =SUM(O34:Z34) -> 0 | AP34: =SUM(AA34:AL34) -> 0
A35: Senior full-stack engineer | B35: Product and Engineering | C35: =IF(1<$C$10,0,$E$10*$D$10*(1+$C$27)*(1+$C$28)^0) -> 2772 | D35: =IF(2<$C$10,0,$E$10*$D$10*(1+$C$27)*(1+$C$28)^0) -> 2772 | E35: =IF(3<$C$10,0,$E$10*$D$10*(1+$C$27)*(1+$C$28)^0) -> 2772 | F35: =IF(4<$C$10,0,$E$10*$D$10*(1+$C$27)*(1+$C$28)^0) -> 2772 | G35: =IF(5<$C$10,0,$E$10*$D$10*(1+$C$27)*(1+$C$28)^0) -> 2772 | H35: =IF(6<$C$10,0,$E$10*$D$10*(1+$C$27)*(1+$C$28)^0) -> 2772 | I35: =IF(7<$C$10,0,$E$10*$D$10*(1+$C$27)*(1+$C$28)^0) -> 2772 | J35: =IF(8<$C$10,0,$E$10*$D$10*(1+$C$27)*(1+$C$28)^0) -> 2772 | K35: =IF(9<$C$10,0,$E$10*$D$10*(1+$C$27)*(1+$C$28)^0) -> 2772 | L35: =IF(10<$C$10,0,$E$10*$D$10*(1+$C$27)*(1+$C$28)^0) -> 2772 | M35: =IF(11<$C$10,0,$E$10*$D$10*(1+$C$27)*(1+$C$28)^0) -> 2772 | N35: =IF(12<$C$10,0,$E$10*$D$10*(1+$C$27)*(1+$C$28)^0) -> 2772 | O35: =IF(13<$C$10,0,$F$10*$D$10*(1+$C$27)*(1+$C$28)^1) -> 5987.52 | P35: =IF(14<$C$10,0,$F$10*$D$10*(1+$C$27)*(1+$C$28)^1) -> 5987.52 | Q35: =IF(15<$C$10,0,$F$10*$D$10*(1+$C$27)*(1+$C$28)^1) -> 5987.52 | R35: =IF(16<$C$10,0,$F$10*$D$10*(1+$C$27)*(1+$C$28)^1) -> 5987.52 | S35: =IF(17<$C$10,0,$F$10*$D$10*(1+$C$27)*(1+$C$28)^1) -> 5987.52 | T35: =IF(18<$C$10,0,$F$10*$D$10*(1+$C$27)*(1+$C$28)^1) -> 5987.52 | U35: =IF(19<$C$10,0,$F$10*$D$10*(1+$C$27)*(1+$C$28)^1) -> 5987.52 | V35: =IF(20<$C$10,0,$F$10*$D$10*(1+$C$27)*(1+$C$28)^1) -> 5987.52 | W35: =IF(21<$C$10,0,$F$10*$D$10*(1+$C$27)*(1+$C$28)^1) -> 5987.52 | X35: =IF(22<$C$10,0,$F$10*$D$10*(1+$C$27)*(1+$C$28)^1) -> 5987.52 | Y35: =IF(23<$C$10,0,$F$10*$D$10*(1+$C$27)*(1+$C$28)^1) -> 5987.52 | Z35: =IF(24<$C$10,0,$F$10*$D$10*(1+$C$27)*(1+$C$28)^1) -> 5987.52 | AA35: =IF(25<$C$10,0,$G$10*$D$10*(1+$C$27)*(1+$C$28)^2) -> 6466.5216 | AB35: =IF(26<$C$10,0,$G$10*$D$10*(1+$C$27)*(1+$C$28)^2) -> 6466.5216 | AC35: =IF(27<$C$10,0,$G$10*$D$10*(1+$C$27)*(1+$C$28)^2) -> 6466.5216 | AD35: =IF(28<$C$10,0,$G$10*$D$10*(1+$C$27)*(1+$C$28)^2) -> 6466.5216 | AE35: =IF(29<$C$10,0,$G$10*$D$10*(1+$C$27)*(1+$C$28)^2) -> 6466.5216 | AF35: =IF(30<$C$10,0,$G$10*$D$10*(1+$C$27)*(1+$C$28)^2) -> 6466.5216 | AG35: =IF(31<$C$10,0,$G$10*$D$10*(1+$C$27)*(1+$C$28)^2) -> 6466.5216 | AH35: =IF(32<$C$10,0,$G$10*$D$10*(1+$C$27)*(1+$C$28)^2) -> 6466.5216 | AI35: =IF(33<$C$10,0,$G$10*$D$10*(1+$C$27)*(1+$C$28)^2) -> 6466.5216 | AJ35: =IF(34<$C$10,0,$G$10*$D$10*(1+$C$27)*(1+$C$28)^2) -> 6466.5216 | AK35: =IF(35<$C$10,0,$G$10*$D$10*(1+$C$27)*(1+$C$28)^2) -> 6466.5216 | AL35: =IF(36<$C$10,0,$G$10*$D$10*(1+$C$27)*(1+$C$28)^2) -> 6466.5216 | AN35: =SUM(C35:N35) -> 33264 | AO35: =SUM(O35:Z35) -> 71850.24 | AP35: =SUM(AA35:AL35) -> 77598.259
A36: AI and data engineer | B36: Product and Engineering | C36: =IF(1<$C$11,0,$E$11*$D$11*(1+$C$27)*(1+$C$28)^0) -> 0 | D36: =IF(2<$C$11,0,$E$11*$D$11*(1+$C$27)*(1+$C$28)^0) -> 0 | E36: =IF(3<$C$11,0,$E$11*$D$11*(1+$C$27)*(1+$C$28)^0) -> 0 | F36: =IF(4<$C$11,0,$E$11*$D$11*(1+$C$27)*(1+$C$28)^0) -> 0 | G36: =IF(5<$C$11,0,$E$11*$D$11*(1+$C$27)*(1+$C$28)^0) -> 0 | H36: =IF(6<$C$11,0,$E$11*$D$11*(1+$C$27)*(1+$C$28)^0) -> 0 | I36: =IF(7<$C$11,0,$E$11*$D$11*(1+$C$27)*(1+$C$28)^0) -> 0 | J36: =IF(8<$C$11,0,$E$11*$D$11*(1+$C$27)*(1+$C$28)^0) -> 0 | K36: =IF(9<$C$11,0,$E$11*$D$11*(1+$C$27)*(1+$C$28)^0) -> 0 | L36: =IF(10<$C$11,0,$E$11*$D$11*(1+$C$27)*(1+$C$28)^0) -> 0 | M36: =IF(11<$C$11,0,$E$11*$D$11*(1+$C$27)*(1+$C$28)^0) -> 0 | N36: =IF(12<$C$11,0,$E$11*$D$11*(1+$C$27)*(1+$C$28)^0) -> 0 | O36: =IF(13<$C$11,0,$F$11*$D$11*(1+$C$27)*(1+$C$28)^1) -> 0 | P36: =IF(14<$C$11,0,$F$11*$D$11*(1+$C$27)*(1+$C$28)^1) -> 0 | Q36: =IF(15<$C$11,0,$F$11*$D$11*(1+$C$27)*(1+$C$28)^1) -> 0 | R36: =IF(16<$C$11,0,$F$11*$D$11*(1+$C$27)*(1+$C$28)^1) -> 0 | S36: =IF(17<$C$11,0,$F$11*$D$11*(1+$C$27)*(1+$C$28)^1) -> 0 | T36: =IF(18<$C$11,0,$F$11*$D$11*(1+$C$27)*(1+$C$28)^1) -> 0 | U36: =IF(19<$C$11,0,$F$11*$D$11*(1+$C$27)*(1+$C$28)^1) -> 0 | V36: =IF(20<$C$11,0,$F$11*$D$11*(1+$C$27)*(1+$C$28)^1) -> 0 | W36: =IF(21<$C$11,0,$F$11*$D$11*(1+$C$27)*(1+$C$28)^1) -> 0 | X36: =IF(22<$C$11,0,$F$11*$D$11*(1+$C$27)*(1+$C$28)^1) -> 0 | Y36: =IF(23<$C$11,0,$F$11*$D$11*(1+$C$27)*(1+$C$28)^1) -> 0 | Z36: =IF(24<$C$11,0,$F$11*$D$11*(1+$C$27)*(1+$C$28)^1) -> 0 | AA36: =IF(25<$C$11,0,$G$11*$D$11*(1+$C$27)*(1+$C$28)^2) -> 0 | AB36: =IF(26<$C$11,0,$G$11*$D$11*(1+$C$27)*(1+$C$28)^2) -> 0 | AC36: =IF(27<$C$11,0,$G$11*$D$11*(1+$C$27)*(1+$C$28)^2) -> 0 | AD36: =IF(28<$C$11,0,$G$11*$D$11*(1+$C$27)*(1+$C$28)^2) -> 0 | AE36: =IF(29<$C$11,0,$G$11*$D$11*(1+$C$27)*(1+$C$28)^2) -> 0 | AF36: =IF(30<$C$11,0,$G$11*$D$11*(1+$C$27)*(1+$C$28)^2) -> 0 | AG36: =IF(31<$C$11,0,$G$11*$D$11*(1+$C$27)*(1+$C$28)^2) -> 0 | AH36: =IF(32<$C$11,0,$G$11*$D$11*(1+$C$27)*(1+$C$28)^2) -> 0 | AI36: =IF(33<$C$11,0,$G$11*$D$11*(1+$C$27)*(1+$C$28)^2) -> 0 | AJ36: =IF(34<$C$11,0,$G$11*$D$11*(1+$C$27)*(1+$C$28)^2) -> 0 | AK36: =IF(35<$C$11,0,$G$11*$D$11*(1+$C$27)*(1+$C$28)^2) -> 0 | AL36: =IF(36<$C$11,0,$G$11*$D$11*(1+$C$27)*(1+$C$28)^2) -> 0 | AN36: =SUM(C36:N36) -> 0 | AO36: =SUM(O36:Z36) -> 0 | AP36: =SUM(AA36:AL36) -> 0
A37: Product designer | B37: Product and Engineering | C37: =IF(1<$C$12,0,$E$12*$D$12*(1+$C$27)*(1+$C$28)^0) -> 0 | D37: =IF(2<$C$12,0,$E$12*$D$12*(1+$C$27)*(1+$C$28)^0) -> 0 | E37: =IF(3<$C$12,0,$E$12*$D$12*(1+$C$27)*(1+$C$28)^0) -> 0 | F37: =IF(4<$C$12,0,$E$12*$D$12*(1+$C$27)*(1+$C$28)^0) -> 0 | G37: =IF(5<$C$12,0,$E$12*$D$12*(1+$C$27)*(1+$C$28)^0) -> 0 | H37: =IF(6<$C$12,0,$E$12*$D$12*(1+$C$27)*(1+$C$28)^0) -> 0 | I37: =IF(7<$C$12,0,$E$12*$D$12*(1+$C$27)*(1+$C$28)^0) -> 0 | J37: =IF(8<$C$12,0,$E$12*$D$12*(1+$C$27)*(1+$C$28)^0) -> 0 | K37: =IF(9<$C$12,0,$E$12*$D$12*(1+$C$27)*(1+$C$28)^0) -> 0 | L37: =IF(10<$C$12,0,$E$12*$D$12*(1+$C$27)*(1+$C$28)^0) -> 0 | M37: =IF(11<$C$12,0,$E$12*$D$12*(1+$C$27)*(1+$C$28)^0) -> 0 | N37: =IF(12<$C$12,0,$E$12*$D$12*(1+$C$27)*(1+$C$28)^0) -> 0 | O37: =IF(13<$C$12,0,$F$12*$D$12*(1+$C$27)*(1+$C$28)^1) -> 0 | P37: =IF(14<$C$12,0,$F$12*$D$12*(1+$C$27)*(1+$C$28)^1) -> 0 | Q37: =IF(15<$C$12,0,$F$12*$D$12*(1+$C$27)*(1+$C$28)^1) -> 0 | R37: =IF(16<$C$12,0,$F$12*$D$12*(1+$C$27)*(1+$C$28)^1) -> 0 | S37: =IF(17<$C$12,0,$F$12*$D$12*(1+$C$27)*(1+$C$28)^1) -> 0 | T37: =IF(18<$C$12,0,$F$12*$D$12*(1+$C$27)*(1+$C$28)^1) -> 0 | U37: =IF(19<$C$12,0,$F$12*$D$12*(1+$C$27)*(1+$C$28)^1) -> 0 | V37: =IF(20<$C$12,0,$F$12*$D$12*(1+$C$27)*(1+$C$28)^1) -> 0 | W37: =IF(21<$C$12,0,$F$12*$D$12*(1+$C$27)*(1+$C$28)^1) -> 0 | X37: =IF(22<$C$12,0,$F$12*$D$12*(1+$C$27)*(1+$C$28)^1) -> 0 | Y37: =IF(23<$C$12,0,$F$12*$D$12*(1+$C$27)*(1+$C$28)^1) -> 0 | Z37: =IF(24<$C$12,0,$F$12*$D$12*(1+$C$27)*(1+$C$28)^1) -> 0 | AA37: =IF(25<$C$12,0,$G$12*$D$12*(1+$C$27)*(1+$C$28)^2) -> 0 | AB37: =IF(26<$C$12,0,$G$12*$D$12*(1+$C$27)*(1+$C$28)^2) -> 0 | AC37: =IF(27<$C$12,0,$G$12*$D$12*(1+$C$27)*(1+$C$28)^2) -> 0 | AD37: =IF(28<$C$12,0,$G$12*$D$12*(1+$C$27)*(1+$C$28)^2) -> 0 | AE37: =IF(29<$C$12,0,$G$12*$D$12*(1+$C$27)*(1+$C$28)^2) -> 0 | AF37: =IF(30<$C$12,0,$G$12*$D$12*(1+$C$27)*(1+$C$28)^2) -> 0 | AG37: =IF(31<$C$12,0,$G$12*$D$12*(1+$C$27)*(1+$C$28)^2) -> 0 | AH37: =IF(32<$C$12,0,$G$12*$D$12*(1+$C$27)*(1+$C$28)^2) -> 0 | AI37: =IF(33<$C$12,0,$G$12*$D$12*(1+$C$27)*(1+$C$28)^2) -> 0 | AJ37: =IF(34<$C$12,0,$G$12*$D$12*(1+$C$27)*(1+$C$28)^2) -> 0 | AK37: =IF(35<$C$12,0,$G$12*$D$12*(1+$C$27)*(1+$C$28)^2) -> 0 | AL37: =IF(36<$C$12,0,$G$12*$D$12*(1+$C$27)*(1+$C$28)^2) -> 0 | AN37: =SUM(C37:N37) -> 0 | AO37: =SUM(O37:Z37) -> 0 | AP37: =SUM(AA37:AL37) -> 0
A38: Head of Curriculum and Certification | B38: Curriculum and Delivery | C38: =IF(1<$C$13,0,$E$13*$D$13*(1+$C$27)*(1+$C$28)^0) -> 2772 | D38: =IF(2<$C$13,0,$E$13*$D$13*(1+$C$27)*(1+$C$28)^0) -> 2772 | E38: =IF(3<$C$13,0,$E$13*$D$13*(1+$C$27)*(1+$C$28)^0) -> 2772 | F38: =IF(4<$C$13,0,$E$13*$D$13*(1+$C$27)*(1+$C$28)^0) -> 2772 | G38: =IF(5<$C$13,0,$E$13*$D$13*(1+$C$27)*(1+$C$28)^0) -> 2772 | H38: =IF(6<$C$13,0,$E$13*$D$13*(1+$C$27)*(1+$C$28)^0) -> 2772 | I38: =IF(7<$C$13,0,$E$13*$D$13*(1+$C$27)*(1+$C$28)^0) -> 2772 | J38: =IF(8<$C$13,0,$E$13*$D$13*(1+$C$27)*(1+$C$28)^0) -> 2772 | K38: =IF(9<$C$13,0,$E$13*$D$13*(1+$C$27)*(1+$C$28)^0) -> 2772 | L38: =IF(10<$C$13,0,$E$13*$D$13*(1+$C$27)*(1+$C$28)^0) -> 2772 | M38: =IF(11<$C$13,0,$E$13*$D$13*(1+$C$27)*(1+$C$28)^0) -> 2772 | N38: =IF(12<$C$13,0,$E$13*$D$13*(1+$C$27)*(1+$C$28)^0) -> 2772 | O38: =IF(13<$C$13,0,$F$13*$D$13*(1+$C$27)*(1+$C$28)^1) -> 2993.76 | P38: =IF(14<$C$13,0,$F$13*$D$13*(1+$C$27)*(1+$C$28)^1) -> 2993.76 | Q38: =IF(15<$C$13,0,$F$13*$D$13*(1+$C$27)*(1+$C$28)^1) -> 2993.76 | R38: =IF(16<$C$13,0,$F$13*$D$13*(1+$C$27)*(1+$C$28)^1) -> 2993.76 | S38: =IF(17<$C$13,0,$F$13*$D$13*(1+$C$27)*(1+$C$28)^1) -> 2993.76 | T38: =IF(18<$C$13,0,$F$13*$D$13*(1+$C$27)*(1+$C$28)^1) -> 2993.76 | U38: =IF(19<$C$13,0,$F$13*$D$13*(1+$C$27)*(1+$C$28)^1) -> 2993.76 | V38: =IF(20<$C$13,0,$F$13*$D$13*(1+$C$27)*(1+$C$28)^1) -> 2993.76 | W38: =IF(21<$C$13,0,$F$13*$D$13*(1+$C$27)*(1+$C$28)^1) -> 2993.76 | X38: =IF(22<$C$13,0,$F$13*$D$13*(1+$C$27)*(1+$C$28)^1) -> 2993.76 | Y38: =IF(23<$C$13,0,$F$13*$D$13*(1+$C$27)*(1+$C$28)^1) -> 2993.76 | Z38: =IF(24<$C$13,0,$F$13*$D$13*(1+$C$27)*(1+$C$28)^1) -> 2993.76 | AA38: =IF(25<$C$13,0,$G$13*$D$13*(1+$C$27)*(1+$C$28)^2) -> 3233.2608 | AB38: =IF(26<$C$13,0,$G$13*$D$13*(1+$C$27)*(1+$C$28)^2) -> 3233.2608 | AC38: =IF(27<$C$13,0,$G$13*$D$13*(1+$C$27)*(1+$C$28)^2) -> 3233.2608 | AD38: =IF(28<$C$13,0,$G$13*$D$13*(1+$C$27)*(1+$C$28)^2) -> 3233.2608 | AE38: =IF(29<$C$13,0,$G$13*$D$13*(1+$C$27)*(1+$C$28)^2) -> 3233.2608 | AF38: =IF(30<$C$13,0,$G$13*$D$13*(1+$C$27)*(1+$C$28)^2) -> 3233.2608 | AG38: =IF(31<$C$13,0,$G$13*$D$13*(1+$C$27)*(1+$C$28)^2) -> 3233.2608 | AH38: =IF(32<$C$13,0,$G$13*$D$13*(1+$C$27)*(1+$C$28)^2) -> 3233.2608 | AI38: =IF(33<$C$13,0,$G$13*$D$13*(1+$C$27)*(1+$C$28)^2) -> 3233.2608 | AJ38: =IF(34<$C$13,0,$G$13*$D$13*(1+$C$27)*(1+$C$28)^2) -> 3233.2608 | AK38: =IF(35<$C$13,0,$G$13*$D$13*(1+$C$27)*(1+$C$28)^2) -> 3233.2608 | AL38: =IF(36<$C$13,0,$G$13*$D$13*(1+$C$27)*(1+$C$28)^2) -> 3233.2608 | AN38: =SUM(C38:N38) -> 33264 | AO38: =SUM(O38:Z38) -> 35925.12 | AP38: =SUM(AA38:AL38) -> 38799.13
A39: Partner network manager | B39: Curriculum and Delivery | C39: =IF(1<$C$14,0,$E$14*$D$14*(1+$C$27)*(1+$C$28)^0) -> 0 | D39: =IF(2<$C$14,0,$E$14*$D$14*(1+$C$27)*(1+$C$28)^0) -> 0 | E39: =IF(3<$C$14,0,$E$14*$D$14*(1+$C$27)*(1+$C$28)^0) -> 0 | F39: =IF(4<$C$14,0,$E$14*$D$14*(1+$C$27)*(1+$C$28)^0) -> 0 | G39: =IF(5<$C$14,0,$E$14*$D$14*(1+$C$27)*(1+$C$28)^0) -> 0 | H39: =IF(6<$C$14,0,$E$14*$D$14*(1+$C$27)*(1+$C$28)^0) -> 0 | I39: =IF(7<$C$14,0,$E$14*$D$14*(1+$C$27)*(1+$C$28)^0) -> 0 | J39: =IF(8<$C$14,0,$E$14*$D$14*(1+$C$27)*(1+$C$28)^0) -> 0 | K39: =IF(9<$C$14,0,$E$14*$D$14*(1+$C$27)*(1+$C$28)^0) -> 0 | L39: =IF(10<$C$14,0,$E$14*$D$14*(1+$C$27)*(1+$C$28)^0) -> 0 | M39: =IF(11<$C$14,0,$E$14*$D$14*(1+$C$27)*(1+$C$28)^0) -> 0 | N39: =IF(12<$C$14,0,$E$14*$D$14*(1+$C$27)*(1+$C$28)^0) -> 0 | O39: =IF(13<$C$14,0,$F$14*$D$14*(1+$C$27)*(1+$C$28)^1) -> 2494.8 | P39: =IF(14<$C$14,0,$F$14*$D$14*(1+$C$27)*(1+$C$28)^1) -> 2494.8 | Q39: =IF(15<$C$14,0,$F$14*$D$14*(1+$C$27)*(1+$C$28)^1) -> 2494.8 | R39: =IF(16<$C$14,0,$F$14*$D$14*(1+$C$27)*(1+$C$28)^1) -> 2494.8 | S39: =IF(17<$C$14,0,$F$14*$D$14*(1+$C$27)*(1+$C$28)^1) -> 2494.8 | T39: =IF(18<$C$14,0,$F$14*$D$14*(1+$C$27)*(1+$C$28)^1) -> 2494.8 | U39: =IF(19<$C$14,0,$F$14*$D$14*(1+$C$27)*(1+$C$28)^1) -> 2494.8 | V39: =IF(20<$C$14,0,$F$14*$D$14*(1+$C$27)*(1+$C$28)^1) -> 2494.8 | W39: =IF(21<$C$14,0,$F$14*$D$14*(1+$C$27)*(1+$C$28)^1) -> 2494.8 | X39: =IF(22<$C$14,0,$F$14*$D$14*(1+$C$27)*(1+$C$28)^1) -> 2494.8 | Y39: =IF(23<$C$14,0,$F$14*$D$14*(1+$C$27)*(1+$C$28)^1) -> 2494.8 | Z39: =IF(24<$C$14,0,$F$14*$D$14*(1+$C$27)*(1+$C$28)^1) -> 2494.8 | AA39: =IF(25<$C$14,0,$G$14*$D$14*(1+$C$27)*(1+$C$28)^2) -> 2694.384 | AB39: =IF(26<$C$14,0,$G$14*$D$14*(1+$C$27)*(1+$C$28)^2) -> 2694.384 | AC39: =IF(27<$C$14,0,$G$14*$D$14*(1+$C$27)*(1+$C$28)^2) -> 2694.384 | AD39: =IF(28<$C$14,0,$G$14*$D$14*(1+$C$27)*(1+$C$28)^2) -> 2694.384 | AE39: =IF(29<$C$14,0,$G$14*$D$14*(1+$C$27)*(1+$C$28)^2) -> 2694.384 | AF39: =IF(30<$C$14,0,$G$14*$D$14*(1+$C$27)*(1+$C$28)^2) -> 2694.384 | AG39: =IF(31<$C$14,0,$G$14*$D$14*(1+$C$27)*(1+$C$28)^2) -> 2694.384 | AH39: =IF(32<$C$14,0,$G$14*$D$14*(1+$C$27)*(1+$C$28)^2) -> 2694.384 | AI39: =IF(33<$C$14,0,$G$14*$D$14*(1+$C$27)*(1+$C$28)^2) -> 2694.384 | AJ39: =IF(34<$C$14,0,$G$14*$D$14*(1+$C$27)*(1+$C$28)^2) -> 2694.384 | AK39: =IF(35<$C$14,0,$G$14*$D$14*(1+$C$27)*(1+$C$28)^2) -> 2694.384 | AL39: =IF(36<$C$14,0,$G$14*$D$14*(1+$C$27)*(1+$C$28)^2) -> 2694.384 | AN39: =SUM(C39:N39) -> 0 | AO39: =SUM(O39:Z39) -> 29937.6 | AP39: =SUM(AA39:AL39) -> 32332.608
A40: Programme delivery coordinator | B40: Curriculum and Delivery | C40: =IF(1<$C$15,0,$E$15*$D$15*(1+$C$27)*(1+$C$28)^0) -> 0 | D40: =IF(2<$C$15,0,$E$15*$D$15*(1+$C$27)*(1+$C$28)^0) -> 0 | E40: =IF(3<$C$15,0,$E$15*$D$15*(1+$C$27)*(1+$C$28)^0) -> 0 | F40: =IF(4<$C$15,0,$E$15*$D$15*(1+$C$27)*(1+$C$28)^0) -> 0 | G40: =IF(5<$C$15,0,$E$15*$D$15*(1+$C$27)*(1+$C$28)^0) -> 0 | H40: =IF(6<$C$15,0,$E$15*$D$15*(1+$C$27)*(1+$C$28)^0) -> 0 | I40: =IF(7<$C$15,0,$E$15*$D$15*(1+$C$27)*(1+$C$28)^0) -> 0 | J40: =IF(8<$C$15,0,$E$15*$D$15*(1+$C$27)*(1+$C$28)^0) -> 0 | K40: =IF(9<$C$15,0,$E$15*$D$15*(1+$C$27)*(1+$C$28)^0) -> 0 | L40: =IF(10<$C$15,0,$E$15*$D$15*(1+$C$27)*(1+$C$28)^0) -> 0 | M40: =IF(11<$C$15,0,$E$15*$D$15*(1+$C$27)*(1+$C$28)^0) -> 0 | N40: =IF(12<$C$15,0,$E$15*$D$15*(1+$C$27)*(1+$C$28)^0) -> 0 | O40: =IF(13<$C$15,0,$F$15*$D$15*(1+$C$27)*(1+$C$28)^1) -> 0 | P40: =IF(14<$C$15,0,$F$15*$D$15*(1+$C$27)*(1+$C$28)^1) -> 0 | Q40: =IF(15<$C$15,0,$F$15*$D$15*(1+$C$27)*(1+$C$28)^1) -> 0 | R40: =IF(16<$C$15,0,$F$15*$D$15*(1+$C$27)*(1+$C$28)^1) -> 0 | S40: =IF(17<$C$15,0,$F$15*$D$15*(1+$C$27)*(1+$C$28)^1) -> 0 | T40: =IF(18<$C$15,0,$F$15*$D$15*(1+$C$27)*(1+$C$28)^1) -> 0 | U40: =IF(19<$C$15,0,$F$15*$D$15*(1+$C$27)*(1+$C$28)^1) -> 0 | V40: =IF(20<$C$15,0,$F$15*$D$15*(1+$C$27)*(1+$C$28)^1) -> 0 | W40: =IF(21<$C$15,0,$F$15*$D$15*(1+$C$27)*(1+$C$28)^1) -> 0 | X40: =IF(22<$C$15,0,$F$15*$D$15*(1+$C$27)*(1+$C$28)^1) -> 0 | Y40: =IF(23<$C$15,0,$F$15*$D$15*(1+$C$27)*(1+$C$28)^1) -> 0 | Z40: =IF(24<$C$15,0,$F$15*$D$15*(1+$C$27)*(1+$C$28)^1) -> 0 | AA40: =IF(25<$C$15,0,$G$15*$D$15*(1+$C$27)*(1+$C$28)^2) -> 2020.788 | AB40: =IF(26<$C$15,0,$G$15*$D$15*(1+$C$27)*(1+$C$28)^2) -> 2020.788 | AC40: =IF(27<$C$15,0,$G$15*$D$15*(1+$C$27)*(1+$C$28)^2) -> 2020.788 | AD40: =IF(28<$C$15,0,$G$15*$D$15*(1+$C$27)*(1+$C$28)^2) -> 2020.788 | AE40: =IF(29<$C$15,0,$G$15*$D$15*(1+$C$27)*(1+$C$28)^2) -> 2020.788 | AF40: =IF(30<$C$15,0,$G$15*$D$15*(1+$C$27)*(1+$C$28)^2) -> 2020.788 | AG40: =IF(31<$C$15,0,$G$15*$D$15*(1+$C$27)*(1+$C$28)^2) -> 2020.788 | AH40: =IF(32<$C$15,0,$G$15*$D$15*(1+$C$27)*(1+$C$28)^2) -> 2020.788 | AI40: =IF(33<$C$15,0,$G$15*$D$15*(1+$C$27)*(1+$C$28)^2) -> 2020.788 | AJ40: =IF(34<$C$15,0,$G$15*$D$15*(1+$C$27)*(1+$C$28)^2) -> 2020.788 | AK40: =IF(35<$C$15,0,$G$15*$D$15*(1+$C$27)*(1+$C$28)^2) -> 2020.788 | AL40: =IF(36<$C$15,0,$G$15*$D$15*(1+$C$27)*(1+$C$28)^2) -> 2020.788 | AN40: =SUM(C40:N40) -> 0 | AO40: =SUM(O40:Z40) -> 0 | AP40: =SUM(AA40:AL40) -> 24249.456
A41: Bilingual curriculum producer | B41: Curriculum and Delivery | C41: =IF(1<$C$16,0,$E$16*$D$16*(1+$C$27)*(1+$C$28)^0) -> 0 | D41: =IF(2<$C$16,0,$E$16*$D$16*(1+$C$27)*(1+$C$28)^0) -> 0 | E41: =IF(3<$C$16,0,$E$16*$D$16*(1+$C$27)*(1+$C$28)^0) -> 0 | F41: =IF(4<$C$16,0,$E$16*$D$16*(1+$C$27)*(1+$C$28)^0) -> 0 | G41: =IF(5<$C$16,0,$E$16*$D$16*(1+$C$27)*(1+$C$28)^0) -> 0 | H41: =IF(6<$C$16,0,$E$16*$D$16*(1+$C$27)*(1+$C$28)^0) -> 0 | I41: =IF(7<$C$16,0,$E$16*$D$16*(1+$C$27)*(1+$C$28)^0) -> 0 | J41: =IF(8<$C$16,0,$E$16*$D$16*(1+$C$27)*(1+$C$28)^0) -> 0 | K41: =IF(9<$C$16,0,$E$16*$D$16*(1+$C$27)*(1+$C$28)^0) -> 0 | L41: =IF(10<$C$16,0,$E$16*$D$16*(1+$C$27)*(1+$C$28)^0) -> 0 | M41: =IF(11<$C$16,0,$E$16*$D$16*(1+$C$27)*(1+$C$28)^0) -> 0 | N41: =IF(12<$C$16,0,$E$16*$D$16*(1+$C$27)*(1+$C$28)^0) -> 0 | O41: =IF(13<$C$16,0,$F$16*$D$16*(1+$C$27)*(1+$C$28)^1) -> 0 | P41: =IF(14<$C$16,0,$F$16*$D$16*(1+$C$27)*(1+$C$28)^1) -> 0 | Q41: =IF(15<$C$16,0,$F$16*$D$16*(1+$C$27)*(1+$C$28)^1) -> 0 | R41: =IF(16<$C$16,0,$F$16*$D$16*(1+$C$27)*(1+$C$28)^1) -> 0 | S41: =IF(17<$C$16,0,$F$16*$D$16*(1+$C$27)*(1+$C$28)^1) -> 0 | T41: =IF(18<$C$16,0,$F$16*$D$16*(1+$C$27)*(1+$C$28)^1) -> 0 | U41: =IF(19<$C$16,0,$F$16*$D$16*(1+$C$27)*(1+$C$28)^1) -> 0 | V41: =IF(20<$C$16,0,$F$16*$D$16*(1+$C$27)*(1+$C$28)^1) -> 0 | W41: =IF(21<$C$16,0,$F$16*$D$16*(1+$C$27)*(1+$C$28)^1) -> 0 | X41: =IF(22<$C$16,0,$F$16*$D$16*(1+$C$27)*(1+$C$28)^1) -> 0 | Y41: =IF(23<$C$16,0,$F$16*$D$16*(1+$C$27)*(1+$C$28)^1) -> 0 | Z41: =IF(24<$C$16,0,$F$16*$D$16*(1+$C$27)*(1+$C$28)^1) -> 0 | AA41: =IF(25<$C$16,0,$G$16*$D$16*(1+$C$27)*(1+$C$28)^2) -> 0 | AB41: =IF(26<$C$16,0,$G$16*$D$16*(1+$C$27)*(1+$C$28)^2) -> 0 | AC41: =IF(27<$C$16,0,$G$16*$D$16*(1+$C$27)*(1+$C$28)^2) -> 0 | AD41: =IF(28<$C$16,0,$G$16*$D$16*(1+$C$27)*(1+$C$28)^2) -> 0 | AE41: =IF(29<$C$16,0,$G$16*$D$16*(1+$C$27)*(1+$C$28)^2) -> 0 | AF41: =IF(30<$C$16,0,$G$16*$D$16*(1+$C$27)*(1+$C$28)^2) -> 0 | AG41: =IF(31<$C$16,0,$G$16*$D$16*(1+$C$27)*(1+$C$28)^2) -> 0 | AH41: =IF(32<$C$16,0,$G$16*$D$16*(1+$C$27)*(1+$C$28)^2) -> 0 | AI41: =IF(33<$C$16,0,$G$16*$D$16*(1+$C$27)*(1+$C$28)^2) -> 0 | AJ41: =IF(34<$C$16,0,$G$16*$D$16*(1+$C$27)*(1+$C$28)^2) -> 0 | AK41: =IF(35<$C$16,0,$G$16*$D$16*(1+$C$27)*(1+$C$28)^2) -> 0 | AL41: =IF(36<$C$16,0,$G$16*$D$16*(1+$C$27)*(1+$C$28)^2) -> 0 | AN41: =SUM(C41:N41) -> 0 | AO41: =SUM(O41:Z41) -> 0 | AP41: =SUM(AA41:AL41) -> 0
A42: Head of Partnerships — Egypt | B42: Institutional Partnerships | C42: =IF(1<$C$17,0,$E$17*$D$17*(1+$C$27)*(1+$C$28)^0) -> 2541 | D42: =IF(2<$C$17,0,$E$17*$D$17*(1+$C$27)*(1+$C$28)^0) -> 2541 | E42: =IF(3<$C$17,0,$E$17*$D$17*(1+$C$27)*(1+$C$28)^0) -> 2541 | F42: =IF(4<$C$17,0,$E$17*$D$17*(1+$C$27)*(1+$C$28)^0) -> 2541 | G42: =IF(5<$C$17,0,$E$17*$D$17*(1+$C$27)*(1+$C$28)^0) -> 2541 | H42: =IF(6<$C$17,0,$E$17*$D$17*(1+$C$27)*(1+$C$28)^0) -> 2541 | I42: =IF(7<$C$17,0,$E$17*$D$17*(1+$C$27)*(1+$C$28)^0) -> 2541 | J42: =IF(8<$C$17,0,$E$17*$D$17*(1+$C$27)*(1+$C$28)^0) -> 2541 | K42: =IF(9<$C$17,0,$E$17*$D$17*(1+$C$27)*(1+$C$28)^0) -> 2541 | L42: =IF(10<$C$17,0,$E$17*$D$17*(1+$C$27)*(1+$C$28)^0) -> 2541 | M42: =IF(11<$C$17,0,$E$17*$D$17*(1+$C$27)*(1+$C$28)^0) -> 2541 | N42: =IF(12<$C$17,0,$E$17*$D$17*(1+$C$27)*(1+$C$28)^0) -> 2541 | O42: =IF(13<$C$17,0,$F$17*$D$17*(1+$C$27)*(1+$C$28)^1) -> 2744.28 | P42: =IF(14<$C$17,0,$F$17*$D$17*(1+$C$27)*(1+$C$28)^1) -> 2744.28 | Q42: =IF(15<$C$17,0,$F$17*$D$17*(1+$C$27)*(1+$C$28)^1) -> 2744.28 | R42: =IF(16<$C$17,0,$F$17*$D$17*(1+$C$27)*(1+$C$28)^1) -> 2744.28 | S42: =IF(17<$C$17,0,$F$17*$D$17*(1+$C$27)*(1+$C$28)^1) -> 2744.28 | T42: =IF(18<$C$17,0,$F$17*$D$17*(1+$C$27)*(1+$C$28)^1) -> 2744.28 | U42: =IF(19<$C$17,0,$F$17*$D$17*(1+$C$27)*(1+$C$28)^1) -> 2744.28 | V42: =IF(20<$C$17,0,$F$17*$D$17*(1+$C$27)*(1+$C$28)^1) -> 2744.28 | W42: =IF(21<$C$17,0,$F$17*$D$17*(1+$C$27)*(1+$C$28)^1) -> 2744.28 | X42: =IF(22<$C$17,0,$F$17*$D$17*(1+$C$27)*(1+$C$28)^1) -> 2744.28 | Y42: =IF(23<$C$17,0,$F$17*$D$17*(1+$C$27)*(1+$C$28)^1) -> 2744.28 | Z42: =IF(24<$C$17,0,$F$17*$D$17*(1+$C$27)*(1+$C$28)^1) -> 2744.28 | AA42: =IF(25<$C$17,0,$G$17*$D$17*(1+$C$27)*(1+$C$28)^2) -> 2963.8224 | AB42: =IF(26<$C$17,0,$G$17*$D$17*(1+$C$27)*(1+$C$28)^2) -> 2963.8224 | AC42: =IF(27<$C$17,0,$G$17*$D$17*(1+$C$27)*(1+$C$28)^2) -> 2963.8224 | AD42: =IF(28<$C$17,0,$G$17*$D$17*(1+$C$27)*(1+$C$28)^2) -> 2963.8224 | AE42: =IF(29<$C$17,0,$G$17*$D$17*(1+$C$27)*(1+$C$28)^2) -> 2963.8224 | AF42: =IF(30<$C$17,0,$G$17*$D$17*(1+$C$27)*(1+$C$28)^2) -> 2963.8224 | AG42: =IF(31<$C$17,0,$G$17*$D$17*(1+$C$27)*(1+$C$28)^2) -> 2963.8224 | AH42: =IF(32<$C$17,0,$G$17*$D$17*(1+$C$27)*(1+$C$28)^2) -> 2963.8224 | AI42: =IF(33<$C$17,0,$G$17*$D$17*(1+$C$27)*(1+$C$28)^2) -> 2963.8224 | AJ42: =IF(34<$C$17,0,$G$17*$D$17*(1+$C$27)*(1+$C$28)^2) -> 2963.8224 | AK42: =IF(35<$C$17,0,$G$17*$D$17*(1+$C$27)*(1+$C$28)^2) -> 2963.8224 | AL42: =IF(36<$C$17,0,$G$17*$D$17*(1+$C$27)*(1+$C$28)^2) -> 2963.8224 | AN42: =SUM(C42:N42) -> 30492 | AO42: =SUM(O42:Z42) -> 32931.36 | AP42: =SUM(AA42:AL42) -> 35565.869
A43: Country Manager — KSA (Riyadh) | B43: Institutional Partnerships | C43: =IF(1<$C$18,0,$E$18*$D$18*(1+$C$27)*(1+$C$28)^0) -> 0 | D43: =IF(2<$C$18,0,$E$18*$D$18*(1+$C$27)*(1+$C$28)^0) -> 0 | E43: =IF(3<$C$18,0,$E$18*$D$18*(1+$C$27)*(1+$C$28)^0) -> 0 | F43: =IF(4<$C$18,0,$E$18*$D$18*(1+$C$27)*(1+$C$28)^0) -> 0 | G43: =IF(5<$C$18,0,$E$18*$D$18*(1+$C$27)*(1+$C$28)^0) -> 0 | H43: =IF(6<$C$18,0,$E$18*$D$18*(1+$C$27)*(1+$C$28)^0) -> 0 | I43: =IF(7<$C$18,0,$E$18*$D$18*(1+$C$27)*(1+$C$28)^0) -> 0 | J43: =IF(8<$C$18,0,$E$18*$D$18*(1+$C$27)*(1+$C$28)^0) -> 0 | K43: =IF(9<$C$18,0,$E$18*$D$18*(1+$C$27)*(1+$C$28)^0) -> 0 | L43: =IF(10<$C$18,0,$E$18*$D$18*(1+$C$27)*(1+$C$28)^0) -> 0 | M43: =IF(11<$C$18,0,$E$18*$D$18*(1+$C$27)*(1+$C$28)^0) -> 0 | N43: =IF(12<$C$18,0,$E$18*$D$18*(1+$C$27)*(1+$C$28)^0) -> 0 | O43: =IF(13<$C$18,0,$F$18*$D$18*(1+$C$27)*(1+$C$28)^1) -> 6237 | P43: =IF(14<$C$18,0,$F$18*$D$18*(1+$C$27)*(1+$C$28)^1) -> 6237 | Q43: =IF(15<$C$18,0,$F$18*$D$18*(1+$C$27)*(1+$C$28)^1) -> 6237 | R43: =IF(16<$C$18,0,$F$18*$D$18*(1+$C$27)*(1+$C$28)^1) -> 6237 | S43: =IF(17<$C$18,0,$F$18*$D$18*(1+$C$27)*(1+$C$28)^1) -> 6237 | T43: =IF(18<$C$18,0,$F$18*$D$18*(1+$C$27)*(1+$C$28)^1) -> 6237 | U43: =IF(19<$C$18,0,$F$18*$D$18*(1+$C$27)*(1+$C$28)^1) -> 6237 | V43: =IF(20<$C$18,0,$F$18*$D$18*(1+$C$27)*(1+$C$28)^1) -> 6237 | W43: =IF(21<$C$18,0,$F$18*$D$18*(1+$C$27)*(1+$C$28)^1) -> 6237 | X43: =IF(22<$C$18,0,$F$18*$D$18*(1+$C$27)*(1+$C$28)^1) -> 6237 | Y43: =IF(23<$C$18,0,$F$18*$D$18*(1+$C$27)*(1+$C$28)^1) -> 6237 | Z43: =IF(24<$C$18,0,$F$18*$D$18*(1+$C$27)*(1+$C$28)^1) -> 6237 | AA43: =IF(25<$C$18,0,$G$18*$D$18*(1+$C$27)*(1+$C$28)^2) -> 6735.96 | AB43: =IF(26<$C$18,0,$G$18*$D$18*(1+$C$27)*(1+$C$28)^2) -> 6735.96 | AC43: =IF(27<$C$18,0,$G$18*$D$18*(1+$C$27)*(1+$C$28)^2) -> 6735.96 | AD43: =IF(28<$C$18,0,$G$18*$D$18*(1+$C$27)*(1+$C$28)^2) -> 6735.96 | AE43: =IF(29<$C$18,0,$G$18*$D$18*(1+$C$27)*(1+$C$28)^2) -> 6735.96 | AF43: =IF(30<$C$18,0,$G$18*$D$18*(1+$C$27)*(1+$C$28)^2) -> 6735.96 | AG43: =IF(31<$C$18,0,$G$18*$D$18*(1+$C$27)*(1+$C$28)^2) -> 6735.96 | AH43: =IF(32<$C$18,0,$G$18*$D$18*(1+$C$27)*(1+$C$28)^2) -> 6735.96 | AI43: =IF(33<$C$18,0,$G$18*$D$18*(1+$C$27)*(1+$C$28)^2) -> 6735.96 | AJ43: =IF(34<$C$18,0,$G$18*$D$18*(1+$C$27)*(1+$C$28)^2) -> 6735.96 | AK43: =IF(35<$C$18,0,$G$18*$D$18*(1+$C$27)*(1+$C$28)^2) -> 6735.96 | AL43: =IF(36<$C$18,0,$G$18*$D$18*(1+$C$27)*(1+$C$28)^2) -> 6735.96 | AN43: =SUM(C43:N43) -> 0 | AO43: =SUM(O43:Z43) -> 74844 | AP43: =SUM(AA43:AL43) -> 80831.52
A44: Head of Government, Initiatives and Donors | B44: Institutional Partnerships | C44: =IF(1<$C$19,0,$E$19*$D$19*(1+$C$27)*(1+$C$28)^0) -> 0 | D44: =IF(2<$C$19,0,$E$19*$D$19*(1+$C$27)*(1+$C$28)^0) -> 0 | E44: =IF(3<$C$19,0,$E$19*$D$19*(1+$C$27)*(1+$C$28)^0) -> 0 | F44: =IF(4<$C$19,0,$E$19*$D$19*(1+$C$27)*(1+$C$28)^0) -> 0 | G44: =IF(5<$C$19,0,$E$19*$D$19*(1+$C$27)*(1+$C$28)^0) -> 0 | H44: =IF(6<$C$19,0,$E$19*$D$19*(1+$C$27)*(1+$C$28)^0) -> 0 | I44: =IF(7<$C$19,0,$E$19*$D$19*(1+$C$27)*(1+$C$28)^0) -> 0 | J44: =IF(8<$C$19,0,$E$19*$D$19*(1+$C$27)*(1+$C$28)^0) -> 0 | K44: =IF(9<$C$19,0,$E$19*$D$19*(1+$C$27)*(1+$C$28)^0) -> 0 | L44: =IF(10<$C$19,0,$E$19*$D$19*(1+$C$27)*(1+$C$28)^0) -> 0 | M44: =IF(11<$C$19,0,$E$19*$D$19*(1+$C$27)*(1+$C$28)^0) -> 0 | N44: =IF(12<$C$19,0,$E$19*$D$19*(1+$C$27)*(1+$C$28)^0) -> 0 | O44: =IF(13<$C$19,0,$F$19*$D$19*(1+$C$27)*(1+$C$28)^1) -> 0 | P44: =IF(14<$C$19,0,$F$19*$D$19*(1+$C$27)*(1+$C$28)^1) -> 0 | Q44: =IF(15<$C$19,0,$F$19*$D$19*(1+$C$27)*(1+$C$28)^1) -> 0 | R44: =IF(16<$C$19,0,$F$19*$D$19*(1+$C$27)*(1+$C$28)^1) -> 0 | S44: =IF(17<$C$19,0,$F$19*$D$19*(1+$C$27)*(1+$C$28)^1) -> 0 | T44: =IF(18<$C$19,0,$F$19*$D$19*(1+$C$27)*(1+$C$28)^1) -> 0 | U44: =IF(19<$C$19,0,$F$19*$D$19*(1+$C$27)*(1+$C$28)^1) -> 0 | V44: =IF(20<$C$19,0,$F$19*$D$19*(1+$C$27)*(1+$C$28)^1) -> 0 | W44: =IF(21<$C$19,0,$F$19*$D$19*(1+$C$27)*(1+$C$28)^1) -> 0 | X44: =IF(22<$C$19,0,$F$19*$D$19*(1+$C$27)*(1+$C$28)^1) -> 0 | Y44: =IF(23<$C$19,0,$F$19*$D$19*(1+$C$27)*(1+$C$28)^1) -> 0 | Z44: =IF(24<$C$19,0,$F$19*$D$19*(1+$C$27)*(1+$C$28)^1) -> 0 | AA44: =IF(25<$C$19,0,$G$19*$D$19*(1+$C$27)*(1+$C$28)^2) -> 3502.6992 | AB44: =IF(26<$C$19,0,$G$19*$D$19*(1+$C$27)*(1+$C$28)^2) -> 3502.6992 | AC44: =IF(27<$C$19,0,$G$19*$D$19*(1+$C$27)*(1+$C$28)^2) -> 3502.6992 | AD44: =IF(28<$C$19,0,$G$19*$D$19*(1+$C$27)*(1+$C$28)^2) -> 3502.6992 | AE44: =IF(29<$C$19,0,$G$19*$D$19*(1+$C$27)*(1+$C$28)^2) -> 3502.6992 | AF44: =IF(30<$C$19,0,$G$19*$D$19*(1+$C$27)*(1+$C$28)^2) -> 3502.6992 | AG44: =IF(31<$C$19,0,$G$19*$D$19*(1+$C$27)*(1+$C$28)^2) -> 3502.6992 | AH44: =IF(32<$C$19,0,$G$19*$D$19*(1+$C$27)*(1+$C$28)^2) -> 3502.6992 | AI44: =IF(33<$C$19,0,$G$19*$D$19*(1+$C$27)*(1+$C$28)^2) -> 3502.6992 | AJ44: =IF(34<$C$19,0,$G$19*$D$19*(1+$C$27)*(1+$C$28)^2) -> 3502.6992 | AK44: =IF(35<$C$19,0,$G$19*$D$19*(1+$C$27)*(1+$C$28)^2) -> 3502.6992 | AL44: =IF(36<$C$19,0,$G$19*$D$19*(1+$C$27)*(1+$C$28)^2) -> 3502.6992 | AN44: =SUM(C44:N44) -> 0 | AO44: =SUM(O44:Z44) -> 0 | AP44: =SUM(AA44:AL44) -> 42032.39
A45: Partnerships and bids associate | B45: Institutional Partnerships | C45: =IF(1<$C$20,0,$E$20*$D$20*(1+$C$27)*(1+$C$28)^0) -> 0 | D45: =IF(2<$C$20,0,$E$20*$D$20*(1+$C$27)*(1+$C$28)^0) -> 0 | E45: =IF(3<$C$20,0,$E$20*$D$20*(1+$C$27)*(1+$C$28)^0) -> 0 | F45: =IF(4<$C$20,0,$E$20*$D$20*(1+$C$27)*(1+$C$28)^0) -> 0 | G45: =IF(5<$C$20,0,$E$20*$D$20*(1+$C$27)*(1+$C$28)^0) -> 0 | H45: =IF(6<$C$20,0,$E$20*$D$20*(1+$C$27)*(1+$C$28)^0) -> 0 | I45: =IF(7<$C$20,0,$E$20*$D$20*(1+$C$27)*(1+$C$28)^0) -> 0 | J45: =IF(8<$C$20,0,$E$20*$D$20*(1+$C$27)*(1+$C$28)^0) -> 0 | K45: =IF(9<$C$20,0,$E$20*$D$20*(1+$C$27)*(1+$C$28)^0) -> 0 | L45: =IF(10<$C$20,0,$E$20*$D$20*(1+$C$27)*(1+$C$28)^0) -> 0 | M45: =IF(11<$C$20,0,$E$20*$D$20*(1+$C$27)*(1+$C$28)^0) -> 0 | N45: =IF(12<$C$20,0,$E$20*$D$20*(1+$C$27)*(1+$C$28)^0) -> 0 | O45: =IF(13<$C$20,0,$F$20*$D$20*(1+$C$27)*(1+$C$28)^1) -> 0 | P45: =IF(14<$C$20,0,$F$20*$D$20*(1+$C$27)*(1+$C$28)^1) -> 0 | Q45: =IF(15<$C$20,0,$F$20*$D$20*(1+$C$27)*(1+$C$28)^1) -> 0 | R45: =IF(16<$C$20,0,$F$20*$D$20*(1+$C$27)*(1+$C$28)^1) -> 0 | S45: =IF(17<$C$20,0,$F$20*$D$20*(1+$C$27)*(1+$C$28)^1) -> 0 | T45: =IF(18<$C$20,0,$F$20*$D$20*(1+$C$27)*(1+$C$28)^1) -> 0 | U45: =IF(19<$C$20,0,$F$20*$D$20*(1+$C$27)*(1+$C$28)^1) -> 0 | V45: =IF(20<$C$20,0,$F$20*$D$20*(1+$C$27)*(1+$C$28)^1) -> 0 | W45: =IF(21<$C$20,0,$F$20*$D$20*(1+$C$27)*(1+$C$28)^1) -> 0 | X45: =IF(22<$C$20,0,$F$20*$D$20*(1+$C$27)*(1+$C$28)^1) -> 0 | Y45: =IF(23<$C$20,0,$F$20*$D$20*(1+$C$27)*(1+$C$28)^1) -> 0 | Z45: =IF(24<$C$20,0,$F$20*$D$20*(1+$C$27)*(1+$C$28)^1) -> 0 | AA45: =IF(25<$C$20,0,$G$20*$D$20*(1+$C$27)*(1+$C$28)^2) -> 1616.6304 | AB45: =IF(26<$C$20,0,$G$20*$D$20*(1+$C$27)*(1+$C$28)^2) -> 1616.6304 | AC45: =IF(27<$C$20,0,$G$20*$D$20*(1+$C$27)*(1+$C$28)^2) -> 1616.6304 | AD45: =IF(28<$C$20,0,$G$20*$D$20*(1+$C$27)*(1+$C$28)^2) -> 1616.6304 | AE45: =IF(29<$C$20,0,$G$20*$D$20*(1+$C$27)*(1+$C$28)^2) -> 1616.6304 | AF45: =IF(30<$C$20,0,$G$20*$D$20*(1+$C$27)*(1+$C$28)^2) -> 1616.6304 | AG45: =IF(31<$C$20,0,$G$20*$D$20*(1+$C$27)*(1+$C$28)^2) -> 1616.6304 | AH45: =IF(32<$C$20,0,$G$20*$D$20*(1+$C$27)*(1+$C$28)^2) -> 1616.6304 | AI45: =IF(33<$C$20,0,$G$20*$D$20*(1+$C$27)*(1+$C$28)^2) -> 1616.6304 | AJ45: =IF(34<$C$20,0,$G$20*$D$20*(1+$C$27)*(1+$C$28)^2) -> 1616.6304 | AK45: =IF(35<$C$20,0,$G$20*$D$20*(1+$C$27)*(1+$C$28)^2) -> 1616.6304 | AL45: =IF(36<$C$20,0,$G$20*$D$20*(1+$C$27)*(1+$C$28)^2) -> 1616.6304 | AN45: =SUM(C45:N45) -> 0 | AO45: =SUM(O45:Z45) -> 0 | AP45: =SUM(AA45:AL45) -> 19399.565
A46: Head of Schools and Technical Education | B46: Institutional Partnerships | C46: =IF(1<$C$21,0,$E$21*$D$21*(1+$C$27)*(1+$C$28)^0) -> 0 | D46: =IF(2<$C$21,0,$E$21*$D$21*(1+$C$27)*(1+$C$28)^0) -> 0 | E46: =IF(3<$C$21,0,$E$21*$D$21*(1+$C$27)*(1+$C$28)^0) -> 0 | F46: =IF(4<$C$21,0,$E$21*$D$21*(1+$C$27)*(1+$C$28)^0) -> 0 | G46: =IF(5<$C$21,0,$E$21*$D$21*(1+$C$27)*(1+$C$28)^0) -> 0 | H46: =IF(6<$C$21,0,$E$21*$D$21*(1+$C$27)*(1+$C$28)^0) -> 0 | I46: =IF(7<$C$21,0,$E$21*$D$21*(1+$C$27)*(1+$C$28)^0) -> 0 | J46: =IF(8<$C$21,0,$E$21*$D$21*(1+$C$27)*(1+$C$28)^0) -> 0 | K46: =IF(9<$C$21,0,$E$21*$D$21*(1+$C$27)*(1+$C$28)^0) -> 0 | L46: =IF(10<$C$21,0,$E$21*$D$21*(1+$C$27)*(1+$C$28)^0) -> 0 | M46: =IF(11<$C$21,0,$E$21*$D$21*(1+$C$27)*(1+$C$28)^0) -> 0 | N46: =IF(12<$C$21,0,$E$21*$D$21*(1+$C$27)*(1+$C$28)^0) -> 0 | O46: =IF(13<$C$21,0,$F$21*$D$21*(1+$C$27)*(1+$C$28)^1) -> 0 | P46: =IF(14<$C$21,0,$F$21*$D$21*(1+$C$27)*(1+$C$28)^1) -> 0 | Q46: =IF(15<$C$21,0,$F$21*$D$21*(1+$C$27)*(1+$C$28)^1) -> 0 | R46: =IF(16<$C$21,0,$F$21*$D$21*(1+$C$27)*(1+$C$28)^1) -> 0 | S46: =IF(17<$C$21,0,$F$21*$D$21*(1+$C$27)*(1+$C$28)^1) -> 0 | T46: =IF(18<$C$21,0,$F$21*$D$21*(1+$C$27)*(1+$C$28)^1) -> 0 | U46: =IF(19<$C$21,0,$F$21*$D$21*(1+$C$27)*(1+$C$28)^1) -> 0 | V46: =IF(20<$C$21,0,$F$21*$D$21*(1+$C$27)*(1+$C$28)^1) -> 0 | W46: =IF(21<$C$21,0,$F$21*$D$21*(1+$C$27)*(1+$C$28)^1) -> 0 | X46: =IF(22<$C$21,0,$F$21*$D$21*(1+$C$27)*(1+$C$28)^1) -> 0 | Y46: =IF(23<$C$21,0,$F$21*$D$21*(1+$C$27)*(1+$C$28)^1) -> 0 | Z46: =IF(24<$C$21,0,$F$21*$D$21*(1+$C$27)*(1+$C$28)^1) -> 0 | AA46: =IF(25<$C$21,0,$G$21*$D$21*(1+$C$27)*(1+$C$28)^2) -> 0 | AB46: =IF(26<$C$21,0,$G$21*$D$21*(1+$C$27)*(1+$C$28)^2) -> 0 | AC46: =IF(27<$C$21,0,$G$21*$D$21*(1+$C$27)*(1+$C$28)^2) -> 0 | AD46: =IF(28<$C$21,0,$G$21*$D$21*(1+$C$27)*(1+$C$28)^2) -> 0 | AE46: =IF(29<$C$21,0,$G$21*$D$21*(1+$C$27)*(1+$C$28)^2) -> 0 | AF46: =IF(30<$C$21,0,$G$21*$D$21*(1+$C$27)*(1+$C$28)^2) -> 0 | AG46: =IF(31<$C$21,0,$G$21*$D$21*(1+$C$27)*(1+$C$28)^2) -> 0 | AH46: =IF(32<$C$21,0,$G$21*$D$21*(1+$C$27)*(1+$C$28)^2) -> 0 | AI46: =IF(33<$C$21,0,$G$21*$D$21*(1+$C$27)*(1+$C$28)^2) -> 0 | AJ46: =IF(34<$C$21,0,$G$21*$D$21*(1+$C$27)*(1+$C$28)^2) -> 0 | AK46: =IF(35<$C$21,0,$G$21*$D$21*(1+$C$27)*(1+$C$28)^2) -> 0 | AL46: =IF(36<$C$21,0,$G$21*$D$21*(1+$C$27)*(1+$C$28)^2) -> 0 | AN46: =SUM(C46:N46) -> 0 | AO46: =SUM(O46:Z46) -> 0 | AP46: =SUM(AA46:AL46) -> 0
A47: Account manager — renewals | B47: Institutional Partnerships | C47: =IF(1<$C$22,0,$E$22*$D$22*(1+$C$27)*(1+$C$28)^0) -> 0 | D47: =IF(2<$C$22,0,$E$22*$D$22*(1+$C$27)*(1+$C$28)^0) -> 0 | E47: =IF(3<$C$22,0,$E$22*$D$22*(1+$C$27)*(1+$C$28)^0) -> 0 | F47: =IF(4<$C$22,0,$E$22*$D$22*(1+$C$27)*(1+$C$28)^0) -> 0 | G47: =IF(5<$C$22,0,$E$22*$D$22*(1+$C$27)*(1+$C$28)^0) -> 0 | H47: =IF(6<$C$22,0,$E$22*$D$22*(1+$C$27)*(1+$C$28)^0) -> 0 | I47: =IF(7<$C$22,0,$E$22*$D$22*(1+$C$27)*(1+$C$28)^0) -> 0 | J47: =IF(8<$C$22,0,$E$22*$D$22*(1+$C$27)*(1+$C$28)^0) -> 0 | K47: =IF(9<$C$22,0,$E$22*$D$22*(1+$C$27)*(1+$C$28)^0) -> 0 | L47: =IF(10<$C$22,0,$E$22*$D$22*(1+$C$27)*(1+$C$28)^0) -> 0 | M47: =IF(11<$C$22,0,$E$22*$D$22*(1+$C$27)*(1+$C$28)^0) -> 0 | N47: =IF(12<$C$22,0,$E$22*$D$22*(1+$C$27)*(1+$C$28)^0) -> 0 | O47: =IF(13<$C$22,0,$F$22*$D$22*(1+$C$27)*(1+$C$28)^1) -> 0 | P47: =IF(14<$C$22,0,$F$22*$D$22*(1+$C$27)*(1+$C$28)^1) -> 0 | Q47: =IF(15<$C$22,0,$F$22*$D$22*(1+$C$27)*(1+$C$28)^1) -> 0 | R47: =IF(16<$C$22,0,$F$22*$D$22*(1+$C$27)*(1+$C$28)^1) -> 0 | S47: =IF(17<$C$22,0,$F$22*$D$22*(1+$C$27)*(1+$C$28)^1) -> 0 | T47: =IF(18<$C$22,0,$F$22*$D$22*(1+$C$27)*(1+$C$28)^1) -> 0 | U47: =IF(19<$C$22,0,$F$22*$D$22*(1+$C$27)*(1+$C$28)^1) -> 0 | V47: =IF(20<$C$22,0,$F$22*$D$22*(1+$C$27)*(1+$C$28)^1) -> 0 | W47: =IF(21<$C$22,0,$F$22*$D$22*(1+$C$27)*(1+$C$28)^1) -> 0 | X47: =IF(22<$C$22,0,$F$22*$D$22*(1+$C$27)*(1+$C$28)^1) -> 0 | Y47: =IF(23<$C$22,0,$F$22*$D$22*(1+$C$27)*(1+$C$28)^1) -> 0 | Z47: =IF(24<$C$22,0,$F$22*$D$22*(1+$C$27)*(1+$C$28)^1) -> 0 | AA47: =IF(25<$C$22,0,$G$22*$D$22*(1+$C$27)*(1+$C$28)^2) -> 0 | AB47: =IF(26<$C$22,0,$G$22*$D$22*(1+$C$27)*(1+$C$28)^2) -> 0 | AC47: =IF(27<$C$22,0,$G$22*$D$22*(1+$C$27)*(1+$C$28)^2) -> 0 | AD47: =IF(28<$C$22,0,$G$22*$D$22*(1+$C$27)*(1+$C$28)^2) -> 0 | AE47: =IF(29<$C$22,0,$G$22*$D$22*(1+$C$27)*(1+$C$28)^2) -> 0 | AF47: =IF(30<$C$22,0,$G$22*$D$22*(1+$C$27)*(1+$C$28)^2) -> 0 | AG47: =IF(31<$C$22,0,$G$22*$D$22*(1+$C$27)*(1+$C$28)^2) -> 0 | AH47: =IF(32<$C$22,0,$G$22*$D$22*(1+$C$27)*(1+$C$28)^2) -> 0 | AI47: =IF(33<$C$22,0,$G$22*$D$22*(1+$C$27)*(1+$C$28)^2) -> 0 | AJ47: =IF(34<$C$22,0,$G$22*$D$22*(1+$C$27)*(1+$C$28)^2) -> 0 | AK47: =IF(35<$C$22,0,$G$22*$D$22*(1+$C$27)*(1+$C$28)^2) -> 0 | AL47: =IF(36<$C$22,0,$G$22*$D$22*(1+$C$27)*(1+$C$28)^2) -> 0 | AN47: =SUM(C47:N47) -> 0 | AO47: =SUM(O47:Z47) -> 0 | AP47: =SUM(AA47:AL47) -> 0
A48: Head of Growth and Content | B48: Growth and Content | C48: =IF(1<$C$23,0,$E$23*$D$23*(1+$C$27)*(1+$C$28)^0) -> 2310 | D48: =IF(2<$C$23,0,$E$23*$D$23*(1+$C$27)*(1+$C$28)^0) -> 2310 | E48: =IF(3<$C$23,0,$E$23*$D$23*(1+$C$27)*(1+$C$28)^0) -> 2310 | F48: =IF(4<$C$23,0,$E$23*$D$23*(1+$C$27)*(1+$C$28)^0) -> 2310 | G48: =IF(5<$C$23,0,$E$23*$D$23*(1+$C$27)*(1+$C$28)^0) -> 2310 | H48: =IF(6<$C$23,0,$E$23*$D$23*(1+$C$27)*(1+$C$28)^0) -> 2310 | I48: =IF(7<$C$23,0,$E$23*$D$23*(1+$C$27)*(1+$C$28)^0) -> 2310 | J48: =IF(8<$C$23,0,$E$23*$D$23*(1+$C$27)*(1+$C$28)^0) -> 2310 | K48: =IF(9<$C$23,0,$E$23*$D$23*(1+$C$27)*(1+$C$28)^0) -> 2310 | L48: =IF(10<$C$23,0,$E$23*$D$23*(1+$C$27)*(1+$C$28)^0) -> 2310 | M48: =IF(11<$C$23,0,$E$23*$D$23*(1+$C$27)*(1+$C$28)^0) -> 2310 | N48: =IF(12<$C$23,0,$E$23*$D$23*(1+$C$27)*(1+$C$28)^0) -> 2310 | O48: =IF(13<$C$23,0,$F$23*$D$23*(1+$C$27)*(1+$C$28)^1) -> 2494.8 | P48: =IF(14<$C$23,0,$F$23*$D$23*(1+$C$27)*(1+$C$28)^1) -> 2494.8 | Q48: =IF(15<$C$23,0,$F$23*$D$23*(1+$C$27)*(1+$C$28)^1) -> 2494.8 | R48: =IF(16<$C$23,0,$F$23*$D$23*(1+$C$27)*(1+$C$28)^1) -> 2494.8 | S48: =IF(17<$C$23,0,$F$23*$D$23*(1+$C$27)*(1+$C$28)^1) -> 2494.8 | T48: =IF(18<$C$23,0,$F$23*$D$23*(1+$C$27)*(1+$C$28)^1) -> 2494.8 | U48: =IF(19<$C$23,0,$F$23*$D$23*(1+$C$27)*(1+$C$28)^1) -> 2494.8 | V48: =IF(20<$C$23,0,$F$23*$D$23*(1+$C$27)*(1+$C$28)^1) -> 2494.8 | W48: =IF(21<$C$23,0,$F$23*$D$23*(1+$C$27)*(1+$C$28)^1) -> 2494.8 | X48: =IF(22<$C$23,0,$F$23*$D$23*(1+$C$27)*(1+$C$28)^1) -> 2494.8 | Y48: =IF(23<$C$23,0,$F$23*$D$23*(1+$C$27)*(1+$C$28)^1) -> 2494.8 | Z48: =IF(24<$C$23,0,$F$23*$D$23*(1+$C$27)*(1+$C$28)^1) -> 2494.8 | AA48: =IF(25<$C$23,0,$G$23*$D$23*(1+$C$27)*(1+$C$28)^2) -> 2694.384 | AB48: =IF(26<$C$23,0,$G$23*$D$23*(1+$C$27)*(1+$C$28)^2) -> 2694.384 | AC48: =IF(27<$C$23,0,$G$23*$D$23*(1+$C$27)*(1+$C$28)^2) -> 2694.384 | AD48: =IF(28<$C$23,0,$G$23*$D$23*(1+$C$27)*(1+$C$28)^2) -> 2694.384 | AE48: =IF(29<$C$23,0,$G$23*$D$23*(1+$C$27)*(1+$C$28)^2) -> 2694.384 | AF48: =IF(30<$C$23,0,$G$23*$D$23*(1+$C$27)*(1+$C$28)^2) -> 2694.384 | AG48: =IF(31<$C$23,0,$G$23*$D$23*(1+$C$27)*(1+$C$28)^2) -> 2694.384 | AH48: =IF(32<$C$23,0,$G$23*$D$23*(1+$C$27)*(1+$C$28)^2) -> 2694.384 | AI48: =IF(33<$C$23,0,$G$23*$D$23*(1+$C$27)*(1+$C$28)^2) -> 2694.384 | AJ48: =IF(34<$C$23,0,$G$23*$D$23*(1+$C$27)*(1+$C$28)^2) -> 2694.384 | AK48: =IF(35<$C$23,0,$G$23*$D$23*(1+$C$27)*(1+$C$28)^2) -> 2694.384 | AL48: =IF(36<$C$23,0,$G$23*$D$23*(1+$C$27)*(1+$C$28)^2) -> 2694.384 | AN48: =SUM(C48:N48) -> 27720 | AO48: =SUM(O48:Z48) -> 29937.6 | AP48: =SUM(AA48:AL48) -> 32332.608
A49: Student success (bilingual) | B49: Growth and Content | C49: =IF(1<$C$24,0,$E$24*$D$24*(1+$C$27)*(1+$C$28)^0) -> 0 | D49: =IF(2<$C$24,0,$E$24*$D$24*(1+$C$27)*(1+$C$28)^0) -> 0 | E49: =IF(3<$C$24,0,$E$24*$D$24*(1+$C$27)*(1+$C$28)^0) -> 0 | F49: =IF(4<$C$24,0,$E$24*$D$24*(1+$C$27)*(1+$C$28)^0) -> 0 | G49: =IF(5<$C$24,0,$E$24*$D$24*(1+$C$27)*(1+$C$28)^0) -> 0 | H49: =IF(6<$C$24,0,$E$24*$D$24*(1+$C$27)*(1+$C$28)^0) -> 0 | I49: =IF(7<$C$24,0,$E$24*$D$24*(1+$C$27)*(1+$C$28)^0) -> 0 | J49: =IF(8<$C$24,0,$E$24*$D$24*(1+$C$27)*(1+$C$28)^0) -> 0 | K49: =IF(9<$C$24,0,$E$24*$D$24*(1+$C$27)*(1+$C$28)^0) -> 0 | L49: =IF(10<$C$24,0,$E$24*$D$24*(1+$C$27)*(1+$C$28)^0) -> 0 | M49: =IF(11<$C$24,0,$E$24*$D$24*(1+$C$27)*(1+$C$28)^0) -> 0 | N49: =IF(12<$C$24,0,$E$24*$D$24*(1+$C$27)*(1+$C$28)^0) -> 0 | O49: =IF(13<$C$24,0,$F$24*$D$24*(1+$C$27)*(1+$C$28)^1) -> 0 | P49: =IF(14<$C$24,0,$F$24*$D$24*(1+$C$27)*(1+$C$28)^1) -> 0 | Q49: =IF(15<$C$24,0,$F$24*$D$24*(1+$C$27)*(1+$C$28)^1) -> 0 | R49: =IF(16<$C$24,0,$F$24*$D$24*(1+$C$27)*(1+$C$28)^1) -> 0 | S49: =IF(17<$C$24,0,$F$24*$D$24*(1+$C$27)*(1+$C$28)^1) -> 0 | T49: =IF(18<$C$24,0,$F$24*$D$24*(1+$C$27)*(1+$C$28)^1) -> 0 | U49: =IF(19<$C$24,0,$F$24*$D$24*(1+$C$27)*(1+$C$28)^1) -> 0 | V49: =IF(20<$C$24,0,$F$24*$D$24*(1+$C$27)*(1+$C$28)^1) -> 0 | W49: =IF(21<$C$24,0,$F$24*$D$24*(1+$C$27)*(1+$C$28)^1) -> 0 | X49: =IF(22<$C$24,0,$F$24*$D$24*(1+$C$27)*(1+$C$28)^1) -> 0 | Y49: =IF(23<$C$24,0,$F$24*$D$24*(1+$C$27)*(1+$C$28)^1) -> 0 | Z49: =IF(24<$C$24,0,$F$24*$D$24*(1+$C$27)*(1+$C$28)^1) -> 0 | AA49: =IF(25<$C$24,0,$G$24*$D$24*(1+$C$27)*(1+$C$28)^2) -> 0 | AB49: =IF(26<$C$24,0,$G$24*$D$24*(1+$C$27)*(1+$C$28)^2) -> 0 | AC49: =IF(27<$C$24,0,$G$24*$D$24*(1+$C$27)*(1+$C$28)^2) -> 0 | AD49: =IF(28<$C$24,0,$G$24*$D$24*(1+$C$27)*(1+$C$28)^2) -> 0 | AE49: =IF(29<$C$24,0,$G$24*$D$24*(1+$C$27)*(1+$C$28)^2) -> 0 | AF49: =IF(30<$C$24,0,$G$24*$D$24*(1+$C$27)*(1+$C$28)^2) -> 0 | AG49: =IF(31<$C$24,0,$G$24*$D$24*(1+$C$27)*(1+$C$28)^2) -> 0 | AH49: =IF(32<$C$24,0,$G$24*$D$24*(1+$C$27)*(1+$C$28)^2) -> 0 | AI49: =IF(33<$C$24,0,$G$24*$D$24*(1+$C$27)*(1+$C$28)^2) -> 0 | AJ49: =IF(34<$C$24,0,$G$24*$D$24*(1+$C$27)*(1+$C$28)^2) -> 0 | AK49: =IF(35<$C$24,0,$G$24*$D$24*(1+$C$27)*(1+$C$28)^2) -> 0 | AL49: =IF(36<$C$24,0,$G$24*$D$24*(1+$C$27)*(1+$C$28)^2) -> 0 | AN49: =SUM(C49:N49) -> 0 | AO49: =SUM(O49:Z49) -> 0 | AP49: =SUM(AA49:AL49) -> 0
A50: Total payroll | B50: fully loaded, all roles | C50: =SUM(C32:C49) -> 17325 | D50: =SUM(D32:D49) -> 17325 | E50: =SUM(E32:E49) -> 17325 | F50: =SUM(F32:F49) -> 17325 | G50: =SUM(G32:G49) -> 17325 | H50: =SUM(H32:H49) -> 17325 | I50: =SUM(I32:I49) -> 17325 | J50: =SUM(J32:J49) -> 17325 | ... AL50: =SUM(AL32:AL49) -> 40011.602 | AN50: =SUM(C50:N50) -> 207900 | AO50: =SUM(O50:Z50) -> 365238.72 | AP50: =SUM(AA50:AL50) -> 480139.23
A52: MONTHLY HEADCOUNT
A53: Line item | B53: Driver / source | C53: Oct 26 | D53: Nov 26 | E53: Dec 26 | F53: Jan 26 | G53: Feb 26 | H53: Mar 26 | I53: Apr 26 | J53: May 26 | K53: Jun 26 | L53: Jul 27 | M53: Aug 27 | N53: Sep 27 | O53: Oct 27 | P53: Nov 27 | Q53: Dec 27 | R53: Jan 27 | S53: Feb 27 | T53: Mar 27 | U53: Apr 27 | V53: May 27 | W53: Jun 27 | X53: Jul 28 | Y53: Aug 28 | Z53: Sep 28 | AA53: Oct 28 | AB53: Nov 28 | AC53: Dec 28 | AD53: Jan 28 | AE53: Feb 28 | AF53: Mar 28 | AG53: Apr 28 | AH53: May 28 | AI53: Jun 28 | AJ53: Jul 29 | AK53: Aug 29 | AL53: Sep 29 | AN53: YEAR 1 | AO53: YEAR 2 | AP53: YEAR 3
A54: Chief Executive Officer | B54: Leadership | C54: =IF(1<$C$7,0,$E$7) -> 1 | D54: =IF(2<$C$7,0,$E$7) -> 1 | E54: =IF(3<$C$7,0,$E$7) -> 1 | F54: =IF(4<$C$7,0,$E$7) -> 1 | G54: =IF(5<$C$7,0,$E$7) -> 1 | H54: =IF(6<$C$7,0,$E$7) -> 1 | I54: =IF(7<$C$7,0,$E$7) -> 1 | J54: =IF(8<$C$7,0,$E$7) -> 1 | K54: =IF(9<$C$7,0,$E$7) -> 1 | L54: =IF(10<$C$7,0,$E$7) -> 1 | M54: =IF(11<$C$7,0,$E$7) -> 1 | N54: =IF(12<$C$7,0,$E$7) -> 1 | O54: =IF(13<$C$7,0,$F$7) -> 1 | P54: =IF(14<$C$7,0,$F$7) -> 1 | Q54: =IF(15<$C$7,0,$F$7) -> 1 | R54: =IF(16<$C$7,0,$F$7) -> 1 | S54: =IF(17<$C$7,0,$F$7) -> 1 | T54: =IF(18<$C$7,0,$F$7) -> 1 | U54: =IF(19<$C$7,0,$F$7) -> 1 | V54: =IF(20<$C$7,0,$F$7) -> 1 | W54: =IF(21<$C$7,0,$F$7) -> 1 | X54: =IF(22<$C$7,0,$F$7) -> 1 | Y54: =IF(23<$C$7,0,$F$7) -> 1 | Z54: =IF(24<$C$7,0,$F$7) -> 1 | AA54: =IF(25<$C$7,0,$G$7) -> 1 | AB54: =IF(26<$C$7,0,$G$7) -> 1 | AC54: =IF(27<$C$7,0,$G$7) -> 1 | AD54: =IF(28<$C$7,0,$G$7) -> 1 | AE54: =IF(29<$C$7,0,$G$7) -> 1 | AF54: =IF(30<$C$7,0,$G$7) -> 1 | AG54: =IF(31<$C$7,0,$G$7) -> 1 | AH54: =IF(32<$C$7,0,$G$7) -> 1 | AI54: =IF(33<$C$7,0,$G$7) -> 1 | AJ54: =IF(34<$C$7,0,$G$7) -> 1 | AK54: =IF(35<$C$7,0,$G$7) -> 1 | AL54: =IF(36<$C$7,0,$G$7) -> 1 | AN54: =N54 -> 1 | AO54: =Z54 -> 1 | AP54: =AL54 -> 1
A55: Chief Technology Officer | B55: Leadership | C55: =IF(1<$C$8,0,$E$8) -> 1 | D55: =IF(2<$C$8,0,$E$8) -> 1 | E55: =IF(3<$C$8,0,$E$8) -> 1 | F55: =IF(4<$C$8,0,$E$8) -> 1 | G55: =IF(5<$C$8,0,$E$8) -> 1 | H55: =IF(6<$C$8,0,$E$8) -> 1 | I55: =IF(7<$C$8,0,$E$8) -> 1 | J55: =IF(8<$C$8,0,$E$8) -> 1 | K55: =IF(9<$C$8,0,$E$8) -> 1 | L55: =IF(10<$C$8,0,$E$8) -> 1 | M55: =IF(11<$C$8,0,$E$8) -> 1 | N55: =IF(12<$C$8,0,$E$8) -> 1 | O55: =IF(13<$C$8,0,$F$8) -> 1 | P55: =IF(14<$C$8,0,$F$8) -> 1 | Q55: =IF(15<$C$8,0,$F$8) -> 1 | R55: =IF(16<$C$8,0,$F$8) -> 1 | S55: =IF(17<$C$8,0,$F$8) -> 1 | T55: =IF(18<$C$8,0,$F$8) -> 1 | U55: =IF(19<$C$8,0,$F$8) -> 1 | V55: =IF(20<$C$8,0,$F$8) -> 1 | W55: =IF(21<$C$8,0,$F$8) -> 1 | X55: =IF(22<$C$8,0,$F$8) -> 1 | Y55: =IF(23<$C$8,0,$F$8) -> 1 | Z55: =IF(24<$C$8,0,$F$8) -> 1 | AA55: =IF(25<$C$8,0,$G$8) -> 1 | AB55: =IF(26<$C$8,0,$G$8) -> 1 | AC55: =IF(27<$C$8,0,$G$8) -> 1 | AD55: =IF(28<$C$8,0,$G$8) -> 1 | AE55: =IF(29<$C$8,0,$G$8) -> 1 | AF55: =IF(30<$C$8,0,$G$8) -> 1 | AG55: =IF(31<$C$8,0,$G$8) -> 1 | AH55: =IF(32<$C$8,0,$G$8) -> 1 | AI55: =IF(33<$C$8,0,$G$8) -> 1 | AJ55: =IF(34<$C$8,0,$G$8) -> 1 | AK55: =IF(35<$C$8,0,$G$8) -> 1 | AL55: =IF(36<$C$8,0,$G$8) -> 1 | AN55: =N55 -> 1 | AO55: =Z55 -> 1 | AP55: =AL55 -> 1
A56: Chief Operating Officer | B56: Leadership | C56: =IF(1<$C$9,0,$E$9) -> 0 | D56: =IF(2<$C$9,0,$E$9) -> 0 | E56: =IF(3<$C$9,0,$E$9) -> 0 | F56: =IF(4<$C$9,0,$E$9) -> 0 | G56: =IF(5<$C$9,0,$E$9) -> 0 | H56: =IF(6<$C$9,0,$E$9) -> 0 | I56: =IF(7<$C$9,0,$E$9) -> 0 | J56: =IF(8<$C$9,0,$E$9) -> 0 | K56: =IF(9<$C$9,0,$E$9) -> 0 | L56: =IF(10<$C$9,0,$E$9) -> 0 | M56: =IF(11<$C$9,0,$E$9) -> 0 | N56: =IF(12<$C$9,0,$E$9) -> 0 | O56: =IF(13<$C$9,0,$F$9) -> 0 | P56: =IF(14<$C$9,0,$F$9) -> 0 | Q56: =IF(15<$C$9,0,$F$9) -> 0 | R56: =IF(16<$C$9,0,$F$9) -> 0 | S56: =IF(17<$C$9,0,$F$9) -> 0 | T56: =IF(18<$C$9,0,$F$9) -> 0 | U56: =IF(19<$C$9,0,$F$9) -> 0 | V56: =IF(20<$C$9,0,$F$9) -> 0 | W56: =IF(21<$C$9,0,$F$9) -> 0 | X56: =IF(22<$C$9,0,$F$9) -> 0 | Y56: =IF(23<$C$9,0,$F$9) -> 0 | Z56: =IF(24<$C$9,0,$F$9) -> 0 | AA56: =IF(25<$C$9,0,$G$9) -> 0 | AB56: =IF(26<$C$9,0,$G$9) -> 0 | AC56: =IF(27<$C$9,0,$G$9) -> 0 | AD56: =IF(28<$C$9,0,$G$9) -> 0 | AE56: =IF(29<$C$9,0,$G$9) -> 0 | AF56: =IF(30<$C$9,0,$G$9) -> 0 | AG56: =IF(31<$C$9,0,$G$9) -> 0 | AH56: =IF(32<$C$9,0,$G$9) -> 0 | AI56: =IF(33<$C$9,0,$G$9) -> 0 | AJ56: =IF(34<$C$9,0,$G$9) -> 0 | AK56: =IF(35<$C$9,0,$G$9) -> 0 | AL56: =IF(36<$C$9,0,$G$9) -> 0 | AN56: =N56 -> 0 | AO56: =Z56 -> 0 | AP56: =AL56 -> 0
A57: Senior full-stack engineer | B57: Product and Engineering | C57: =IF(1<$C$10,0,$E$10) -> 1 | D57: =IF(2<$C$10,0,$E$10) -> 1 | E57: =IF(3<$C$10,0,$E$10) -> 1 | F57: =IF(4<$C$10,0,$E$10) -> 1 | G57: =IF(5<$C$10,0,$E$10) -> 1 | H57: =IF(6<$C$10,0,$E$10) -> 1 | I57: =IF(7<$C$10,0,$E$10) -> 1 | J57: =IF(8<$C$10,0,$E$10) -> 1 | K57: =IF(9<$C$10,0,$E$10) -> 1 | L57: =IF(10<$C$10,0,$E$10) -> 1 | M57: =IF(11<$C$10,0,$E$10) -> 1 | N57: =IF(12<$C$10,0,$E$10) -> 1 | O57: =IF(13<$C$10,0,$F$10) -> 2 | P57: =IF(14<$C$10,0,$F$10) -> 2 | Q57: =IF(15<$C$10,0,$F$10) -> 2 | R57: =IF(16<$C$10,0,$F$10) -> 2 | S57: =IF(17<$C$10,0,$F$10) -> 2 | T57: =IF(18<$C$10,0,$F$10) -> 2 | U57: =IF(19<$C$10,0,$F$10) -> 2 | V57: =IF(20<$C$10,0,$F$10) -> 2 | W57: =IF(21<$C$10,0,$F$10) -> 2 | X57: =IF(22<$C$10,0,$F$10) -> 2 | Y57: =IF(23<$C$10,0,$F$10) -> 2 | Z57: =IF(24<$C$10,0,$F$10) -> 2 | AA57: =IF(25<$C$10,0,$G$10) -> 2 | AB57: =IF(26<$C$10,0,$G$10) -> 2 | AC57: =IF(27<$C$10,0,$G$10) -> 2 | AD57: =IF(28<$C$10,0,$G$10) -> 2 | AE57: =IF(29<$C$10,0,$G$10) -> 2 | AF57: =IF(30<$C$10,0,$G$10) -> 2 | AG57: =IF(31<$C$10,0,$G$10) -> 2 | AH57: =IF(32<$C$10,0,$G$10) -> 2 | AI57: =IF(33<$C$10,0,$G$10) -> 2 | AJ57: =IF(34<$C$10,0,$G$10) -> 2 | AK57: =IF(35<$C$10,0,$G$10) -> 2 | AL57: =IF(36<$C$10,0,$G$10) -> 2 | AN57: =N57 -> 1 | AO57: =Z57 -> 2 | AP57: =AL57 -> 2
A58: AI and data engineer | B58: Product and Engineering | C58: =IF(1<$C$11,0,$E$11) -> 0 | D58: =IF(2<$C$11,0,$E$11) -> 0 | E58: =IF(3<$C$11,0,$E$11) -> 0 | F58: =IF(4<$C$11,0,$E$11) -> 0 | G58: =IF(5<$C$11,0,$E$11) -> 0 | H58: =IF(6<$C$11,0,$E$11) -> 0 | I58: =IF(7<$C$11,0,$E$11) -> 0 | J58: =IF(8<$C$11,0,$E$11) -> 0 | K58: =IF(9<$C$11,0,$E$11) -> 0 | L58: =IF(10<$C$11,0,$E$11) -> 0 | M58: =IF(11<$C$11,0,$E$11) -> 0 | N58: =IF(12<$C$11,0,$E$11) -> 0 | O58: =IF(13<$C$11,0,$F$11) -> 0 | P58: =IF(14<$C$11,0,$F$11) -> 0 | Q58: =IF(15<$C$11,0,$F$11) -> 0 | R58: =IF(16<$C$11,0,$F$11) -> 0 | S58: =IF(17<$C$11,0,$F$11) -> 0 | T58: =IF(18<$C$11,0,$F$11) -> 0 | U58: =IF(19<$C$11,0,$F$11) -> 0 | V58: =IF(20<$C$11,0,$F$11) -> 0 | W58: =IF(21<$C$11,0,$F$11) -> 0 | X58: =IF(22<$C$11,0,$F$11) -> 0 | Y58: =IF(23<$C$11,0,$F$11) -> 0 | Z58: =IF(24<$C$11,0,$F$11) -> 0 | AA58: =IF(25<$C$11,0,$G$11) -> 0 | AB58: =IF(26<$C$11,0,$G$11) -> 0 | AC58: =IF(27<$C$11,0,$G$11) -> 0 | AD58: =IF(28<$C$11,0,$G$11) -> 0 | AE58: =IF(29<$C$11,0,$G$11) -> 0 | AF58: =IF(30<$C$11,0,$G$11) -> 0 | AG58: =IF(31<$C$11,0,$G$11) -> 0 | AH58: =IF(32<$C$11,0,$G$11) -> 0 | AI58: =IF(33<$C$11,0,$G$11) -> 0 | AJ58: =IF(34<$C$11,0,$G$11) -> 0 | AK58: =IF(35<$C$11,0,$G$11) -> 0 | AL58: =IF(36<$C$11,0,$G$11) -> 0 | AN58: =N58 -> 0 | AO58: =Z58 -> 0 | AP58: =AL58 -> 0
A59: Product designer | B59: Product and Engineering | C59: =IF(1<$C$12,0,$E$12) -> 0 | D59: =IF(2<$C$12,0,$E$12) -> 0 | E59: =IF(3<$C$12,0,$E$12) -> 0 | F59: =IF(4<$C$12,0,$E$12) -> 0 | G59: =IF(5<$C$12,0,$E$12) -> 0 | H59: =IF(6<$C$12,0,$E$12) -> 0 | I59: =IF(7<$C$12,0,$E$12) -> 0 | J59: =IF(8<$C$12,0,$E$12) -> 0 | K59: =IF(9<$C$12,0,$E$12) -> 0 | L59: =IF(10<$C$12,0,$E$12) -> 0 | M59: =IF(11<$C$12,0,$E$12) -> 0 | N59: =IF(12<$C$12,0,$E$12) -> 0 | O59: =IF(13<$C$12,0,$F$12) -> 0 | P59: =IF(14<$C$12,0,$F$12) -> 0 | Q59: =IF(15<$C$12,0,$F$12) -> 0 | R59: =IF(16<$C$12,0,$F$12) -> 0 | S59: =IF(17<$C$12,0,$F$12) -> 0 | T59: =IF(18<$C$12,0,$F$12) -> 0 | U59: =IF(19<$C$12,0,$F$12) -> 0 | V59: =IF(20<$C$12,0,$F$12) -> 0 | W59: =IF(21<$C$12,0,$F$12) -> 0 | X59: =IF(22<$C$12,0,$F$12) -> 0 | Y59: =IF(23<$C$12,0,$F$12) -> 0 | Z59: =IF(24<$C$12,0,$F$12) -> 0 | AA59: =IF(25<$C$12,0,$G$12) -> 0 | AB59: =IF(26<$C$12,0,$G$12) -> 0 | AC59: =IF(27<$C$12,0,$G$12) -> 0 | AD59: =IF(28<$C$12,0,$G$12) -> 0 | AE59: =IF(29<$C$12,0,$G$12) -> 0 | AF59: =IF(30<$C$12,0,$G$12) -> 0 | AG59: =IF(31<$C$12,0,$G$12) -> 0 | AH59: =IF(32<$C$12,0,$G$12) -> 0 | AI59: =IF(33<$C$12,0,$G$12) -> 0 | AJ59: =IF(34<$C$12,0,$G$12) -> 0 | AK59: =IF(35<$C$12,0,$G$12) -> 0 | AL59: =IF(36<$C$12,0,$G$12) -> 0 | AN59: =N59 -> 0 | AO59: =Z59 -> 0 | AP59: =AL59 -> 0
A60: Head of Curriculum and Certification | B60: Curriculum and Delivery | C60: =IF(1<$C$13,0,$E$13) -> 1 | D60: =IF(2<$C$13,0,$E$13) -> 1 | E60: =IF(3<$C$13,0,$E$13) -> 1 | F60: =IF(4<$C$13,0,$E$13) -> 1 | G60: =IF(5<$C$13,0,$E$13) -> 1 | H60: =IF(6<$C$13,0,$E$13) -> 1 | I60: =IF(7<$C$13,0,$E$13) -> 1 | J60: =IF(8<$C$13,0,$E$13) -> 1 | K60: =IF(9<$C$13,0,$E$13) -> 1 | L60: =IF(10<$C$13,0,$E$13) -> 1 | M60: =IF(11<$C$13,0,$E$13) -> 1 | N60: =IF(12<$C$13,0,$E$13) -> 1 | O60: =IF(13<$C$13,0,$F$13) -> 1 | P60: =IF(14<$C$13,0,$F$13) -> 1 | Q60: =IF(15<$C$13,0,$F$13) -> 1 | R60: =IF(16<$C$13,0,$F$13) -> 1 | S60: =IF(17<$C$13,0,$F$13) -> 1 | T60: =IF(18<$C$13,0,$F$13) -> 1 | U60: =IF(19<$C$13,0,$F$13) -> 1 | V60: =IF(20<$C$13,0,$F$13) -> 1 | W60: =IF(21<$C$13,0,$F$13) -> 1 | X60: =IF(22<$C$13,0,$F$13) -> 1 | Y60: =IF(23<$C$13,0,$F$13) -> 1 | Z60: =IF(24<$C$13,0,$F$13) -> 1 | AA60: =IF(25<$C$13,0,$G$13) -> 1 | AB60: =IF(26<$C$13,0,$G$13) -> 1 | AC60: =IF(27<$C$13,0,$G$13) -> 1 | AD60: =IF(28<$C$13,0,$G$13) -> 1 | AE60: =IF(29<$C$13,0,$G$13) -> 1 | AF60: =IF(30<$C$13,0,$G$13) -> 1 | AG60: =IF(31<$C$13,0,$G$13) -> 1 | AH60: =IF(32<$C$13,0,$G$13) -> 1 | AI60: =IF(33<$C$13,0,$G$13) -> 1 | AJ60: =IF(34<$C$13,0,$G$13) -> 1 | AK60: =IF(35<$C$13,0,$G$13) -> 1 | AL60: =IF(36<$C$13,0,$G$13) -> 1 | AN60: =N60 -> 1 | AO60: =Z60 -> 1 | AP60: =AL60 -> 1
A61: Partner network manager | B61: Curriculum and Delivery | C61: =IF(1<$C$14,0,$E$14) -> 0 | D61: =IF(2<$C$14,0,$E$14) -> 0 | E61: =IF(3<$C$14,0,$E$14) -> 0 | F61: =IF(4<$C$14,0,$E$14) -> 0 | G61: =IF(5<$C$14,0,$E$14) -> 0 | H61: =IF(6<$C$14,0,$E$14) -> 0 | I61: =IF(7<$C$14,0,$E$14) -> 0 | J61: =IF(8<$C$14,0,$E$14) -> 0 | K61: =IF(9<$C$14,0,$E$14) -> 0 | L61: =IF(10<$C$14,0,$E$14) -> 0 | M61: =IF(11<$C$14,0,$E$14) -> 0 | N61: =IF(12<$C$14,0,$E$14) -> 0 | O61: =IF(13<$C$14,0,$F$14) -> 1 | P61: =IF(14<$C$14,0,$F$14) -> 1 | Q61: =IF(15<$C$14,0,$F$14) -> 1 | R61: =IF(16<$C$14,0,$F$14) -> 1 | S61: =IF(17<$C$14,0,$F$14) -> 1 | T61: =IF(18<$C$14,0,$F$14) -> 1 | U61: =IF(19<$C$14,0,$F$14) -> 1 | V61: =IF(20<$C$14,0,$F$14) -> 1 | W61: =IF(21<$C$14,0,$F$14) -> 1 | X61: =IF(22<$C$14,0,$F$14) -> 1 | Y61: =IF(23<$C$14,0,$F$14) -> 1 | Z61: =IF(24<$C$14,0,$F$14) -> 1 | AA61: =IF(25<$C$14,0,$G$14) -> 1 | AB61: =IF(26<$C$14,0,$G$14) -> 1 | AC61: =IF(27<$C$14,0,$G$14) -> 1 | AD61: =IF(28<$C$14,0,$G$14) -> 1 | AE61: =IF(29<$C$14,0,$G$14) -> 1 | AF61: =IF(30<$C$14,0,$G$14) -> 1 | AG61: =IF(31<$C$14,0,$G$14) -> 1 | AH61: =IF(32<$C$14,0,$G$14) -> 1 | AI61: =IF(33<$C$14,0,$G$14) -> 1 | AJ61: =IF(34<$C$14,0,$G$14) -> 1 | AK61: =IF(35<$C$14,0,$G$14) -> 1 | AL61: =IF(36<$C$14,0,$G$14) -> 1 | AN61: =N61 -> 0 | AO61: =Z61 -> 1 | AP61: =AL61 -> 1
A62: Programme delivery coordinator | B62: Curriculum and Delivery | C62: =IF(1<$C$15,0,$E$15) -> 0 | D62: =IF(2<$C$15,0,$E$15) -> 0 | E62: =IF(3<$C$15,0,$E$15) -> 0 | F62: =IF(4<$C$15,0,$E$15) -> 0 | G62: =IF(5<$C$15,0,$E$15) -> 0 | H62: =IF(6<$C$15,0,$E$15) -> 0 | I62: =IF(7<$C$15,0,$E$15) -> 0 | J62: =IF(8<$C$15,0,$E$15) -> 0 | K62: =IF(9<$C$15,0,$E$15) -> 0 | L62: =IF(10<$C$15,0,$E$15) -> 0 | M62: =IF(11<$C$15,0,$E$15) -> 0 | N62: =IF(12<$C$15,0,$E$15) -> 0 | O62: =IF(13<$C$15,0,$F$15) -> 0 | P62: =IF(14<$C$15,0,$F$15) -> 0 | Q62: =IF(15<$C$15,0,$F$15) -> 0 | R62: =IF(16<$C$15,0,$F$15) -> 0 | S62: =IF(17<$C$15,0,$F$15) -> 0 | T62: =IF(18<$C$15,0,$F$15) -> 0 | U62: =IF(19<$C$15,0,$F$15) -> 0 | V62: =IF(20<$C$15,0,$F$15) -> 0 | W62: =IF(21<$C$15,0,$F$15) -> 0 | X62: =IF(22<$C$15,0,$F$15) -> 0 | Y62: =IF(23<$C$15,0,$F$15) -> 0 | Z62: =IF(24<$C$15,0,$F$15) -> 0 | AA62: =IF(25<$C$15,0,$G$15) -> 1 | AB62: =IF(26<$C$15,0,$G$15) -> 1 | AC62: =IF(27<$C$15,0,$G$15) -> 1 | AD62: =IF(28<$C$15,0,$G$15) -> 1 | AE62: =IF(29<$C$15,0,$G$15) -> 1 | AF62: =IF(30<$C$15,0,$G$15) -> 1 | AG62: =IF(31<$C$15,0,$G$15) -> 1 | AH62: =IF(32<$C$15,0,$G$15) -> 1 | AI62: =IF(33<$C$15,0,$G$15) -> 1 | AJ62: =IF(34<$C$15,0,$G$15) -> 1 | AK62: =IF(35<$C$15,0,$G$15) -> 1 | AL62: =IF(36<$C$15,0,$G$15) -> 1 | AN62: =N62 -> 0 | AO62: =Z62 -> 0 | AP62: =AL62 -> 1
A63: Bilingual curriculum producer | B63: Curriculum and Delivery | C63: =IF(1<$C$16,0,$E$16) -> 0 | D63: =IF(2<$C$16,0,$E$16) -> 0 | E63: =IF(3<$C$16,0,$E$16) -> 0 | F63: =IF(4<$C$16,0,$E$16) -> 0 | G63: =IF(5<$C$16,0,$E$16) -> 0 | H63: =IF(6<$C$16,0,$E$16) -> 0 | I63: =IF(7<$C$16,0,$E$16) -> 0 | J63: =IF(8<$C$16,0,$E$16) -> 0 | K63: =IF(9<$C$16,0,$E$16) -> 0 | L63: =IF(10<$C$16,0,$E$16) -> 0 | M63: =IF(11<$C$16,0,$E$16) -> 0 | N63: =IF(12<$C$16,0,$E$16) -> 0 | O63: =IF(13<$C$16,0,$F$16) -> 0 | P63: =IF(14<$C$16,0,$F$16) -> 0 | Q63: =IF(15<$C$16,0,$F$16) -> 0 | R63: =IF(16<$C$16,0,$F$16) -> 0 | S63: =IF(17<$C$16,0,$F$16) -> 0 | T63: =IF(18<$C$16,0,$F$16) -> 0 | U63: =IF(19<$C$16,0,$F$16) -> 0 | V63: =IF(20<$C$16,0,$F$16) -> 0 | W63: =IF(21<$C$16,0,$F$16) -> 0 | X63: =IF(22<$C$16,0,$F$16) -> 0 | Y63: =IF(23<$C$16,0,$F$16) -> 0 | Z63: =IF(24<$C$16,0,$F$16) -> 0 | AA63: =IF(25<$C$16,0,$G$16) -> 0 | AB63: =IF(26<$C$16,0,$G$16) -> 0 | AC63: =IF(27<$C$16,0,$G$16) -> 0 | AD63: =IF(28<$C$16,0,$G$16) -> 0 | AE63: =IF(29<$C$16,0,$G$16) -> 0 | AF63: =IF(30<$C$16,0,$G$16) -> 0 | AG63: =IF(31<$C$16,0,$G$16) -> 0 | AH63: =IF(32<$C$16,0,$G$16) -> 0 | AI63: =IF(33<$C$16,0,$G$16) -> 0 | AJ63: =IF(34<$C$16,0,$G$16) -> 0 | AK63: =IF(35<$C$16,0,$G$16) -> 0 | AL63: =IF(36<$C$16,0,$G$16) -> 0 | AN63: =N63 -> 0 | AO63: =Z63 -> 0 | AP63: =AL63 -> 0
A64: Head of Partnerships — Egypt | B64: Institutional Partnerships | C64: =IF(1<$C$17,0,$E$17) -> 1 | D64: =IF(2<$C$17,0,$E$17) -> 1 | E64: =IF(3<$C$17,0,$E$17) -> 1 | F64: =IF(4<$C$17,0,$E$17) -> 1 | G64: =IF(5<$C$17,0,$E$17) -> 1 | H64: =IF(6<$C$17,0,$E$17) -> 1 | I64: =IF(7<$C$17,0,$E$17) -> 1 | J64: =IF(8<$C$17,0,$E$17) -> 1 | K64: =IF(9<$C$17,0,$E$17) -> 1 | L64: =IF(10<$C$17,0,$E$17) -> 1 | M64: =IF(11<$C$17,0,$E$17) -> 1 | N64: =IF(12<$C$17,0,$E$17) -> 1 | O64: =IF(13<$C$17,0,$F$17) -> 1 | P64: =IF(14<$C$17,0,$F$17) -> 1 | Q64: =IF(15<$C$17,0,$F$17) -> 1 | R64: =IF(16<$C$17,0,$F$17) -> 1 | S64: =IF(17<$C$17,0,$F$17) -> 1 | T64: =IF(18<$C$17,0,$F$17) -> 1 | U64: =IF(19<$C$17,0,$F$17) -> 1 | V64: =IF(20<$C$17,0,$F$17) -> 1 | W64: =IF(21<$C$17,0,$F$17) -> 1 | X64: =IF(22<$C$17,0,$F$17) -> 1 | Y64: =IF(23<$C$17,0,$F$17) -> 1 | Z64: =IF(24<$C$17,0,$F$17) -> 1 | AA64: =IF(25<$C$17,0,$G$17) -> 1 | AB64: =IF(26<$C$17,0,$G$17) -> 1 | AC64: =IF(27<$C$17,0,$G$17) -> 1 | AD64: =IF(28<$C$17,0,$G$17) -> 1 | AE64: =IF(29<$C$17,0,$G$17) -> 1 | AF64: =IF(30<$C$17,0,$G$17) -> 1 | AG64: =IF(31<$C$17,0,$G$17) -> 1 | AH64: =IF(32<$C$17,0,$G$17) -> 1 | AI64: =IF(33<$C$17,0,$G$17) -> 1 | AJ64: =IF(34<$C$17,0,$G$17) -> 1 | AK64: =IF(35<$C$17,0,$G$17) -> 1 | AL64: =IF(36<$C$17,0,$G$17) -> 1 | AN64: =N64 -> 1 | AO64: =Z64 -> 1 | AP64: =AL64 -> 1
A65: Country Manager — KSA (Riyadh) | B65: Institutional Partnerships | C65: =IF(1<$C$18,0,$E$18) -> 0 | D65: =IF(2<$C$18,0,$E$18) -> 0 | E65: =IF(3<$C$18,0,$E$18) -> 0 | F65: =IF(4<$C$18,0,$E$18) -> 0 | G65: =IF(5<$C$18,0,$E$18) -> 0 | H65: =IF(6<$C$18,0,$E$18) -> 0 | I65: =IF(7<$C$18,0,$E$18) -> 0 | J65: =IF(8<$C$18,0,$E$18) -> 0 | K65: =IF(9<$C$18,0,$E$18) -> 0 | L65: =IF(10<$C$18,0,$E$18) -> 0 | M65: =IF(11<$C$18,0,$E$18) -> 0 | N65: =IF(12<$C$18,0,$E$18) -> 0 | O65: =IF(13<$C$18,0,$F$18) -> 1 | P65: =IF(14<$C$18,0,$F$18) -> 1 | Q65: =IF(15<$C$18,0,$F$18) -> 1 | R65: =IF(16<$C$18,0,$F$18) -> 1 | S65: =IF(17<$C$18,0,$F$18) -> 1 | T65: =IF(18<$C$18,0,$F$18) -> 1 | U65: =IF(19<$C$18,0,$F$18) -> 1 | V65: =IF(20<$C$18,0,$F$18) -> 1 | W65: =IF(21<$C$18,0,$F$18) -> 1 | X65: =IF(22<$C$18,0,$F$18) -> 1 | Y65: =IF(23<$C$18,0,$F$18) -> 1 | Z65: =IF(24<$C$18,0,$F$18) -> 1 | AA65: =IF(25<$C$18,0,$G$18) -> 1 | AB65: =IF(26<$C$18,0,$G$18) -> 1 | AC65: =IF(27<$C$18,0,$G$18) -> 1 | AD65: =IF(28<$C$18,0,$G$18) -> 1 | AE65: =IF(29<$C$18,0,$G$18) -> 1 | AF65: =IF(30<$C$18,0,$G$18) -> 1 | AG65: =IF(31<$C$18,0,$G$18) -> 1 | AH65: =IF(32<$C$18,0,$G$18) -> 1 | AI65: =IF(33<$C$18,0,$G$18) -> 1 | AJ65: =IF(34<$C$18,0,$G$18) -> 1 | AK65: =IF(35<$C$18,0,$G$18) -> 1 | AL65: =IF(36<$C$18,0,$G$18) -> 1 | AN65: =N65 -> 0 | AO65: =Z65 -> 1 | AP65: =AL65 -> 1
A66: Head of Government, Initiatives and Donors | B66: Institutional Partnerships | C66: =IF(1<$C$19,0,$E$19) -> 0 | D66: =IF(2<$C$19,0,$E$19) -> 0 | E66: =IF(3<$C$19,0,$E$19) -> 0 | F66: =IF(4<$C$19,0,$E$19) -> 0 | G66: =IF(5<$C$19,0,$E$19) -> 0 | H66: =IF(6<$C$19,0,$E$19) -> 0 | I66: =IF(7<$C$19,0,$E$19) -> 0 | J66: =IF(8<$C$19,0,$E$19) -> 0 | K66: =IF(9<$C$19,0,$E$19) -> 0 | L66: =IF(10<$C$19,0,$E$19) -> 0 | M66: =IF(11<$C$19,0,$E$19) -> 0 | N66: =IF(12<$C$19,0,$E$19) -> 0 | O66: =IF(13<$C$19,0,$F$19) -> 0 | P66: =IF(14<$C$19,0,$F$19) -> 0 | Q66: =IF(15<$C$19,0,$F$19) -> 0 | R66: =IF(16<$C$19,0,$F$19) -> 0 | S66: =IF(17<$C$19,0,$F$19) -> 0 | T66: =IF(18<$C$19,0,$F$19) -> 0 | U66: =IF(19<$C$19,0,$F$19) -> 0 | V66: =IF(20<$C$19,0,$F$19) -> 0 | W66: =IF(21<$C$19,0,$F$19) -> 0 | X66: =IF(22<$C$19,0,$F$19) -> 0 | Y66: =IF(23<$C$19,0,$F$19) -> 0 | Z66: =IF(24<$C$19,0,$F$19) -> 0 | AA66: =IF(25<$C$19,0,$G$19) -> 1 | AB66: =IF(26<$C$19,0,$G$19) -> 1 | AC66: =IF(27<$C$19,0,$G$19) -> 1 | AD66: =IF(28<$C$19,0,$G$19) -> 1 | AE66: =IF(29<$C$19,0,$G$19) -> 1 | AF66: =IF(30<$C$19,0,$G$19) -> 1 | AG66: =IF(31<$C$19,0,$G$19) -> 1 | AH66: =IF(32<$C$19,0,$G$19) -> 1 | AI66: =IF(33<$C$19,0,$G$19) -> 1 | AJ66: =IF(34<$C$19,0,$G$19) -> 1 | AK66: =IF(35<$C$19,0,$G$19) -> 1 | AL66: =IF(36<$C$19,0,$G$19) -> 1 | AN66: =N66 -> 0 | AO66: =Z66 -> 0 | AP66: =AL66 -> 1
A67: Partnerships and bids associate | B67: Institutional Partnerships | C67: =IF(1<$C$20,0,$E$20) -> 0 | D67: =IF(2<$C$20,0,$E$20) -> 0 | E67: =IF(3<$C$20,0,$E$20) -> 0 | F67: =IF(4<$C$20,0,$E$20) -> 0 | G67: =IF(5<$C$20,0,$E$20) -> 0 | H67: =IF(6<$C$20,0,$E$20) -> 0 | I67: =IF(7<$C$20,0,$E$20) -> 0 | J67: =IF(8<$C$20,0,$E$20) -> 0 | K67: =IF(9<$C$20,0,$E$20) -> 0 | L67: =IF(10<$C$20,0,$E$20) -> 0 | M67: =IF(11<$C$20,0,$E$20) -> 0 | N67: =IF(12<$C$20,0,$E$20) -> 0 | O67: =IF(13<$C$20,0,$F$20) -> 0 | P67: =IF(14<$C$20,0,$F$20) -> 0 | Q67: =IF(15<$C$20,0,$F$20) -> 0 | R67: =IF(16<$C$20,0,$F$20) -> 0 | S67: =IF(17<$C$20,0,$F$20) -> 0 | T67: =IF(18<$C$20,0,$F$20) -> 0 | U67: =IF(19<$C$20,0,$F$20) -> 0 | V67: =IF(20<$C$20,0,$F$20) -> 0 | W67: =IF(21<$C$20,0,$F$20) -> 0 | X67: =IF(22<$C$20,0,$F$20) -> 0 | Y67: =IF(23<$C$20,0,$F$20) -> 0 | Z67: =IF(24<$C$20,0,$F$20) -> 0 | AA67: =IF(25<$C$20,0,$G$20) -> 1 | AB67: =IF(26<$C$20,0,$G$20) -> 1 | AC67: =IF(27<$C$20,0,$G$20) -> 1 | AD67: =IF(28<$C$20,0,$G$20) -> 1 | AE67: =IF(29<$C$20,0,$G$20) -> 1 | AF67: =IF(30<$C$20,0,$G$20) -> 1 | AG67: =IF(31<$C$20,0,$G$20) -> 1 | AH67: =IF(32<$C$20,0,$G$20) -> 1 | AI67: =IF(33<$C$20,0,$G$20) -> 1 | AJ67: =IF(34<$C$20,0,$G$20) -> 1 | AK67: =IF(35<$C$20,0,$G$20) -> 1 | AL67: =IF(36<$C$20,0,$G$20) -> 1 | AN67: =N67 -> 0 | AO67: =Z67 -> 0 | AP67: =AL67 -> 1
A68: Head of Schools and Technical Education | B68: Institutional Partnerships | C68: =IF(1<$C$21,0,$E$21) -> 0 | D68: =IF(2<$C$21,0,$E$21) -> 0 | E68: =IF(3<$C$21,0,$E$21) -> 0 | F68: =IF(4<$C$21,0,$E$21) -> 0 | G68: =IF(5<$C$21,0,$E$21) -> 0 | H68: =IF(6<$C$21,0,$E$21) -> 0 | I68: =IF(7<$C$21,0,$E$21) -> 0 | J68: =IF(8<$C$21,0,$E$21) -> 0 | K68: =IF(9<$C$21,0,$E$21) -> 0 | L68: =IF(10<$C$21,0,$E$21) -> 0 | M68: =IF(11<$C$21,0,$E$21) -> 0 | N68: =IF(12<$C$21,0,$E$21) -> 0 | O68: =IF(13<$C$21,0,$F$21) -> 0 | P68: =IF(14<$C$21,0,$F$21) -> 0 | Q68: =IF(15<$C$21,0,$F$21) -> 0 | R68: =IF(16<$C$21,0,$F$21) -> 0 | S68: =IF(17<$C$21,0,$F$21) -> 0 | T68: =IF(18<$C$21,0,$F$21) -> 0 | U68: =IF(19<$C$21,0,$F$21) -> 0 | V68: =IF(20<$C$21,0,$F$21) -> 0 | W68: =IF(21<$C$21,0,$F$21) -> 0 | X68: =IF(22<$C$21,0,$F$21) -> 0 | Y68: =IF(23<$C$21,0,$F$21) -> 0 | Z68: =IF(24<$C$21,0,$F$21) -> 0 | AA68: =IF(25<$C$21,0,$G$21) -> 0 | AB68: =IF(26<$C$21,0,$G$21) -> 0 | AC68: =IF(27<$C$21,0,$G$21) -> 0 | AD68: =IF(28<$C$21,0,$G$21) -> 0 | AE68: =IF(29<$C$21,0,$G$21) -> 0 | AF68: =IF(30<$C$21,0,$G$21) -> 0 | AG68: =IF(31<$C$21,0,$G$21) -> 0 | AH68: =IF(32<$C$21,0,$G$21) -> 0 | AI68: =IF(33<$C$21,0,$G$21) -> 0 | AJ68: =IF(34<$C$21,0,$G$21) -> 0 | AK68: =IF(35<$C$21,0,$G$21) -> 0 | AL68: =IF(36<$C$21,0,$G$21) -> 0 | AN68: =N68 -> 0 | AO68: =Z68 -> 0 | AP68: =AL68 -> 0
A69: Account manager — renewals | B69: Institutional Partnerships | C69: =IF(1<$C$22,0,$E$22) -> 0 | D69: =IF(2<$C$22,0,$E$22) -> 0 | E69: =IF(3<$C$22,0,$E$22) -> 0 | F69: =IF(4<$C$22,0,$E$22) -> 0 | G69: =IF(5<$C$22,0,$E$22) -> 0 | H69: =IF(6<$C$22,0,$E$22) -> 0 | I69: =IF(7<$C$22,0,$E$22) -> 0 | J69: =IF(8<$C$22,0,$E$22) -> 0 | K69: =IF(9<$C$22,0,$E$22) -> 0 | L69: =IF(10<$C$22,0,$E$22) -> 0 | M69: =IF(11<$C$22,0,$E$22) -> 0 | N69: =IF(12<$C$22,0,$E$22) -> 0 | O69: =IF(13<$C$22,0,$F$22) -> 0 | P69: =IF(14<$C$22,0,$F$22) -> 0 | Q69: =IF(15<$C$22,0,$F$22) -> 0 | R69: =IF(16<$C$22,0,$F$22) -> 0 | S69: =IF(17<$C$22,0,$F$22) -> 0 | T69: =IF(18<$C$22,0,$F$22) -> 0 | U69: =IF(19<$C$22,0,$F$22) -> 0 | V69: =IF(20<$C$22,0,$F$22) -> 0 | W69: =IF(21<$C$22,0,$F$22) -> 0 | X69: =IF(22<$C$22,0,$F$22) -> 0 | Y69: =IF(23<$C$22,0,$F$22) -> 0 | Z69: =IF(24<$C$22,0,$F$22) -> 0 | AA69: =IF(25<$C$22,0,$G$22) -> 0 | AB69: =IF(26<$C$22,0,$G$22) -> 0 | AC69: =IF(27<$C$22,0,$G$22) -> 0 | AD69: =IF(28<$C$22,0,$G$22) -> 0 | AE69: =IF(29<$C$22,0,$G$22) -> 0 | AF69: =IF(30<$C$22,0,$G$22) -> 0 | AG69: =IF(31<$C$22,0,$G$22) -> 0 | AH69: =IF(32<$C$22,0,$G$22) -> 0 | AI69: =IF(33<$C$22,0,$G$22) -> 0 | AJ69: =IF(34<$C$22,0,$G$22) -> 0 | AK69: =IF(35<$C$22,0,$G$22) -> 0 | AL69: =IF(36<$C$22,0,$G$22) -> 0 | AN69: =N69 -> 0 | AO69: =Z69 -> 0 | AP69: =AL69 -> 0
A70: Head of Growth and Content | B70: Growth and Content | C70: =IF(1<$C$23,0,$E$23) -> 1 | D70: =IF(2<$C$23,0,$E$23) -> 1 | E70: =IF(3<$C$23,0,$E$23) -> 1 | F70: =IF(4<$C$23,0,$E$23) -> 1 | G70: =IF(5<$C$23,0,$E$23) -> 1 | H70: =IF(6<$C$23,0,$E$23) -> 1 | I70: =IF(7<$C$23,0,$E$23) -> 1 | J70: =IF(8<$C$23,0,$E$23) -> 1 | K70: =IF(9<$C$23,0,$E$23) -> 1 | L70: =IF(10<$C$23,0,$E$23) -> 1 | M70: =IF(11<$C$23,0,$E$23) -> 1 | N70: =IF(12<$C$23,0,$E$23) -> 1 | O70: =IF(13<$C$23,0,$F$23) -> 1 | P70: =IF(14<$C$23,0,$F$23) -> 1 | Q70: =IF(15<$C$23,0,$F$23) -> 1 | R70: =IF(16<$C$23,0,$F$23) -> 1 | S70: =IF(17<$C$23,0,$F$23) -> 1 | T70: =IF(18<$C$23,0,$F$23) -> 1 | U70: =IF(19<$C$23,0,$F$23) -> 1 | V70: =IF(20<$C$23,0,$F$23) -> 1 | W70: =IF(21<$C$23,0,$F$23) -> 1 | X70: =IF(22<$C$23,0,$F$23) -> 1 | Y70: =IF(23<$C$23,0,$F$23) -> 1 | Z70: =IF(24<$C$23,0,$F$23) -> 1 | AA70: =IF(25<$C$23,0,$G$23) -> 1 | AB70: =IF(26<$C$23,0,$G$23) -> 1 | AC70: =IF(27<$C$23,0,$G$23) -> 1 | AD70: =IF(28<$C$23,0,$G$23) -> 1 | AE70: =IF(29<$C$23,0,$G$23) -> 1 | AF70: =IF(30<$C$23,0,$G$23) -> 1 | AG70: =IF(31<$C$23,0,$G$23) -> 1 | AH70: =IF(32<$C$23,0,$G$23) -> 1 | AI70: =IF(33<$C$23,0,$G$23) -> 1 | AJ70: =IF(34<$C$23,0,$G$23) -> 1 | AK70: =IF(35<$C$23,0,$G$23) -> 1 | AL70: =IF(36<$C$23,0,$G$23) -> 1 | AN70: =N70 -> 1 | AO70: =Z70 -> 1 | AP70: =AL70 -> 1
A71: Student success (bilingual) | B71: Growth and Content | C71: =IF(1<$C$24,0,$E$24) -> 0 | D71: =IF(2<$C$24,0,$E$24) -> 0 | E71: =IF(3<$C$24,0,$E$24) -> 0 | F71: =IF(4<$C$24,0,$E$24) -> 0 | G71: =IF(5<$C$24,0,$E$24) -> 0 | H71: =IF(6<$C$24,0,$E$24) -> 0 | I71: =IF(7<$C$24,0,$E$24) -> 0 | J71: =IF(8<$C$24,0,$E$24) -> 0 | K71: =IF(9<$C$24,0,$E$24) -> 0 | L71: =IF(10<$C$24,0,$E$24) -> 0 | M71: =IF(11<$C$24,0,$E$24) -> 0 | N71: =IF(12<$C$24,0,$E$24) -> 0 | O71: =IF(13<$C$24,0,$F$24) -> 0 | P71: =IF(14<$C$24,0,$F$24) -> 0 | Q71: =IF(15<$C$24,0,$F$24) -> 0 | R71: =IF(16<$C$24,0,$F$24) -> 0 | S71: =IF(17<$C$24,0,$F$24) -> 0 | T71: =IF(18<$C$24,0,$F$24) -> 0 | U71: =IF(19<$C$24,0,$F$24) -> 0 | V71: =IF(20<$C$24,0,$F$24) -> 0 | W71: =IF(21<$C$24,0,$F$24) -> 0 | X71: =IF(22<$C$24,0,$F$24) -> 0 | Y71: =IF(23<$C$24,0,$F$24) -> 0 | Z71: =IF(24<$C$24,0,$F$24) -> 0 | AA71: =IF(25<$C$24,0,$G$24) -> 0 | AB71: =IF(26<$C$24,0,$G$24) -> 0 | AC71: =IF(27<$C$24,0,$G$24) -> 0 | AD71: =IF(28<$C$24,0,$G$24) -> 0 | AE71: =IF(29<$C$24,0,$G$24) -> 0 | AF71: =IF(30<$C$24,0,$G$24) -> 0 | AG71: =IF(31<$C$24,0,$G$24) -> 0 | AH71: =IF(32<$C$24,0,$G$24) -> 0 | AI71: =IF(33<$C$24,0,$G$24) -> 0 | AJ71: =IF(34<$C$24,0,$G$24) -> 0 | AK71: =IF(35<$C$24,0,$G$24) -> 0 | AL71: =IF(36<$C$24,0,$G$24) -> 0 | AN71: =N71 -> 0 | AO71: =Z71 -> 0 | AP71: =AL71 -> 0
A72: Total headcount | B72: at month end | C72: =SUM(C54:C71) -> 6 | D72: =SUM(D54:D71) -> 6 | E72: =SUM(E54:E71) -> 6 | F72: =SUM(F54:F71) -> 6 | G72: =SUM(G54:G71) -> 6 | H72: =SUM(H54:H71) -> 6 | I72: =SUM(I54:I71) -> 6 | J72: =SUM(J54:J71) -> 6 | ... AL72: =SUM(AL54:AL71) -> 12 | AN72: =N72 -> 6 | AO72: =Z72 -> 9 | AP72: =AL72 -> 12
A73: New employees joining in the month | B73: drives the Capex sheet | C73: =C72 -> 6 | D73: =MAX(0,D72-C72) -> 0 | E73: =MAX(0,E72-D72) -> 0 | F73: =MAX(0,F72-E72) -> 0 | G73: =MAX(0,G72-F72) -> 0 | H73: =MAX(0,H72-G72) -> 0 | I73: =MAX(0,I72-H72) -> 0 | J73: =MAX(0,J72-I72) -> 0 | K73: =MAX(0,K72-J72) -> 0 | ... AL73: =MAX(0,AL72-AK72) -> 0 | AN73: =SUM(C73:N73) -> 6 | AO73: =SUM(O73:Z73) -> 3 | AP73: =SUM(AA73:AL73) -> 3
A74: Commercial heads on the road | B74: drives the travel line on Expenses | C74: =IF(1<$C$17,0,$E$17)+IF(1<$C$18,0,$E$18)+IF(1<$C$19,0,$E$19)+IF(1<$C$20,0,$E$20)+IF(1<$C$21,0,$E$21)+IF(1<$C$22,0,$E$22) -> 1 | D74: =IF(2<$C$17,0,$E$17)+IF(2<$C$18,0,$E$18)+IF(2<$C$19,0,$E$19)+IF(2<$C$20,0,$E$20)+IF(2<$C$21,0,$E$21)+IF(2<$C$22,0,$E$22) -> 1 | E74: =IF(3<$C$17,0,$E$17)+IF(3<$C$18,0,$E$18)+IF(3<$C$19,0,$E$19)+IF(3<$C$20,0,$E$20)+IF(3<$C$21,0,$E$21)+IF(3<$C$22,0,$E$22) -> 1 | F74: =IF(4<$C$17,0,$E$17)+IF(4<$C$18,0,$E$18)+IF(4<$C$19,0,$E$19)+IF(4<$C$20,0,$E$20)+IF(4<$C$21,0,$E$21)+IF(4<$C$22,0,$E$22) -> 1 | G74: =IF(5<$C$17,0,$E$17)+IF(5<$C$18,0,$E$18)+IF(5<$C$19,0,$E$19)+IF(5<$C$20,0,$E$20)+IF(5<$C$21,0,$E$21)+IF(5<$C$22,0,$E$22) -> 1 | H74: =IF(6<$C$17,0,$E$17)+IF(6<$C$18,0,$E$18)+IF(6<$C$19,0,$E$19)+IF(6<$C$20,0,$E$20)+IF(6<$C$21,0,$E$21)+IF(6<$C$22,0,$E$22) -> 1 | I74: =IF(7<$C$17,0,$E$17)+IF(7<$C$18,0,$E$18)+IF(7<$C$19,0,$E$19)+IF(7<$C$20,0,$E$20)+IF(7<$C$21,0,$E$21)+IF(7<$C$22,0,$E$22) -> 1 | J74: =IF(8<$C$17,0,$E$17)+IF(8<$C$18,0,$E$18)+IF(8<$C$19,0,$E$19)+IF(8<$C$20,0,$E$20)+IF(8<$C$21,0,$E$21)+IF(8<$C$22,0,$E$22) -> 1 | K74: =IF(9<$C$17,0,$E$17)+IF(9<$C$18,0,$E$18)+IF(9<$C$19,0,$E$19)+IF(9<$C$20,0,$E$20)+IF(9<$C$21,0,$E$21)+IF(9<$C$22,0,$E$22) -> 1 | L74: =IF(10<$C$17,0,$E$17)+IF(10<$C$18,0,$E$18)+IF(10<$C$19,0,$E$19)+IF(10<$C$20,0,$E$20)+IF(10<$C$21,0,$E$21)+IF(10<$C$22,0,$E$22) -> 1 | M74: =IF(11<$C$17,0,$E$17)+IF(11<$C$18,0,$E$18)+IF(11<$C$19,0,$E$19)+IF(11<$C$20,0,$E$20)+IF(11<$C$21,0,$E$21)+IF(11<$C$22,0,$E$22) -> 1 | N74: =IF(12<$C$17,0,$E$17)+IF(12<$C$18,0,$E$18)+IF(12<$C$19,0,$E$19)+IF(12<$C$20,0,$E$20)+IF(12<$C$21,0,$E$21)+IF(12<$C$22,0,$E$22) -> 1 | O74: =IF(13<$C$17,0,$F$17)+IF(13<$C$18,0,$F$18)+IF(13<$C$19,0,$F$19)+IF(13<$C$20,0,$F$20)+IF(13<$C$21,0,$F$21)+IF(13<$C$22,0,$F$22) -> 2 | P74: =IF(14<$C$17,0,$F$17)+IF(14<$C$18,0,$F$18)+IF(14<$C$19,0,$F$19)+IF(14<$C$20,0,$F$20)+IF(14<$C$21,0,$F$21)+IF(14<$C$22,0,$F$22) -> 2 | Q74: =IF(15<$C$17,0,$F$17)+IF(15<$C$18,0,$F$18)+IF(15<$C$19,0,$F$19)+IF(15<$C$20,0,$F$20)+IF(15<$C$21,0,$F$21)+IF(15<$C$22,0,$F$22) -> 2 | R74: =IF(16<$C$17,0,$F$17)+IF(16<$C$18,0,$F$18)+IF(16<$C$19,0,$F$19)+IF(16<$C$20,0,$F$20)+IF(16<$C$21,0,$F$21)+IF(16<$C$22,0,$F$22) -> 2 | S74: =IF(17<$C$17,0,$F$17)+IF(17<$C$18,0,$F$18)+IF(17<$C$19,0,$F$19)+IF(17<$C$20,0,$F$20)+IF(17<$C$21,0,$F$21)+IF(17<$C$22,0,$F$22) -> 2 | T74: =IF(18<$C$17,0,$F$17)+IF(18<$C$18,0,$F$18)+IF(18<$C$19,0,$F$19)+IF(18<$C$20,0,$F$20)+IF(18<$C$21,0,$F$21)+IF(18<$C$22,0,$F$22) -> 2 | U74: =IF(19<$C$17,0,$F$17)+IF(19<$C$18,0,$F$18)+IF(19<$C$19,0,$F$19)+IF(19<$C$20,0,$F$20)+IF(19<$C$21,0,$F$21)+IF(19<$C$22,0,$F$22) -> 2 | V74: =IF(20<$C$17,0,$F$17)+IF(20<$C$18,0,$F$18)+IF(20<$C$19,0,$F$19)+IF(20<$C$20,0,$F$20)+IF(20<$C$21,0,$F$21)+IF(20<$C$22,0,$F$22) -> 2 | W74: =IF(21<$C$17,0,$F$17)+IF(21<$C$18,0,$F$18)+IF(21<$C$19,0,$F$19)+IF(21<$C$20,0,$F$20)+IF(21<$C$21,0,$F$21)+IF(21<$C$22,0,$F$22) -> 2 | X74: =IF(22<$C$17,0,$F$17)+IF(22<$C$18,0,$F$18)+IF(22<$C$19,0,$F$19)+IF(22<$C$20,0,$F$20)+IF(22<$C$21,0,$F$21)+IF(22<$C$22,0,$F$22) -> 2 | Y74: =IF(23<$C$17,0,$F$17)+IF(23<$C$18,0,$F$18)+IF(23<$C$19,0,$F$19)+IF(23<$C$20,0,$F$20)+IF(23<$C$21,0,$F$21)+IF(23<$C$22,0,$F$22) -> 2 | Z74: =IF(24<$C$17,0,$F$17)+IF(24<$C$18,0,$F$18)+IF(24<$C$19,0,$F$19)+IF(24<$C$20,0,$F$20)+IF(24<$C$21,0,$F$21)+IF(24<$C$22,0,$F$22) -> 2 | AA74: =IF(25<$C$17,0,$G$17)+IF(25<$C$18,0,$G$18)+IF(25<$C$19,0,$G$19)+IF(25<$C$20,0,$G$20)+IF(25<$C$21,0,$G$21)+IF(25<$C$22,0,$G$22) -> 4 | AB74: =IF(26<$C$17,0,$G$17)+IF(26<$C$18,0,$G$18)+IF(26<$C$19,0,$G$19)+IF(26<$C$20,0,$G$20)+IF(26<$C$21,0,$G$21)+IF(26<$C$22,0,$G$22) -> 4 | AC74: =IF(27<$C$17,0,$G$17)+IF(27<$C$18,0,$G$18)+IF(27<$C$19,0,$G$19)+IF(27<$C$20,0,$G$20)+IF(27<$C$21,0,$G$21)+IF(27<$C$22,0,$G$22) -> 4 | AD74: =IF(28<$C$17,0,$G$17)+IF(28<$C$18,0,$G$18)+IF(28<$C$19,0,$G$19)+IF(28<$C$20,0,$G$20)+IF(28<$C$21,0,$G$21)+IF(28<$C$22,0,$G$22) -> 4 | AE74: =IF(29<$C$17,0,$G$17)+IF(29<$C$18,0,$G$18)+IF(29<$C$19,0,$G$19)+IF(29<$C$20,0,$G$20)+IF(29<$C$21,0,$G$21)+IF(29<$C$22,0,$G$22) -> 4 | AF74: =IF(30<$C$17,0,$G$17)+IF(30<$C$18,0,$G$18)+IF(30<$C$19,0,$G$19)+IF(30<$C$20,0,$G$20)+IF(30<$C$21,0,$G$21)+IF(30<$C$22,0,$G$22) -> 4 | AG74: =IF(31<$C$17,0,$G$17)+IF(31<$C$18,0,$G$18)+IF(31<$C$19,0,$G$19)+IF(31<$C$20,0,$G$20)+IF(31<$C$21,0,$G$21)+IF(31<$C$22,0,$G$22) -> 4 | AH74: =IF(32<$C$17,0,$G$17)+IF(32<$C$18,0,$G$18)+IF(32<$C$19,0,$G$19)+IF(32<$C$20,0,$G$20)+IF(32<$C$21,0,$G$21)+IF(32<$C$22,0,$G$22) -> 4 | AI74: =IF(33<$C$17,0,$G$17)+IF(33<$C$18,0,$G$18)+IF(33<$C$19,0,$G$19)+IF(33<$C$20,0,$G$20)+IF(33<$C$21,0,$G$21)+IF(33<$C$22,0,$G$22) -> 4 | AJ74: =IF(34<$C$17,0,$G$17)+IF(34<$C$18,0,$G$18)+IF(34<$C$19,0,$G$19)+IF(34<$C$20,0,$G$20)+IF(34<$C$21,0,$G$21)+IF(34<$C$22,0,$G$22) -> 4 | AK74: =IF(35<$C$17,0,$G$17)+IF(35<$C$18,0,$G$18)+IF(35<$C$19,0,$G$19)+IF(35<$C$20,0,$G$20)+IF(35<$C$21,0,$G$21)+IF(35<$C$22,0,$G$22) -> 4 | AL74: =IF(36<$C$17,0,$G$17)+IF(36<$C$18,0,$G$18)+IF(36<$C$19,0,$G$19)+IF(36<$C$20,0,$G$20)+IF(36<$C$21,0,$G$21)+IF(36<$C$22,0,$G$22) -> 4 | AN74: =N74 -> 1 | AO74: =Z74 -> 2 | AP74: =AL74 -> 4

Sheet Actuals
A1: Actuals and Opening Position
A2: The money already in, the opening balance sheet it creates, and a grid to record each month as it closes so this becomes an operating tool rather than a one-off forecast.
A5: OPENING POSITION AT 30 SEPTEMBER 2026
A6: Cash at bank | B6: founder capital already contributed | C6: =Assumptions!$C$140 -> 50000
A7: Trade receivables | B7: nothing invoiced yet | C7: 0
A8: Property and equipment, net | B8: nothing acquired yet | C8: 0
A9: Intangible assets, net | B9: capitalised from month 1 | C9: 0
A10: Total opening assets | C10: =SUM(C6:C9) -> 50000
A12: Trade and other payables | B12: none at inception | C12: 0
A13: Paid-in share capital | B13: the opening cash, recorded as equity | C13: =Assumptions!$C$140 -> 50000
A14: Retained earnings | B14: no trading before month 1 | C14: 0
A15: Total opening liabilities and equity | C15: =C12+C13+C14 -> 50000
A16: CHECK — assets less liabilities and equity | B16: must read nil | C16: =C10-C15 -> 0
A18: MONTHLY ACTUALS — ENTER AS EACH MONTH CLOSES
A19: Leave a month blank until it has closed. Nothing downstream reads this grid: the statements run on the forecast, and these rows exist so the variance can be read without disturbing the model.
A20: Line item | B20: Driver / source | C20: Oct 26 | D20: Nov 26 | E20: Dec 26 | F20: Jan 26 | G20: Feb 26 | H20: Mar 26 | I20: Apr 26 | J20: May 26 | K20: Jun 26 | L20: Jul 27 | M20: Aug 27 | N20: Sep 27 | O20: Oct 27 | P20: Nov 27 | Q20: Dec 27 | R20: Jan 27 | S20: Feb 27 | T20: Mar 27 | U20: Apr 27 | V20: May 27 | W20: Jun 27 | X20: Jul 28 | Y20: Aug 28 | Z20: Sep 28 | AA20: Oct 28 | AB20: Nov 28 | AC20: Dec 28 | AD20: Jan 28 | AE20: Feb 28 | AF20: Mar 28 | AG20: Apr 28 | AH20: May 28 | AI20: Jun 28 | AJ20: Jul 29 | AK20: Aug 29 | AL20: Sep 29 | AN20: YEAR 1 | AO20: YEAR 2 | AP20: YEAR 3
A21: Revenue — actual | B21: enter when the month closes | AN21: =SUM(C21:N21) -> 0 | AO21: =SUM(O21:Z21) -> 0 | AP21: =SUM(AA21:AL21) -> 0
A22: Direct cost — actual | B22: enter when the month closes | AN22: =SUM(C22:N22) -> 0 | AO22: =SUM(O22:Z22) -> 0 | AP22: =SUM(AA22:AL22) -> 0
A23: Operating cost — actual | B23: enter when the month closes | AN23: =SUM(C23:N23) -> 0 | AO23: =SUM(O23:Z23) -> 0 | AP23: =SUM(AA23:AL23) -> 0
A24: Closing cash — actual | B24: enter when the month closes | AN24: =SUM(C24:N24) -> 0 | AO24: =SUM(O24:Z24) -> 0 | AP24: =SUM(AA24:AL24) -> 0
A26: VARIANCE AGAINST THE MODEL
A27: Line item | B27: Driver / source | C27: Oct 26 | D27: Nov 26 | E27: Dec 26 | F27: Jan 26 | G27: Feb 26 | H27: Mar 26 | I27: Apr 26 | J27: May 26 | K27: Jun 26 | L27: Jul 27 | M27: Aug 27 | N27: Sep 27 | O27: Oct 27 | P27: Nov 27 | Q27: Dec 27 | R27: Jan 27 | S27: Feb 27 | T27: Mar 27 | U27: Apr 27 | V27: May 27 | W27: Jun 27 | X27: Jul 28 | Y27: Aug 28 | Z27: Sep 28 | AA27: Oct 28 | AB27: Nov 28 | AC27: Dec 28 | AD27: Jan 28 | AE27: Feb 28 | AF27: Mar 28 | AG27: Apr 28 | AH27: May 28 | AI27: Jun 28 | AJ27: Jul 29 | AK27: Aug 29 | AL27: Sep 29 | AN27: YEAR 1 | AO27: YEAR 2 | AP27: YEAR 3
A28: Revenue — forecast | B28: from the model | C28: =Revenue!C$49 -> 2340.7128 | D28: =Revenue!D$49 -> 2656.9074 | E28: =Revenue!E$49 -> 3048.7445 | F28: =Revenue!F$49 -> 23738.958 | G28: =Revenue!G$49 -> 26202.103 | H28: =Revenue!H$49 -> 29448.491 | I28: =Revenue!I$49 -> 48411.774 | J28: =Revenue!J$49 -> 53317.397 | ... AL28: =Revenue!AL$49 -> 672449.28 | AN28: =SUM(C28:N28) -> 614990.61 | AO28: =SUM(O28:Z28) -> 2786041.1 | AP28: =SUM(AA28:AL28) -> 6112588
A29: Revenue — variance | B29: blank months read as nil | C29: =IF(C21=0,0,C21-C28) -> 0 | D29: =IF(D21=0,0,D21-D28) -> 0 | E29: =IF(E21=0,0,E21-E28) -> 0 | F29: =IF(F21=0,0,F21-F28) -> 0 | G29: =IF(G21=0,0,G21-G28) -> 0 | H29: =IF(H21=0,0,H21-H28) -> 0 | I29: =IF(I21=0,0,I21-I28) -> 0 | J29: =IF(J21=0,0,J21-J28) -> 0 | ... AL29: =IF(AL21=0,0,AL21-AL28) -> 0 | AN29: =SUM(C29:N29) -> 0 | AO29: =SUM(O29:Z29) -> 0 | AP29: =SUM(AA29:AL29) -> 0
A30: Direct cost — forecast | B30: from the model | C30: =Expenses!C$21 -> 3386.9812 | D30: =Expenses!D$21 -> 3736.1298 | E30: =Expenses!E$21 -> 4197.4827 | F30: =Expenses!F$21 -> 10715.978 | G30: =Expenses!G$21 -> 11797.956 | H30: =Expenses!H$21 -> 13235.657 | I30: =Expenses!I$21 -> 17469.593 | J30: =Expenses!J$21 -> 19222.824 | ... AL30: =Expenses!AL$21 -> 226754.71 | AN30: =SUM(C30:N30) -> 226175.82 | AO30: =SUM(O30:Z30) -> 929744.1 | AP30: =SUM(AA30:AL30) -> 2068776.3
A31: Direct cost — variance | B31: blank months read as nil | C31: =IF(C22=0,0,C22-C30) -> 0 | D31: =IF(D22=0,0,D22-D30) -> 0 | E31: =IF(E22=0,0,E22-E30) -> 0 | F31: =IF(F22=0,0,F22-F30) -> 0 | G31: =IF(G22=0,0,G22-G30) -> 0 | H31: =IF(H22=0,0,H22-H30) -> 0 | I31: =IF(I22=0,0,I22-I30) -> 0 | J31: =IF(J22=0,0,J22-J30) -> 0 | ... AL31: =IF(AL22=0,0,AL22-AL30) -> 0 | AN31: =SUM(C31:N31) -> 0 | AO31: =SUM(O31:Z31) -> 0 | AP31: =SUM(AA31:AL31) -> 0
A32: Operating cost — forecast | B32: from the model | C32: =Expenses!C$42 -> 42877.379 | D32: =Expenses!D$42 -> 42893.382 | E32: =Expenses!E$42 -> 42914.318 | F32: =Expenses!F$42 -> 44272.18 | G32: =Expenses!G$42 -> 44427.621 | H32: =Expenses!H$42 -> 44634.416 | I32: =Expenses!I$42 -> 45859.099 | J32: =Expenses!J$42 -> 46172.82 | ... AL32: =Expenses!AL$42 -> 191522.98 | AN32: =SUM(C32:N32) -> 552680.12 | AO32: =SUM(O32:Z32) -> 1214717.6 | AP32: =SUM(AA32:AL32) -> 2174212.3
A33: Operating cost — variance | B33: blank months read as nil | C33: =IF(C23=0,0,C23-C32) -> 0 | D33: =IF(D23=0,0,D23-D32) -> 0 | E33: =IF(E23=0,0,E23-E32) -> 0 | F33: =IF(F23=0,0,F23-F32) -> 0 | G33: =IF(G23=0,0,G23-G32) -> 0 | H33: =IF(H23=0,0,H23-H32) -> 0 | I33: =IF(I23=0,0,I23-I32) -> 0 | J33: =IF(J23=0,0,J23-J32) -> 0 | ... AL33: =IF(AL23=0,0,AL23-AL32) -> 0 | AN33: =SUM(C33:N33) -> 0 | AO33: =SUM(O33:Z33) -> 0 | AP33: =SUM(AA33:AL33) -> 0
A34: Closing cash — forecast | B34: from the model | C34: =Cash_Flow!C$33 -> 468135.73 | D34: =Cash_Flow!D$33 -> 415500.49 | E34: =Cash_Flow!E$33 -> 372162.28 | F34: =Cash_Flow!F$33 -> 305954.42 | G34: =Cash_Flow!G$33 -> 273252.83 | H34: =Cash_Flow!H$33 -> 240844.63 | I34: =Cash_Flow!I$33 -> 191743.64 | J34: =Cash_Flow!J$33 -> 172382.07 | ... AL34: =Cash_Flow!AL$33 -> 1903484.2 | AN34: =SUM(C34:N34) -> 2909551.8 | AO34: =SUM(O34:Z34) -> 2960222.1 | AP34: =SUM(AA34:AL34) -> 13479345
A35: Closing cash — variance | B35: blank months read as nil | C35: =IF(C24=0,0,C24-C34) -> 0 | D35: =IF(D24=0,0,D24-D34) -> 0 | E35: =IF(E24=0,0,E24-E34) -> 0 | F35: =IF(F24=0,0,F24-F34) -> 0 | G35: =IF(G24=0,0,G24-G34) -> 0 | H35: =IF(H24=0,0,H24-H34) -> 0 | I35: =IF(I24=0,0,I24-I34) -> 0 | J35: =IF(J24=0,0,J24-J34) -> 0 | ... AL35: =IF(AL24=0,0,AL24-AL34) -> 0 | AN35: =SUM(C35:N35) -> 0 | AO35: =SUM(O35:Z35) -> 0 | AP35: =SUM(AA35:AL35) -> 0

Sheet Capex
A1: Assets and Capital Expenditure
A2: Per-employee assets follow the hiring plan: every new employee arrives with a laptop, a desk, peripherals and a handset. Shared and intangible assets are dated explicitly.
A5: ADDITIONS IN THE MONTH
A6: Line item | B6: Driver / source | C6: Oct 26 | D6: Nov 26 | E6: Dec 26 | F6: Jan 26 | G6: Feb 26 | H6: Mar 26 | I6: Apr 26 | J6: May 26 | K6: Jun 26 | L6: Jul 27 | M6: Aug 27 | N6: Sep 27 | O6: Oct 27 | P6: Nov 27 | Q6: Dec 27 | R6: Jan 27 | S6: Feb 27 | T6: Mar 27 | U6: Apr 27 | V6: May 27 | W6: Jun 27 | X6: Jul 28 | Y6: Aug 28 | Z6: Sep 28 | AA6: Oct 28 | AB6: Nov 28 | AC6: Dec 28 | AD6: Jan 28 | AE6: Feb 28 | AF6: Mar 28 | AG6: Apr 28 | AH6: May 28 | AI6: Jun 28 | AJ6: Jul 29 | AK6: Aug 29 | AL6: Sep 29 | AN6: YEAR 1 | AO6: YEAR 2 | AP6: YEAR 3
A7: Laptop | B7: per new employee · 36 month life | C7: =HR_Model!C$73*Assumptions!$C$148*Assumptions!$D$148 -> 8400 | D7: =HR_Model!D$73*Assumptions!$C$148*Assumptions!$D$148 -> 0 | E7: =HR_Model!E$73*Assumptions!$C$148*Assumptions!$D$148 -> 0 | F7: =HR_Model!F$73*Assumptions!$C$148*Assumptions!$D$148 -> 0 | G7: =HR_Model!G$73*Assumptions!$C$148*Assumptions!$D$148 -> 0 | H7: =HR_Model!H$73*Assumptions!$C$148*Assumptions!$D$148 -> 0 | I7: =HR_Model!I$73*Assumptions!$C$148*Assumptions!$D$148 -> 0 | J7: =HR_Model!J$73*Assumptions!$C$148*Assumptions!$D$148 -> 0 | ... AL7: =HR_Model!AL$73*Assumptions!$C$148*Assumptions!$D$148 -> 0 | AN7: =SUM(C7:N7) -> 8400 | AO7: =SUM(O7:Z7) -> 4200 | AP7: =SUM(AA7:AL7) -> 4200
A8: Desk, chair and storage | B8: per new employee · 60 month life | C8: =HR_Model!C$73*Assumptions!$C$149*Assumptions!$D$149 -> 3720 | D8: =HR_Model!D$73*Assumptions!$C$149*Assumptions!$D$149 -> 0 | E8: =HR_Model!E$73*Assumptions!$C$149*Assumptions!$D$149 -> 0 | F8: =HR_Model!F$73*Assumptions!$C$149*Assumptions!$D$149 -> 0 | G8: =HR_Model!G$73*Assumptions!$C$149*Assumptions!$D$149 -> 0 | H8: =HR_Model!H$73*Assumptions!$C$149*Assumptions!$D$149 -> 0 | I8: =HR_Model!I$73*Assumptions!$C$149*Assumptions!$D$149 -> 0 | J8: =HR_Model!J$73*Assumptions!$C$149*Assumptions!$D$149 -> 0 | ... AL8: =HR_Model!AL$73*Assumptions!$C$149*Assumptions!$D$149 -> 0 | AN8: =SUM(C8:N8) -> 3720 | AO8: =SUM(O8:Z8) -> 1860 | AP8: =SUM(AA8:AL8) -> 1860
A9: Monitor and peripherals | B9: per new employee · 48 month life | C9: =HR_Model!C$73*Assumptions!$C$150*Assumptions!$D$150 -> 1860 | D9: =HR_Model!D$73*Assumptions!$C$150*Assumptions!$D$150 -> 0 | E9: =HR_Model!E$73*Assumptions!$C$150*Assumptions!$D$150 -> 0 | F9: =HR_Model!F$73*Assumptions!$C$150*Assumptions!$D$150 -> 0 | G9: =HR_Model!G$73*Assumptions!$C$150*Assumptions!$D$150 -> 0 | H9: =HR_Model!H$73*Assumptions!$C$150*Assumptions!$D$150 -> 0 | I9: =HR_Model!I$73*Assumptions!$C$150*Assumptions!$D$150 -> 0 | J9: =HR_Model!J$73*Assumptions!$C$150*Assumptions!$D$150 -> 0 | ... AL9: =HR_Model!AL$73*Assumptions!$C$150*Assumptions!$D$150 -> 0 | AN9: =SUM(C9:N9) -> 1860 | AO9: =SUM(O9:Z9) -> 930 | AP9: =SUM(AA9:AL9) -> 930
A10: Mobile handset and line setup | B10: per new employee · 24 month life | C10: =HR_Model!C$73*Assumptions!$C$151*Assumptions!$D$151 -> 2340 | D10: =HR_Model!D$73*Assumptions!$C$151*Assumptions!$D$151 -> 0 | E10: =HR_Model!E$73*Assumptions!$C$151*Assumptions!$D$151 -> 0 | F10: =HR_Model!F$73*Assumptions!$C$151*Assumptions!$D$151 -> 0 | G10: =HR_Model!G$73*Assumptions!$C$151*Assumptions!$D$151 -> 0 | H10: =HR_Model!H$73*Assumptions!$C$151*Assumptions!$D$151 -> 0 | I10: =HR_Model!I$73*Assumptions!$C$151*Assumptions!$D$151 -> 0 | J10: =HR_Model!J$73*Assumptions!$C$151*Assumptions!$D$151 -> 0 | ... AL10: =HR_Model!AL$73*Assumptions!$C$151*Assumptions!$D$151 -> 0 | AN10: =SUM(C10:N10) -> 2340 | AO10: =SUM(O10:Z10) -> 1170 | AP10: =SUM(AA10:AL10) -> 1170
A11: Office fit-out — Cairo | B11: one-off · 60 month life | C11: =IF(1=Assumptions!$C$155,Assumptions!$D$155,0) -> 14000 | D11: =IF(2=Assumptions!$C$155,Assumptions!$D$155,0) -> 0 | E11: =IF(3=Assumptions!$C$155,Assumptions!$D$155,0) -> 0 | F11: =IF(4=Assumptions!$C$155,Assumptions!$D$155,0) -> 0 | G11: =IF(5=Assumptions!$C$155,Assumptions!$D$155,0) -> 0 | H11: =IF(6=Assumptions!$C$155,Assumptions!$D$155,0) -> 0 | I11: =IF(7=Assumptions!$C$155,Assumptions!$D$155,0) -> 0 | J11: =IF(8=Assumptions!$C$155,Assumptions!$D$155,0) -> 0 | K11: =IF(9=Assumptions!$C$155,Assumptions!$D$155,0) -> 0 | L11: =IF(10=Assumptions!$C$155,Assumptions!$D$155,0) -> 0 | M11: =IF(11=Assumptions!$C$155,Assumptions!$D$155,0) -> 0 | N11: =IF(12=Assumptions!$C$155,Assumptions!$D$155,0) -> 0 | O11: =IF(13=Assumptions!$C$155,Assumptions!$D$155,0) -> 0 | P11: =IF(14=Assumptions!$C$155,Assumptions!$D$155,0) -> 0 | Q11: =IF(15=Assumptions!$C$155,Assumptions!$D$155,0) -> 0 | R11: =IF(16=Assumptions!$C$155,Assumptions!$D$155,0) -> 0 | S11: =IF(17=Assumptions!$C$155,Assumptions!$D$155,0) -> 0 | T11: =IF(18=Assumptions!$C$155,Assumptions!$D$155,0) -> 0 | U11: =IF(19=Assumptions!$C$155,Assumptions!$D$155,0) -> 0 | V11: =IF(20=Assumptions!$C$155,Assumptions!$D$155,0) -> 0 | W11: =IF(21=Assumptions!$C$155,Assumptions!$D$155,0) -> 0 | X11: =IF(22=Assumptions!$C$155,Assumptions!$D$155,0) -> 0 | Y11: =IF(23=Assumptions!$C$155,Assumptions!$D$155,0) -> 0 | Z11: =IF(24=Assumptions!$C$155,Assumptions!$D$155,0) -> 0 | AA11: =IF(25=Assumptions!$C$155,Assumptions!$D$155,0) -> 0 | AB11: =IF(26=Assumptions!$C$155,Assumptions!$D$155,0) -> 0 | AC11: =IF(27=Assumptions!$C$155,Assumptions!$D$155,0) -> 0 | AD11: =IF(28=Assumptions!$C$155,Assumptions!$D$155,0) -> 0 | AE11: =IF(29=Assumptions!$C$155,Assumptions!$D$155,0) -> 0 | AF11: =IF(30=Assumptions!$C$155,Assumptions!$D$155,0) -> 0 | AG11: =IF(31=Assumptions!$C$155,Assumptions!$D$155,0) -> 0 | AH11: =IF(32=Assumptions!$C$155,Assumptions!$D$155,0) -> 0 | AI11: =IF(33=Assumptions!$C$155,Assumptions!$D$155,0) -> 0 | AJ11: =IF(34=Assumptions!$C$155,Assumptions!$D$155,0) -> 0 | AK11: =IF(35=Assumptions!$C$155,Assumptions!$D$155,0) -> 0 | AL11: =IF(36=Assumptions!$C$155,Assumptions!$D$155,0) -> 0 | AN11: =SUM(C11:N11) -> 14000 | AO11: =SUM(O11:Z11) -> 0 | AP11: =SUM(AA11:AL11) -> 0
A12: Mission Zero production kit — camera, audio, lighting | B12: one-off · 48 month life | C12: =IF(1=Assumptions!$C$156,Assumptions!$D$156,0) -> 0 | D12: =IF(2=Assumptions!$C$156,Assumptions!$D$156,0) -> 9500 | E12: =IF(3=Assumptions!$C$156,Assumptions!$D$156,0) -> 0 | F12: =IF(4=Assumptions!$C$156,Assumptions!$D$156,0) -> 0 | G12: =IF(5=Assumptions!$C$156,Assumptions!$D$156,0) -> 0 | H12: =IF(6=Assumptions!$C$156,Assumptions!$D$156,0) -> 0 | I12: =IF(7=Assumptions!$C$156,Assumptions!$D$156,0) -> 0 | J12: =IF(8=Assumptions!$C$156,Assumptions!$D$156,0) -> 0 | K12: =IF(9=Assumptions!$C$156,Assumptions!$D$156,0) -> 0 | L12: =IF(10=Assumptions!$C$156,Assumptions!$D$156,0) -> 0 | M12: =IF(11=Assumptions!$C$156,Assumptions!$D$156,0) -> 0 | N12: =IF(12=Assumptions!$C$156,Assumptions!$D$156,0) -> 0 | O12: =IF(13=Assumptions!$C$156,Assumptions!$D$156,0) -> 0 | P12: =IF(14=Assumptions!$C$156,Assumptions!$D$156,0) -> 0 | Q12: =IF(15=Assumptions!$C$156,Assumptions!$D$156,0) -> 0 | R12: =IF(16=Assumptions!$C$156,Assumptions!$D$156,0) -> 0 | S12: =IF(17=Assumptions!$C$156,Assumptions!$D$156,0) -> 0 | T12: =IF(18=Assumptions!$C$156,Assumptions!$D$156,0) -> 0 | U12: =IF(19=Assumptions!$C$156,Assumptions!$D$156,0) -> 0 | V12: =IF(20=Assumptions!$C$156,Assumptions!$D$156,0) -> 0 | W12: =IF(21=Assumptions!$C$156,Assumptions!$D$156,0) -> 0 | X12: =IF(22=Assumptions!$C$156,Assumptions!$D$156,0) -> 0 | Y12: =IF(23=Assumptions!$C$156,Assumptions!$D$156,0) -> 0 | Z12: =IF(24=Assumptions!$C$156,Assumptions!$D$156,0) -> 0 | AA12: =IF(25=Assumptions!$C$156,Assumptions!$D$156,0) -> 0 | AB12: =IF(26=Assumptions!$C$156,Assumptions!$D$156,0) -> 0 | AC12: =IF(27=Assumptions!$C$156,Assumptions!$D$156,0) -> 0 | AD12: =IF(28=Assumptions!$C$156,Assumptions!$D$156,0) -> 0 | AE12: =IF(29=Assumptions!$C$156,Assumptions!$D$156,0) -> 0 | AF12: =IF(30=Assumptions!$C$156,Assumptions!$D$156,0) -> 0 | AG12: =IF(31=Assumptions!$C$156,Assumptions!$D$156,0) -> 0 | AH12: =IF(32=Assumptions!$C$156,Assumptions!$D$156,0) -> 0 | AI12: =IF(33=Assumptions!$C$156,Assumptions!$D$156,0) -> 0 | AJ12: =IF(34=Assumptions!$C$156,Assumptions!$D$156,0) -> 0 | AK12: =IF(35=Assumptions!$C$156,Assumptions!$D$156,0) -> 0 | AL12: =IF(36=Assumptions!$C$156,Assumptions!$D$156,0) -> 0 | AN12: =SUM(C12:N12) -> 9500 | AO12: =SUM(O12:Z12) -> 0 | AP12: =SUM(AA12:AL12) -> 0
A13: Riyadh office setup | B13: one-off · 60 month life | C13: =IF(1=Assumptions!$C$157,Assumptions!$D$157,0) -> 0 | D13: =IF(2=Assumptions!$C$157,Assumptions!$D$157,0) -> 0 | E13: =IF(3=Assumptions!$C$157,Assumptions!$D$157,0) -> 0 | F13: =IF(4=Assumptions!$C$157,Assumptions!$D$157,0) -> 0 | G13: =IF(5=Assumptions!$C$157,Assumptions!$D$157,0) -> 0 | H13: =IF(6=Assumptions!$C$157,Assumptions!$D$157,0) -> 0 | I13: =IF(7=Assumptions!$C$157,Assumptions!$D$157,0) -> 0 | J13: =IF(8=Assumptions!$C$157,Assumptions!$D$157,0) -> 0 | K13: =IF(9=Assumptions!$C$157,Assumptions!$D$157,0) -> 0 | L13: =IF(10=Assumptions!$C$157,Assumptions!$D$157,0) -> 0 | M13: =IF(11=Assumptions!$C$157,Assumptions!$D$157,0) -> 0 | N13: =IF(12=Assumptions!$C$157,Assumptions!$D$157,0) -> 0 | O13: =IF(13=Assumptions!$C$157,Assumptions!$D$157,0) -> 0 | P13: =IF(14=Assumptions!$C$157,Assumptions!$D$157,0) -> 8500 | Q13: =IF(15=Assumptions!$C$157,Assumptions!$D$157,0) -> 0 | R13: =IF(16=Assumptions!$C$157,Assumptions!$D$157,0) -> 0 | S13: =IF(17=Assumptions!$C$157,Assumptions!$D$157,0) -> 0 | T13: =IF(18=Assumptions!$C$157,Assumptions!$D$157,0) -> 0 | U13: =IF(19=Assumptions!$C$157,Assumptions!$D$157,0) -> 0 | V13: =IF(20=Assumptions!$C$157,Assumptions!$D$157,0) -> 0 | W13: =IF(21=Assumptions!$C$157,Assumptions!$D$157,0) -> 0 | X13: =IF(22=Assumptions!$C$157,Assumptions!$D$157,0) -> 0 | Y13: =IF(23=Assumptions!$C$157,Assumptions!$D$157,0) -> 0 | Z13: =IF(24=Assumptions!$C$157,Assumptions!$D$157,0) -> 0 | AA13: =IF(25=Assumptions!$C$157,Assumptions!$D$157,0) -> 0 | AB13: =IF(26=Assumptions!$C$157,Assumptions!$D$157,0) -> 0 | AC13: =IF(27=Assumptions!$C$157,Assumptions!$D$157,0) -> 0 | AD13: =IF(28=Assumptions!$C$157,Assumptions!$D$157,0) -> 0 | AE13: =IF(29=Assumptions!$C$157,Assumptions!$D$157,0) -> 0 | AF13: =IF(30=Assumptions!$C$157,Assumptions!$D$157,0) -> 0 | AG13: =IF(31=Assumptions!$C$157,Assumptions!$D$157,0) -> 0 | AH13: =IF(32=Assumptions!$C$157,Assumptions!$D$157,0) -> 0 | AI13: =IF(33=Assumptions!$C$157,Assumptions!$D$157,0) -> 0 | AJ13: =IF(34=Assumptions!$C$157,Assumptions!$D$157,0) -> 0 | AK13: =IF(35=Assumptions!$C$157,Assumptions!$D$157,0) -> 0 | AL13: =IF(36=Assumptions!$C$157,Assumptions!$D$157,0) -> 0 | AN13: =SUM(C13:N13) -> 0 | AO13: =SUM(O13:Z13) -> 8500 | AP13: =SUM(AA13:AL13) -> 0
A14: Network, servers and security | B14: one-off · 48 month life | C14: =IF(1=Assumptions!$C$158,Assumptions!$D$158,0) -> 4200 | D14: =IF(2=Assumptions!$C$158,Assumptions!$D$158,0) -> 0 | E14: =IF(3=Assumptions!$C$158,Assumptions!$D$158,0) -> 0 | F14: =IF(4=Assumptions!$C$158,Assumptions!$D$158,0) -> 0 | G14: =IF(5=Assumptions!$C$158,Assumptions!$D$158,0) -> 0 | H14: =IF(6=Assumptions!$C$158,Assumptions!$D$158,0) -> 0 | I14: =IF(7=Assumptions!$C$158,Assumptions!$D$158,0) -> 0 | J14: =IF(8=Assumptions!$C$158,Assumptions!$D$158,0) -> 0 | K14: =IF(9=Assumptions!$C$158,Assumptions!$D$158,0) -> 0 | L14: =IF(10=Assumptions!$C$158,Assumptions!$D$158,0) -> 0 | M14: =IF(11=Assumptions!$C$158,Assumptions!$D$158,0) -> 0 | N14: =IF(12=Assumptions!$C$158,Assumptions!$D$158,0) -> 0 | O14: =IF(13=Assumptions!$C$158,Assumptions!$D$158,0) -> 0 | P14: =IF(14=Assumptions!$C$158,Assumptions!$D$158,0) -> 0 | Q14: =IF(15=Assumptions!$C$158,Assumptions!$D$158,0) -> 0 | R14: =IF(16=Assumptions!$C$158,Assumptions!$D$158,0) -> 0 | S14: =IF(17=Assumptions!$C$158,Assumptions!$D$158,0) -> 0 | T14: =IF(18=Assumptions!$C$158,Assumptions!$D$158,0) -> 0 | U14: =IF(19=Assumptions!$C$158,Assumptions!$D$158,0) -> 0 | V14: =IF(20=Assumptions!$C$158,Assumptions!$D$158,0) -> 0 | W14: =IF(21=Assumptions!$C$158,Assumptions!$D$158,0) -> 0 | X14: =IF(22=Assumptions!$C$158,Assumptions!$D$158,0) -> 0 | Y14: =IF(23=Assumptions!$C$158,Assumptions!$D$158,0) -> 0 | Z14: =IF(24=Assumptions!$C$158,Assumptions!$D$158,0) -> 0 | AA14: =IF(25=Assumptions!$C$158,Assumptions!$D$158,0) -> 0 | AB14: =IF(26=Assumptions!$C$158,Assumptions!$D$158,0) -> 0 | AC14: =IF(27=Assumptions!$C$158,Assumptions!$D$158,0) -> 0 | AD14: =IF(28=Assumptions!$C$158,Assumptions!$D$158,0) -> 0 | AE14: =IF(29=Assumptions!$C$158,Assumptions!$D$158,0) -> 0 | AF14: =IF(30=Assumptions!$C$158,Assumptions!$D$158,0) -> 0 | AG14: =IF(31=Assumptions!$C$158,Assumptions!$D$158,0) -> 0 | AH14: =IF(32=Assumptions!$C$158,Assumptions!$D$158,0) -> 0 | AI14: =IF(33=Assumptions!$C$158,Assumptions!$D$158,0) -> 0 | AJ14: =IF(34=Assumptions!$C$158,Assumptions!$D$158,0) -> 0 | AK14: =IF(35=Assumptions!$C$158,Assumptions!$D$158,0) -> 0 | AL14: =IF(36=Assumptions!$C$158,Assumptions!$D$158,0) -> 0 | AN14: =SUM(C14:N14) -> 4200 | AO14: =SUM(O14:Z14) -> 0 | AP14: =SUM(AA14:AL14) -> 0
A15: Capitalised platform development | B15: one-off · 36 month life | C15: =IF(1=Assumptions!$C$159,Assumptions!$D$159,0) -> 86000 | D15: =IF(2=Assumptions!$C$159,Assumptions!$D$159,0) -> 0 | E15: =IF(3=Assumptions!$C$159,Assumptions!$D$159,0) -> 0 | F15: =IF(4=Assumptions!$C$159,Assumptions!$D$159,0) -> 0 | G15: =IF(5=Assumptions!$C$159,Assumptions!$D$159,0) -> 0 | H15: =IF(6=Assumptions!$C$159,Assumptions!$D$159,0) -> 0 | I15: =IF(7=Assumptions!$C$159,Assumptions!$D$159,0) -> 0 | J15: =IF(8=Assumptions!$C$159,Assumptions!$D$159,0) -> 0 | K15: =IF(9=Assumptions!$C$159,Assumptions!$D$159,0) -> 0 | L15: =IF(10=Assumptions!$C$159,Assumptions!$D$159,0) -> 0 | M15: =IF(11=Assumptions!$C$159,Assumptions!$D$159,0) -> 0 | N15: =IF(12=Assumptions!$C$159,Assumptions!$D$159,0) -> 0 | O15: =IF(13=Assumptions!$C$159,Assumptions!$D$159,0) -> 0 | P15: =IF(14=Assumptions!$C$159,Assumptions!$D$159,0) -> 0 | Q15: =IF(15=Assumptions!$C$159,Assumptions!$D$159,0) -> 0 | R15: =IF(16=Assumptions!$C$159,Assumptions!$D$159,0) -> 0 | S15: =IF(17=Assumptions!$C$159,Assumptions!$D$159,0) -> 0 | T15: =IF(18=Assumptions!$C$159,Assumptions!$D$159,0) -> 0 | U15: =IF(19=Assumptions!$C$159,Assumptions!$D$159,0) -> 0 | V15: =IF(20=Assumptions!$C$159,Assumptions!$D$159,0) -> 0 | W15: =IF(21=Assumptions!$C$159,Assumptions!$D$159,0) -> 0 | X15: =IF(22=Assumptions!$C$159,Assumptions!$D$159,0) -> 0 | Y15: =IF(23=Assumptions!$C$159,Assumptions!$D$159,0) -> 0 | Z15: =IF(24=Assumptions!$C$159,Assumptions!$D$159,0) -> 0 | AA15: =IF(25=Assumptions!$C$159,Assumptions!$D$159,0) -> 0 | AB15: =IF(26=Assumptions!$C$159,Assumptions!$D$159,0) -> 0 | AC15: =IF(27=Assumptions!$C$159,Assumptions!$D$159,0) -> 0 | AD15: =IF(28=Assumptions!$C$159,Assumptions!$D$159,0) -> 0 | AE15: =IF(29=Assumptions!$C$159,Assumptions!$D$159,0) -> 0 | AF15: =IF(30=Assumptions!$C$159,Assumptions!$D$159,0) -> 0 | AG15: =IF(31=Assumptions!$C$159,Assumptions!$D$159,0) -> 0 | AH15: =IF(32=Assumptions!$C$159,Assumptions!$D$159,0) -> 0 | AI15: =IF(33=Assumptions!$C$159,Assumptions!$D$159,0) -> 0 | AJ15: =IF(34=Assumptions!$C$159,Assumptions!$D$159,0) -> 0 | AK15: =IF(35=Assumptions!$C$159,Assumptions!$D$159,0) -> 0 | AL15: =IF(36=Assumptions!$C$159,Assumptions!$D$159,0) -> 0 | AN15: =SUM(C15:N15) -> 86000 | AO15: =SUM(O15:Z15) -> 0 | AP15: =SUM(AA15:AL15) -> 0
A16: Capitalised curriculum and certification build | B16: one-off · 36 month life | C16: =IF(1=Assumptions!$C$160,Assumptions!$D$160,0) -> 42000 | D16: =IF(2=Assumptions!$C$160,Assumptions!$D$160,0) -> 0 | E16: =IF(3=Assumptions!$C$160,Assumptions!$D$160,0) -> 0 | F16: =IF(4=Assumptions!$C$160,Assumptions!$D$160,0) -> 0 | G16: =IF(5=Assumptions!$C$160,Assumptions!$D$160,0) -> 0 | H16: =IF(6=Assumptions!$C$160,Assumptions!$D$160,0) -> 0 | I16: =IF(7=Assumptions!$C$160,Assumptions!$D$160,0) -> 0 | J16: =IF(8=Assumptions!$C$160,Assumptions!$D$160,0) -> 0 | K16: =IF(9=Assumptions!$C$160,Assumptions!$D$160,0) -> 0 | L16: =IF(10=Assumptions!$C$160,Assumptions!$D$160,0) -> 0 | M16: =IF(11=Assumptions!$C$160,Assumptions!$D$160,0) -> 0 | N16: =IF(12=Assumptions!$C$160,Assumptions!$D$160,0) -> 0 | O16: =IF(13=Assumptions!$C$160,Assumptions!$D$160,0) -> 0 | P16: =IF(14=Assumptions!$C$160,Assumptions!$D$160,0) -> 0 | Q16: =IF(15=Assumptions!$C$160,Assumptions!$D$160,0) -> 0 | R16: =IF(16=Assumptions!$C$160,Assumptions!$D$160,0) -> 0 | S16: =IF(17=Assumptions!$C$160,Assumptions!$D$160,0) -> 0 | T16: =IF(18=Assumptions!$C$160,Assumptions!$D$160,0) -> 0 | U16: =IF(19=Assumptions!$C$160,Assumptions!$D$160,0) -> 0 | V16: =IF(20=Assumptions!$C$160,Assumptions!$D$160,0) -> 0 | W16: =IF(21=Assumptions!$C$160,Assumptions!$D$160,0) -> 0 | X16: =IF(22=Assumptions!$C$160,Assumptions!$D$160,0) -> 0 | Y16: =IF(23=Assumptions!$C$160,Assumptions!$D$160,0) -> 0 | Z16: =IF(24=Assumptions!$C$160,Assumptions!$D$160,0) -> 0 | AA16: =IF(25=Assumptions!$C$160,Assumptions!$D$160,0) -> 0 | AB16: =IF(26=Assumptions!$C$160,Assumptions!$D$160,0) -> 0 | AC16: =IF(27=Assumptions!$C$160,Assumptions!$D$160,0) -> 0 | AD16: =IF(28=Assumptions!$C$160,Assumptions!$D$160,0) -> 0 | AE16: =IF(29=Assumptions!$C$160,Assumptions!$D$160,0) -> 0 | AF16: =IF(30=Assumptions!$C$160,Assumptions!$D$160,0) -> 0 | AG16: =IF(31=Assumptions!$C$160,Assumptions!$D$160,0) -> 0 | AH16: =IF(32=Assumptions!$C$160,Assumptions!$D$160,0) -> 0 | AI16: =IF(33=Assumptions!$C$160,Assumptions!$D$160,0) -> 0 | AJ16: =IF(34=Assumptions!$C$160,Assumptions!$D$160,0) -> 0 | AK16: =IF(35=Assumptions!$C$160,Assumptions!$D$160,0) -> 0 | AL16: =IF(36=Assumptions!$C$160,Assumptions!$D$160,0) -> 0 | AN16: =SUM(C16:N16) -> 42000 | AO16: =SUM(O16:Z16) -> 0 | AP16: =SUM(AA16:AL16) -> 0
A17: Trademark, IP registration and entity formation | B17: one-off · 60 month life | C17: =IF(1=Assumptions!$C$161,Assumptions!$D$161,0) -> 11000 | D17: =IF(2=Assumptions!$C$161,Assumptions!$D$161,0) -> 0 | E17: =IF(3=Assumptions!$C$161,Assumptions!$D$161,0) -> 0 | F17: =IF(4=Assumptions!$C$161,Assumptions!$D$161,0) -> 0 | G17: =IF(5=Assumptions!$C$161,Assumptions!$D$161,0) -> 0 | H17: =IF(6=Assumptions!$C$161,Assumptions!$D$161,0) -> 0 | I17: =IF(7=Assumptions!$C$161,Assumptions!$D$161,0) -> 0 | J17: =IF(8=Assumptions!$C$161,Assumptions!$D$161,0) -> 0 | K17: =IF(9=Assumptions!$C$161,Assumptions!$D$161,0) -> 0 | L17: =IF(10=Assumptions!$C$161,Assumptions!$D$161,0) -> 0 | M17: =IF(11=Assumptions!$C$161,Assumptions!$D$161,0) -> 0 | N17: =IF(12=Assumptions!$C$161,Assumptions!$D$161,0) -> 0 | O17: =IF(13=Assumptions!$C$161,Assumptions!$D$161,0) -> 0 | P17: =IF(14=Assumptions!$C$161,Assumptions!$D$161,0) -> 0 | Q17: =IF(15=Assumptions!$C$161,Assumptions!$D$161,0) -> 0 | R17: =IF(16=Assumptions!$C$161,Assumptions!$D$161,0) -> 0 | S17: =IF(17=Assumptions!$C$161,Assumptions!$D$161,0) -> 0 | T17: =IF(18=Assumptions!$C$161,Assumptions!$D$161,0) -> 0 | U17: =IF(19=Assumptions!$C$161,Assumptions!$D$161,0) -> 0 | V17: =IF(20=Assumptions!$C$161,Assumptions!$D$161,0) -> 0 | W17: =IF(21=Assumptions!$C$161,Assumptions!$D$161,0) -> 0 | X17: =IF(22=Assumptions!$C$161,Assumptions!$D$161,0) -> 0 | Y17: =IF(23=Assumptions!$C$161,Assumptions!$D$161,0) -> 0 | Z17: =IF(24=Assumptions!$C$161,Assumptions!$D$161,0) -> 0 | AA17: =IF(25=Assumptions!$C$161,Assumptions!$D$161,0) -> 0 | AB17: =IF(26=Assumptions!$C$161,Assumptions!$D$161,0) -> 0 | AC17: =IF(27=Assumptions!$C$161,Assumptions!$D$161,0) -> 0 | AD17: =IF(28=Assumptions!$C$161,Assumptions!$D$161,0) -> 0 | AE17: =IF(29=Assumptions!$C$161,Assumptions!$D$161,0) -> 0 | AF17: =IF(30=Assumptions!$C$161,Assumptions!$D$161,0) -> 0 | AG17: =IF(31=Assumptions!$C$161,Assumptions!$D$161,0) -> 0 | AH17: =IF(32=Assumptions!$C$161,Assumptions!$D$161,0) -> 0 | AI17: =IF(33=Assumptions!$C$161,Assumptions!$D$161,0) -> 0 | AJ17: =IF(34=Assumptions!$C$161,Assumptions!$D$161,0) -> 0 | AK17: =IF(35=Assumptions!$C$161,Assumptions!$D$161,0) -> 0 | AL17: =IF(36=Assumptions!$C$161,Assumptions!$D$161,0) -> 0 | AN17: =SUM(C17:N17) -> 11000 | AO17: =SUM(O17:Z17) -> 0 | AP17: =SUM(AA17:AL17) -> 0
A18: Total capital expenditure | B18: feeds investing activities | C18: =SUM(C7:C17) -> 173520 | D18: =SUM(D7:D17) -> 9500 | E18: =SUM(E7:E17) -> 0 | F18: =SUM(F7:F17) -> 0 | G18: =SUM(G7:G17) -> 0 | H18: =SUM(H7:H17) -> 0 | I18: =SUM(I7:I17) -> 0 | J18: =SUM(J7:J17) -> 0 | ... AL18: =SUM(AL7:AL17) -> 0 | AN18: =SUM(C18:N18) -> 183020 | AO18: =SUM(O18:Z18) -> 16660 | AP18: =SUM(AA18:AL18) -> 8160
A20: GROSS COST — CUMULATIVE
A21: Line item | B21: Driver / source | C21: Oct 26 | D21: Nov 26 | E21: Dec 26 | F21: Jan 26 | G21: Feb 26 | H21: Mar 26 | I21: Apr 26 | J21: May 26 | K21: Jun 26 | L21: Jul 27 | M21: Aug 27 | N21: Sep 27 | O21: Oct 27 | P21: Nov 27 | Q21: Dec 27 | R21: Jan 27 | S21: Feb 27 | T21: Mar 27 | U21: Apr 27 | V21: May 27 | W21: Jun 27 | X21: Jul 28 | Y21: Aug 28 | Z21: Sep 28 | AA21: Oct 28 | AB21: Nov 28 | AC21: Dec 28 | AD21: Jan 28 | AE21: Feb 28 | AF21: Mar 28 | AG21: Apr 28 | AH21: May 28 | AI21: Jun 28 | AJ21: Jul 29 | AK21: Aug 29 | AL21: Sep 29 | AN21: YEAR 1 | AO21: YEAR 2 | AP21: YEAR 3
A22: Laptop | C22: =C7 -> 8400 | D22: =C22+D7 -> 8400 | E22: =D22+E7 -> 8400 | F22: =E22+F7 -> 8400 | G22: =F22+G7 -> 8400 | H22: =G22+H7 -> 8400 | I22: =H22+I7 -> 8400 | J22: =I22+J7 -> 8400 | K22: =J22+K7 -> 8400 | ... AL22: =AK22+AL7 -> 16800 | AN22: =N22 -> 8400 | AO22: =Z22 -> 12600 | AP22: =AL22 -> 16800
A23: Desk, chair and storage | C23: =C8 -> 3720 | D23: =C23+D8 -> 3720 | E23: =D23+E8 -> 3720 | F23: =E23+F8 -> 3720 | G23: =F23+G8 -> 3720 | H23: =G23+H8 -> 3720 | I23: =H23+I8 -> 3720 | J23: =I23+J8 -> 3720 | K23: =J23+K8 -> 3720 | ... AL23: =AK23+AL8 -> 7440 | AN23: =N23 -> 3720 | AO23: =Z23 -> 5580 | AP23: =AL23 -> 7440
A24: Monitor and peripherals | C24: =C9 -> 1860 | D24: =C24+D9 -> 1860 | E24: =D24+E9 -> 1860 | F24: =E24+F9 -> 1860 | G24: =F24+G9 -> 1860 | H24: =G24+H9 -> 1860 | I24: =H24+I9 -> 1860 | J24: =I24+J9 -> 1860 | K24: =J24+K9 -> 1860 | ... AL24: =AK24+AL9 -> 3720 | AN24: =N24 -> 1860 | AO24: =Z24 -> 2790 | AP24: =AL24 -> 3720
A25: Mobile handset and line setup | C25: =C10 -> 2340 | D25: =C25+D10 -> 2340 | E25: =D25+E10 -> 2340 | F25: =E25+F10 -> 2340 | G25: =F25+G10 -> 2340 | H25: =G25+H10 -> 2340 | I25: =H25+I10 -> 2340 | J25: =I25+J10 -> 2340 | K25: =J25+K10 -> 2340 | ... AL25: =AK25+AL10 -> 4680 | AN25: =N25 -> 2340 | AO25: =Z25 -> 3510 | AP25: =AL25 -> 4680
A26: Office fit-out — Cairo | C26: =C11 -> 14000 | D26: =C26+D11 -> 14000 | E26: =D26+E11 -> 14000 | F26: =E26+F11 -> 14000 | G26: =F26+G11 -> 14000 | H26: =G26+H11 -> 14000 | I26: =H26+I11 -> 14000 | J26: =I26+J11 -> 14000 | K26: =J26+K11 -> 14000 | ... AL26: =AK26+AL11 -> 14000 | AN26: =N26 -> 14000 | AO26: =Z26 -> 14000 | AP26: =AL26 -> 14000
A27: Mission Zero production kit — camera, audio, lighting | C27: =C12 -> 0 | D27: =C27+D12 -> 9500 | E27: =D27+E12 -> 9500 | F27: =E27+F12 -> 9500 | G27: =F27+G12 -> 9500 | H27: =G27+H12 -> 9500 | I27: =H27+I12 -> 9500 | J27: =I27+J12 -> 9500 | K27: =J27+K12 -> 9500 | ... AL27: =AK27+AL12 -> 9500 | AN27: =N27 -> 9500 | AO27: =Z27 -> 9500 | AP27: =AL27 -> 9500
A28: Riyadh office setup | C28: =C13 -> 0 | D28: =C28+D13 -> 0 | E28: =D28+E13 -> 0 | F28: =E28+F13 -> 0 | G28: =F28+G13 -> 0 | H28: =G28+H13 -> 0 | I28: =H28+I13 -> 0 | J28: =I28+J13 -> 0 | K28: =J28+K13 -> 0 | ... AL28: =AK28+AL13 -> 8500 | AN28: =N28 -> 0 | AO28: =Z28 -> 8500 | AP28: =AL28 -> 8500
A29: Network, servers and security | C29: =C14 -> 4200 | D29: =C29+D14 -> 4200 | E29: =D29+E14 -> 4200 | F29: =E29+F14 -> 4200 | G29: =F29+G14 -> 4200 | H29: =G29+H14 -> 4200 | I29: =H29+I14 -> 4200 | J29: =I29+J14 -> 4200 | K29: =J29+K14 -> 4200 | ... AL29: =AK29+AL14 -> 4200 | AN29: =N29 -> 4200 | AO29: =Z29 -> 4200 | AP29: =AL29 -> 4200
A30: Capitalised platform development | C30: =C15 -> 86000 | D30: =C30+D15 -> 86000 | E30: =D30+E15 -> 86000 | F30: =E30+F15 -> 86000 | G30: =F30+G15 -> 86000 | H30: =G30+H15 -> 86000 | I30: =H30+I15 -> 86000 | J30: =I30+J15 -> 86000 | K30: =J30+K15 -> 86000 | ... AL30: =AK30+AL15 -> 86000 | AN30: =N30 -> 86000 | AO30: =Z30 -> 86000 | AP30: =AL30 -> 86000
A31: Capitalised curriculum and certification build | C31: =C16 -> 42000 | D31: =C31+D16 -> 42000 | E31: =D31+E16 -> 42000 | F31: =E31+F16 -> 42000 | G31: =F31+G16 -> 42000 | H31: =G31+H16 -> 42000 | I31: =H31+I16 -> 42000 | J31: =I31+J16 -> 42000 | K31: =J31+K16 -> 42000 | ... AL31: =AK31+AL16 -> 42000 | AN31: =N31 -> 42000 | AO31: =Z31 -> 42000 | AP31: =AL31 -> 42000
A32: Trademark, IP registration and entity formation | C32: =C17 -> 11000 | D32: =C32+D17 -> 11000 | E32: =D32+E17 -> 11000 | F32: =E32+F17 -> 11000 | G32: =F32+G17 -> 11000 | H32: =G32+H17 -> 11000 | I32: =H32+I17 -> 11000 | J32: =I32+J17 -> 11000 | K32: =J32+K17 -> 11000 | ... AL32: =AK32+AL17 -> 11000 | AN32: =N32 -> 11000 | AO32: =Z32 -> 11000 | AP32: =AL32 -> 11000
A33: Total gross assets | C33: =SUM(C22:C32) -> 173520 | D33: =SUM(D22:D32) -> 183020 | E33: =SUM(E22:E32) -> 183020 | F33: =SUM(F22:F32) -> 183020 | G33: =SUM(G22:G32) -> 183020 | H33: =SUM(H22:H32) -> 183020 | I33: =SUM(I22:I32) -> 183020 | J33: =SUM(J22:J32) -> 183020 | ... AL33: =SUM(AL22:AL32) -> 207840 | AN33: =N33 -> 183020 | AO33: =Z33 -> 199680 | AP33: =AL33 -> 207840

Sheet Acquisition
A1: Acquisition
A2: Two funnels. Offline channels create sign-ups and institutional leads; online channels create reach. Both land on the same first step — Mission 01 — and only then on a paid plan.
A5: OFFLINE CHANNELS — THEY CREATE SIGN-UPS
A6: Line item | B6: Driver / source | C6: Oct 26 | D6: Nov 26 | E6: Dec 26 | F6: Jan 26 | G6: Feb 26 | H6: Mar 26 | I6: Apr 26 | J6: May 26 | K6: Jun 26 | L6: Jul 27 | M6: Aug 27 | N6: Sep 27 | O6: Oct 27 | P6: Nov 27 | Q6: Dec 27 | R6: Jan 27 | S6: Feb 27 | T6: Mar 27 | U6: Apr 27 | V6: May 27 | W6: Jun 27 | X6: Jul 28 | Y6: Aug 28 | Z6: Sep 28 | AA6: Oct 28 | AB6: Nov 28 | AC6: Dec 28 | AD6: Jan 28 | AE6: Feb 28 | AF6: Mar 28 | AG6: Apr 28 | AH6: May 28 | AI6: Jun 28 | AJ6: Jul 29 | AK6: Aug 29 | AL6: Sep 29 | AN6: YEAR 1 | AO6: YEAR 2 | AP6: YEAR 3
A7: Campus workshops | B7: activities in the month | C7: =Assumptions!$C$55 -> 2 | D7: =Assumptions!$C$55 -> 2 | E7: =Assumptions!$C$55 -> 2 | F7: =Assumptions!$C$55 -> 2 | G7: =Assumptions!$C$55 -> 2 | H7: =Assumptions!$C$55 -> 2 | I7: =Assumptions!$C$55 -> 2 | J7: =Assumptions!$C$55 -> 2 | ... N7: =Assumptions!$C$55 -> 2 | O7: =Assumptions!$D$55 -> 6 | P7: =Assumptions!$D$55 -> 6 | Q7: =Assumptions!$D$55 -> 6 | R7: =Assumptions!$D$55 -> 6 | S7: =Assumptions!$D$55 -> 6 | T7: =Assumptions!$D$55 -> 6 | U7: =Assumptions!$D$55 -> 6 | V7: =Assumptions!$D$55 -> 6 | ... Z7: =Assumptions!$D$55 -> 6 | AA7: =Assumptions!$E$55 -> 11 | AB7: =Assumptions!$E$55 -> 11 | AC7: =Assumptions!$E$55 -> 11 | AD7: =Assumptions!$E$55 -> 11 | AE7: =Assumptions!$E$55 -> 11 | AF7: =Assumptions!$E$55 -> 11 | AG7: =Assumptions!$E$55 -> 11 | AH7: =Assumptions!$E$55 -> 11 | ... AL7: =Assumptions!$E$55 -> 11 | AN7: =SUM(C7:N7) -> 24 | AO7: =SUM(O7:Z7) -> 72 | AP7: =SUM(AA7:AL7) -> 132
A8: Cost | C8: =C7*Assumptions!$F$55 -> 840 | D8: =D7*Assumptions!$F$55 -> 840 | E8: =E7*Assumptions!$F$55 -> 840 | F8: =F7*Assumptions!$F$55 -> 840 | G8: =G7*Assumptions!$F$55 -> 840 | H8: =H7*Assumptions!$F$55 -> 840 | I8: =I7*Assumptions!$F$55 -> 840 | J8: =J7*Assumptions!$F$55 -> 840 | ... AL8: =AL7*Assumptions!$F$55 -> 4620 | AN8: =SUM(C8:N8) -> 10080 | AO8: =SUM(O8:Z8) -> 30240 | AP8: =SUM(AA8:AL8) -> 55440
A9: Free sign-ups | C9: =C7*Assumptions!$G$55 -> 90 | D9: =D7*Assumptions!$G$55 -> 90 | E9: =E7*Assumptions!$G$55 -> 90 | F9: =F7*Assumptions!$G$55 -> 90 | G9: =G7*Assumptions!$G$55 -> 90 | H9: =H7*Assumptions!$G$55 -> 90 | I9: =I7*Assumptions!$G$55 -> 90 | J9: =J7*Assumptions!$G$55 -> 90 | ... AL9: =AL7*Assumptions!$G$55 -> 495 | AN9: =SUM(C9:N9) -> 1080 | AO9: =SUM(O9:Z9) -> 3240 | AP9: =SUM(AA9:AL9) -> 5940
A10: Institutional leads | C10: =C7*Assumptions!$H$55 -> 1.8 | D10: =D7*Assumptions!$H$55 -> 1.8 | E10: =E7*Assumptions!$H$55 -> 1.8 | F10: =F7*Assumptions!$H$55 -> 1.8 | G10: =G7*Assumptions!$H$55 -> 1.8 | H10: =H7*Assumptions!$H$55 -> 1.8 | I10: =I7*Assumptions!$H$55 -> 1.8 | J10: =J7*Assumptions!$H$55 -> 1.8 | ... AL10: =AL7*Assumptions!$H$55 -> 9.9 | AN10: =SUM(C10:N10) -> 21.6 | AO10: =SUM(O10:Z10) -> 64.8 | AP10: =SUM(AA10:AL10) -> 118.8
A11: Ambassador campus activity | B11: activities in the month | C11: =Assumptions!$C$56 -> 3 | D11: =Assumptions!$C$56 -> 3 | E11: =Assumptions!$C$56 -> 3 | F11: =Assumptions!$C$56 -> 3 | G11: =Assumptions!$C$56 -> 3 | H11: =Assumptions!$C$56 -> 3 | I11: =Assumptions!$C$56 -> 3 | J11: =Assumptions!$C$56 -> 3 | ... N11: =Assumptions!$C$56 -> 3 | O11: =Assumptions!$D$56 -> 8 | P11: =Assumptions!$D$56 -> 8 | Q11: =Assumptions!$D$56 -> 8 | R11: =Assumptions!$D$56 -> 8 | S11: =Assumptions!$D$56 -> 8 | T11: =Assumptions!$D$56 -> 8 | U11: =Assumptions!$D$56 -> 8 | V11: =Assumptions!$D$56 -> 8 | ... Z11: =Assumptions!$D$56 -> 8 | AA11: =Assumptions!$E$56 -> 14 | AB11: =Assumptions!$E$56 -> 14 | AC11: =Assumptions!$E$56 -> 14 | AD11: =Assumptions!$E$56 -> 14 | AE11: =Assumptions!$E$56 -> 14 | AF11: =Assumptions!$E$56 -> 14 | AG11: =Assumptions!$E$56 -> 14 | AH11: =Assumptions!$E$56 -> 14 | ... AL11: =Assumptions!$E$56 -> 14 | AN11: =SUM(C11:N11) -> 36 | AO11: =SUM(O11:Z11) -> 96 | AP11: =SUM(AA11:AL11) -> 168
A12: Cost | C12: =C11*Assumptions!$F$56 -> 540 | D12: =D11*Assumptions!$F$56 -> 540 | E12: =E11*Assumptions!$F$56 -> 540 | F12: =F11*Assumptions!$F$56 -> 540 | G12: =G11*Assumptions!$F$56 -> 540 | H12: =H11*Assumptions!$F$56 -> 540 | I12: =I11*Assumptions!$F$56 -> 540 | J12: =J11*Assumptions!$F$56 -> 540 | ... AL12: =AL11*Assumptions!$F$56 -> 2520 | AN12: =SUM(C12:N12) -> 6480 | AO12: =SUM(O12:Z12) -> 17280 | AP12: =SUM(AA12:AL12) -> 30240
A13: Free sign-ups | C13: =C11*Assumptions!$G$56 -> 114 | D13: =D11*Assumptions!$G$56 -> 114 | E13: =E11*Assumptions!$G$56 -> 114 | F13: =F11*Assumptions!$G$56 -> 114 | G13: =G11*Assumptions!$G$56 -> 114 | H13: =H11*Assumptions!$G$56 -> 114 | I13: =I11*Assumptions!$G$56 -> 114 | J13: =J11*Assumptions!$G$56 -> 114 | ... AL13: =AL11*Assumptions!$G$56 -> 532 | AN13: =SUM(C13:N13) -> 1368 | AO13: =SUM(O13:Z13) -> 3648 | AP13: =SUM(AA13:AL13) -> 6384
A14: Institutional leads | C14: =C11*Assumptions!$H$56 -> 1.8 | D14: =D11*Assumptions!$H$56 -> 1.8 | E14: =E11*Assumptions!$H$56 -> 1.8 | F14: =F11*Assumptions!$H$56 -> 1.8 | G14: =G11*Assumptions!$H$56 -> 1.8 | H14: =H11*Assumptions!$H$56 -> 1.8 | I14: =I11*Assumptions!$H$56 -> 1.8 | J14: =J11*Assumptions!$H$56 -> 1.8 | ... AL14: =AL11*Assumptions!$H$56 -> 8.4 | AN14: =SUM(C14:N14) -> 21.6 | AO14: =SUM(O14:Z14) -> 57.6 | AP14: =SUM(AA14:AL14) -> 100.8
A15: Competitions and qualifying rounds | B15: activities in the month | C15: =Assumptions!$C$57 -> 0.5 | D15: =Assumptions!$C$57 -> 0.5 | E15: =Assumptions!$C$57 -> 0.5 | F15: =Assumptions!$C$57 -> 0.5 | G15: =Assumptions!$C$57 -> 0.5 | H15: =Assumptions!$C$57 -> 0.5 | I15: =Assumptions!$C$57 -> 0.5 | J15: =Assumptions!$C$57 -> 0.5 | ... N15: =Assumptions!$C$57 -> 0.5 | O15: =Assumptions!$D$57 -> 1.2 | P15: =Assumptions!$D$57 -> 1.2 | Q15: =Assumptions!$D$57 -> 1.2 | R15: =Assumptions!$D$57 -> 1.2 | S15: =Assumptions!$D$57 -> 1.2 | T15: =Assumptions!$D$57 -> 1.2 | U15: =Assumptions!$D$57 -> 1.2 | V15: =Assumptions!$D$57 -> 1.2 | ... Z15: =Assumptions!$D$57 -> 1.2 | AA15: =Assumptions!$E$57 -> 2 | AB15: =Assumptions!$E$57 -> 2 | AC15: =Assumptions!$E$57 -> 2 | AD15: =Assumptions!$E$57 -> 2 | AE15: =Assumptions!$E$57 -> 2 | AF15: =Assumptions!$E$57 -> 2 | AG15: =Assumptions!$E$57 -> 2 | AH15: =Assumptions!$E$57 -> 2 | ... AL15: =Assumptions!$E$57 -> 2 | AN15: =SUM(C15:N15) -> 6 | AO15: =SUM(O15:Z15) -> 14.4 | AP15: =SUM(AA15:AL15) -> 24
A16: Cost | C16: =C15*Assumptions!$F$57 -> 1300 | D16: =D15*Assumptions!$F$57 -> 1300 | E16: =E15*Assumptions!$F$57 -> 1300 | F16: =F15*Assumptions!$F$57 -> 1300 | G16: =G15*Assumptions!$F$57 -> 1300 | H16: =H15*Assumptions!$F$57 -> 1300 | I16: =I15*Assumptions!$F$57 -> 1300 | J16: =J15*Assumptions!$F$57 -> 1300 | ... AL16: =AL15*Assumptions!$F$57 -> 5200 | AN16: =SUM(C16:N16) -> 15600 | AO16: =SUM(O16:Z16) -> 37440 | AP16: =SUM(AA16:AL16) -> 62400
A17: Free sign-ups | C17: =C15*Assumptions!$G$57 -> 160 | D17: =D15*Assumptions!$G$57 -> 160 | E17: =E15*Assumptions!$G$57 -> 160 | F17: =F15*Assumptions!$G$57 -> 160 | G17: =G15*Assumptions!$G$57 -> 160 | H17: =H15*Assumptions!$G$57 -> 160 | I17: =I15*Assumptions!$G$57 -> 160 | J17: =J15*Assumptions!$G$57 -> 160 | ... AL17: =AL15*Assumptions!$G$57 -> 640 | AN17: =SUM(C17:N17) -> 1920 | AO17: =SUM(O17:Z17) -> 4608 | AP17: =SUM(AA17:AL17) -> 7680
A18: Institutional leads | C18: =C15*Assumptions!$H$57 -> 1.2 | D18: =D15*Assumptions!$H$57 -> 1.2 | E18: =E15*Assumptions!$H$57 -> 1.2 | F18: =F15*Assumptions!$H$57 -> 1.2 | G18: =G15*Assumptions!$H$57 -> 1.2 | H18: =H15*Assumptions!$H$57 -> 1.2 | I18: =I15*Assumptions!$H$57 -> 1.2 | J18: =J15*Assumptions!$H$57 -> 1.2 | ... AL18: =AL15*Assumptions!$H$57 -> 4.8 | AN18: =SUM(C18:N18) -> 14.4 | AO18: =SUM(O18:Z18) -> 34.56 | AP18: =SUM(AA18:AL18) -> 57.6
A19: Events, fairs and conferences | B19: activities in the month | C19: =Assumptions!$C$58 -> 1 | D19: =Assumptions!$C$58 -> 1 | E19: =Assumptions!$C$58 -> 1 | F19: =Assumptions!$C$58 -> 1 | G19: =Assumptions!$C$58 -> 1 | H19: =Assumptions!$C$58 -> 1 | I19: =Assumptions!$C$58 -> 1 | J19: =Assumptions!$C$58 -> 1 | ... N19: =Assumptions!$C$58 -> 1 | O19: =Assumptions!$D$58 -> 2 | P19: =Assumptions!$D$58 -> 2 | Q19: =Assumptions!$D$58 -> 2 | R19: =Assumptions!$D$58 -> 2 | S19: =Assumptions!$D$58 -> 2 | T19: =Assumptions!$D$58 -> 2 | U19: =Assumptions!$D$58 -> 2 | V19: =Assumptions!$D$58 -> 2 | ... Z19: =Assumptions!$D$58 -> 2 | AA19: =Assumptions!$E$58 -> 3.5 | AB19: =Assumptions!$E$58 -> 3.5 | AC19: =Assumptions!$E$58 -> 3.5 | AD19: =Assumptions!$E$58 -> 3.5 | AE19: =Assumptions!$E$58 -> 3.5 | AF19: =Assumptions!$E$58 -> 3.5 | AG19: =Assumptions!$E$58 -> 3.5 | AH19: =Assumptions!$E$58 -> 3.5 | ... AL19: =Assumptions!$E$58 -> 3.5 | AN19: =SUM(C19:N19) -> 12 | AO19: =SUM(O19:Z19) -> 24 | AP19: =SUM(AA19:AL19) -> 42
A20: Cost | C20: =C19*Assumptions!$F$58 -> 1900 | D20: =D19*Assumptions!$F$58 -> 1900 | E20: =E19*Assumptions!$F$58 -> 1900 | F20: =F19*Assumptions!$F$58 -> 1900 | G20: =G19*Assumptions!$F$58 -> 1900 | H20: =H19*Assumptions!$F$58 -> 1900 | I20: =I19*Assumptions!$F$58 -> 1900 | J20: =J19*Assumptions!$F$58 -> 1900 | ... AL20: =AL19*Assumptions!$F$58 -> 6650 | AN20: =SUM(C20:N20) -> 22800 | AO20: =SUM(O20:Z20) -> 45600 | AP20: =SUM(AA20:AL20) -> 79800
A21: Free sign-ups | C21: =C19*Assumptions!$G$58 -> 150 | D21: =D19*Assumptions!$G$58 -> 150 | E21: =E19*Assumptions!$G$58 -> 150 | F21: =F19*Assumptions!$G$58 -> 150 | G21: =G19*Assumptions!$G$58 -> 150 | H21: =H19*Assumptions!$G$58 -> 150 | I21: =I19*Assumptions!$G$58 -> 150 | J21: =J19*Assumptions!$G$58 -> 150 | ... AL21: =AL19*Assumptions!$G$58 -> 525 | AN21: =SUM(C21:N21) -> 1800 | AO21: =SUM(O21:Z21) -> 3600 | AP21: =SUM(AA21:AL21) -> 6300
A22: Institutional leads | C22: =C19*Assumptions!$H$58 -> 3.2 | D22: =D19*Assumptions!$H$58 -> 3.2 | E22: =E19*Assumptions!$H$58 -> 3.2 | F22: =F19*Assumptions!$H$58 -> 3.2 | G22: =G19*Assumptions!$H$58 -> 3.2 | H22: =H19*Assumptions!$H$58 -> 3.2 | I22: =I19*Assumptions!$H$58 -> 3.2 | J22: =J19*Assumptions!$H$58 -> 3.2 | ... AL22: =AL19*Assumptions!$H$58 -> 11.2 | AN22: =SUM(C22:N22) -> 38.4 | AO22: =SUM(O22:Z22) -> 76.8 | AP22: =SUM(AA22:AL22) -> 134.4
A23: Partner sessions inside NGO and programme cohorts | B23: activities in the month | C23: =Assumptions!$C$59 -> 1 | D23: =Assumptions!$C$59 -> 1 | E23: =Assumptions!$C$59 -> 1 | F23: =Assumptions!$C$59 -> 1 | G23: =Assumptions!$C$59 -> 1 | H23: =Assumptions!$C$59 -> 1 | I23: =Assumptions!$C$59 -> 1 | J23: =Assumptions!$C$59 -> 1 | ... N23: =Assumptions!$C$59 -> 1 | O23: =Assumptions!$D$59 -> 3 | P23: =Assumptions!$D$59 -> 3 | Q23: =Assumptions!$D$59 -> 3 | R23: =Assumptions!$D$59 -> 3 | S23: =Assumptions!$D$59 -> 3 | T23: =Assumptions!$D$59 -> 3 | U23: =Assumptions!$D$59 -> 3 | V23: =Assumptions!$D$59 -> 3 | ... Z23: =Assumptions!$D$59 -> 3 | AA23: =Assumptions!$E$59 -> 5 | AB23: =Assumptions!$E$59 -> 5 | AC23: =Assumptions!$E$59 -> 5 | AD23: =Assumptions!$E$59 -> 5 | AE23: =Assumptions!$E$59 -> 5 | AF23: =Assumptions!$E$59 -> 5 | AG23: =Assumptions!$E$59 -> 5 | AH23: =Assumptions!$E$59 -> 5 | ... AL23: =Assumptions!$E$59 -> 5 | AN23: =SUM(C23:N23) -> 12 | AO23: =SUM(O23:Z23) -> 36 | AP23: =SUM(AA23:AL23) -> 60
A24: Cost | C24: =C23*Assumptions!$F$59 -> 350 | D24: =D23*Assumptions!$F$59 -> 350 | E24: =E23*Assumptions!$F$59 -> 350 | F24: =F23*Assumptions!$F$59 -> 350 | G24: =G23*Assumptions!$F$59 -> 350 | H24: =H23*Assumptions!$F$59 -> 350 | I24: =I23*Assumptions!$F$59 -> 350 | J24: =J23*Assumptions!$F$59 -> 350 | ... AL24: =AL23*Assumptions!$F$59 -> 1750 | AN24: =SUM(C24:N24) -> 4200 | AO24: =SUM(O24:Z24) -> 12600 | AP24: =SUM(AA24:AL24) -> 21000
A25: Free sign-ups | C25: =C23*Assumptions!$G$59 -> 60 | D25: =D23*Assumptions!$G$59 -> 60 | E25: =E23*Assumptions!$G$59 -> 60 | F25: =F23*Assumptions!$G$59 -> 60 | G25: =G23*Assumptions!$G$59 -> 60 | H25: =H23*Assumptions!$G$59 -> 60 | I25: =I23*Assumptions!$G$59 -> 60 | J25: =J23*Assumptions!$G$59 -> 60 | ... AL25: =AL23*Assumptions!$G$59 -> 300 | AN25: =SUM(C25:N25) -> 720 | AO25: =SUM(O25:Z25) -> 2160 | AP25: =SUM(AA25:AL25) -> 3600
A26: Institutional leads | C26: =C23*Assumptions!$H$59 -> 1.4 | D26: =D23*Assumptions!$H$59 -> 1.4 | E26: =E23*Assumptions!$H$59 -> 1.4 | F26: =F23*Assumptions!$H$59 -> 1.4 | G26: =G23*Assumptions!$H$59 -> 1.4 | H26: =H23*Assumptions!$H$59 -> 1.4 | I26: =I23*Assumptions!$H$59 -> 1.4 | J26: =J23*Assumptions!$H$59 -> 1.4 | ... AL26: =AL23*Assumptions!$H$59 -> 7 | AN26: =SUM(C26:N26) -> 16.8 | AO26: =SUM(O26:Z26) -> 50.4 | AP26: =SUM(AA26:AL26) -> 84
A27: Direct outreach by the partnership heads | B27: activities in the month | C27: =Assumptions!$C$60 -> 4 | D27: =Assumptions!$C$60 -> 4 | E27: =Assumptions!$C$60 -> 4 | F27: =Assumptions!$C$60 -> 4 | G27: =Assumptions!$C$60 -> 4 | H27: =Assumptions!$C$60 -> 4 | I27: =Assumptions!$C$60 -> 4 | J27: =Assumptions!$C$60 -> 4 | ... N27: =Assumptions!$C$60 -> 4 | O27: =Assumptions!$D$60 -> 7 | P27: =Assumptions!$D$60 -> 7 | Q27: =Assumptions!$D$60 -> 7 | R27: =Assumptions!$D$60 -> 7 | S27: =Assumptions!$D$60 -> 7 | T27: =Assumptions!$D$60 -> 7 | U27: =Assumptions!$D$60 -> 7 | V27: =Assumptions!$D$60 -> 7 | ... Z27: =Assumptions!$D$60 -> 7 | AA27: =Assumptions!$E$60 -> 9 | AB27: =Assumptions!$E$60 -> 9 | AC27: =Assumptions!$E$60 -> 9 | AD27: =Assumptions!$E$60 -> 9 | AE27: =Assumptions!$E$60 -> 9 | AF27: =Assumptions!$E$60 -> 9 | AG27: =Assumptions!$E$60 -> 9 | AH27: =Assumptions!$E$60 -> 9 | ... AL27: =Assumptions!$E$60 -> 9 | AN27: =SUM(C27:N27) -> 48 | AO27: =SUM(O27:Z27) -> 84 | AP27: =SUM(AA27:AL27) -> 108
A28: Cost | C28: =C27*Assumptions!$F$60 -> 0 | D28: =D27*Assumptions!$F$60 -> 0 | E28: =E27*Assumptions!$F$60 -> 0 | F28: =F27*Assumptions!$F$60 -> 0 | G28: =G27*Assumptions!$F$60 -> 0 | H28: =H27*Assumptions!$F$60 -> 0 | I28: =I27*Assumptions!$F$60 -> 0 | J28: =J27*Assumptions!$F$60 -> 0 | ... AL28: =AL27*Assumptions!$F$60 -> 0 | AN28: =SUM(C28:N28) -> 0 | AO28: =SUM(O28:Z28) -> 0 | AP28: =SUM(AA28:AL28) -> 0
A29: Free sign-ups | C29: =C27*Assumptions!$G$60 -> 0 | D29: =D27*Assumptions!$G$60 -> 0 | E29: =E27*Assumptions!$G$60 -> 0 | F29: =F27*Assumptions!$G$60 -> 0 | G29: =G27*Assumptions!$G$60 -> 0 | H29: =H27*Assumptions!$G$60 -> 0 | I29: =I27*Assumptions!$G$60 -> 0 | J29: =J27*Assumptions!$G$60 -> 0 | ... AL29: =AL27*Assumptions!$G$60 -> 0 | AN29: =SUM(C29:N29) -> 0 | AO29: =SUM(O29:Z29) -> 0 | AP29: =SUM(AA29:AL29) -> 0
A30: Institutional leads | C30: =C27*Assumptions!$H$60 -> 24 | D30: =D27*Assumptions!$H$60 -> 24 | E30: =E27*Assumptions!$H$60 -> 24 | F30: =F27*Assumptions!$H$60 -> 24 | G30: =G27*Assumptions!$H$60 -> 24 | H30: =H27*Assumptions!$H$60 -> 24 | I30: =I27*Assumptions!$H$60 -> 24 | J30: =J27*Assumptions!$H$60 -> 24 | ... AL30: =AL27*Assumptions!$H$60 -> 54 | AN30: =SUM(C30:N30) -> 288 | AO30: =SUM(O30:Z30) -> 504 | AP30: =SUM(AA30:AL30) -> 648
A31: Offline marketing cost | C31: =C8+C12+C16+C20+C24+C28 -> 4930 | D31: =D8+D12+D16+D20+D24+D28 -> 4930 | E31: =E8+E12+E16+E20+E24+E28 -> 4930 | F31: =F8+F12+F16+F20+F24+F28 -> 4930 | G31: =G8+G12+G16+G20+G24+G28 -> 4930 | H31: =H8+H12+H16+H20+H24+H28 -> 4930 | I31: =I8+I12+I16+I20+I24+I28 -> 4930 | J31: =J8+J12+J16+J20+J24+J28 -> 4930 | ... AL31: =AL8+AL12+AL16+AL20+AL24+AL28 -> 20740 | AN31: =SUM(C31:N31) -> 59160 | AO31: =SUM(O31:Z31) -> 143160 | AP31: =SUM(AA31:AL31) -> 248880
A32: Offline sign-ups | C32: =C9+C13+C17+C21+C25+C29 -> 574 | D32: =D9+D13+D17+D21+D25+D29 -> 574 | E32: =E9+E13+E17+E21+E25+E29 -> 574 | F32: =F9+F13+F17+F21+F25+F29 -> 574 | G32: =G9+G13+G17+G21+G25+G29 -> 574 | H32: =H9+H13+H17+H21+H25+H29 -> 574 | I32: =I9+I13+I17+I21+I25+I29 -> 574 | J32: =J9+J13+J17+J21+J25+J29 -> 574 | ... AL32: =AL9+AL13+AL17+AL21+AL25+AL29 -> 2492 | AN32: =SUM(C32:N32) -> 6888 | AO32: =SUM(O32:Z32) -> 17256 | AP32: =SUM(AA32:AL32) -> 29904
A33: Offline institutional leads | C33: =C10+C14+C18+C22+C26+C30 -> 33.4 | D33: =D10+D14+D18+D22+D26+D30 -> 33.4 | E33: =E10+E14+E18+E22+E26+E30 -> 33.4 | F33: =F10+F14+F18+F22+F26+F30 -> 33.4 | G33: =G10+G14+G18+G22+G26+G30 -> 33.4 | H33: =H10+H14+H18+H22+H26+H30 -> 33.4 | I33: =I10+I14+I18+I22+I26+I30 -> 33.4 | J33: =J10+J14+J18+J22+J26+J30 -> 33.4 | ... AL33: =AL10+AL14+AL18+AL22+AL26+AL30 -> 95.3 | AN33: =SUM(C33:N33) -> 400.8 | AO33: =SUM(O33:Z33) -> 788.16 | AP33: =SUM(AA33:AL33) -> 1143.6
A35: ONLINE CHANNELS — THEY CREATE REACH
A36: Line item | B36: Driver / source | C36: Oct 26 | D36: Nov 26 | E36: Dec 26 | F36: Jan 26 | G36: Feb 26 | H36: Mar 26 | I36: Apr 26 | J36: May 26 | K36: Jun 26 | L36: Jul 27 | M36: Aug 27 | N36: Sep 27 | O36: Oct 27 | P36: Nov 27 | Q36: Dec 27 | R36: Jan 27 | S36: Feb 27 | T36: Mar 27 | U36: Apr 27 | V36: May 27 | W36: Jun 27 | X36: Jul 28 | Y36: Aug 28 | Z36: Sep 28 | AA36: Oct 28 | AB36: Nov 28 | AC36: Dec 28 | AD36: Jan 28 | AE36: Feb 28 | AF36: Mar 28 | AG36: Apr 28 | AH36: May 28 | AI36: Jun 28 | AJ36: Jul 29 | AK36: Aug 29 | AL36: Sep 29 | AN36: YEAR 1 | AO36: YEAR 2 | AP36: YEAR 3
A37: Short video — TikTok, Instagram, Facebook | B37: spend in the month | C37: =Assumptions!$C$65 -> 900 | D37: =Assumptions!$C$65 -> 900 | E37: =Assumptions!$C$65 -> 900 | F37: =Assumptions!$C$65 -> 900 | G37: =Assumptions!$C$65 -> 900 | H37: =Assumptions!$C$65 -> 900 | I37: =Assumptions!$C$65 -> 900 | J37: =Assumptions!$C$65 -> 900 | ... N37: =Assumptions!$C$65 -> 900 | O37: =Assumptions!$D$65 -> 2200 | P37: =Assumptions!$D$65 -> 2200 | Q37: =Assumptions!$D$65 -> 2200 | R37: =Assumptions!$D$65 -> 2200 | S37: =Assumptions!$D$65 -> 2200 | T37: =Assumptions!$D$65 -> 2200 | U37: =Assumptions!$D$65 -> 2200 | V37: =Assumptions!$D$65 -> 2200 | ... Z37: =Assumptions!$D$65 -> 2200 | AA37: =Assumptions!$E$65 -> 4200 | AB37: =Assumptions!$E$65 -> 4200 | AC37: =Assumptions!$E$65 -> 4200 | AD37: =Assumptions!$E$65 -> 4200 | AE37: =Assumptions!$E$65 -> 4200 | AF37: =Assumptions!$E$65 -> 4200 | AG37: =Assumptions!$E$65 -> 4200 | AH37: =Assumptions!$E$65 -> 4200 | ... AL37: =Assumptions!$E$65 -> 4200 | AN37: =SUM(C37:N37) -> 10800 | AO37: =SUM(O37:Z37) -> 26400 | AP37: =SUM(AA37:AL37) -> 50400
A38: Reach | C38: =IFERROR(C37/Assumptions!$F$65*1000,0) -> 257142.86 | D38: =IFERROR(D37/Assumptions!$F$65*1000,0) -> 257142.86 | E38: =IFERROR(E37/Assumptions!$F$65*1000,0) -> 257142.86 | F38: =IFERROR(F37/Assumptions!$F$65*1000,0) -> 257142.86 | G38: =IFERROR(G37/Assumptions!$F$65*1000,0) -> 257142.86 | H38: =IFERROR(H37/Assumptions!$F$65*1000,0) -> 257142.86 | I38: =IFERROR(I37/Assumptions!$F$65*1000,0) -> 257142.86 | J38: =IFERROR(J37/Assumptions!$F$65*1000,0) -> 257142.86 | ... AL38: =IFERROR(AL37/Assumptions!$F$65*1000,0) -> 1200000 | AN38: =SUM(C38:N38) -> 3085714.3 | AO38: =SUM(O38:Z38) -> 7542857.1 | AP38: =SUM(AA38:AL38) -> 14400000
A39: Free sign-ups | B39: reach x click-through x conversion | C39: =C38*Assumptions!$G$65*Assumptions!$H$65 -> 277.71429 | D39: =D38*Assumptions!$G$65*Assumptions!$H$65 -> 277.71429 | E39: =E38*Assumptions!$G$65*Assumptions!$H$65 -> 277.71429 | F39: =F38*Assumptions!$G$65*Assumptions!$H$65 -> 277.71429 | G39: =G38*Assumptions!$G$65*Assumptions!$H$65 -> 277.71429 | H39: =H38*Assumptions!$G$65*Assumptions!$H$65 -> 277.71429 | I39: =I38*Assumptions!$G$65*Assumptions!$H$65 -> 277.71429 | J39: =J38*Assumptions!$G$65*Assumptions!$H$65 -> 277.71429 | ... AL39: =AL38*Assumptions!$G$65*Assumptions!$H$65 -> 1296 | AN39: =SUM(C39:N39) -> 3332.5714 | AO39: =SUM(O39:Z39) -> 8146.2857 | AP39: =SUM(AA39:AL39) -> 15552
A40: Paid social — targeted by age, city, university | B40: spend in the month | C40: =Assumptions!$C$66 -> 850 | D40: =Assumptions!$C$66 -> 850 | E40: =Assumptions!$C$66 -> 850 | F40: =Assumptions!$C$66 -> 850 | G40: =Assumptions!$C$66 -> 850 | H40: =Assumptions!$C$66 -> 850 | I40: =Assumptions!$C$66 -> 850 | J40: =Assumptions!$C$66 -> 850 | ... N40: =Assumptions!$C$66 -> 850 | O40: =Assumptions!$D$66 -> 2000 | P40: =Assumptions!$D$66 -> 2000 | Q40: =Assumptions!$D$66 -> 2000 | R40: =Assumptions!$D$66 -> 2000 | S40: =Assumptions!$D$66 -> 2000 | T40: =Assumptions!$D$66 -> 2000 | U40: =Assumptions!$D$66 -> 2000 | V40: =Assumptions!$D$66 -> 2000 | ... Z40: =Assumptions!$D$66 -> 2000 | AA40: =Assumptions!$E$66 -> 4000 | AB40: =Assumptions!$E$66 -> 4000 | AC40: =Assumptions!$E$66 -> 4000 | AD40: =Assumptions!$E$66 -> 4000 | AE40: =Assumptions!$E$66 -> 4000 | AF40: =Assumptions!$E$66 -> 4000 | AG40: =Assumptions!$E$66 -> 4000 | AH40: =Assumptions!$E$66 -> 4000 | ... AL40: =Assumptions!$E$66 -> 4000 | AN40: =SUM(C40:N40) -> 10200 | AO40: =SUM(O40:Z40) -> 24000 | AP40: =SUM(AA40:AL40) -> 48000
A41: Reach | C41: =IFERROR(C40/Assumptions!$F$66*1000,0) -> 130769.23 | D41: =IFERROR(D40/Assumptions!$F$66*1000,0) -> 130769.23 | E41: =IFERROR(E40/Assumptions!$F$66*1000,0) -> 130769.23 | F41: =IFERROR(F40/Assumptions!$F$66*1000,0) -> 130769.23 | G41: =IFERROR(G40/Assumptions!$F$66*1000,0) -> 130769.23 | H41: =IFERROR(H40/Assumptions!$F$66*1000,0) -> 130769.23 | I41: =IFERROR(I40/Assumptions!$F$66*1000,0) -> 130769.23 | J41: =IFERROR(J40/Assumptions!$F$66*1000,0) -> 130769.23 | ... AL41: =IFERROR(AL40/Assumptions!$F$66*1000,0) -> 615384.62 | AN41: =SUM(C41:N41) -> 1569230.8 | AO41: =SUM(O41:Z41) -> 3692307.7 | AP41: =SUM(AA41:AL41) -> 7384615.4
A42: Free sign-ups | B42: reach x click-through x conversion | C42: =C41*Assumptions!$G$66*Assumptions!$H$66 -> 129.46154 | D42: =D41*Assumptions!$G$66*Assumptions!$H$66 -> 129.46154 | E42: =E41*Assumptions!$G$66*Assumptions!$H$66 -> 129.46154 | F42: =F41*Assumptions!$G$66*Assumptions!$H$66 -> 129.46154 | G42: =G41*Assumptions!$G$66*Assumptions!$H$66 -> 129.46154 | H42: =H41*Assumptions!$G$66*Assumptions!$H$66 -> 129.46154 | I42: =I41*Assumptions!$G$66*Assumptions!$H$66 -> 129.46154 | J42: =J41*Assumptions!$G$66*Assumptions!$H$66 -> 129.46154 | ... AL42: =AL41*Assumptions!$G$66*Assumptions!$H$66 -> 609.23077 | AN42: =SUM(C42:N42) -> 1553.5385 | AO42: =SUM(O42:Z42) -> 3655.3846 | AP42: =SUM(AA42:AL42) -> 7310.7692
A43: Influencers and student creators | B43: spend in the month | C43: =Assumptions!$C$67 -> 700 | D43: =Assumptions!$C$67 -> 700 | E43: =Assumptions!$C$67 -> 700 | F43: =Assumptions!$C$67 -> 700 | G43: =Assumptions!$C$67 -> 700 | H43: =Assumptions!$C$67 -> 700 | I43: =Assumptions!$C$67 -> 700 | J43: =Assumptions!$C$67 -> 700 | ... N43: =Assumptions!$C$67 -> 700 | O43: =Assumptions!$D$67 -> 1700 | P43: =Assumptions!$D$67 -> 1700 | Q43: =Assumptions!$D$67 -> 1700 | R43: =Assumptions!$D$67 -> 1700 | S43: =Assumptions!$D$67 -> 1700 | T43: =Assumptions!$D$67 -> 1700 | U43: =Assumptions!$D$67 -> 1700 | V43: =Assumptions!$D$67 -> 1700 | ... Z43: =Assumptions!$D$67 -> 1700 | AA43: =Assumptions!$E$67 -> 3200 | AB43: =Assumptions!$E$67 -> 3200 | AC43: =Assumptions!$E$67 -> 3200 | AD43: =Assumptions!$E$67 -> 3200 | AE43: =Assumptions!$E$67 -> 3200 | AF43: =Assumptions!$E$67 -> 3200 | AG43: =Assumptions!$E$67 -> 3200 | AH43: =Assumptions!$E$67 -> 3200 | ... AL43: =Assumptions!$E$67 -> 3200 | AN43: =SUM(C43:N43) -> 8400 | AO43: =SUM(O43:Z43) -> 20400 | AP43: =SUM(AA43:AL43) -> 38400
A44: Reach | C44: =IFERROR(C43/Assumptions!$F$67*1000,0) -> 127272.73 | D44: =IFERROR(D43/Assumptions!$F$67*1000,0) -> 127272.73 | E44: =IFERROR(E43/Assumptions!$F$67*1000,0) -> 127272.73 | F44: =IFERROR(F43/Assumptions!$F$67*1000,0) -> 127272.73 | G44: =IFERROR(G43/Assumptions!$F$67*1000,0) -> 127272.73 | H44: =IFERROR(H43/Assumptions!$F$67*1000,0) -> 127272.73 | I44: =IFERROR(I43/Assumptions!$F$67*1000,0) -> 127272.73 | J44: =IFERROR(J43/Assumptions!$F$67*1000,0) -> 127272.73 | ... AL44: =IFERROR(AL43/Assumptions!$F$67*1000,0) -> 581818.18 | AN44: =SUM(C44:N44) -> 1527272.7 | AO44: =SUM(O44:Z44) -> 3709090.9 | AP44: =SUM(AA44:AL44) -> 6981818.2
A45: Free sign-ups | B45: reach x click-through x conversion | C45: =C44*Assumptions!$G$67*Assumptions!$H$67 -> 140 | D45: =D44*Assumptions!$G$67*Assumptions!$H$67 -> 140 | E45: =E44*Assumptions!$G$67*Assumptions!$H$67 -> 140 | F45: =F44*Assumptions!$G$67*Assumptions!$H$67 -> 140 | G45: =G44*Assumptions!$G$67*Assumptions!$H$67 -> 140 | H45: =H44*Assumptions!$G$67*Assumptions!$H$67 -> 140 | I45: =I44*Assumptions!$G$67*Assumptions!$H$67 -> 140 | J45: =J44*Assumptions!$G$67*Assumptions!$H$67 -> 140 | ... AL45: =AL44*Assumptions!$G$67*Assumptions!$H$67 -> 640 | AN45: =SUM(C45:N45) -> 1680 | AO45: =SUM(O45:Z45) -> 4080 | AP45: =SUM(AA45:AL45) -> 7680
A46: Mission Zero — the founder podcast | B46: spend in the month | C46: =Assumptions!$C$68 -> 2100 | D46: =Assumptions!$C$68 -> 2100 | E46: =Assumptions!$C$68 -> 2100 | F46: =Assumptions!$C$68 -> 2100 | G46: =Assumptions!$C$68 -> 2100 | H46: =Assumptions!$C$68 -> 2100 | I46: =Assumptions!$C$68 -> 2100 | J46: =Assumptions!$C$68 -> 2100 | ... N46: =Assumptions!$C$68 -> 2100 | O46: =Assumptions!$D$68 -> 4000 | P46: =Assumptions!$D$68 -> 4000 | Q46: =Assumptions!$D$68 -> 4000 | R46: =Assumptions!$D$68 -> 4000 | S46: =Assumptions!$D$68 -> 4000 | T46: =Assumptions!$D$68 -> 4000 | U46: =Assumptions!$D$68 -> 4000 | V46: =Assumptions!$D$68 -> 4000 | ... Z46: =Assumptions!$D$68 -> 4000 | AA46: =Assumptions!$E$68 -> 8000 | AB46: =Assumptions!$E$68 -> 8000 | AC46: =Assumptions!$E$68 -> 8000 | AD46: =Assumptions!$E$68 -> 8000 | AE46: =Assumptions!$E$68 -> 8000 | AF46: =Assumptions!$E$68 -> 8000 | AG46: =Assumptions!$E$68 -> 8000 | AH46: =Assumptions!$E$68 -> 8000 | ... AL46: =Assumptions!$E$68 -> 8000 | AN46: =SUM(C46:N46) -> 25200 | AO46: =SUM(O46:Z46) -> 48000 | AP46: =SUM(AA46:AL46) -> 96000
A47: Reach | C47: =IFERROR(C46/Assumptions!$F$68*1000,0) -> 150000 | D47: =IFERROR(D46/Assumptions!$F$68*1000,0) -> 150000 | E47: =IFERROR(E46/Assumptions!$F$68*1000,0) -> 150000 | F47: =IFERROR(F46/Assumptions!$F$68*1000,0) -> 150000 | G47: =IFERROR(G46/Assumptions!$F$68*1000,0) -> 150000 | H47: =IFERROR(H46/Assumptions!$F$68*1000,0) -> 150000 | I47: =IFERROR(I46/Assumptions!$F$68*1000,0) -> 150000 | J47: =IFERROR(J46/Assumptions!$F$68*1000,0) -> 150000 | ... AL47: =IFERROR(AL46/Assumptions!$F$68*1000,0) -> 571428.57 | AN47: =SUM(C47:N47) -> 1800000 | AO47: =SUM(O47:Z47) -> 3428571.4 | AP47: =SUM(AA47:AL47) -> 6857142.9
A48: Free sign-ups | B48: reach x click-through x conversion | C48: =C47*Assumptions!$G$68*Assumptions!$H$68 -> 180 | D48: =D47*Assumptions!$G$68*Assumptions!$H$68 -> 180 | E48: =E47*Assumptions!$G$68*Assumptions!$H$68 -> 180 | F48: =F47*Assumptions!$G$68*Assumptions!$H$68 -> 180 | G48: =G47*Assumptions!$G$68*Assumptions!$H$68 -> 180 | H48: =H47*Assumptions!$G$68*Assumptions!$H$68 -> 180 | I48: =I47*Assumptions!$G$68*Assumptions!$H$68 -> 180 | J48: =J47*Assumptions!$G$68*Assumptions!$H$68 -> 180 | ... AL48: =AL47*Assumptions!$G$68*Assumptions!$H$68 -> 685.71429 | AN48: =SUM(C48:N48) -> 2160 | AO48: =SUM(O48:Z48) -> 4114.2857 | AP48: =SUM(AA48:AL48) -> 8228.5714
A49: Webinars — live Mission 01 sessions | B49: spend in the month | C49: =Assumptions!$C$69 -> 260 | D49: =Assumptions!$C$69 -> 260 | E49: =Assumptions!$C$69 -> 260 | F49: =Assumptions!$C$69 -> 260 | G49: =Assumptions!$C$69 -> 260 | H49: =Assumptions!$C$69 -> 260 | I49: =Assumptions!$C$69 -> 260 | J49: =Assumptions!$C$69 -> 260 | ... N49: =Assumptions!$C$69 -> 260 | O49: =Assumptions!$D$69 -> 600 | P49: =Assumptions!$D$69 -> 600 | Q49: =Assumptions!$D$69 -> 600 | R49: =Assumptions!$D$69 -> 600 | S49: =Assumptions!$D$69 -> 600 | T49: =Assumptions!$D$69 -> 600 | U49: =Assumptions!$D$69 -> 600 | V49: =Assumptions!$D$69 -> 600 | ... Z49: =Assumptions!$D$69 -> 600 | AA49: =Assumptions!$E$69 -> 1150 | AB49: =Assumptions!$E$69 -> 1150 | AC49: =Assumptions!$E$69 -> 1150 | AD49: =Assumptions!$E$69 -> 1150 | AE49: =Assumptions!$E$69 -> 1150 | AF49: =Assumptions!$E$69 -> 1150 | AG49: =Assumptions!$E$69 -> 1150 | AH49: =Assumptions!$E$69 -> 1150 | ... AL49: =Assumptions!$E$69 -> 1150 | AN49: =SUM(C49:N49) -> 3120 | AO49: =SUM(O49:Z49) -> 7200 | AP49: =SUM(AA49:AL49) -> 13800
A50: Reach | C50: =IFERROR(C49/Assumptions!$F$69*1000,0) -> 10400 | D50: =IFERROR(D49/Assumptions!$F$69*1000,0) -> 10400 | E50: =IFERROR(E49/Assumptions!$F$69*1000,0) -> 10400 | F50: =IFERROR(F49/Assumptions!$F$69*1000,0) -> 10400 | G50: =IFERROR(G49/Assumptions!$F$69*1000,0) -> 10400 | H50: =IFERROR(H49/Assumptions!$F$69*1000,0) -> 10400 | I50: =IFERROR(I49/Assumptions!$F$69*1000,0) -> 10400 | J50: =IFERROR(J49/Assumptions!$F$69*1000,0) -> 10400 | ... AL50: =IFERROR(AL49/Assumptions!$F$69*1000,0) -> 46000 | AN50: =SUM(C50:N50) -> 124800 | AO50: =SUM(O50:Z50) -> 288000 | AP50: =SUM(AA50:AL50) -> 552000
A51: Free sign-ups | B51: reach x click-through x conversion | C51: =C50*Assumptions!$G$69*Assumptions!$H$69 -> 130 | D51: =D50*Assumptions!$G$69*Assumptions!$H$69 -> 130 | E51: =E50*Assumptions!$G$69*Assumptions!$H$69 -> 130 | F51: =F50*Assumptions!$G$69*Assumptions!$H$69 -> 130 | G51: =G50*Assumptions!$G$69*Assumptions!$H$69 -> 130 | H51: =H50*Assumptions!$G$69*Assumptions!$H$69 -> 130 | I51: =I50*Assumptions!$G$69*Assumptions!$H$69 -> 130 | J51: =J50*Assumptions!$G$69*Assumptions!$H$69 -> 130 | ... AL51: =AL50*Assumptions!$G$69*Assumptions!$H$69 -> 575 | AN51: =SUM(C51:N51) -> 1560 | AO51: =SUM(O51:Z51) -> 3600 | AP51: =SUM(AA51:AL51) -> 6900
A52: SEO and organic search | B52: spend in the month | C52: =Assumptions!$C$70 -> 500 | D52: =Assumptions!$C$70 -> 500 | E52: =Assumptions!$C$70 -> 500 | F52: =Assumptions!$C$70 -> 500 | G52: =Assumptions!$C$70 -> 500 | H52: =Assumptions!$C$70 -> 500 | I52: =Assumptions!$C$70 -> 500 | J52: =Assumptions!$C$70 -> 500 | ... N52: =Assumptions!$C$70 -> 500 | O52: =Assumptions!$D$70 -> 1150 | P52: =Assumptions!$D$70 -> 1150 | Q52: =Assumptions!$D$70 -> 1150 | R52: =Assumptions!$D$70 -> 1150 | S52: =Assumptions!$D$70 -> 1150 | T52: =Assumptions!$D$70 -> 1150 | U52: =Assumptions!$D$70 -> 1150 | V52: =Assumptions!$D$70 -> 1150 | ... Z52: =Assumptions!$D$70 -> 1150 | AA52: =Assumptions!$E$70 -> 2100 | AB52: =Assumptions!$E$70 -> 2100 | AC52: =Assumptions!$E$70 -> 2100 | AD52: =Assumptions!$E$70 -> 2100 | AE52: =Assumptions!$E$70 -> 2100 | AF52: =Assumptions!$E$70 -> 2100 | AG52: =Assumptions!$E$70 -> 2100 | AH52: =Assumptions!$E$70 -> 2100 | ... AL52: =Assumptions!$E$70 -> 2100 | AN52: =SUM(C52:N52) -> 6000 | AO52: =SUM(O52:Z52) -> 13800 | AP52: =SUM(AA52:AL52) -> 25200
A53: Reach | C53: =IFERROR(C52/Assumptions!$F$70*1000,0) -> 166666.67 | D53: =IFERROR(D52/Assumptions!$F$70*1000,0) -> 166666.67 | E53: =IFERROR(E52/Assumptions!$F$70*1000,0) -> 166666.67 | F53: =IFERROR(F52/Assumptions!$F$70*1000,0) -> 166666.67 | G53: =IFERROR(G52/Assumptions!$F$70*1000,0) -> 166666.67 | H53: =IFERROR(H52/Assumptions!$F$70*1000,0) -> 166666.67 | I53: =IFERROR(I52/Assumptions!$F$70*1000,0) -> 166666.67 | J53: =IFERROR(J52/Assumptions!$F$70*1000,0) -> 166666.67 | ... AL53: =IFERROR(AL52/Assumptions!$F$70*1000,0) -> 700000 | AN53: =SUM(C53:N53) -> 2000000 | AO53: =SUM(O53:Z53) -> 4600000 | AP53: =SUM(AA53:AL53) -> 8400000
A54: Free sign-ups | B54: reach x click-through x conversion | C54: =C53*Assumptions!$G$70*Assumptions!$H$70 -> 240 | D54: =D53*Assumptions!$G$70*Assumptions!$H$70 -> 240 | E54: =E53*Assumptions!$G$70*Assumptions!$H$70 -> 240 | F54: =F53*Assumptions!$G$70*Assumptions!$H$70 -> 240 | G54: =G53*Assumptions!$G$70*Assumptions!$H$70 -> 240 | H54: =H53*Assumptions!$G$70*Assumptions!$H$70 -> 240 | I54: =I53*Assumptions!$G$70*Assumptions!$H$70 -> 240 | J54: =J53*Assumptions!$G$70*Assumptions!$H$70 -> 240 | ... AL54: =AL53*Assumptions!$G$70*Assumptions!$H$70 -> 1008 | AN54: =SUM(C54:N54) -> 2880 | AO54: =SUM(O54:Z54) -> 6624 | AP54: =SUM(AA54:AL54) -> 12096
A55: Online marketing cost | C55: =C37+C40+C43+C46+C49+C52 -> 5310 | D55: =D37+D40+D43+D46+D49+D52 -> 5310 | E55: =E37+E40+E43+E46+E49+E52 -> 5310 | F55: =F37+F40+F43+F46+F49+F52 -> 5310 | G55: =G37+G40+G43+G46+G49+G52 -> 5310 | H55: =H37+H40+H43+H46+H49+H52 -> 5310 | I55: =I37+I40+I43+I46+I49+I52 -> 5310 | J55: =J37+J40+J43+J46+J49+J52 -> 5310 | ... AL55: =AL37+AL40+AL43+AL46+AL49+AL52 -> 22650 | AN55: =SUM(C55:N55) -> 63720 | AO55: =SUM(O55:Z55) -> 139800 | AP55: =SUM(AA55:AL55) -> 271800
A56: Online reach | C56: =C38+C41+C44+C47+C50+C53 -> 842251.48 | D56: =D38+D41+D44+D47+D50+D53 -> 842251.48 | E56: =E38+E41+E44+E47+E50+E53 -> 842251.48 | F56: =F38+F41+F44+F47+F50+F53 -> 842251.48 | G56: =G38+G41+G44+G47+G50+G53 -> 842251.48 | H56: =H38+H41+H44+H47+H50+H53 -> 842251.48 | I56: =I38+I41+I44+I47+I50+I53 -> 842251.48 | J56: =J38+J41+J44+J47+J50+J53 -> 842251.48 | ... AL56: =AL38+AL41+AL44+AL47+AL50+AL53 -> 3714631.4 | AN56: =SUM(C56:N56) -> 10107018 | AO56: =SUM(O56:Z56) -> 23260827 | AP56: =SUM(AA56:AL56) -> 44575576
A57: Online sign-ups | C57: =C39+C42+C45+C48+C51+C54 -> 1097.1758 | D57: =D39+D42+D45+D48+D51+D54 -> 1097.1758 | E57: =E39+E42+E45+E48+E51+E54 -> 1097.1758 | F57: =F39+F42+F45+F48+F51+F54 -> 1097.1758 | G57: =G39+G42+G45+G48+G51+G54 -> 1097.1758 | H57: =H39+H42+H45+H48+H51+H54 -> 1097.1758 | I57: =I39+I42+I45+I48+I51+I54 -> 1097.1758 | J57: =J39+J42+J45+J48+J51+J54 -> 1097.1758 | ... AL57: =AL39+AL42+AL45+AL48+AL51+AL54 -> 4813.9451 | AN57: =SUM(C57:N57) -> 13166.11 | AO57: =SUM(O57:Z57) -> 30219.956 | AP57: =SUM(AA57:AL57) -> 57767.341
A58: Total marketing cost | B58: carried to the Expenses sheet | C58: =C31+C55 -> 10240 | D58: =D31+D55 -> 10240 | E58: =E31+E55 -> 10240 | F58: =F31+F55 -> 10240 | G58: =G31+G55 -> 10240 | H58: =H31+H55 -> 10240 | I58: =I31+I55 -> 10240 | J58: =J31+J55 -> 10240 | ... AL58: =AL31+AL55 -> 43390 | AN58: =SUM(C58:N58) -> 122880 | AO58: =SUM(O58:Z58) -> 282960 | AP58: =SUM(AA58:AL58) -> 520680
A60: INSTITUTIONAL FUNNEL — MAP, MEET, SIGN
A61: Line item | B61: Driver / source | C61: Oct 26 | D61: Nov 26 | E61: Dec 26 | F61: Jan 26 | G61: Feb 26 | H61: Mar 26 | I61: Apr 26 | J61: May 26 | K61: Jun 26 | L61: Jul 27 | M61: Aug 27 | N61: Sep 27 | O61: Oct 27 | P61: Nov 27 | Q61: Dec 27 | R61: Jan 27 | S61: Feb 27 | T61: Mar 27 | U61: Apr 27 | V61: May 27 | W61: Jun 27 | X61: Jul 28 | Y61: Aug 28 | Z61: Sep 28 | AA61: Oct 28 | AB61: Nov 28 | AC61: Dec 28 | AD61: Jan 28 | AE61: Feb 28 | AF61: Mar 28 | AG61: Apr 28 | AH61: May 28 | AI61: Jun 28 | AJ61: Jul 29 | AK61: Aug 29 | AL61: Sep 29 | AN61: YEAR 1 | AO61: YEAR 2 | AP61: YEAR 3
A62: Inbound enquiries from content | B62: podcast, search and the readiness report | C62: =C57/1000*Assumptions!$C$82 -> 15.360462 | D62: =D57/1000*Assumptions!$C$82 -> 15.360462 | E62: =E57/1000*Assumptions!$C$82 -> 15.360462 | F62: =F57/1000*Assumptions!$C$82 -> 15.360462 | G62: =G57/1000*Assumptions!$C$82 -> 15.360462 | H62: =H57/1000*Assumptions!$C$82 -> 15.360462 | I62: =I57/1000*Assumptions!$C$82 -> 15.360462 | J62: =J57/1000*Assumptions!$C$82 -> 15.360462 | ... AL62: =AL57/1000*Assumptions!$C$82 -> 67.395231 | AN62: =SUM(C62:N62) -> 184.32554 | AO62: =SUM(O62:Z62) -> 423.07938 | AP62: =SUM(AA62:AL62) -> 808.74277
A63: Total institutional leads | C63: =C33+C62 -> 48.760462 | D63: =D33+D62 -> 48.760462 | E63: =E33+E62 -> 48.760462 | F63: =F33+F62 -> 48.760462 | G63: =G33+G62 -> 48.760462 | H63: =H33+H62 -> 48.760462 | I63: =I33+I62 -> 48.760462 | J63: =J33+J62 -> 48.760462 | ... AL63: =AL33+AL62 -> 162.69523 | AN63: =SUM(C63:N63) -> 585.12554 | AO63: =SUM(O63:Z63) -> 1211.2394 | AP63: =SUM(AA63:AL63) -> 1952.3428
A64: First meetings held | C64: =C63*Assumptions!$C$74 -> 19.504185 | D64: =D63*Assumptions!$C$74 -> 19.504185 | E64: =E63*Assumptions!$C$74 -> 19.504185 | F64: =F63*Assumptions!$C$74 -> 19.504185 | G64: =G63*Assumptions!$C$74 -> 19.504185 | H64: =H63*Assumptions!$C$74 -> 19.504185 | I64: =I63*Assumptions!$C$74 -> 19.504185 | J64: =J63*Assumptions!$C$74 -> 19.504185 | ... N64: =N63*Assumptions!$C$74 -> 19.504185 | O64: =O63*Assumptions!$D$74 -> 44.412111 | P64: =P63*Assumptions!$D$74 -> 44.412111 | Q64: =Q63*Assumptions!$D$74 -> 44.412111 | R64: =R63*Assumptions!$D$74 -> 44.412111 | S64: =S63*Assumptions!$D$74 -> 44.412111 | T64: =T63*Assumptions!$D$74 -> 44.412111 | U64: =U63*Assumptions!$D$74 -> 44.412111 | V64: =V63*Assumptions!$D$74 -> 44.412111 | ... Z64: =Z63*Assumptions!$D$74 -> 44.412111 | AA64: =AA63*Assumptions!$E$74 -> 78.093711 | AB64: =AB63*Assumptions!$E$74 -> 78.093711 | AC64: =AC63*Assumptions!$E$74 -> 78.093711 | AD64: =AD63*Assumptions!$E$74 -> 78.093711 | AE64: =AE63*Assumptions!$E$74 -> 78.093711 | AF64: =AF63*Assumptions!$E$74 -> 78.093711 | AG64: =AG63*Assumptions!$E$74 -> 78.093711 | AH64: =AH63*Assumptions!$E$74 -> 78.093711 | ... AL64: =AL63*Assumptions!$E$74 -> 78.093711 | AN64: =SUM(C64:N64) -> 234.05022 | AO64: =SUM(O64:Z64) -> 532.94533 | AP64: =SUM(AA64:AL64) -> 937.12453
A65: Proposals, pilots and bids submitted | C65: =C64*Assumptions!$C$75 -> 9.7520923 | D65: =D64*Assumptions!$C$75 -> 9.7520923 | E65: =E64*Assumptions!$C$75 -> 9.7520923 | F65: =F64*Assumptions!$C$75 -> 9.7520923 | G65: =G64*Assumptions!$C$75 -> 9.7520923 | H65: =H64*Assumptions!$C$75 -> 9.7520923 | I65: =I64*Assumptions!$C$75 -> 9.7520923 | J65: =J64*Assumptions!$C$75 -> 9.7520923 | ... N65: =N64*Assumptions!$C$75 -> 9.7520923 | O65: =O64*Assumptions!$D$75 -> 23.98254 | P65: =P64*Assumptions!$D$75 -> 23.98254 | Q65: =Q64*Assumptions!$D$75 -> 23.98254 | R65: =R64*Assumptions!$D$75 -> 23.98254 | S65: =S64*Assumptions!$D$75 -> 23.98254 | T65: =T64*Assumptions!$D$75 -> 23.98254 | U65: =U64*Assumptions!$D$75 -> 23.98254 | V65: =V64*Assumptions!$D$75 -> 23.98254 | ... Z65: =Z64*Assumptions!$D$75 -> 23.98254 | AA65: =AA64*Assumptions!$E$75 -> 45.294352 | AB65: =AB64*Assumptions!$E$75 -> 45.294352 | AC65: =AC64*Assumptions!$E$75 -> 45.294352 | AD65: =AD64*Assumptions!$E$75 -> 45.294352 | AE65: =AE64*Assumptions!$E$75 -> 45.294352 | AF65: =AF64*Assumptions!$E$75 -> 45.294352 | AG65: =AG64*Assumptions!$E$75 -> 45.294352 | AH65: =AH64*Assumptions!$E$75 -> 45.294352 | ... AL65: =AL64*Assumptions!$E$75 -> 45.294352 | AN65: =SUM(C65:N65) -> 117.02511 | AO65: =SUM(O65:Z65) -> 287.79048 | AP65: =SUM(AA65:AL65) -> 543.53223
A66: Contracts signed | B66: proposals lagged by the sales cycle | C66: =IFERROR(INDEX($C65:$AL65,1,1-Assumptions!$C$77)*Assumptions!$C$76,0) -> 0 | D66: =IFERROR(INDEX($C65:$AL65,1,2-Assumptions!$C$77)*Assumptions!$C$76,0) -> 0 | E66: =IFERROR(INDEX($C65:$AL65,1,3-Assumptions!$C$77)*Assumptions!$C$76,0) -> 0 | F66: =IFERROR(INDEX($C65:$AL65,1,4-Assumptions!$C$77)*Assumptions!$C$76,0) -> 3.7057951 | G66: =IFERROR(INDEX($C65:$AL65,1,5-Assumptions!$C$77)*Assumptions!$C$76,0) -> 3.7057951 | H66: =IFERROR(INDEX($C65:$AL65,1,6-Assumptions!$C$77)*Assumptions!$C$76,0) -> 3.7057951 | I66: =IFERROR(INDEX($C65:$AL65,1,7-Assumptions!$C$77)*Assumptions!$C$76,0) -> 3.7057951 | J66: =IFERROR(INDEX($C65:$AL65,1,8-Assumptions!$C$77)*Assumptions!$C$76,0) -> 3.7057951 | K66: =IFERROR(INDEX($C65:$AL65,1,9-Assumptions!$C$77)*Assumptions!$C$76,0) -> 3.7057951 | L66: =IFERROR(INDEX($C65:$AL65,1,10-Assumptions!$C$77)*Assumptions!$C$76,0) -> 3.7057951 | M66: =IFERROR(INDEX($C65:$AL65,1,11-Assumptions!$C$77)*Assumptions!$C$76,0) -> 3.7057951 | N66: =IFERROR(INDEX($C65:$AL65,1,12-Assumptions!$C$77)*Assumptions!$C$76,0) -> 3.7057951 | O66: =IFERROR(INDEX($C65:$AL65,1,13-Assumptions!$C$77)*Assumptions!$D$76,0) -> 4.2909206 | P66: =IFERROR(INDEX($C65:$AL65,1,14-Assumptions!$C$77)*Assumptions!$D$76,0) -> 4.2909206 | Q66: =IFERROR(INDEX($C65:$AL65,1,15-Assumptions!$C$77)*Assumptions!$D$76,0) -> 4.2909206 | R66: =IFERROR(INDEX($C65:$AL65,1,16-Assumptions!$C$77)*Assumptions!$D$76,0) -> 4.2909206 | S66: =IFERROR(INDEX($C65:$AL65,1,17-Assumptions!$C$77)*Assumptions!$D$76,0) -> 10.552318 | T66: =IFERROR(INDEX($C65:$AL65,1,18-Assumptions!$C$77)*Assumptions!$D$76,0) -> 10.552318 | U66: =IFERROR(INDEX($C65:$AL65,1,19-Assumptions!$C$77)*Assumptions!$D$76,0) -> 10.552318 | V66: =IFERROR(INDEX($C65:$AL65,1,20-Assumptions!$C$77)*Assumptions!$D$76,0) -> 10.552318 | W66: =IFERROR(INDEX($C65:$AL65,1,21-Assumptions!$C$77)*Assumptions!$D$76,0) -> 10.552318 | X66: =IFERROR(INDEX($C65:$AL65,1,22-Assumptions!$C$77)*Assumptions!$D$76,0) -> 10.552318 | Y66: =IFERROR(INDEX($C65:$AL65,1,23-Assumptions!$C$77)*Assumptions!$D$76,0) -> 10.552318 | Z66: =IFERROR(INDEX($C65:$AL65,1,24-Assumptions!$C$77)*Assumptions!$D$76,0) -> 10.552318 | AA66: =IFERROR(INDEX($C65:$AL65,1,25-Assumptions!$C$77)*Assumptions!$E$76,0) -> 11.99127 | AB66: =IFERROR(INDEX($C65:$AL65,1,26-Assumptions!$C$77)*Assumptions!$E$76,0) -> 11.99127 | AC66: =IFERROR(INDEX($C65:$AL65,1,27-Assumptions!$C$77)*Assumptions!$E$76,0) -> 11.99127 | AD66: =IFERROR(INDEX($C65:$AL65,1,28-Assumptions!$C$77)*Assumptions!$E$76,0) -> 11.99127 | AE66: =IFERROR(INDEX($C65:$AL65,1,29-Assumptions!$C$77)*Assumptions!$E$76,0) -> 22.647176 | AF66: =IFERROR(INDEX($C65:$AL65,1,30-Assumptions!$C$77)*Assumptions!$E$76,0) -> 22.647176 | AG66: =IFERROR(INDEX($C65:$AL65,1,31-Assumptions!$C$77)*Assumptions!$E$76,0) -> 22.647176 | AH66: =IFERROR(INDEX($C65:$AL65,1,32-Assumptions!$C$77)*Assumptions!$E$76,0) -> 22.647176 | AI66: =IFERROR(INDEX($C65:$AL65,1,33-Assumptions!$C$77)*Assumptions!$E$76,0) -> 22.647176 | AJ66: =IFERROR(INDEX($C65:$AL65,1,34-Assumptions!$C$77)*Assumptions!$E$76,0) -> 22.647176 | AK66: =IFERROR(INDEX($C65:$AL65,1,35-Assumptions!$C$77)*Assumptions!$E$76,0) -> 22.647176 | AL66: =IFERROR(INDEX($C65:$AL65,1,36-Assumptions!$C$77)*Assumptions!$E$76,0) -> 22.647176 | AN66: =SUM(C66:N66) -> 33.352156 | AO66: =SUM(O66:Z66) -> 101.58222 | AP66: =SUM(AA66:AL66) -> 229.14249
A67: Contracts the delivery plan requires | B67: deliveries, over deliveries per contract | C67: =(Revenue!C$7+Revenue!C$8+Revenue!C$10+Revenue!C$11+Revenue!C$12+Revenue!C$13+Revenue!C$15+Revenue!C$16+Revenue!C$17+Revenue!C$18)/Assumptions!$C$84 -> 0.16666667 | D67: =(Revenue!D$7+Revenue!D$8+Revenue!D$10+Revenue!D$11+Revenue!D$12+Revenue!D$13+Revenue!D$15+Revenue!D$16+Revenue!D$17+Revenue!D$18)/Assumptions!$C$84 -> 0.18333333 | E67: =(Revenue!E$7+Revenue!E$8+Revenue!E$10+Revenue!E$11+Revenue!E$12+Revenue!E$13+Revenue!E$15+Revenue!E$16+Revenue!E$17+Revenue!E$18)/Assumptions!$C$84 -> 0.20555556 | F67: =(Revenue!F$7+Revenue!F$8+Revenue!F$10+Revenue!F$11+Revenue!F$12+Revenue!F$13+Revenue!F$15+Revenue!F$16+Revenue!F$17+Revenue!F$18)/Assumptions!$C$84 -> 1.1666667 | G67: =(Revenue!G$7+Revenue!G$8+Revenue!G$10+Revenue!G$11+Revenue!G$12+Revenue!G$13+Revenue!G$15+Revenue!G$16+Revenue!G$17+Revenue!G$18)/Assumptions!$C$84 -> 1.2833333 | H67: =(Revenue!H$7+Revenue!H$8+Revenue!H$10+Revenue!H$11+Revenue!H$12+Revenue!H$13+Revenue!H$15+Revenue!H$16+Revenue!H$17+Revenue!H$18)/Assumptions!$C$84 -> 1.4388889 | I67: =(Revenue!I$7+Revenue!I$8+Revenue!I$10+Revenue!I$11+Revenue!I$12+Revenue!I$13+Revenue!I$15+Revenue!I$16+Revenue!I$17+Revenue!I$18)/Assumptions!$C$84 -> 2.5 | J67: =(Revenue!J$7+Revenue!J$8+Revenue!J$10+Revenue!J$11+Revenue!J$12+Revenue!J$13+Revenue!J$15+Revenue!J$16+Revenue!J$17+Revenue!J$18)/Assumptions!$C$84 -> 2.75 | ... N67: =(Revenue!N$7+Revenue!N$8+Revenue!N$10+Revenue!N$11+Revenue!N$12+Revenue!N$13+Revenue!N$15+Revenue!N$16+Revenue!N$17+Revenue!N$18)/Assumptions!$C$84 -> 5.55 | O67: =(Revenue!O$7+Revenue!O$8+Revenue!O$10+Revenue!O$11+Revenue!O$12+Revenue!O$13+Revenue!O$15+Revenue!O$16+Revenue!O$17+Revenue!O$18)/Assumptions!$D$84 -> 5.0454545 | P67: =(Revenue!P$7+Revenue!P$8+Revenue!P$10+Revenue!P$11+Revenue!P$12+Revenue!P$13+Revenue!P$15+Revenue!P$16+Revenue!P$17+Revenue!P$18)/Assumptions!$D$84 -> 5.55 | Q67: =(Revenue!Q$7+Revenue!Q$8+Revenue!Q$10+Revenue!Q$11+Revenue!Q$12+Revenue!Q$13+Revenue!Q$15+Revenue!Q$16+Revenue!Q$17+Revenue!Q$18)/Assumptions!$D$84 -> 6.2227273 | R67: =(Revenue!R$7+Revenue!R$8+Revenue!R$10+Revenue!R$11+Revenue!R$12+Revenue!R$13+Revenue!R$15+Revenue!R$16+Revenue!R$17+Revenue!R$18)/Assumptions!$D$84 -> 6 | S67: =(Revenue!S$7+Revenue!S$8+Revenue!S$10+Revenue!S$11+Revenue!S$12+Revenue!S$13+Revenue!S$15+Revenue!S$16+Revenue!S$17+Revenue!S$18)/Assumptions!$D$84 -> 6.6 | T67: =(Revenue!T$7+Revenue!T$8+Revenue!T$10+Revenue!T$11+Revenue!T$12+Revenue!T$13+Revenue!T$15+Revenue!T$16+Revenue!T$17+Revenue!T$18)/Assumptions!$D$84 -> 7.4 | U67: =(Revenue!U$7+Revenue!U$8+Revenue!U$10+Revenue!U$11+Revenue!U$12+Revenue!U$13+Revenue!U$15+Revenue!U$16+Revenue!U$17+Revenue!U$18)/Assumptions!$D$84 -> 7.5 | V67: =(Revenue!V$7+Revenue!V$8+Revenue!V$10+Revenue!V$11+Revenue!V$12+Revenue!V$13+Revenue!V$15+Revenue!V$16+Revenue!V$17+Revenue!V$18)/Assumptions!$D$84 -> 8.25 | ... Z67: =(Revenue!Z$7+Revenue!Z$8+Revenue!Z$10+Revenue!Z$11+Revenue!Z$12+Revenue!Z$13+Revenue!Z$15+Revenue!Z$16+Revenue!Z$17+Revenue!Z$18)/Assumptions!$D$84 -> 10.259091 | AA67: =(Revenue!AA$7+Revenue!AA$8+Revenue!AA$10+Revenue!AA$11+Revenue!AA$12+Revenue!AA$13+Revenue!AA$15+Revenue!AA$16+Revenue!AA$17+Revenue!AA$18)/Assumptions!$E$84 -> 9 | AB67: =(Revenue!AB$7+Revenue!AB$8+Revenue!AB$10+Revenue!AB$11+Revenue!AB$12+Revenue!AB$13+Revenue!AB$15+Revenue!AB$16+Revenue!AB$17+Revenue!AB$18)/Assumptions!$E$84 -> 9.9 | AC67: =(Revenue!AC$7+Revenue!AC$8+Revenue!AC$10+Revenue!AC$11+Revenue!AC$12+Revenue!AC$13+Revenue!AC$15+Revenue!AC$16+Revenue!AC$17+Revenue!AC$18)/Assumptions!$E$84 -> 11.1 | AD67: =(Revenue!AD$7+Revenue!AD$8+Revenue!AD$10+Revenue!AD$11+Revenue!AD$12+Revenue!AD$13+Revenue!AD$15+Revenue!AD$16+Revenue!AD$17+Revenue!AD$18)/Assumptions!$E$84 -> 10.269231 | AE67: =(Revenue!AE$7+Revenue!AE$8+Revenue!AE$10+Revenue!AE$11+Revenue!AE$12+Revenue!AE$13+Revenue!AE$15+Revenue!AE$16+Revenue!AE$17+Revenue!AE$18)/Assumptions!$E$84 -> 11.296154 | AF67: =(Revenue!AF$7+Revenue!AF$8+Revenue!AF$10+Revenue!AF$11+Revenue!AF$12+Revenue!AF$13+Revenue!AF$15+Revenue!AF$16+Revenue!AF$17+Revenue!AF$18)/Assumptions!$E$84 -> 12.665385 | AG67: =(Revenue!AG$7+Revenue!AG$8+Revenue!AG$10+Revenue!AG$11+Revenue!AG$12+Revenue!AG$13+Revenue!AG$15+Revenue!AG$16+Revenue!AG$17+Revenue!AG$18)/Assumptions!$E$84 -> 11.423077 | AH67: =(Revenue!AH$7+Revenue!AH$8+Revenue!AH$10+Revenue!AH$11+Revenue!AH$12+Revenue!AH$13+Revenue!AH$15+Revenue!AH$16+Revenue!AH$17+Revenue!AH$18)/Assumptions!$E$84 -> 12.565385 | ... AL67: =(Revenue!AL$7+Revenue!AL$8+Revenue!AL$10+Revenue!AL$11+Revenue!AL$12+Revenue!AL$13+Revenue!AL$15+Revenue!AL$16+Revenue!AL$17+Revenue!AL$18)/Assumptions!$E$84 -> 15.796154 | AN67: =SUM(C67:N67) -> 27.777778 | AO67: =SUM(O67:Z67) -> 89.545455 | AP67: =SUM(AA67:AL67) -> 145
A68: Coverage — signings against the plan | B68: below 1.0x means the funnel is short | C68: =IFERROR(C66/C67,0) -> 0 | D68: =IFERROR(D66/D67,0) -> 0 | E68: =IFERROR(E66/E67,0) -> 0 | F68: =IFERROR(F66/F67,0) -> 3.1763958 | G68: =IFERROR(G66/G67,0) -> 2.8876325 | H68: =IFERROR(H66/H67,0) -> 2.575456 | I68: =IFERROR(I66/I67,0) -> 1.482318 | J68: =IFERROR(J66/J67,0) -> 1.3475618 | ... AL68: =IFERROR(AL66/AL67,0) -> 1.4337146 | AN68: =IFERROR(AVERAGE(C68:N68),0) -> 1.2425925 | AO68: =IFERROR(AVERAGE(O68:Z68),0) -> 1.1108656 | AP68: =IFERROR(AVERAGE(AA68:AL68),0) -> 1.5655372
A69: Cost per institutional contract won | B69: institutional CAC | C69: =IFERROR((C31+C55*Assumptions!$C$83)/C66,0) -> 0 | D69: =IFERROR((D31+D55*Assumptions!$C$83)/D66,0) -> 0 | E69: =IFERROR((E31+E55*Assumptions!$C$83)/E66,0) -> 0 | F69: =IFERROR((F31+F55*Assumptions!$C$83)/F66,0) -> 1831.8606 | G69: =IFERROR((G31+G55*Assumptions!$C$83)/G66,0) -> 1831.8606 | H69: =IFERROR((H31+H55*Assumptions!$C$83)/H66,0) -> 1831.8606 | I69: =IFERROR((I31+I55*Assumptions!$C$83)/I66,0) -> 1831.8606 | J69: =IFERROR((J31+J55*Assumptions!$C$83)/J66,0) -> 1831.8606 | ... AL69: =IFERROR((AL31+AL55*Assumptions!$C$83)/AL66,0) -> 1265.8311 | AN69: =IFERROR(AVERAGE(C69:N69),0) -> 1373.8955 | AO69: =IFERROR(AVERAGE(O69:Z69),0) -> 2254.8274 | AP69: =IFERROR(AVERAGE(AA69:AL69),0) -> 1640.7866
A71: LEARNER FUNNEL — EVERY CHANNEL LANDS ON MISSION 01
A72: Line item | B72: Driver / source | C72: Oct 26 | D72: Nov 26 | E72: Dec 26 | F72: Jan 26 | G72: Feb 26 | H72: Mar 26 | I72: Apr 26 | J72: May 26 | K72: Jun 26 | L72: Jul 27 | M72: Aug 27 | N72: Sep 27 | O72: Oct 27 | P72: Nov 27 | Q72: Dec 27 | R72: Jan 27 | S72: Feb 27 | T72: Mar 27 | U72: Apr 27 | V72: May 27 | W72: Jun 27 | X72: Jul 28 | Y72: Aug 28 | Z72: Sep 28 | AA72: Oct 28 | AB72: Nov 28 | AC72: Dec 28 | AD72: Jan 28 | AE72: Feb 28 | AF72: Mar 28 | AG72: Apr 28 | AH72: May 28 | AI72: Jun 28 | AJ72: Jul 29 | AK72: Aug 29 | AL72: Sep 29 | AN72: YEAR 1 | AO72: YEAR 2 | AP72: YEAR 3
A73: Reached — cohort participants | B73: university, school and technical | C73: =(Revenue!C$7+Revenue!C$8+Revenue!C$9)*Assumptions!$C$49+(Revenue!C$11+Revenue!C$13)*Assumptions!$C$50 -> 37.5 | D73: =(Revenue!D$7+Revenue!D$8+Revenue!D$9)*Assumptions!$C$49+(Revenue!D$11+Revenue!D$13)*Assumptions!$C$50 -> 41.25 | E73: =(Revenue!E$7+Revenue!E$8+Revenue!E$9)*Assumptions!$C$49+(Revenue!E$11+Revenue!E$13)*Assumptions!$C$50 -> 46.25 | F73: =(Revenue!F$7+Revenue!F$8+Revenue!F$9)*Assumptions!$C$49+(Revenue!F$11+Revenue!F$13)*Assumptions!$C$50 -> 60 | G73: =(Revenue!G$7+Revenue!G$8+Revenue!G$9)*Assumptions!$C$49+(Revenue!G$11+Revenue!G$13)*Assumptions!$C$50 -> 66 | H73: =(Revenue!H$7+Revenue!H$8+Revenue!H$9)*Assumptions!$C$49+(Revenue!H$11+Revenue!H$13)*Assumptions!$C$50 -> 74 | I73: =(Revenue!I$7+Revenue!I$8+Revenue!I$9)*Assumptions!$C$49+(Revenue!I$11+Revenue!I$13)*Assumptions!$C$50 -> 109.5 | J73: =(Revenue!J$7+Revenue!J$8+Revenue!J$9)*Assumptions!$C$49+(Revenue!J$11+Revenue!J$13)*Assumptions!$C$50 -> 120.45 | ... AL73: =(Revenue!AL$7+Revenue!AL$8+Revenue!AL$9)*Assumptions!$C$49+(Revenue!AL$11+Revenue!AL$13)*Assumptions!$C$50 -> 869.5 | AN73: =SUM(C73:N73) -> 1280 | AO73: =SUM(O73:Z73) -> 4300 | AP73: =SUM(AA73:AL73) -> 7950
A74: Reached — competition entrants | B74: entry is a free account | C74: =Revenue!C$17*Assumptions!$C$85 -> 0 | D74: =Revenue!D$17*Assumptions!$C$85 -> 0 | E74: =Revenue!E$17*Assumptions!$C$85 -> 0 | F74: =Revenue!F$17*Assumptions!$C$85 -> 210 | G74: =Revenue!G$17*Assumptions!$C$85 -> 231 | H74: =Revenue!H$17*Assumptions!$C$85 -> 259 | I74: =Revenue!I$17*Assumptions!$C$85 -> 210 | J74: =Revenue!J$17*Assumptions!$C$85 -> 231 | ... AL74: =Revenue!AL$17*Assumptions!$C$85 -> 1295 | AN74: =SUM(C74:N74) -> 2800 | AO74: =SUM(O74:Z74) -> 7000 | AP74: =SUM(AA74:AL74) -> 12600
A75: Reached — sponsored and programme seats | C75: =Revenue!C$14+Revenue!C$20 -> 0 | D75: =Revenue!D$14+Revenue!D$20 -> 0 | E75: =Revenue!E$14+Revenue!E$20 -> 0 | F75: =Revenue!F$14+Revenue!F$20 -> 36 | G75: =Revenue!G$14+Revenue!G$20 -> 39.6 | H75: =Revenue!H$14+Revenue!H$20 -> 44.4 | I75: =Revenue!I$14+Revenue!I$20 -> 54 | J75: =Revenue!J$14+Revenue!J$20 -> 59.4 | ... AL75: =Revenue!AL$14+Revenue!AL$20 -> 7784.8 | AN75: =SUM(C75:N75) -> 2540 | AO75: =SUM(O75:Z75) -> 22820 | AP75: =SUM(AA75:AL75) -> 68680
A76: Reached — NGO and corporate participants | C76: =Revenue!C$16*Assumptions!$C$86+Revenue!C$18*Assumptions!$C$87 -> 0 | D76: =Revenue!D$16*Assumptions!$C$86+Revenue!D$18*Assumptions!$C$87 -> 0 | E76: =Revenue!E$16*Assumptions!$C$86+Revenue!E$18*Assumptions!$C$87 -> 0 | F76: =Revenue!F$16*Assumptions!$C$86+Revenue!F$18*Assumptions!$C$87 -> 0 | G76: =Revenue!G$16*Assumptions!$C$86+Revenue!G$18*Assumptions!$C$87 -> 0 | H76: =Revenue!H$16*Assumptions!$C$86+Revenue!H$18*Assumptions!$C$87 -> 0 | I76: =Revenue!I$16*Assumptions!$C$86+Revenue!I$18*Assumptions!$C$87 -> 42 | J76: =Revenue!J$16*Assumptions!$C$86+Revenue!J$18*Assumptions!$C$87 -> 46.2 | ... AL76: =Revenue!AL$16*Assumptions!$C$86+Revenue!AL$18*Assumptions!$C$87 -> 325.6 | AN76: =SUM(C76:N76) -> 340 | AO76: =SUM(O76:Z76) -> 1640 | AP76: =SUM(AA76:AL76) -> 3060
A77: Free accounts — through an institution | C77: =C73+C74+C75+C76 -> 37.5 | D77: =D73+D74+D75+D76 -> 41.25 | E77: =E73+E74+E75+E76 -> 46.25 | F77: =F73+F74+F75+F76 -> 306 | G77: =G73+G74+G75+G76 -> 336.6 | H77: =H73+H74+H75+H76 -> 377.4 | I77: =I73+I74+I75+I76 -> 415.5 | J77: =J73+J74+J75+J76 -> 457.05 | ... AL77: =AL73+AL74+AL75+AL76 -> 10274.9 | AN77: =SUM(C77:N77) -> 6960 | AO77: =SUM(O77:Z77) -> 35760 | AP77: =SUM(AA77:AL77) -> 92290
A78: Free accounts — direct, offline and online | C78: =C32+C57 -> 1671.1758 | D78: =D32+D57 -> 1671.1758 | E78: =E32+E57 -> 1671.1758 | F78: =F32+F57 -> 1671.1758 | G78: =G32+G57 -> 1671.1758 | H78: =H32+H57 -> 1671.1758 | I78: =I32+I57 -> 1671.1758 | J78: =J32+J57 -> 1671.1758 | ... AL78: =AL32+AL57 -> 7305.9451 | AN78: =SUM(C78:N78) -> 20054.11 | AO78: =SUM(O78:Z78) -> 47475.956 | AP78: =SUM(AA78:AL78) -> 87671.341
A79: Total new free accounts | C79: =C77+C78 -> 1708.6758 | D79: =D77+D78 -> 1712.4258 | E79: =E77+E78 -> 1717.4258 | F79: =F77+F78 -> 1977.1758 | G79: =G77+G78 -> 2007.7758 | H79: =H77+H78 -> 2048.5758 | I79: =I77+I78 -> 2086.6758 | J79: =J77+J78 -> 2128.2258 | ... AL79: =AL77+AL78 -> 17580.845 | AN79: =SUM(C79:N79) -> 27014.11 | AO79: =SUM(O79:Z79) -> 83235.956 | AP79: =SUM(AA79:AL79) -> 179961.34
A80: Activated — Mission 01 completed | B80: activation is finishing Mission 01, not opening an account | C80: =(C77+C78)*Assumptions!$C$78 -> 717.64385 | D80: =(D77+D78)*Assumptions!$C$78 -> 719.21885 | E80: =(E77+E78)*Assumptions!$C$78 -> 721.31885 | F80: =(F77+F78)*Assumptions!$C$78 -> 830.41385 | G80: =(G77+G78)*Assumptions!$C$78 -> 843.26585 | H80: =(H77+H78)*Assumptions!$C$78 -> 860.40185 | I80: =(I77+I78)*Assumptions!$C$78 -> 876.40385 | J80: =(J77+J78)*Assumptions!$C$78 -> 893.85485 | ... N80: =(N77+N78)*Assumptions!$C$78 -> 1390.3158 | O80: =(O77+O78)*Assumptions!$D$78 -> 2634.8016 | P80: =(P77+P78)*Assumptions!$D$78 -> 2716.2906 | Q80: =(Q77+Q78)*Assumptions!$D$78 -> 2824.9426 | R80: =(R77+R78)*Assumptions!$D$78 -> 2805.9216 | S80: =(S77+S78)*Assumptions!$D$78 -> 2904.5226 | T80: =(T77+T78)*Assumptions!$D$78 -> 3035.9906 | U80: =(U77+U78)*Assumptions!$D$78 -> 3234.4116 | V80: =(V77+V78)*Assumptions!$D$78 -> 3375.8616 | ... Z80: =(Z77+Z78)*Assumptions!$D$78 -> 3940.6036 | AA80: =(AA77+AA78)*Assumptions!$E$78 -> 6338.7225 | AB80: =(AB77+AB78)*Assumptions!$E$78 -> 6607.2975 | AC80: =(AC77+AC78)*Assumptions!$E$78 -> 6965.3975 | AD80: =(AD77+AD78)*Assumptions!$E$78 -> 6842.7225 | AE80: =(AE77+AE78)*Assumptions!$E$78 -> 7161.6975 | AF80: =(AF77+AF78)*Assumptions!$E$78 -> 7586.9975 | AG80: =(AG77+AG78)*Assumptions!$E$78 -> 7455.4725 | AH80: =(AH77+AH78)*Assumptions!$E$78 -> 7835.7225 | ... AL80: =(AL77+AL78)*Assumptions!$E$78 -> 8790.4225 | AN80: =SUM(C80:N80) -> 11345.926 | AO80: =SUM(O80:Z80) -> 38288.54 | AP80: =SUM(AA80:AL80) -> 89980.67
A81: Engaged — through an institution | C81: =C77*Assumptions!$C$78*Assumptions!$C$79 -> 8.6625 | D81: =D77*Assumptions!$C$78*Assumptions!$C$79 -> 9.52875 | E81: =E77*Assumptions!$C$78*Assumptions!$C$79 -> 10.68375 | F81: =F77*Assumptions!$C$78*Assumptions!$C$79 -> 70.686 | G81: =G77*Assumptions!$C$78*Assumptions!$C$79 -> 77.7546 | H81: =H77*Assumptions!$C$78*Assumptions!$C$79 -> 87.1794 | I81: =I77*Assumptions!$C$78*Assumptions!$C$79 -> 95.9805 | J81: =J77*Assumptions!$C$78*Assumptions!$C$79 -> 105.57855 | ... N81: =N77*Assumptions!$C$78*Assumptions!$C$79 -> 378.6321 | O81: =O77*Assumptions!$D$78*Assumptions!$D$79 -> 472.6362 | P81: =P77*Assumptions!$D$78*Assumptions!$D$79 -> 519.89982 | Q81: =Q77*Assumptions!$D$78*Assumptions!$D$79 -> 582.91798 | R81: =R77*Assumptions!$D$78*Assumptions!$D$79 -> 571.8858 | S81: =S77*Assumptions!$D$78*Assumptions!$D$79 -> 629.07438 | T81: =T77*Assumptions!$D$78*Assumptions!$D$79 -> 705.32582 | U81: =U77*Assumptions!$D$78*Assumptions!$D$79 -> 820.41 | V81: =V77*Assumptions!$D$78*Assumptions!$D$79 -> 902.451 | ... Z81: =Z77*Assumptions!$D$78*Assumptions!$D$79 -> 1230.0014 | AA81: =AA77*Assumptions!$E$78*Assumptions!$E$79 -> 1638.3075 | AB81: =AB77*Assumptions!$E$78*Assumptions!$E$79 -> 1802.1382 | AC81: =AC77*Assumptions!$E$78*Assumptions!$E$79 -> 2020.5793 | AD81: =AD77*Assumptions!$E$78*Assumptions!$E$79 -> 1945.7475 | AE81: =AE77*Assumptions!$E$78*Assumptions!$E$79 -> 2140.3223 | AF81: =AF77*Assumptions!$E$78*Assumptions!$E$79 -> 2399.7553 | AG81: =AG77*Assumptions!$E$78*Assumptions!$E$79 -> 2319.525 | AH81: =AH77*Assumptions!$E$78*Assumptions!$E$79 -> 2551.4775 | ... AL81: =AL77*Assumptions!$E$78*Assumptions!$E$79 -> 3133.8445 | AN81: =SUM(C81:N81) -> 1607.76 | AO81: =SUM(O81:Z81) -> 9540.768 | AP81: =SUM(AA81:AL81) -> 28148.45
A82: Engaged — direct | C82: =C78*Assumptions!$C$78*Assumptions!$C$79 -> 386.04162 | D82: =D78*Assumptions!$C$78*Assumptions!$C$79 -> 386.04162 | E82: =E78*Assumptions!$C$78*Assumptions!$C$79 -> 386.04162 | F82: =F78*Assumptions!$C$78*Assumptions!$C$79 -> 386.04162 | G82: =G78*Assumptions!$C$78*Assumptions!$C$79 -> 386.04162 | H82: =H78*Assumptions!$C$78*Assumptions!$C$79 -> 386.04162 | I82: =I78*Assumptions!$C$78*Assumptions!$C$79 -> 386.04162 | J82: =J78*Assumptions!$C$78*Assumptions!$C$79 -> 386.04162 | ... N82: =N78*Assumptions!$C$78*Assumptions!$C$79 -> 386.04162 | O82: =O78*Assumptions!$D$78*Assumptions!$D$79 -> 1055.5488 | P82: =P78*Assumptions!$D$78*Assumptions!$D$79 -> 1055.5488 | Q82: =Q78*Assumptions!$D$78*Assumptions!$D$79 -> 1055.5488 | R82: =R78*Assumptions!$D$78*Assumptions!$D$79 -> 1055.5488 | S82: =S78*Assumptions!$D$78*Assumptions!$D$79 -> 1055.5488 | T82: =T78*Assumptions!$D$78*Assumptions!$D$79 -> 1055.5488 | U82: =U78*Assumptions!$D$78*Assumptions!$D$79 -> 1055.5488 | V82: =V78*Assumptions!$D$78*Assumptions!$D$79 -> 1055.5488 | ... Z82: =Z78*Assumptions!$D$78*Assumptions!$D$79 -> 1055.5488 | AA82: =AA78*Assumptions!$E$78*Assumptions!$E$79 -> 2228.3132 | AB82: =AB78*Assumptions!$E$78*Assumptions!$E$79 -> 2228.3132 | AC82: =AC78*Assumptions!$E$78*Assumptions!$E$79 -> 2228.3132 | AD82: =AD78*Assumptions!$E$78*Assumptions!$E$79 -> 2228.3132 | AE82: =AE78*Assumptions!$E$78*Assumptions!$E$79 -> 2228.3132 | AF82: =AF78*Assumptions!$E$78*Assumptions!$E$79 -> 2228.3132 | AG82: =AG78*Assumptions!$E$78*Assumptions!$E$79 -> 2228.3132 | AH82: =AH78*Assumptions!$E$78*Assumptions!$E$79 -> 2228.3132 | ... AL82: =AL78*Assumptions!$E$78*Assumptions!$E$79 -> 2228.3132 | AN82: =SUM(C82:N82) -> 4632.4994 | AO82: =SUM(O82:Z82) -> 12666.585 | AP82: =SUM(AA82:AL82) -> 26739.759
A83: New paid subscribers | B83: institutional reach converts far better | C83: =C81*Assumptions!$C$80+C82*Assumptions!$C$81 -> 12.230936 | D83: =D81*Assumptions!$C$80+D82*Assumptions!$C$81 -> 12.295905 | E83: =E81*Assumptions!$C$80+E82*Assumptions!$C$81 -> 12.38253 | F83: =F81*Assumptions!$C$80+F82*Assumptions!$C$81 -> 16.882698 | G83: =G81*Assumptions!$C$80+G82*Assumptions!$C$81 -> 17.412843 | H83: =H81*Assumptions!$C$80+H82*Assumptions!$C$81 -> 18.119703 | I83: =I81*Assumptions!$C$80+I82*Assumptions!$C$81 -> 18.779786 | J83: =J81*Assumptions!$C$80+J82*Assumptions!$C$81 -> 19.49964 | ... N83: =N81*Assumptions!$C$80+N82*Assumptions!$C$81 -> 39.978656 | O83: =O81*Assumptions!$D$80+O82*Assumptions!$D$81 -> 76.062735 | P83: =P81*Assumptions!$D$80+P82*Assumptions!$D$81 -> 80.080142 | Q83: =Q81*Assumptions!$D$80+Q82*Assumptions!$D$81 -> 85.436686 | R83: =R81*Assumptions!$D$80+R82*Assumptions!$D$81 -> 84.498951 | S83: =S81*Assumptions!$D$80+S82*Assumptions!$D$81 -> 89.35998 | T83: =T81*Assumptions!$D$80+T82*Assumptions!$D$81 -> 95.841352 | U83: =U81*Assumptions!$D$80+U82*Assumptions!$D$81 -> 105.62351 | V83: =V81*Assumptions!$D$80+V82*Assumptions!$D$81 -> 112.59699 | ... Z83: =Z81*Assumptions!$D$80+Z82*Assumptions!$D$81 -> 140.43877 | AA83: =AA81*Assumptions!$E$80+AA82*Assumptions!$E$81 -> 240.31512 | AB83: =AB81*Assumptions!$E$80+AB82*Assumptions!$E$81 -> 255.87904 | AC83: =AC81*Assumptions!$E$80+AC82*Assumptions!$E$81 -> 276.63093 | AD83: =AD81*Assumptions!$E$80+AD82*Assumptions!$E$81 -> 269.52192 | AE83: =AE81*Assumptions!$E$80+AE82*Assumptions!$E$81 -> 288.00652 | AF83: =AF81*Assumptions!$E$80+AF82*Assumptions!$E$81 -> 312.65265 | AG83: =AG81*Assumptions!$E$80+AG82*Assumptions!$E$81 -> 305.03078 | AH83: =AH81*Assumptions!$E$80+AH82*Assumptions!$E$81 -> 327.06627 | ... AL83: =AL81*Assumptions!$E$80+AL82*Assumptions!$E$81 -> 382.39113 | AN83: =SUM(C83:N83) -> 259.55698 | AO83: =SUM(O83:Z83) -> 1241.6292 | AP83: =SUM(AA83:AL83) -> 3690.2136
A84: Active paid subscribers | B84: after monthly churn | C84: =C83 -> 12.230936 | D84: =C84*(1-Assumptions!$C$48)+D83 -> 23.976449 | E84: =D84*(1-Assumptions!$C$48)+E83 -> 35.280038 | F84: =E84*(1-Assumptions!$C$48)+F83 -> 50.575135 | G84: =F84*(1-Assumptions!$C$48)+G83 -> 65.712097 | H84: =G84*(1-Assumptions!$C$48)+H83 -> 80.874756 | I84: =H84*(1-Assumptions!$C$48)+I83 -> 96.015178 | J84: =I84*(1-Assumptions!$C$48)+J83 -> 111.19413 | K84: =J84*(1-Assumptions!$C$48)+K83 -> 126.64984 | ... AL84: =AK84*(1-Assumptions!$C$48)+AL83 -> 3611.4016 | AN84: =N84 -> 217.0981 | AO84: =Z84 -> 1131.2018 | AP84: =AL84 -> 3611.4016
A85: Cost per paid subscriber | B85: learner CAC, on the online spend only | C85: =IFERROR(C55*(1-Assumptions!$C$83)/C83,0) -> 282.19427 | D85: =IFERROR(D55*(1-Assumptions!$C$83)/D83,0) -> 280.70322 | E85: =IFERROR(E55*(1-Assumptions!$C$83)/E83,0) -> 278.73949 | F85: =IFERROR(F55*(1-Assumptions!$C$83)/F83,0) -> 204.44007 | G85: =IFERROR(G55*(1-Assumptions!$C$83)/G83,0) -> 198.21576 | H85: =IFERROR(H55*(1-Assumptions!$C$83)/H83,0) -> 190.48325 | I85: =IFERROR(I55*(1-Assumptions!$C$83)/I83,0) -> 183.78804 | J85: =IFERROR(J55*(1-Assumptions!$C$83)/J83,0) -> 177.00327 | ... AL85: =IFERROR(AL55*(1-Assumptions!$C$83)/AL83,0) -> 38.501154 | AN85: =IFERROR(AVERAGE(C85:N85),0) -> 186.98764 | AO85: =IFERROR(AVERAGE(O85:Z85),0) -> 76.042356 | AP85: =IFERROR(AVERAGE(AA85:AL85),0) -> 48.760716

Sheet Revenue
A1: Revenue Streams
A2: Thirteen lines across eight engines. Volume comes from the quarterly plan split by the monthly phasing weight, so every annual total ties back to the business plan exactly.
A5: DELIVERY VOLUME
A6: Line item | B6: Driver / source | C6: Oct 26 | D6: Nov 26 | E6: Dec 26 | F6: Jan 26 | G6: Feb 26 | H6: Mar 26 | I6: Apr 26 | J6: May 26 | K6: Jun 26 | L6: Jul 27 | M6: Aug 27 | N6: Sep 27 | O6: Oct 27 | P6: Nov 27 | Q6: Dec 27 | R6: Jan 27 | S6: Feb 27 | T6: Mar 27 | U6: Apr 27 | V6: May 27 | W6: Jun 27 | X6: Jul 28 | Y6: Aug 28 | Z6: Sep 28 | AA6: Oct 28 | AB6: Nov 28 | AC6: Dec 28 | AD6: Jan 28 | AE6: Feb 28 | AF6: Mar 28 | AG6: Apr 28 | AH6: May 28 | AI6: Jun 28 | AJ6: Jul 29 | AK6: Aug 29 | AL6: Sep 29 | AN6: YEAR 1 | AO6: YEAR 2 | AP6: YEAR 3
A7: University cohorts — Egypt | B7: cohorts | C7: =Assumptions!$C$14*Assumptions!$C$31 -> 0 | D7: =Assumptions!$C$14*Assumptions!$D$31 -> 0 | E7: =Assumptions!$C$14*Assumptions!$E$31 -> 0 | F7: =Assumptions!$D$14*Assumptions!$C$31 -> 1.2 | G7: =Assumptions!$D$14*Assumptions!$D$31 -> 1.32 | H7: =Assumptions!$D$14*Assumptions!$E$31 -> 1.48 | I7: =Assumptions!$E$14*Assumptions!$C$31 -> 2.1 | J7: =Assumptions!$E$14*Assumptions!$D$31 -> 2.31 | K7: =Assumptions!$E$14*Assumptions!$E$31 -> 2.59 | L7: =Assumptions!$F$14*Assumptions!$C$31 -> 2.7 | M7: =Assumptions!$F$14*Assumptions!$D$31 -> 2.97 | N7: =Assumptions!$F$14*Assumptions!$E$31 -> 3.33 | O7: =Assumptions!$G$14*Assumptions!$C$31 -> 3.3 | P7: =Assumptions!$G$14*Assumptions!$D$31 -> 3.63 | Q7: =Assumptions!$G$14*Assumptions!$E$31 -> 4.07 | R7: =Assumptions!$H$14*Assumptions!$C$31 -> 3.9 | S7: =Assumptions!$H$14*Assumptions!$D$31 -> 4.29 | T7: =Assumptions!$H$14*Assumptions!$E$31 -> 4.81 | U7: =Assumptions!$I$14*Assumptions!$C$31 -> 4.5 | V7: =Assumptions!$I$14*Assumptions!$D$31 -> 4.95 | W7: =Assumptions!$I$14*Assumptions!$E$31 -> 5.55 | X7: =Assumptions!$J$14*Assumptions!$C$31 -> 5.1 | Y7: =Assumptions!$J$14*Assumptions!$D$31 -> 5.61 | Z7: =Assumptions!$J$14*Assumptions!$E$31 -> 6.29 | AA7: =Assumptions!$K$14*Assumptions!$C$31 -> 6 | AB7: =Assumptions!$K$14*Assumptions!$D$31 -> 6.6 | AC7: =Assumptions!$K$14*Assumptions!$E$31 -> 7.4 | AD7: =Assumptions!$L$14*Assumptions!$C$31 -> 6.9 | AE7: =Assumptions!$L$14*Assumptions!$D$31 -> 7.59 | AF7: =Assumptions!$L$14*Assumptions!$E$31 -> 8.51 | AG7: =Assumptions!$M$14*Assumptions!$C$31 -> 7.5 | AH7: =Assumptions!$M$14*Assumptions!$D$31 -> 8.25 | AI7: =Assumptions!$M$14*Assumptions!$E$31 -> 9.25 | AJ7: =Assumptions!$N$14*Assumptions!$C$31 -> 8.4 | AK7: =Assumptions!$N$14*Assumptions!$D$31 -> 9.24 | AL7: =Assumptions!$N$14*Assumptions!$E$31 -> 10.36 | AN7: =SUM(C7:N7) -> 20 | AO7: =SUM(O7:Z7) -> 56 | AP7: =SUM(AA7:AL7) -> 96
A8: University cohorts — Saudi Arabia | B8: cohorts | C8: =Assumptions!$C$15*Assumptions!$C$31 -> 0.3 | D8: =Assumptions!$C$15*Assumptions!$D$31 -> 0.33 | E8: =Assumptions!$C$15*Assumptions!$E$31 -> 0.37 | F8: =Assumptions!$D$15*Assumptions!$C$31 -> 0.6 | G8: =Assumptions!$D$15*Assumptions!$D$31 -> 0.66 | H8: =Assumptions!$D$15*Assumptions!$E$31 -> 0.74 | I8: =Assumptions!$E$15*Assumptions!$C$31 -> 0.9 | J8: =Assumptions!$E$15*Assumptions!$D$31 -> 0.99 | K8: =Assumptions!$E$15*Assumptions!$E$31 -> 1.11 | L8: =Assumptions!$F$15*Assumptions!$C$31 -> 1.2 | M8: =Assumptions!$F$15*Assumptions!$D$31 -> 1.32 | N8: =Assumptions!$F$15*Assumptions!$E$31 -> 1.48 | O8: =Assumptions!$G$15*Assumptions!$C$31 -> 1.5 | P8: =Assumptions!$G$15*Assumptions!$D$31 -> 1.65 | Q8: =Assumptions!$G$15*Assumptions!$E$31 -> 1.85 | R8: =Assumptions!$H$15*Assumptions!$C$31 -> 1.5 | S8: =Assumptions!$H$15*Assumptions!$D$31 -> 1.65 | T8: =Assumptions!$H$15*Assumptions!$E$31 -> 1.85 | U8: =Assumptions!$I$15*Assumptions!$C$31 -> 1.8 | V8: =Assumptions!$I$15*Assumptions!$D$31 -> 1.98 | W8: =Assumptions!$I$15*Assumptions!$E$31 -> 2.22 | X8: =Assumptions!$J$15*Assumptions!$C$31 -> 1.8 | Y8: =Assumptions!$J$15*Assumptions!$D$31 -> 1.98 | Z8: =Assumptions!$J$15*Assumptions!$E$31 -> 2.22 | AA8: =Assumptions!$K$15*Assumptions!$C$31 -> 2.4 | AB8: =Assumptions!$K$15*Assumptions!$D$31 -> 2.64 | AC8: =Assumptions!$K$15*Assumptions!$E$31 -> 2.96 | AD8: =Assumptions!$L$15*Assumptions!$C$31 -> 2.7 | AE8: =Assumptions!$L$15*Assumptions!$D$31 -> 2.97 | AF8: =Assumptions!$L$15*Assumptions!$E$31 -> 3.33 | AG8: =Assumptions!$M$15*Assumptions!$C$31 -> 3 | AH8: =Assumptions!$M$15*Assumptions!$D$31 -> 3.3 | AI8: =Assumptions!$M$15*Assumptions!$E$31 -> 3.7 | AJ8: =Assumptions!$N$15*Assumptions!$C$31 -> 3.3 | AK8: =Assumptions!$N$15*Assumptions!$D$31 -> 3.63 | AL8: =Assumptions!$N$15*Assumptions!$E$31 -> 4.07 | AN8: =SUM(C8:N8) -> 10 | AO8: =SUM(O8:Z8) -> 22 | AP8: =SUM(AA8:AL8) -> 38
A9: University pilot cohorts (unpaid) | B9: sales cost | C9: =Assumptions!$C$16*Assumptions!$C$31 -> 1.2 | D9: =Assumptions!$C$16*Assumptions!$D$31 -> 1.32 | E9: =Assumptions!$C$16*Assumptions!$E$31 -> 1.48 | F9: =Assumptions!$D$16*Assumptions!$C$31 -> 0.6 | G9: =Assumptions!$D$16*Assumptions!$D$31 -> 0.66 | H9: =Assumptions!$D$16*Assumptions!$E$31 -> 0.74 | I9: =Assumptions!$E$16*Assumptions!$C$31 -> 0.3 | J9: =Assumptions!$E$16*Assumptions!$D$31 -> 0.33 | K9: =Assumptions!$E$16*Assumptions!$E$31 -> 0.37 | L9: =Assumptions!$F$16*Assumptions!$C$31 -> 0.3 | M9: =Assumptions!$F$16*Assumptions!$D$31 -> 0.33 | N9: =Assumptions!$F$16*Assumptions!$E$31 -> 0.37 | O9: =Assumptions!$G$16*Assumptions!$C$31 -> 0.3 | P9: =Assumptions!$G$16*Assumptions!$D$31 -> 0.33 | Q9: =Assumptions!$G$16*Assumptions!$E$31 -> 0.37 | R9: =Assumptions!$H$16*Assumptions!$C$31 -> 0.3 | S9: =Assumptions!$H$16*Assumptions!$D$31 -> 0.33 | T9: =Assumptions!$H$16*Assumptions!$E$31 -> 0.37 | U9: =Assumptions!$I$16*Assumptions!$C$31 -> 0.3 | V9: =Assumptions!$I$16*Assumptions!$D$31 -> 0.33 | W9: =Assumptions!$I$16*Assumptions!$E$31 -> 0.37 | X9: =Assumptions!$J$16*Assumptions!$C$31 -> 0.3 | Y9: =Assumptions!$J$16*Assumptions!$D$31 -> 0.33 | Z9: =Assumptions!$J$16*Assumptions!$E$31 -> 0.37 | AA9: =Assumptions!$K$16*Assumptions!$C$31 -> 0.3 | AB9: =Assumptions!$K$16*Assumptions!$D$31 -> 0.33 | AC9: =Assumptions!$K$16*Assumptions!$E$31 -> 0.37 | AD9: =Assumptions!$L$16*Assumptions!$C$31 -> 0.3 | AE9: =Assumptions!$L$16*Assumptions!$D$31 -> 0.33 | AF9: =Assumptions!$L$16*Assumptions!$E$31 -> 0.37 | AG9: =Assumptions!$M$16*Assumptions!$C$31 -> 0.3 | AH9: =Assumptions!$M$16*Assumptions!$D$31 -> 0.33 | AI9: =Assumptions!$M$16*Assumptions!$E$31 -> 0.37 | AJ9: =Assumptions!$N$16*Assumptions!$C$31 -> 0.3 | AK9: =Assumptions!$N$16*Assumptions!$D$31 -> 0.33 | AL9: =Assumptions!$N$16*Assumptions!$E$31 -> 0.37 | AN9: =SUM(C9:N9) -> 8 | AO9: =SUM(O9:Z9) -> 4 | AP9: =SUM(AA9:AL9) -> 4
A10: Faculty licences | B10: licences | C10: =Assumptions!$C$17*Assumptions!$C$31 -> 0 | D10: =Assumptions!$C$17*Assumptions!$D$31 -> 0 | E10: =Assumptions!$C$17*Assumptions!$E$31 -> 0 | F10: =Assumptions!$D$17*Assumptions!$C$31 -> 0 | G10: =Assumptions!$D$17*Assumptions!$D$31 -> 0 | H10: =Assumptions!$D$17*Assumptions!$E$31 -> 0 | I10: =Assumptions!$E$17*Assumptions!$C$31 -> 0 | J10: =Assumptions!$E$17*Assumptions!$D$31 -> 0 | K10: =Assumptions!$E$17*Assumptions!$E$31 -> 0 | L10: =Assumptions!$F$17*Assumptions!$C$31 -> 0.3 | M10: =Assumptions!$F$17*Assumptions!$D$31 -> 0.33 | N10: =Assumptions!$F$17*Assumptions!$E$31 -> 0.37 | O10: =Assumptions!$G$17*Assumptions!$C$31 -> 0.3 | P10: =Assumptions!$G$17*Assumptions!$D$31 -> 0.33 | Q10: =Assumptions!$G$17*Assumptions!$E$31 -> 0.37 | R10: =Assumptions!$H$17*Assumptions!$C$31 -> 0.3 | S10: =Assumptions!$H$17*Assumptions!$D$31 -> 0.33 | T10: =Assumptions!$H$17*Assumptions!$E$31 -> 0.37 | U10: =Assumptions!$I$17*Assumptions!$C$31 -> 0.6 | V10: =Assumptions!$I$17*Assumptions!$D$31 -> 0.66 | W10: =Assumptions!$I$17*Assumptions!$E$31 -> 0.74 | X10: =Assumptions!$J$17*Assumptions!$C$31 -> 0.6 | Y10: =Assumptions!$J$17*Assumptions!$D$31 -> 0.66 | Z10: =Assumptions!$J$17*Assumptions!$E$31 -> 0.74 | AA10: =Assumptions!$K$17*Assumptions!$C$31 -> 0.9 | AB10: =Assumptions!$K$17*Assumptions!$D$31 -> 0.99 | AC10: =Assumptions!$K$17*Assumptions!$E$31 -> 1.11 | AD10: =Assumptions!$L$17*Assumptions!$C$31 -> 0.9 | AE10: =Assumptions!$L$17*Assumptions!$D$31 -> 0.99 | AF10: =Assumptions!$L$17*Assumptions!$E$31 -> 1.11 | AG10: =Assumptions!$M$17*Assumptions!$C$31 -> 1.2 | AH10: =Assumptions!$M$17*Assumptions!$D$31 -> 1.32 | AI10: =Assumptions!$M$17*Assumptions!$E$31 -> 1.48 | AJ10: =Assumptions!$N$17*Assumptions!$C$31 -> 1.2 | AK10: =Assumptions!$N$17*Assumptions!$D$31 -> 1.32 | AL10: =Assumptions!$N$17*Assumptions!$E$31 -> 1.48 | AN10: =SUM(C10:N10) -> 1 | AO10: =SUM(O10:Z10) -> 6 | AP10: =SUM(AA10:AL10) -> 14
A11: School cohorts | B11: cohorts | C11: =Assumptions!$C$18*Assumptions!$C$31 -> 0 | D11: =Assumptions!$C$18*Assumptions!$D$31 -> 0 | E11: =Assumptions!$C$18*Assumptions!$E$31 -> 0 | F11: =Assumptions!$D$18*Assumptions!$C$31 -> 0 | G11: =Assumptions!$D$18*Assumptions!$D$31 -> 0 | H11: =Assumptions!$D$18*Assumptions!$E$31 -> 0 | I11: =Assumptions!$E$18*Assumptions!$C$31 -> 0.9 | J11: =Assumptions!$E$18*Assumptions!$D$31 -> 0.99 | K11: =Assumptions!$E$18*Assumptions!$E$31 -> 1.11 | L11: =Assumptions!$F$18*Assumptions!$C$31 -> 1.8 | M11: =Assumptions!$F$18*Assumptions!$D$31 -> 1.98 | N11: =Assumptions!$F$18*Assumptions!$E$31 -> 2.22 | O11: =Assumptions!$G$18*Assumptions!$C$31 -> 2.7 | P11: =Assumptions!$G$18*Assumptions!$D$31 -> 2.97 | Q11: =Assumptions!$G$18*Assumptions!$E$31 -> 3.33 | R11: =Assumptions!$H$18*Assumptions!$C$31 -> 3.6 | S11: =Assumptions!$H$18*Assumptions!$D$31 -> 3.96 | T11: =Assumptions!$H$18*Assumptions!$E$31 -> 4.44 | U11: =Assumptions!$I$18*Assumptions!$C$31 -> 4.2 | V11: =Assumptions!$I$18*Assumptions!$D$31 -> 4.62 | W11: =Assumptions!$I$18*Assumptions!$E$31 -> 5.18 | X11: =Assumptions!$J$18*Assumptions!$C$31 -> 4.8 | Y11: =Assumptions!$J$18*Assumptions!$D$31 -> 5.28 | Z11: =Assumptions!$J$18*Assumptions!$E$31 -> 5.92 | AA11: =Assumptions!$K$18*Assumptions!$C$31 -> 6 | AB11: =Assumptions!$K$18*Assumptions!$D$31 -> 6.6 | AC11: =Assumptions!$K$18*Assumptions!$E$31 -> 7.4 | AD11: =Assumptions!$L$18*Assumptions!$C$31 -> 7.2 | AE11: =Assumptions!$L$18*Assumptions!$D$31 -> 7.92 | AF11: =Assumptions!$L$18*Assumptions!$E$31 -> 8.88 | AG11: =Assumptions!$M$18*Assumptions!$C$31 -> 7.8 | AH11: =Assumptions!$M$18*Assumptions!$D$31 -> 8.58 | AI11: =Assumptions!$M$18*Assumptions!$E$31 -> 9.62 | AJ11: =Assumptions!$N$18*Assumptions!$C$31 -> 9 | AK11: =Assumptions!$N$18*Assumptions!$D$31 -> 9.9 | AL11: =Assumptions!$N$18*Assumptions!$E$31 -> 11.1 | AN11: =SUM(C11:N11) -> 9 | AO11: =SUM(O11:Z11) -> 51 | AP11: =SUM(AA11:AL11) -> 100
A12: School licences | B12: licences | C12: =Assumptions!$C$19*Assumptions!$C$31 -> 0 | D12: =Assumptions!$C$19*Assumptions!$D$31 -> 0 | E12: =Assumptions!$C$19*Assumptions!$E$31 -> 0 | F12: =Assumptions!$D$19*Assumptions!$C$31 -> 0 | G12: =Assumptions!$D$19*Assumptions!$D$31 -> 0 | H12: =Assumptions!$D$19*Assumptions!$E$31 -> 0 | I12: =Assumptions!$E$19*Assumptions!$C$31 -> 0 | J12: =Assumptions!$E$19*Assumptions!$D$31 -> 0 | K12: =Assumptions!$E$19*Assumptions!$E$31 -> 0 | L12: =Assumptions!$F$19*Assumptions!$C$31 -> 0 | M12: =Assumptions!$F$19*Assumptions!$D$31 -> 0 | N12: =Assumptions!$F$19*Assumptions!$E$31 -> 0 | O12: =Assumptions!$G$19*Assumptions!$C$31 -> 0.3 | P12: =Assumptions!$G$19*Assumptions!$D$31 -> 0.33 | Q12: =Assumptions!$G$19*Assumptions!$E$31 -> 0.37 | R12: =Assumptions!$H$19*Assumptions!$C$31 -> 0.3 | S12: =Assumptions!$H$19*Assumptions!$D$31 -> 0.33 | T12: =Assumptions!$H$19*Assumptions!$E$31 -> 0.37 | U12: =Assumptions!$I$19*Assumptions!$C$31 -> 0.6 | V12: =Assumptions!$I$19*Assumptions!$D$31 -> 0.66 | W12: =Assumptions!$I$19*Assumptions!$E$31 -> 0.74 | X12: =Assumptions!$J$19*Assumptions!$C$31 -> 0.6 | Y12: =Assumptions!$J$19*Assumptions!$D$31 -> 0.66 | Z12: =Assumptions!$J$19*Assumptions!$E$31 -> 0.74 | AA12: =Assumptions!$K$19*Assumptions!$C$31 -> 0.9 | AB12: =Assumptions!$K$19*Assumptions!$D$31 -> 0.99 | AC12: =Assumptions!$K$19*Assumptions!$E$31 -> 1.11 | AD12: =Assumptions!$L$19*Assumptions!$C$31 -> 0.9 | AE12: =Assumptions!$L$19*Assumptions!$D$31 -> 0.99 | AF12: =Assumptions!$L$19*Assumptions!$E$31 -> 1.11 | AG12: =Assumptions!$M$19*Assumptions!$C$31 -> 1.2 | AH12: =Assumptions!$M$19*Assumptions!$D$31 -> 1.32 | AI12: =Assumptions!$M$19*Assumptions!$E$31 -> 1.48 | AJ12: =Assumptions!$N$19*Assumptions!$C$31 -> 1.2 | AK12: =Assumptions!$N$19*Assumptions!$D$31 -> 1.32 | AL12: =Assumptions!$N$19*Assumptions!$E$31 -> 1.48 | AN12: =SUM(C12:N12) -> 0 | AO12: =SUM(O12:Z12) -> 6 | AP12: =SUM(AA12:AL12) -> 14
