Workbook

Sheet Cover
B2: Coremerce
B3: Operational Financial Model and Valuation, 2027 to 2031
B6: ABOUT THIS MODEL
B7: Business name | D7: Coremerce
B8: Industry | D8: Cloud commerce software: online stores, point of sale, inventory, payments and analytics for merchants
B9: Markets | D9: Egypt, with the platform built in English and Arabic
B10: Products | D10: Four plans: Launch (free), Starter, Pro and Enterprise, with a transaction fee on online payments
B11: Model currency | D11: USD, with Egyptian pound prices and costs converted at a monthly rate on the Timeline and FX sheet
B12: Model start | C12: date | D12: January 2027
B13: Months in a period | C13: months | D13: 12
B14: Forecast period | C14: years | D14: 5
B15: Total months modeled | C15: months | D15: 60
B17: HOW TO READ IT
B18: Blue figures on a yellow fill are typed inputs. Change those and the whole model moves.
B19: Black figures are formulas on the same sheet. Green figures are links to another sheet.
B20: Red figures are checks. The balance sheet check must read nil in every column.
B21: On every time sheet the year total comes first, then that year's twelve months.
B22: No volume is typed. Free stores, paying accounts and transaction value are produced by the account engine, so cut the activity and the volume goes with it.
B23: The year one spend is an output of the Expenses sheet, not a ceiling anybody typed. The funding ask is built from all twelve months of it on the Funding and Use of Funds sheet.
B25: CONTENTS
B26: Cover | D26: This page: what the model is and how to read it
B27: Summary | D27: The whole model on one page
B28: Market Research | D28: The market the model sells into, and who else is in it
B29: Old Study Corrections | D29: What was wrong in the earlier feasibility study, and what this model does instead
B30: Input
B31: Assumption Setting | D31: In the order the model runs: basis, opening position, acquisition, the funnels, capacity, pricing, expense
B32: Capital Expenditure | D32: Assets driven by new hires, plus shared and intangible assets
B33: Actuals | D33: The opening position and a grid to record each month
B34: Process
B35: Timeline and FX | D35: The calendar, the pound rate and the cost indices
B36: Acquisitions | D36: Spend to activity to signups to paying accounts, sixty months
B37: GTM Capacity and Timing | D37: Who runs the activity, whether there are enough of them, and how long a deal takes
B38: Revenue Streams | D38: Eight engines, every one of them an output of the account engine
B39: Total Revenue | D39: Gathered into four families
B40: Payroll | D40: Roles monthly, with heads set by year
B41: Depreciation and Amortization | D41: Straight line by asset class
B42: Expenses | D42: Direct cost, revenue share, operating cost, and the first twelve months in full
B43: Output
B44: Income Statement | D44: Five years to 31 December
B45: Balance Sheet | D45: Five years, with the balance check
B46: Cash Flow Statement | D46: Monthly working and the annual statement
B47: Financial Indicators | D47: Growth, profitability, unit economics, cash
B48: Funding and Use of Funds | D48: The ask, what it buys, and the runway it produces
B49: Analysis
B50: BEP Analysis | D50: Break even revenue and the month it turns
B51: PB Analysis | D51: When the capital comes back, base and flexed
B52: Sensitivity | D52: Three two way grids on the year five result
B53: Stress Test | D53: Four scenarios on volume, price, cost and collection
B54: Exit Angel and VC | D54: Angel and venture returns, and the routes out
B55: Valuation | D55: Five methods, built up from the cost of capital, and what they conclude

Sheet Summary
A1: Summary
A2: The whole model on one page.
A4: HEADLINES
C5: Year 1 | D5: Year 2 | E5: Year 3 | F5: Year 4 | G5: Year 5
A6: Total revenue | C6: ='Financial Indicators'!C6 -> 68602.054 | D6: ='Financial Indicators'!D6 -> 391860.51 | E6: ='Financial Indicators'!E6 -> 1221612.7 | F6: ='Financial Indicators'!F6 -> 2763830.2 | G6: ='Financial Indicators'!G6 -> 4998712.1
A7: Gross profit | C7: ='Financial Indicators'!C25 -> 52349.611 | D7: ='Financial Indicators'!D25 -> 311491.05 | E7: ='Financial Indicators'!E25 -> 993713.54 | F7: ='Financial Indicators'!F25 -> 2279092.2 | G7: ='Financial Indicators'!G25 -> 4154745.5
A8: Gross margin | C8: ='Financial Indicators'!C26 -> 0.76309101 | D8: ='Financial Indicators'!D26 -> 0.79490288 | E8: ='Financial Indicators'!E26 -> 0.81344401 | F8: ='Financial Indicators'!F26 -> 0.82461369 | G8: ='Financial Indicators'!G26 -> 0.83116318
A9: EBITDA | C9: ='Financial Indicators'!C27 -> -403637.77 | D9: ='Financial Indicators'!D27 -> -440831.34 | E9: ='Financial Indicators'!E27 -> -168454.15 | F9: ='Financial Indicators'!F27 -> 618842.26 | G9: ='Financial Indicators'!G27 -> 1844005.9
A10: Net profit | C10: ='Financial Indicators'!C29 -> -429039.21 | D10: ='Financial Indicators'!D29 -> -471650.56 | E10: ='Financial Indicators'!E29 -> -205902.53 | F10: ='Financial Indicators'!F29 -> 586091.55 | G10: ='Financial Indicators'!G29 -> 1518916.5
A11: Total expenses, direct and operating | C11: ='Financial Indicators'!C31 -> 497641.26 | D11: ='Financial Indicators'!D31 -> 863511.07 | E11: ='Financial Indicators'!E31 -> 1427515.2 | F11: ='Financial Indicators'!F31 -> 2177738.6 | G11: ='Financial Indicators'!G31 -> 3189932.9
A12: Cash at year end | C12: ='Financial Indicators'!C47 -> 185235.3 | D12: ='Financial Indicators'!D47 -> 237273.56 | E12: ='Financial Indicators'!E47 -> 188317.95 | F12: ='Financial Indicators'!F47 -> 1031867.6 | G12: ='Financial Indicators'!G47 -> 3195853.7
A13: Lowest cash balance in the year | C13: ='Financial Indicators'!C48 -> 185235.3 | D13: ='Financial Indicators'!D48 -> 237273.56 | E13: ='Financial Indicators'!E48 -> 118602.47 | F13: ='Financial Indicators'!F48 -> 244212.67 | G13: ='Financial Indicators'!G48 -> 1209507
A14: Employees at year end | C14: ='Financial Indicators'!C17 -> 24 | D14: ='Financial Indicators'!D17 -> 40 | E14: ='Financial Indicators'!E17 -> 60 | F14: ='Financial Indicators'!F17 -> 84 | G14: ='Financial Indicators'!G17 -> 115
A15: Paying accounts at year end | C15: ='Financial Indicators'!C15 -> 319.89518 | D15: ='Financial Indicators'!D15 -> 1234.8023 | E15: ='Financial Indicators'!E15 -> 3089.9291 | F15: ='Financial Indicators'!F15 -> 6004.4174 | G15: ='Financial Indicators'!G15 -> 9567.5154
A16: Launch (free) stores at year end | C16: ='Financial Indicators'!C11 -> 4207.4483 | D16: ='Financial Indicators'!D11 -> 12270 | E16: ='Financial Indicators'!E11 -> 24195.606 | F16: ='Financial Indicators'!F11 -> 37855.297 | G16: ='Financial Indicators'!G11 -> 52258.036
A17: Annualised recurring revenue at year end | C17: ='Financial Indicators'!C20 -> 107448.12 | D17: ='Financial Indicators'!D20 -> 443128.98 | E17: ='Financial Indicators'!E20 -> 1183326.9 | F17: ='Financial Indicators'!F20 -> 2411636.9 | G17: ='Financial Indicators'!G20 -> 4019403.3
A18: Online payment value processed | C18: ='Financial Indicators'!C21 -> 1105450.2 | D18: ='Financial Indicators'!D21 -> 6826394.2 | E18: ='Financial Indicators'!E21 -> 22838228 | F18: ='Financial Indicators'!F21 -> 55358175 | G18: ='Financial Indicators'!G21 -> 1.056398e+08
A19: Cost per new paying account, fully loaded | C19: ='Financial Indicators'!C37 -> 323.43627 | D19: ='Financial Indicators'!D37 -> 221.42482 | E19: ='Financial Indicators'!E37 -> 175.50587 | F19: ='Financial Indicators'!F37 -> 161.43406 | G19: ='Financial Indicators'!G37 -> 171.06171
A20: LTV to CAC | C20: ='Financial Indicators'!C41 -> 2.0657785 | D20: ='Financial Indicators'!D41 -> 4.182758 | E20: ='Financial Indicators'!E41 -> 6.8208769 | F20: ='Financial Indicators'!F41 -> 8.9767299 | G20: ='Financial Indicators'!G41 -> 9.9457682
A22: THE CHECKS THAT MATTER
A23: Year one total expense, produced not typed | C23: =Expenses!$C$93 -> 497641.26
A24: Balance sheet check, must read nil in every column | C24: ='Balance Sheet'!C23 -> 0 | D24: ='Balance Sheet'!D23 -> 0 | E24: ='Balance Sheet'!E23 -> 0 | F24: ='Balance Sheet'!F23 -> 0 | G24: ='Balance Sheet'!G23 -> 0
A25: Months with a capacity shortfall across the five years, must read nil | C25: =SUM('GTM Capacity and Timing'!$C$25:$BN$25)-SUM('GTM Capacity and Timing'!$B$25,'GTM Capacity and Timing'!$O$25,'GTM Capacity and Timing'!$AB$25,'GTM Capacity and Timing'!$AO$25,'GTM Capacity and Timing'!$BB$25) -> 0
A26: Year one cost categories reconcile to the Expenses sheet, must read nil | C26: ='Funding and Use of Funds'!$C$25 -> 0
A28: WHAT THIS MODEL OPENS ON
A29: Active Launch (free) stores | B29: on the platform at 31 December 2026 | C29: ='Assumption Setting'!$C$13 -> 0
A30: Paying Starter accounts | B30: the honest starting point for the subscription engine | C30: ='Assumption Setting'!$C$14 -> 0
A31: Paying Pro accounts | C31: ='Assumption Setting'!$C$15 -> 0
A32: Paying Enterprise accounts | C32: ='Assumption Setting'!$C$16 -> 0
A33: Opening cash | B33: founder capital already contributed | C33: ='Assumption Setting'!$C$17 -> 0
A34: Founder capital spent on the product | B34: carried as an intangible | C34: ='Assumption Setting'!$C$20 -> 58252.427
A36: THE ASK
A37: Seed round sought | C37: ='Funding and Use of Funds'!$C$9 -> 600000
A38: Total cash required in year one, expense and capital | C38: ='Funding and Use of Funds'!$C$5 -> 518418.99
A39: Months of year one spend this round funds | C39: ='Funding and Use of Funds'!$C$12 -> 13.88838
A40: Year one covered in full | C40: ='Funding and Use of Funds'!$C$13 -> Covered
A41: Second round needed after the seed | C41: ='Funding and Use of Funds'!$C$49 -> 450000
A42: Weighted pre money valuation | C42: =Valuation!$C$93 -> 1307992.6
A43: Pre money valuation asked | C43: =Valuation!$C$98 -> 1300000
A44: What the seed buys | C44: =Valuation!$C$100 -> 0.31578947

Sheet Market Research
A1: Market Research
A2: The sector the model sells into. No revenue in this model is attributed to any single name below. Figures are as reported by the sources named and have not been audited.
A4: THE MARKET THE MODEL SELLS INTO
A5: Measure | B5: Figure | C5: Basis | D5: Source
A6: Egypt ecommerce market size, 2025 | B6: USD 9.9 billion; USD 2.3 billion on a narrower definition | C6: Counted, definitions differ by a factor of four | D6: ResearchAndMarkets via ValueSpectrum, January 2026; ECDB
A7: Egypt ecommerce market size, 2024 | B7: USD 9.1 billion | C7: Counted | D7: PS Market Research
A8: Growth outlook | B8: About 10 per cent a year, to USD 14.5 billion by 2029 | C8: Projected | D8: ResearchAndMarkets, 10.0 per cent CAGR; PS Market Research 10.2 per cent to 2032
A9: Cash on delivery share of online orders | B9: 45 per cent of the payment market in 2024; 55 to 70 per cent of shoppers prefer it | C9: Counted, one source | D9: PS Market Research
A10: Financial inclusion | B10: 74.8 per cent of eligible Egyptians at end 2024 | C10: Counted, one source | D10: Reported in 2026 Egypt ecommerce statistics roundups, primary source not confirmed
A11: Micro, small and medium enterprises | B11: 98 per cent of private enterprises | C11: Counted | D11: Al Ahram, citing the United Nations
A12: Small and medium firms that sell online | B12: About 3 per cent, older government estimate | C12: Counted, undated | D12: Bank of Scotland Trade market potential page
A13: Social sellers in Egypt | B13: Nearly 1.3 million | C13: Counted, vendor survey, Q1 2022 | D13: Market research summary of a global survey
A14: Facebook active accounts in Egypt | B14: More than 44 million, February 2022 | C14: Counted | D14: Academic paper citing Kemp 2022
A15: Urban consumer price inflation | B15: 14.9 per cent in July 2026 | C15: Counted | D15: CAPMAS, reported by Daily News Egypt
A16: Egyptian pounds to the dollar | B16: 50.96 to 52.5 across sources in mid 2026 | C16: Counted | D16: Pluang, Wise and CurrencyConvert snapshots
... A18: Regional startup funding, first half 2026 | B18: USD 1.7 billion across MENA; Egypt USD 86 million in Q1 | C18: Counted | D18: Wamda, Arab News
A20: WHO ELSE IS IN THIS MARKET
A21: Company | B21: Position | C21: Funding | D21: What it means for Coremerce
A22: Shopify | B22: Global leader in hosted commerce, listed | C22: Listed, about 13.9 times revenue on one screener | D22: Sets the feature and price reference. Weak on Arabic, cash on delivery and local payments
A23: Salla | B23: Saudi commerce platform, over 80,000 active merchants at the 2024 round | C23: USD 130 million pre IPO round, March 2024, Investcorp and Sanabil | D23: The regional leader. The natural entrant into Egypt, and the natural buyer
A24: Zid | B24: Saudi commerce platform | C24: USD 7 million Series A, 2021; USD 50 million Series B led by IMPACT46 | D24: A funded Gulf peer with the same plan structure
A25: ExpandCart | B25: Egyptian commerce platform | C25: USD 2.5 million Series A led by Sawari Ventures; a USD 2.7 million pre Series B led by Betatron is also reported | D25: The closest Egyptian like for like
A26: Wuilt | B26: Egyptian store builder | C26: USD 2 million, August 2025, Flat6Labs and MTF VC | D26: Dropped subscription fees in April 2025 and earns on shipping, payments and wallet. Proof that free is the pressure on the Launch to paid path
A27: Paymob | B27: Egyptian payments | C27: USD 50 million Series B, May 2022, Kora, PayPal Ventures and Clay Point | D27: The likely payments partner, and a possible acquirer of merchant volume
A28: Wix | B28: Website and commerce platform, listed | C28: Listed, about 4.7 times revenue in 2025 | D28: A mature reference multiple
A29: Commerce.com, formerly BigCommerce | B29: Mid market commerce platform, listed | C29: Listed, about 0.7 times revenue in July 2026 | D29: The floor multiple when growth stalls
A31: Coremerce's own site claims 10,000 plus businesses in 40 plus countries and 99.9 per cent uptime. These claims are not verified and drive nothing in this model.
A32: No revenue in this model is attributed to any one of these companies. They are listed so the competitive position is visible.

Sheet Old Study Corrections
A1: Old Study Corrections
A2: What was wrong in the earlier feasibility study of the USD 200,000 round, the effect, and what this model does instead.
A4: ERRORS AND OMISSIONS FOUND
A5: No | B5: Where in the old study | C5: What was wrong | D5: Effect | E5: What this model does
A6: 1 | B6: Prices and rate | C6: The annual Starter price of EGP 9,600 was divided by 48 to give USD 200, then every figure was converted back at 52. | D6: Pound revenue overstated by 8.3 per cent on every paying account. | E6: Prices are typed in pounds from the public price page and converted at one stated monthly rate.
A7: 2 | B7: Revenue timing, year one | C7: Year one revenue was year end accounts times the full annual price, less one month. | D7: Treats every account as paying for the whole year. Accounts arrive through the year, so average accounts are about half the year end figure. | E7: Revenue is average accounts in each month times the monthly price, for sixty months.
A8: 3 | B8: Revenue timing, later years | C8: Years two to five used year end accounts times the full price. | D8: Overstates revenue by the growth in accounts across the year, about 40 per cent in year two. | E8: Same monthly engine, so growth is recognised as it happens.
A9: 4 | B9: Revenue lines missing | C9: Enterprise had no price and no revenue. Transaction fees of 2 and 1 per cent, extra stores and every add on were left out. | D9: Understates the upside and hides what the paid plans really earn. | E9: Enterprise, transaction fees, extra stores and three roadmap engines are modeled, each with an opening month.
A10: 5 | B10: No cost of revenue | C10: Other expenses were set to zero. Hosting, AI inference, messaging, collection costs and partner shares were all missing. | D10: A gross margin of 100 per cent and a free tier that cost nothing to run. | E10: Ten direct cost lines driven by accounts and revenue, including the free stores.
A11: 6 | B11: Salaries frozen | C11: Salary growth was zero for five years and the insurance ceiling stayed at EGP 16,700. | D11: Payroll understated every year as inflation runs near 15 per cent and the ceiling rises each January. | E11: Annual increase of 12 per cent and a ceiling that steps up each year, both inputs.
A12: 7 | B12: Equipment | C12: EGP 1.53 million of kit was charged in full before launch and never depreciated. | D12: No balance sheet asset, no depreciation, and the kit was not tied to hiring. | E12: Kits follow each hire, and every asset class is depreciated straight line.
A13: 8 | B13: No statements | C13: There was no balance sheet, no cash flow and no working capital. | D13: Cumulative profit was treated as cash. Receivables, payables and annual prepayments were ignored. | E13: Full income statement, balance sheet and monthly cash flow, with a check that must read nil.
A14: 9 | B14: Marketing held flat | C14: Marketing stayed at USD 50,000 a year for five years while paying merchants grew sevenfold. | D14: Either the growth is unfunded or the budget is wrong. | E14: Channel budgets rise by year, and every channel has a cost per click and a conversion.
A15: 10 | B15: Cost of acquiring a customer | C15: Cost per account was a simple average of four channels instead of a budget weighted average. | D15: Understated the weighted cost: 26.25 per cent of price instead of 30 per cent, and USD 4.50 instead of USD 5.20 per free account. | E15: Signups come from clicks and conversions per channel, and cost per new paying account is measured, not assumed.
A16: 11 | B16: Budget split | C16: The marketing budget was split one third each across free, Starter and Pro regardless of channel mix. | D16: Allocation was arbitrary and fixed the mix of plans. | E16: Plan mix comes from trial starts, trial conversion, direct sales and upgrades.
A17: 12 | B17: Churn and upgrades | C17: Churn and the 15 per cent upgrade rate were applied once a year to opening plus new accounts. | D17: Ignores when accounts join and leave. | E17: Monthly churn and upgrade rates by plan and by year.
... A23: 18 | B23: Dates and symbols | C23: The start date was October 2026 and the text carried check marks, arrows, bullets and en dashes. | D23: The start has passed. Symbols do not belong in a model sent to investors. | E23: The model starts January 2027 and carries plain text only.
A25: HEADLINE COMPARISON, OLD STUDY AGAINST THIS MODEL
B26: Measure | C26: Old study | D26: This model | E26: Comment
B27: Seed ask, USD | C27: 200000 | D27: ='Funding and Use of Funds'!$C$9 -> 600000 | E27: The new ask covers all twelve months of year one spend
B28: Year one revenue, USD | C28: 212143 | D28: ='Total Revenue'!B18 -> 68602.054 | E28: The old figure used year end accounts for the whole year
B29: Year five revenue, USD | C29: 1924676 | D29: ='Total Revenue'!BB18 -> 4998712.1
B30: Year five net profit, USD | C30: 1217332 | D30: ='Income Statement'!$G$53 -> 1518916.5 | E30: The old figure had no cost of revenue and frozen salaries
B31: Paying merchants at the end of year five | C31: 6313 | D31: =Acquisitions!BB124 -> 9567.5154
B32: Pre money valuation, USD | C32: 1800000 | D32: =Valuation!$C$98 -> 1300000 | E32: The old figure was the ask divided by 10 per cent less the ask
B34: Old study figures are typed as read from the earlier file. Net profit and paying merchants for the old study are from its sales and study sheets.

Sheet Input>>
B2: Input
B5: Assumption Setting | C5: In the order the model runs: basis, opening position, acquisition, the funnels, capacity, pricing, expense
B6: Capital Expenditure | C6: Assets driven by new hires, plus shared and intangible assets
B7: Actuals | C7: The opening position and a grid to record each month

Sheet Assumption Setting
A1: Assumption Setting
A2: Everything typed in this model is on this sheet, apart from the establishment table on Payroll and the grid on Actuals. Nothing downstream is a typed number.
A4: 1. MODEL BASIS
A5: Reporting currency | C5: USD
A6: First calendar month of the model | C6: 46388
A7: Egyptian pounds to the dollar at the start | B7: EGP | C7: 51.5 | D7: Spot sources in mid 2026 range from 50.96 to 52.5. Change it here and every pound input converts.
A8: Annual change in the pound against the dollar | B8: % | C8: 0.06 | D8: A steady slide of 6 per cent a year. Pound prices and costs convert at the monthly rate this produces.
A9: Prices and revenue are stated net of VAT. VAT collected is passed to the tax authority and is not modeled. No interest is earned on cash and no dividends are paid.
A11: 2. THE OPENING POSITION, WHAT IS ALREADY TRUE
A12: Placeholders to be replaced with the company's own figures at 31 December 2026. The site claims 10,000 plus businesses; this model does not rely on that claim and opens at zero.
A13: Active Launch (free) stores on the platform | B13: # | C13: 0
A14: Paying Starter accounts | B14: # | C14: 0
A15: Paying Pro accounts | B15: # | C15: 0
A16: Paying Enterprise accounts | B16: # | C16: 0
A17: Opening cash at 31 December 2026 | B17: USD | C17: 0
A18: Paid in share capital at inception, cash, equal to opening cash | B18: USD | C18: =C17 -> 0
A19: Founder capital already spent building the product | B19: EGP | C19: 3000000 | D19: EGP 3.0 million, from the earlier feasibility study. Carried as an intangible and amortised.
A20: The same, in dollars at the opening rate | B20: USD | C20: =C19/C7 -> 58252.427
A22: 3. ACQUISITION, ONLINE CHANNELS
A23: Budget divided by cost per click gives paid clicks. Organic and referral visits are a stated share of paid. Visits times click to signup gives free accounts created.
A24: Online channel, monthly budget | B24: Unit | C24: Budget Y1 | D24: Y2 | E24: Y3 | F24: Y4 | G24: Y5 | H24: Cost per click | I24: Organic % of paid | J24: Referral % of paid | K24: Click to signup
A25: Meta and Instagram ads, merchants | B25: USD | C25: 800 | D25: 2000 | E25: 3600 | F25: 5200 | G25: 6800 | H25: 0.1 | I25: 0.22 | J25: 0.07 | K25: 0.026
A26: Google Search, store builder and POS intent | B26: USD | C26: 500 | D26: 1300 | E26: 2300 | F26: 3300 | G26: 4300 | H26: 0.22 | I26: 0.1 | J26: 0.03 | K26: 0.05
A27: TikTok and short video, sellers | B27: USD | C27: 300 | D27: 700 | E27: 1300 | F27: 1900 | G27: 2400 | H27: 0.06 | I27: 0.3 | J27: 0.09 | K27: 0.014
A28: Retargeting, trial starters | B28: USD | C28: 200 | D28: 450 | E28: 800 | F28: 1100 | G28: 1400 | H28: 0.14 | I28: 0.04 | J28: 0.02 | K28: 0.07
A29: Content and SEO, Arabic commerce guides | B29: USD | C29: 833 | D29: 1500 | E29: 2400 | F29: 3200 | G29: 4000 | H29: 0.3 | I29: 0.3 | J29: 0.05 | K29: 0.03
A30: Merchant referral program credits | B30: USD | C30: 417 | D30: 900 | E30: 1500 | F30: 2100 | G30: 2700 | H30: 0.45 | I30: 0 | J30: 0.04 | K30: 0.1
A31: Seller communities and social groups | B31: USD | C31: 300 | D31: 650 | E31: 1100 | F31: 1500 | G31: 1900 | H31: 0.12 | I31: 0.12 | J31: 0.04 | K31: 0.035
A33: Online advertising cost | B33: Unit | C33: Year 1 | D33: Year 2 | E33: Year 3 | F33: Year 4 | G33: Year 5
A34: Annual rise in cost per click as budgets scale | B34: % | C34: 0 | D34: 0.1 | E34: 0.1 | F34: 0.1 | G34: 0.1 | H34: Auction prices rise with spend and with Egyptian inflation
A35: Cumulative cost per click index | B35: x | C35: =1+C34 -> 1 | D35: =C35*(1+D34) -> 1.1 | E35: =D35*(1+E34) -> 1.21 | F35: =E35*(1+F34) -> 1.331 | G35: =F35*(1+G34) -> 1.4641
A37: Signup quality and the self serve path | B37: Unit | C37: Year 1 | D37: Year 2 | E37: Year 3 | F37: Year 4 | G37: Year 5
A38: Signups on the free path who create a store | B38: % | C38: 0.38 | D38: 0.4 | E38: 0.42 | F38: 0.43 | G38: 0.44
A39: Signups who start a Starter trial | B39: % | C39: 0.07 | D39: 0.08 | E39: 0.09 | F39: 0.1 | G39: 0.1
A40: Signups who start a Pro trial | B40: % | C40: 0.015 | D40: 0.02 | E40: 0.025 | F40: 0.03 | G40: 0.03
A41: Signups who book a demo with sales | B41: % | C41: 0.03 | D41: 0.035 | E41: 0.04 | F41: 0.04 | G41: 0.04
A42: Starter trial to paid, after the 14 day trial | B42: % | C42: 0.22 | D42: 0.24 | E42: 0.26 | F42: 0.27 | G42: 0.28
A43: Pro trial to paid, after the 14 day trial | B43: % | C43: 0.28 | D43: 0.3 | E43: 0.32 | F43: 0.33 | G43: 0.34
A44: Unconverted trials that stay on the free Launch plan | B44: % | C44: 0.5 | D44: 0.5 | E44: 0.5 | F44: 0.5 | G44: 0.5
A46: 4. ACQUISITION, OFFLINE ACTIVITY
A47: Everything the commercial team does in the field. Each activity has a cost, free signups it brings and qualified leads it hands to direct sales.
A48: Offline activity | B48: Unit | C48: Per month Y1 | D48: Y2 | E48: Y3 | F48: Y4 | G48: Y5 | H48: Cost per activity | I48: Signups each | J48: Direct sales leads each
A49: Product demos and webinars | B49: # | C49: 4 | D49: 8 | E49: 12 | F49: 16 | G49: 20 | H49: 60 | I49: 28 | J49: 3
A50: Seller community meetups and workshops | B50: # | C50: 1 | D50: 2 | E50: 3 | F50: 4 | G50: 5 | H50: 350 | I50: 45 | J50: 5
A51: Exhibitions and trade events attended | B51: # | C51: 0.25 | D51: 0.5 | E51: 0.75 | F51: 1 | G51: 1.25 | H51: 1600 | I51: 140 | J51: 22
A52: Agency, web developer and accountant partner sessions | B52: # | C52: 2 | D52: 4 | E52: 6 | F52: 8 | G52: 10 | H52: 120 | I52: 14 | J52: 2
A53: Governorate roadshow, Alexandria, Delta and Upper Egypt | B53: # | C53: 0 | D53: 0.5 | E53: 1 | F53: 1.5 | G53: 2 | H53: 900 | I53: 70 | J53: 9
A54: Direct outreach by the sales team, contacts | B54: # | C54: 900 | D54: 1500 | E54: 2300 | F54: 3100 | G54: 3900 | H54: 0 | I54: 0.01 | J54: 0.02
A56: 5. THE DIRECT SALES FUNNEL
A57: Qualified leads split between three segments, each with its own conversion and its own clock. A lead booked this month closes after the sales cycle.
A58: Segment | B58: Unit | C58: Share of qualified leads | D58: Lead to demo | E58: Demo to paid | F58: Sales cycle, months | G58: Share taking Starter | H58: Share taking Pro | I58: Share taking Enterprise
A59: Social sellers and small shops, 1 to 3 staff | C59: 0.5 | D59: 0.32 | E59: 0.3 | F59: 1 | G59: 0.88 | H59: 0.12 | I59: 0
A60: Multi channel retailers and brands, 3 to 10 staff | C60: 0.38 | D60: 0.28 | E60: 0.26 | F60: 1 | G60: 0.25 | H60: 0.73 | I60: 0.02
A61: Chains, distributors and large brands, 3 plus stores | C61: 0.12 | D61: 0.18 | E61: 0.16 | F61: 3 | G61: 0 | H61: 0.3 | I61: 0.7
A62: Shares must total 100% | C62: =SUM(C59:C61) -> 1
A64: Direct sales effectiveness | B64: Unit | C64: Year 1 | D64: Year 2 | E64: Year 3 | F64: Year 4 | G64: Year 5
A65: Win rate uplift as references accumulate | B65: x | C65: 1 | D65: 1.1 | E65: 1.18 | F65: 1.24 | G65: 1.28
A67: 6. THE UPGRADE AND CHURN PATH, MONTHLY
A68: Applied to the opening balance of each plan every month. Free to paid is where the funnel earns its keep.
A69: Monthly rate | B69: Unit | C69: Year 1 | D69: Year 2 | E69: Year 3 | F69: Year 4 | G69: Year 5
A70: Launch to Starter upgrade | B70: % | C70: 0.003 | D70: 0.0035 | E70: 0.004 | F70: 0.0045 | G70: 0.0045
A71: Launch to Pro upgrade | B71: % | C71: 0.0004 | D71: 0.0005 | E71: 0.0006 | F71: 0.0007 | G71: 0.0007
A72: Starter to Pro upgrade | B72: % | C72: 0.01 | D72: 0.011 | E72: 0.012 | F72: 0.012 | G72: 0.012
A73: Pro to Enterprise upgrade | B73: % | C73: 0.001 | D73: 0.0015 | E73: 0.002 | F73: 0.002 | G73: 0.002
A74: Churn, Launch (free) stores | B74: % | C74: 0.035 | D74: 0.03 | E74: 0.027 | F74: 0.025 | G74: 0.024
A75: Churn, Starter accounts | B75: % | C75: 0.055 | D75: 0.045 | E75: 0.04 | F75: 0.036 | G75: 0.033
A76: Churn, Pro accounts | B76: % | C76: 0.03 | D76: 0.024 | E76: 0.02 | F76: 0.018 | G76: 0.016
A77: Churn, Enterprise accounts | B77: % | C77: 0.01 | D77: 0.008 | E77: 0.007 | F77: 0.006 | G77: 0.005
A79: 7. CAPACITY, WHO RUNS THE ACTIVITY
A80: The plan above is only credible if somebody is free to do it. The sheet named GTM Capacity and Timing tests each line against the heads on the Payroll sheet.
A81: Demos one account executive can run per month | B81: # | C81: 55
A82: New paying accounts one onboarding specialist can onboard per month | B82: # | C82: 90
A83: Support tickets per paying account per month | B83: # | C83: 0.8
A84: Support tickets per free store per month | B84: # | C84: 0.05
A85: Tickets one support agent can close per month | B85: # | C85: 550
A86: Paying accounts one merchant success manager can hold | B86: # | C86: 600
A88: 8. REVENUE, PRICING BY YEAR
A89: Priced in Egyptian pounds where an Egyptian merchant pays, and converted at the monthly rate. List prices are the public price page in October 2026.
A90: Starter plan, list price per month, Year 1 | B90: EGP | C90: 999 | D90: Public price page
A91: Pro plan, list price per month, Year 1 | B91: EGP | C91: 2999 | D91: Public price page
A92: Enterprise plan, average contract per month, Year 1 | B92: EGP | C92: 16000 | D92: Custom quote on the site. The earlier study gave Enterprise no revenue. This is a placeholder to confirm.
A93: Discount for annual billing | B93: % | C93: 0.2 | D93: The price page says save up to 20 per cent
A94: Price path | B94: Unit | C94: Year 1 | D94: Year 2 | E94: Year 3 | F94: Year 4 | G94: Year 5
A95: List price increase on 1 January | B95: % | C95: 0 | D95: 0.08 | E95: 0.08 | F95: 0.07 | G95: 0.06 | H95: Held below Egyptian inflation of about 15 per cent because free alternatives are spreading
A96: Cumulative price index | B96: x | C96: =1+C95 -> 1 | D96: =C96*(1+D95) -> 1.08 | E96: =D96*(1+E95) -> 1.1664 | F96: =E96*(1+F95) -> 1.248048 | G96: =F96*(1+G95) -> 1.3229309
A97: Share of paying accounts billed annually in advance | B97: % | C97: 0.2 | D97: 0.26 | E97: 0.31 | F97: 0.35 | G97: 0.38
A99: Extra store on Pro, per store per month | B99: EGP | C99: 79 | D99: Public price page
A100: Share of Pro accounts that buy extra stores | B100: % | C100: 0.2
A101: Extra stores bought by those accounts, average | B101: # | C101: 1.8
A103: Transaction fee on online payments, Starter | B103: % | C103: 0.02 | D103: Public price page
A104: Transaction fee on online payments, Pro | B104: % | C104: 0.01 | D104: Public price page
A105: Transaction fee on online payments, Enterprise | B105: % | C105: 0 | D105: Public price page shows 0.00 per cent
A106: Online payment value per active Starter account per month, Year 1 | B106: EGP | C106: 30000
A107: Online payment value per active Pro account per month, Year 1 | B107: EGP | C107: 140000
A108: Online payments | B108: Unit | C108: Year 1 | D108: Year 2 | E108: Year 3 | F108: Year 4 | G108: Year 5
A109: Starter accounts processing online payments | B109: % | C109: 0.5 | D109: 0.55 | E109: 0.6 | F109: 0.64 | G109: 0.67 | H109: Cash on delivery is still the largest share of Egyptian online orders
A110: Pro accounts processing online payments | B110: % | C110: 0.62 | D110: 0.66 | E110: 0.7 | F110: 0.73 | G110: 0.75
A111: Growth in payment value per account | B111: % | C111: 0 | D111: 0.12 | E111: 0.12 | F111: 0.11 | G111: 0.1
A112: Cumulative payment value index | B112: x | C112: =1+C111 -> 1 | D112: =C112*(1+D111) -> 1.12 | E112: =D112*(1+E111) -> 1.2544 | F112: =E112*(1+F111) -> 1.392384 | G112: =F112*(1+G111) -> 1.5316224
A114: Paid store setup and data migration service, per job | B114: EGP | C114: 3500 | D114: Roadmap service, not on the price page
...

Sheet Capital Expenditure
A1: Capital Expenditure
A2: Assets driven by new hires, plus shared and intangible assets. Cost in pounds, converted at the rate of the month it is bought.
A3: Month number | B3: 9999 | C3: 1 | D3: 2 | E3: 3 | F3: 4 | G3: 5 | H3: 6 | I3: 7 | J3: 8 | K3: 9 | L3: 10 | M3: 11 | N3: 12 | O3: 9999 | P3: 13 | Q3: 14 | R3: 15 | S3: 16 | T3: 17 | U3: 18 | V3: 19 | W3: 20 | X3: 21 | Y3: 22 | Z3: 23 | AA3: 24 | AB3: 9999 | AC3: 25 | AD3: 26 | AE3: 27 | AF3: 28 | AG3: 29 | AH3: 30 | AI3: 31 | AJ3: 32 | AK3: 33 | AL3: 34 | AM3: 35 | AN3: 36 | AO3: 9999 | AP3: 37 | AQ3: 38 | AR3: 39 | AS3: 40 | AT3: 41 | AU3: 42 | AV3: 43 | AW3: 44 | AX3: 45 | AY3: 46 | AZ3: 47 | BA3: 48 | BB3: 9999 | BC3: 49 | BD3: 50 | BE3: 51 | BF3: 52 | BG3: 53 | BH3: 54 | BI3: 55 | BJ3: 56 | BK3: 57 | BL3: 58 | BM3: 59 | BN3: 60
A4: ASSET PURCHASES, USD
A5: Asset class | B5: Year 1 | C5: Jan 27 | D5: Feb 27 | E5: Mar 27 | F5: Apr 27 | G5: May 27 | H5: Jun 27 | I5: Jul 27 | J5: Aug 27 | K5: Sep 27 | L5: Oct 27 | M5: Nov 27 | N5: Dec 27 | O5: Year 2 | P5: Jan 28 | Q5: Feb 28 | R5: Mar 28 | S5: Apr 28 | T5: May 28 | U5: Jun 28 | V5: Jul 28 | W5: Aug 28 | X5: Sep 28 | Y5: Oct 28 | Z5: Nov 28 | AA5: Dec 28 | AB5: Year 3 | AC5: Jan 29 | AD5: Feb 29 | AE5: Mar 29 | AF5: Apr 29 | AG5: May 29 | AH5: Jun 29 | AI5: Jul 29 | AJ5: Aug 29 | AK5: Sep 29 | AL5: Oct 29 | AM5: Nov 29 | AN5: Dec 29 | AO5: Year 4 | AP5: Jan 30 | AQ5: Feb 30 | AR5: Mar 30 | AS5: Apr 30 | AT5: May 30 | AU5: Jun 30 | AV5: Jul 30 | AW5: Aug 30 | AX5: Sep 30 | AY5: Oct 30 | AZ5: Nov 30 | BA5: Dec 30 | BB5: Year 5 | BC5: Jan 31 | BD5: Feb 31 | BE5: Mar 31 | BF5: Apr 31 | BG5: May 31 | BH5: Jun 31 | BI5: Jul 31 | BJ5: Aug 31 | BK5: Sep 31 | BL5: Oct 31 | BM5: Nov 31 | BN5: Dec 31
A6: Employee kits, laptop, monitor and phone | B6: =SUM(C6:N6) -> 29689.32 | C6: =(Payroll!C76*'Assumption Setting'!$C$201+Payroll!C75*'Assumption Setting'!$C$202)*(1+'Assumption Setting'!$C$203)/'Timeline and FX'!C8 -> 29689.32 | D6: =(Payroll!D76*'Assumption Setting'!$C$201+Payroll!D75*'Assumption Setting'!$C$202)*(1+'Assumption Setting'!$C$203)/'Timeline and FX'!D8 -> 0 | E6: =(Payroll!E76*'Assumption Setting'!$C$201+Payroll!E75*'Assumption Setting'!$C$202)*(1+'Assumption Setting'!$C$203)/'Timeline and FX'!E8 -> 0 | F6: =(Payroll!F76*'Assumption Setting'!$C$201+Payroll!F75*'Assumption Setting'!$C$202)*(1+'Assumption Setting'!$C$203)/'Timeline and FX'!F8 -> 0 | G6: =(Payroll!G76*'Assumption Setting'!$C$201+Payroll!G75*'Assumption Setting'!$C$202)*(1+'Assumption Setting'!$C$203)/'Timeline and FX'!G8 -> 0 | H6: =(Payroll!H76*'Assumption Setting'!$C$201+Payroll!H75*'Assumption Setting'!$C$202)*(1+'Assumption Setting'!$C$203)/'Timeline and FX'!H8 -> 0 | I6: =(Payroll!I76*'Assumption Setting'!$C$201+Payroll!I75*'Assumption Setting'!$C$202)*(1+'Assumption Setting'!$C$203)/'Timeline and FX'!I8 -> 0 | J6: =(Payroll!J76*'Assumption Setting'!$C$201+Payroll!J75*'Assumption Setting'!$C$202)*(1+'Assumption Setting'!$C$203)/'Timeline and FX'!J8 -> 0 | ... N6: =(Payroll!N76*'Assumption Setting'!$C$201+Payroll!N75*'Assumption Setting'!$C$202)*(1+'Assumption Setting'!$C$203)/'Timeline and FX'!N8 -> 0 | O6: =SUM(P6:AA6) -> 16819.8 | P6: =(Payroll!P76*'Assumption Setting'!$C$201+Payroll!P75*'Assumption Setting'!$C$202)*(1+'Assumption Setting'!$C$203)/'Timeline and FX'!P8 -> 13218.538 | Q6: =(Payroll!Q76*'Assumption Setting'!$C$201+Payroll!Q75*'Assumption Setting'!$C$202)*(1+'Assumption Setting'!$C$203)/'Timeline and FX'!Q8 -> 0 | R6: =(Payroll!R76*'Assumption Setting'!$C$201+Payroll!R75*'Assumption Setting'!$C$202)*(1+'Assumption Setting'!$C$203)/'Timeline and FX'!R8 -> 0 | S6: =(Payroll!S76*'Assumption Setting'!$C$201+Payroll!S75*'Assumption Setting'!$C$202)*(1+'Assumption Setting'!$C$203)/'Timeline and FX'!S8 -> 0 | T6: =(Payroll!T76*'Assumption Setting'!$C$201+Payroll!T75*'Assumption Setting'!$C$202)*(1+'Assumption Setting'!$C$203)/'Timeline and FX'!T8 -> 909.08006 | U6: =(Payroll!U76*'Assumption Setting'!$C$201+Payroll!U75*'Assumption Setting'!$C$202)*(1+'Assumption Setting'!$C$203)/'Timeline and FX'!U8 -> 0 | V6: =(Payroll!V76*'Assumption Setting'!$C$201+Payroll!V75*'Assumption Setting'!$C$202)*(1+'Assumption Setting'!$C$203)/'Timeline and FX'!V8 -> 1800.5886 | W6: =(Payroll!W76*'Assumption Setting'!$C$201+Payroll!W75*'Assumption Setting'!$C$202)*(1+'Assumption Setting'!$C$203)/'Timeline and FX'!W8 -> 0 | ... AA6: =(Payroll!AA76*'Assumption Setting'!$C$201+Payroll!AA75*'Assumption Setting'!$C$202)*(1+'Assumption Setting'!$C$203)/'Timeline and FX'!AA8 -> 0 | AB6: =SUM(AC6:AN6) -> 20303.972 | AC6: =(Payroll!AC76*'Assumption Setting'!$C$201+Payroll!AC75*'Assumption Setting'!$C$202)*(1+'Assumption Setting'!$C$203)/'Timeline and FX'!AC8 -> 15207.706 | AD6: =(Payroll!AD76*'Assumption Setting'!$C$201+Payroll!AD75*'Assumption Setting'!$C$202)*(1+'Assumption Setting'!$C$203)/'Timeline and FX'!AD8 -> 0 | AE6: =(Payroll!AE76*'Assumption Setting'!$C$201+Payroll!AE75*'Assumption Setting'!$C$202)*(1+'Assumption Setting'!$C$203)/'Timeline and FX'!AE8 -> 0 | AF6: =(Payroll!AF76*'Assumption Setting'!$C$201+Payroll!AF75*'Assumption Setting'!$C$202)*(1+'Assumption Setting'!$C$203)/'Timeline and FX'!AF8 -> 861.79722 | AG6: =(Payroll!AG76*'Assumption Setting'!$C$201+Payroll!AG75*'Assumption Setting'!$C$202)*(1+'Assumption Setting'!$C$203)/'Timeline and FX'!AG8 -> 857.6227 | AH6: =(Payroll!AH76*'Assumption Setting'!$C$201+Payroll!AH75*'Assumption Setting'!$C$202)*(1+'Assumption Setting'!$C$203)/'Timeline and FX'!AH8 -> 0 | AI6: =(Payroll!AI76*'Assumption Setting'!$C$201+Payroll!AI75*'Assumption Setting'!$C$202)*(1+'Assumption Setting'!$C$203)/'Timeline and FX'!AI8 -> 1698.6684 | AJ6: =(Payroll!AJ76*'Assumption Setting'!$C$201+Payroll!AJ75*'Assumption Setting'!$C$202)*(1+'Assumption Setting'!$C$203)/'Timeline and FX'!AJ8 -> 0 | ... AN6: =(Payroll!AN76*'Assumption Setting'!$C$201+Payroll!AN75*'Assumption Setting'!$C$202)*(1+'Assumption Setting'!$C$203)/'Timeline and FX'!AN8 -> 0 | AO6: =SUM(AP6:BA6) -> 21889.776 | AP6: =(Payroll!AP76*'Assumption Setting'!$C$201+Payroll!AP75*'Assumption Setting'!$C$202)*(1+'Assumption Setting'!$C$203)/'Timeline and FX'!AP8 -> 13055.672 | AQ6: =(Payroll!AQ76*'Assumption Setting'!$C$201+Payroll!AQ75*'Assumption Setting'!$C$202)*(1+'Assumption Setting'!$C$203)/'Timeline and FX'!AQ8 -> 820.95031 | AR6: =(Payroll!AR76*'Assumption Setting'!$C$201+Payroll!AR75*'Assumption Setting'!$C$202)*(1+'Assumption Setting'!$C$203)/'Timeline and FX'!AR8 -> 816.97365 | AS6: =(Payroll!AS76*'Assumption Setting'!$C$201+Payroll!AS75*'Assumption Setting'!$C$202)*(1+'Assumption Setting'!$C$203)/'Timeline and FX'!AS8 -> 813.01625 | AT6: =(Payroll!AT76*'Assumption Setting'!$C$201+Payroll!AT75*'Assumption Setting'!$C$202)*(1+'Assumption Setting'!$C$203)/'Timeline and FX'!AT8 -> 809.07802 | AU6: =(Payroll!AU76*'Assumption Setting'!$C$201+Payroll!AU75*'Assumption Setting'!$C$202)*(1+'Assumption Setting'!$C$203)/'Timeline and FX'!AU8 -> 805.15887 | AV6: =(Payroll!AV76*'Assumption Setting'!$C$201+Payroll!AV75*'Assumption Setting'!$C$202)*(1+'Assumption Setting'!$C$203)/'Timeline and FX'!AV8 -> 1602.5174 | AW6: =(Payroll!AW76*'Assumption Setting'!$C$201+Payroll!AW75*'Assumption Setting'!$C$202)*(1+'Assumption Setting'!$C$203)/'Timeline and FX'!AW8 -> 797.37743 | ... BA6: =(Payroll!BA76*'Assumption Setting'!$C$201+Payroll!BA75*'Assumption Setting'!$C$202)*(1+'Assumption Setting'!$C$203)/'Timeline and FX'!BA8 -> 0 | BB6: =SUM(BC6:BN6) -> 26848.423 | BC6: =(Payroll!BC76*'Assumption Setting'!$C$201+Payroll!BC75*'Assumption Setting'!$C$202)*(1+'Assumption Setting'!$C$203)/'Timeline and FX'!BC8 -> 13974.685 | BD6: =(Payroll!BD76*'Assumption Setting'!$C$201+Payroll!BD75*'Assumption Setting'!$C$202)*(1+'Assumption Setting'!$C$203)/'Timeline and FX'!BD8 -> 1548.9628 | BE6: =(Payroll!BE76*'Assumption Setting'!$C$201+Payroll!BE75*'Assumption Setting'!$C$202)*(1+'Assumption Setting'!$C$203)/'Timeline and FX'!BE8 -> 1541.4597 | BF6: =(Payroll!BF76*'Assumption Setting'!$C$201+Payroll!BF75*'Assumption Setting'!$C$202)*(1+'Assumption Setting'!$C$203)/'Timeline and FX'!BF8 -> 0 | BG6: =(Payroll!BG76*'Assumption Setting'!$C$201+Payroll!BG75*'Assumption Setting'!$C$202)*(1+'Assumption Setting'!$C$203)/'Timeline and FX'!BG8 -> 1526.5623 | BH6: =(Payroll!BH76*'Assumption Setting'!$C$201+Payroll!BH75*'Assumption Setting'!$C$202)*(1+'Assumption Setting'!$C$203)/'Timeline and FX'!BH8 -> 1519.1677 | BI6: =(Payroll!BI76*'Assumption Setting'!$C$201+Payroll!BI75*'Assumption Setting'!$C$202)*(1+'Assumption Setting'!$C$203)/'Timeline and FX'!BI8 -> 2267.7133 | BJ6: =(Payroll!BJ76*'Assumption Setting'!$C$201+Payroll!BJ75*'Assumption Setting'!$C$202)*(1+'Assumption Setting'!$C$203)/'Timeline and FX'!BJ8 -> 0 | ... BN6: =(Payroll!BN76*'Assumption Setting'!$C$201+Payroll!BN75*'Assumption Setting'!$C$202)*(1+'Assumption Setting'!$C$203)/'Timeline and FX'!BN8 -> 0
A7: Cairo office fit out | B7: =SUM(C7:N7) -> 6796.1165 | C7: =IF(1='Assumption Setting'!$D$205,'Assumption Setting'!$C$205/'Timeline and FX'!C8,0) -> 6796.1165 | D7: =IF(2='Assumption Setting'!$D$205,'Assumption Setting'!$C$205/'Timeline and FX'!D8,0) -> 0 | E7: =IF(3='Assumption Setting'!$D$205,'Assumption Setting'!$C$205/'Timeline and FX'!E8,0) -> 0 | F7: =IF(4='Assumption Setting'!$D$205,'Assumption Setting'!$C$205/'Timeline and FX'!F8,0) -> 0 | G7: =IF(5='Assumption Setting'!$D$205,'Assumption Setting'!$C$205/'Timeline and FX'!G8,0) -> 0 | H7: =IF(6='Assumption Setting'!$D$205,'Assumption Setting'!$C$205/'Timeline and FX'!H8,0) -> 0 | I7: =IF(7='Assumption Setting'!$D$205,'Assumption Setting'!$C$205/'Timeline and FX'!I8,0) -> 0 | J7: =IF(8='Assumption Setting'!$D$205,'Assumption Setting'!$C$205/'Timeline and FX'!J8,0) -> 0 | K7: =IF(9='Assumption Setting'!$D$205,'Assumption Setting'!$C$205/'Timeline and FX'!K8,0) -> 0 | L7: =IF(10='Assumption Setting'!$D$205,'Assumption Setting'!$C$205/'Timeline and FX'!L8,0) -> 0 | M7: =IF(11='Assumption Setting'!$D$205,'Assumption Setting'!$C$205/'Timeline and FX'!M8,0) -> 0 | N7: =IF(12='Assumption Setting'!$D$205,'Assumption Setting'!$C$205/'Timeline and FX'!N8,0) -> 0 | O7: =SUM(P7:AA7) -> 0 | P7: =IF(13='Assumption Setting'!$D$205,'Assumption Setting'!$C$205/'Timeline and FX'!P8,0) -> 0 | Q7: =IF(14='Assumption Setting'!$D$205,'Assumption Setting'!$C$205/'Timeline and FX'!Q8,0) -> 0 | R7: =IF(15='Assumption Setting'!$D$205,'Assumption Setting'!$C$205/'Timeline and FX'!R8,0) -> 0 | S7: =IF(16='Assumption Setting'!$D$205,'Assumption Setting'!$C$205/'Timeline and FX'!S8,0) -> 0 | T7: =IF(17='Assumption Setting'!$D$205,'Assumption Setting'!$C$205/'Timeline and FX'!T8,0) -> 0 | U7: =IF(18='Assumption Setting'!$D$205,'Assumption Setting'!$C$205/'Timeline and FX'!U8,0) -> 0 | V7: =IF(19='Assumption Setting'!$D$205,'Assumption Setting'!$C$205/'Timeline and FX'!V8,0) -> 0 | W7: =IF(20='Assumption Setting'!$D$205,'Assumption Setting'!$C$205/'Timeline and FX'!W8,0) -> 0 | X7: =IF(21='Assumption Setting'!$D$205,'Assumption Setting'!$C$205/'Timeline and FX'!X8,0) -> 0 | Y7: =IF(22='Assumption Setting'!$D$205,'Assumption Setting'!$C$205/'Timeline and FX'!Y8,0) -> 0 | Z7: =IF(23='Assumption Setting'!$D$205,'Assumption Setting'!$C$205/'Timeline and FX'!Z8,0) -> 0 | AA7: =IF(24='Assumption Setting'!$D$205,'Assumption Setting'!$C$205/'Timeline and FX'!AA8,0) -> 0 | AB7: =SUM(AC7:AN7) -> 0 | AC7: =IF(25='Assumption Setting'!$D$205,'Assumption Setting'!$C$205/'Timeline and FX'!AC8,0) -> 0 | AD7: =IF(26='Assumption Setting'!$D$205,'Assumption Setting'!$C$205/'Timeline and FX'!AD8,0) -> 0 | AE7: =IF(27='Assumption Setting'!$D$205,'Assumption Setting'!$C$205/'Timeline and FX'!AE8,0) -> 0 | AF7: =IF(28='Assumption Setting'!$D$205,'Assumption Setting'!$C$205/'Timeline and FX'!AF8,0) -> 0 | AG7: =IF(29='Assumption Setting'!$D$205,'Assumption Setting'!$C$205/'Timeline and FX'!AG8,0) -> 0 | AH7: =IF(30='Assumption Setting'!$D$205,'Assumption Setting'!$C$205/'Timeline and FX'!AH8,0) -> 0 | AI7: =IF(31='Assumption Setting'!$D$205,'Assumption Setting'!$C$205/'Timeline and FX'!AI8,0) -> 0 | AJ7: =IF(32='Assumption Setting'!$D$205,'Assumption Setting'!$C$205/'Timeline and FX'!AJ8,0) -> 0 | AK7: =IF(33='Assumption Setting'!$D$205,'Assumption Setting'!$C$205/'Timeline and FX'!AK8,0) -> 0 | AL7: =IF(34='Assumption Setting'!$D$205,'Assumption Setting'!$C$205/'Timeline and FX'!AL8,0) -> 0 | AM7: =IF(35='Assumption Setting'!$D$205,'Assumption Setting'!$C$205/'Timeline and FX'!AM8,0) -> 0 | AN7: =IF(36='Assumption Setting'!$D$205,'Assumption Setting'!$C$205/'Timeline and FX'!AN8,0) -> 0 | AO7: =SUM(AP7:BA7) -> 0 | AP7: =IF(37='Assumption Setting'!$D$205,'Assumption Setting'!$C$205/'Timeline and FX'!AP8,0) -> 0 | AQ7: =IF(38='Assumption Setting'!$D$205,'Assumption Setting'!$C$205/'Timeline and FX'!AQ8,0) -> 0 | AR7: =IF(39='Assumption Setting'!$D$205,'Assumption Setting'!$C$205/'Timeline and FX'!AR8,0) -> 0 | AS7: =IF(40='Assumption Setting'!$D$205,'Assumption Setting'!$C$205/'Timeline and FX'!AS8,0) -> 0 | AT7: =IF(41='Assumption Setting'!$D$205,'Assumption Setting'!$C$205/'Timeline and FX'!AT8,0) -> 0 | AU7: =IF(42='Assumption Setting'!$D$205,'Assumption Setting'!$C$205/'Timeline and FX'!AU8,0) -> 0 | AV7: =IF(43='Assumption Setting'!$D$205,'Assumption Setting'!$C$205/'Timeline and FX'!AV8,0) -> 0 | AW7: =IF(44='Assumption Setting'!$D$205,'Assumption Setting'!$C$205/'Timeline and FX'!AW8,0) -> 0 | AX7: =IF(45='Assumption Setting'!$D$205,'Assumption Setting'!$C$205/'Timeline and FX'!AX8,0) -> 0 | AY7: =IF(46='Assumption Setting'!$D$205,'Assumption Setting'!$C$205/'Timeline and FX'!AY8,0) -> 0 | AZ7: =IF(47='Assumption Setting'!$D$205,'Assumption Setting'!$C$205/'Timeline and FX'!AZ8,0) -> 0 | BA7: =IF(48='Assumption Setting'!$D$205,'Assumption Setting'!$C$205/'Timeline and FX'!BA8,0) -> 0 | BB7: =SUM(BC7:BN7) -> 0 | BC7: =IF(49='Assumption Setting'!$D$205,'Assumption Setting'!$C$205/'Timeline and FX'!BC8,0) -> 0 | BD7: =IF(50='Assumption Setting'!$D$205,'Assumption Setting'!$C$205/'Timeline and FX'!BD8,0) -> 0 | BE7: =IF(51='Assumption Setting'!$D$205,'Assumption Setting'!$C$205/'Timeline and FX'!BE8,0) -> 0 | BF7: =IF(52='Assumption Setting'!$D$205,'Assumption Setting'!$C$205/'Timeline and FX'!BF8,0) -> 0 | BG7: =IF(53='Assumption Setting'!$D$205,'Assumption Setting'!$C$205/'Timeline and FX'!BG8,0) -> 0 | BH7: =IF(54='Assumption Setting'!$D$205,'Assumption Setting'!$C$205/'Timeline and FX'!BH8,0) -> 0 | BI7: =IF(55='Assumption Setting'!$D$205,'Assumption Setting'!$C$205/'Timeline and FX'!BI8,0) -> 0 | BJ7: =IF(56='Assumption Setting'!$D$205,'Assumption Setting'!$C$205/'Timeline and FX'!BJ8,0) -> 0 | BK7: =IF(57='Assumption Setting'!$D$205,'Assumption Setting'!$C$205/'Timeline and FX'!BK8,0) -> 0 | BL7: =IF(58='Assumption Setting'!$D$205,'Assumption Setting'!$C$205/'Timeline and FX'!BL8,0) -> 0 | BM7: =IF(59='Assumption Setting'!$D$205,'Assumption Setting'!$C$205/'Timeline and FX'!BM8,0) -> 0 | BN7: =IF(60='Assumption Setting'!$D$205,'Assumption Setting'!$C$205/'Timeline and FX'!BN8,0) -> 0
A8: Network, devices and security | B8: =SUM(C8:N8) -> 2912.6214 | C8: =IF(1='Assumption Setting'!$D$206,'Assumption Setting'!$C$206/'Timeline and FX'!C8,0) -> 2912.6214 | D8: =IF(2='Assumption Setting'!$D$206,'Assumption Setting'!$C$206/'Timeline and FX'!D8,0) -> 0 | E8: =IF(3='Assumption Setting'!$D$206,'Assumption Setting'!$C$206/'Timeline and FX'!E8,0) -> 0 | F8: =IF(4='Assumption Setting'!$D$206,'Assumption Setting'!$C$206/'Timeline and FX'!F8,0) -> 0 | G8: =IF(5='Assumption Setting'!$D$206,'Assumption Setting'!$C$206/'Timeline and FX'!G8,0) -> 0 | H8: =IF(6='Assumption Setting'!$D$206,'Assumption Setting'!$C$206/'Timeline and FX'!H8,0) -> 0 | I8: =IF(7='Assumption Setting'!$D$206,'Assumption Setting'!$C$206/'Timeline and FX'!I8,0) -> 0 | J8: =IF(8='Assumption Setting'!$D$206,'Assumption Setting'!$C$206/'Timeline and FX'!J8,0) -> 0 | K8: =IF(9='Assumption Setting'!$D$206,'Assumption Setting'!$C$206/'Timeline and FX'!K8,0) -> 0 | L8: =IF(10='Assumption Setting'!$D$206,'Assumption Setting'!$C$206/'Timeline and FX'!L8,0) -> 0 | M8: =IF(11='Assumption Setting'!$D$206,'Assumption Setting'!$C$206/'Timeline and FX'!M8,0) -> 0 | N8: =IF(12='Assumption Setting'!$D$206,'Assumption Setting'!$C$206/'Timeline and FX'!N8,0) -> 0 | O8: =SUM(P8:AA8) -> 0 | P8: =IF(13='Assumption Setting'!$D$206,'Assumption Setting'!$C$206/'Timeline and FX'!P8,0) -> 0 | Q8: =IF(14='Assumption Setting'!$D$206,'Assumption Setting'!$C$206/'Timeline and FX'!Q8,0) -> 0 | R8: =IF(15='Assumption Setting'!$D$206,'Assumption Setting'!$C$206/'Timeline and FX'!R8,0) -> 0 | S8: =IF(16='Assumption Setting'!$D$206,'Assumption Setting'!$C$206/'Timeline and FX'!S8,0) -> 0 | T8: =IF(17='Assumption Setting'!$D$206,'Assumption Setting'!$C$206/'Timeline and FX'!T8,0) -> 0 | U8: =IF(18='Assumption Setting'!$D$206,'Assumption Setting'!$C$206/'Timeline and FX'!U8,0) -> 0 | V8: =IF(19='Assumption Setting'!$D$206,'Assumption Setting'!$C$206/'Timeline and FX'!V8,0) -> 0 | W8: =IF(20='Assumption Setting'!$D$206,'Assumption Setting'!$C$206/'Timeline and FX'!W8,0) -> 0 | X8: =IF(21='Assumption Setting'!$D$206,'Assumption Setting'!$C$206/'Timeline and FX'!X8,0) -> 0 | Y8: =IF(22='Assumption Setting'!$D$206,'Assumption Setting'!$C$206/'Timeline and FX'!Y8,0) -> 0 | Z8: =IF(23='Assumption Setting'!$D$206,'Assumption Setting'!$C$206/'Timeline and FX'!Z8,0) -> 0 | AA8: =IF(24='Assumption Setting'!$D$206,'Assumption Setting'!$C$206/'Timeline and FX'!AA8,0) -> 0 | AB8: =SUM(AC8:AN8) -> 0 | AC8: =IF(25='Assumption Setting'!$D$206,'Assumption Setting'!$C$206/'Timeline and FX'!AC8,0) -> 0 | AD8: =IF(26='Assumption Setting'!$D$206,'Assumption Setting'!$C$206/'Timeline and FX'!AD8,0) -> 0 | AE8: =IF(27='Assumption Setting'!$D$206,'Assumption Setting'!$C$206/'Timeline and FX'!AE8,0) -> 0 | AF8: =IF(28='Assumption Setting'!$D$206,'Assumption Setting'!$C$206/'Timeline and FX'!AF8,0) -> 0 | AG8: =IF(29='Assumption Setting'!$D$206,'Assumption Setting'!$C$206/'Timeline and FX'!AG8,0) -> 0 | AH8: =IF(30='Assumption Setting'!$D$206,'Assumption Setting'!$C$206/'Timeline and FX'!AH8,0) -> 0 | AI8: =IF(31='Assumption Setting'!$D$206,'Assumption Setting'!$C$206/'Timeline and FX'!AI8,0) -> 0 | AJ8: =IF(32='Assumption Setting'!$D$206,'Assumption Setting'!$C$206/'Timeline and FX'!AJ8,0) -> 0 | AK8: =IF(33='Assumption Setting'!$D$206,'Assumption Setting'!$C$206/'Timeline and FX'!AK8,0) -> 0 | AL8: =IF(34='Assumption Setting'!$D$206,'Assumption Setting'!$C$206/'Timeline and FX'!AL8,0) -> 0 | AM8: =IF(35='Assumption Setting'!$D$206,'Assumption Setting'!$C$206/'Timeline and FX'!AM8,0) -> 0 | AN8: =IF(36='Assumption Setting'!$D$206,'Assumption Setting'!$C$206/'Timeline and FX'!AN8,0) -> 0 | AO8: =SUM(AP8:BA8) -> 0 | AP8: =IF(37='Assumption Setting'!$D$206,'Assumption Setting'!$C$206/'Timeline and FX'!AP8,0) -> 0 | AQ8: =IF(38='Assumption Setting'!$D$206,'Assumption Setting'!$C$206/'Timeline and FX'!AQ8,0) -> 0 | AR8: =IF(39='Assumption Setting'!$D$206,'Assumption Setting'!$C$206/'Timeline and FX'!AR8,0) -> 0 | AS8: =IF(40='Assumption Setting'!$D$206,'Assumption Setting'!$C$206/'Timeline and FX'!AS8,0) -> 0 | AT8: =IF(41='Assumption Setting'!$D$206,'Assumption Setting'!$C$206/'Timeline and FX'!AT8,0) -> 0 | AU8: =IF(42='Assumption Setting'!$D$206,'Assumption Setting'!$C$206/'Timeline and FX'!AU8,0) -> 0 | AV8: =IF(43='Assumption Setting'!$D$206,'Assumption Setting'!$C$206/'Timeline and FX'!AV8,0) -> 0 | AW8: =IF(44='Assumption Setting'!$D$206,'Assumption Setting'!$C$206/'Timeline and FX'!AW8,0) -> 0 | AX8: =IF(45='Assumption Setting'!$D$206,'Assumption Setting'!$C$206/'Timeline and FX'!AX8,0) -> 0 | AY8: =IF(46='Assumption Setting'!$D$206,'Assumption Setting'!$C$206/'Timeline and FX'!AY8,0) -> 0 | AZ8: =IF(47='Assumption Setting'!$D$206,'Assumption Setting'!$C$206/'Timeline and FX'!AZ8,0) -> 0 | BA8: =IF(48='Assumption Setting'!$D$206,'Assumption Setting'!$C$206/'Timeline and FX'!BA8,0) -> 0 | BB8: =SUM(BC8:BN8) -> 0 | BC8: =IF(49='Assumption Setting'!$D$206,'Assumption Setting'!$C$206/'Timeline and FX'!BC8,0) -> 0 | BD8: =IF(50='Assumption Setting'!$D$206,'Assumption Setting'!$C$206/'Timeline and FX'!BD8,0) -> 0 | BE8: =IF(51='Assumption Setting'!$D$206,'Assumption Setting'!$C$206/'Timeline and FX'!BE8,0) -> 0 | BF8: =IF(52='Assumption Setting'!$D$206,'Assumption Setting'!$C$206/'Timeline and FX'!BF8,0) -> 0 | BG8: =IF(53='Assumption Setting'!$D$206,'Assumption Setting'!$C$206/'Timeline and FX'!BG8,0) -> 0 | BH8: =IF(54='Assumption Setting'!$D$206,'Assumption Setting'!$C$206/'Timeline and FX'!BH8,0) -> 0 | BI8: =IF(55='Assumption Setting'!$D$206,'Assumption Setting'!$C$206/'Timeline and FX'!BI8,0) -> 0 | BJ8: =IF(56='Assumption Setting'!$D$206,'Assumption Setting'!$C$206/'Timeline and FX'!BJ8,0) -> 0 | BK8: =IF(57='Assumption Setting'!$D$206,'Assumption Setting'!$C$206/'Timeline and FX'!BK8,0) -> 0 | BL8: =IF(58='Assumption Setting'!$D$206,'Assumption Setting'!$C$206/'Timeline and FX'!BL8,0) -> 0 | BM8: =IF(59='Assumption Setting'!$D$206,'Assumption Setting'!$C$206/'Timeline and FX'!BM8,0) -> 0 | BN8: =IF(60='Assumption Setting'!$D$206,'Assumption Setting'!$C$206/'Timeline and FX'!BN8,0) -> 0
A9: POS demo and event kit | B9: =SUM(C9:N9) -> 3495.1456 | C9: =IF(1='Assumption Setting'!$D$208,'Assumption Setting'!$C$208/'Timeline and FX'!C8,0) -> 3495.1456 | D9: =IF(2='Assumption Setting'!$D$208,'Assumption Setting'!$C$208/'Timeline and FX'!D8,0) -> 0 | E9: =IF(3='Assumption Setting'!$D$208,'Assumption Setting'!$C$208/'Timeline and FX'!E8,0) -> 0 | F9: =IF(4='Assumption Setting'!$D$208,'Assumption Setting'!$C$208/'Timeline and FX'!F8,0) -> 0 | G9: =IF(5='Assumption Setting'!$D$208,'Assumption Setting'!$C$208/'Timeline and FX'!G8,0) -> 0 | H9: =IF(6='Assumption Setting'!$D$208,'Assumption Setting'!$C$208/'Timeline and FX'!H8,0) -> 0 | I9: =IF(7='Assumption Setting'!$D$208,'Assumption Setting'!$C$208/'Timeline and FX'!I8,0) -> 0 | J9: =IF(8='Assumption Setting'!$D$208,'Assumption Setting'!$C$208/'Timeline and FX'!J8,0) -> 0 | K9: =IF(9='Assumption Setting'!$D$208,'Assumption Setting'!$C$208/'Timeline and FX'!K8,0) -> 0 | L9: =IF(10='Assumption Setting'!$D$208,'Assumption Setting'!$C$208/'Timeline and FX'!L8,0) -> 0 | M9: =IF(11='Assumption Setting'!$D$208,'Assumption Setting'!$C$208/'Timeline and FX'!M8,0) -> 0 | N9: =IF(12='Assumption Setting'!$D$208,'Assumption Setting'!$C$208/'Timeline and FX'!N8,0) -> 0 | O9: =SUM(P9:AA9) -> 0 | P9: =IF(13='Assumption Setting'!$D$208,'Assumption Setting'!$C$208/'Timeline and FX'!P8,0) -> 0 | Q9: =IF(14='Assumption Setting'!$D$208,'Assumption Setting'!$C$208/'Timeline and FX'!Q8,0) -> 0 | R9: =IF(15='Assumption Setting'!$D$208,'Assumption Setting'!$C$208/'Timeline and FX'!R8,0) -> 0 | S9: =IF(16='Assumption Setting'!$D$208,'Assumption Setting'!$C$208/'Timeline and FX'!S8,0) -> 0 | T9: =IF(17='Assumption Setting'!$D$208,'Assumption Setting'!$C$208/'Timeline and FX'!T8,0) -> 0 | U9: =IF(18='Assumption Setting'!$D$208,'Assumption Setting'!$C$208/'Timeline and FX'!U8,0) -> 0 | V9: =IF(19='Assumption Setting'!$D$208,'Assumption Setting'!$C$208/'Timeline and FX'!V8,0) -> 0 | W9: =IF(20='Assumption Setting'!$D$208,'Assumption Setting'!$C$208/'Timeline and FX'!W8,0) -> 0 | X9: =IF(21='Assumption Setting'!$D$208,'Assumption Setting'!$C$208/'Timeline and FX'!X8,0) -> 0 | Y9: =IF(22='Assumption Setting'!$D$208,'Assumption Setting'!$C$208/'Timeline and FX'!Y8,0) -> 0 | Z9: =IF(23='Assumption Setting'!$D$208,'Assumption Setting'!$C$208/'Timeline and FX'!Z8,0) -> 0 | AA9: =IF(24='Assumption Setting'!$D$208,'Assumption Setting'!$C$208/'Timeline and FX'!AA8,0) -> 0 | AB9: =SUM(AC9:AN9) -> 0 | AC9: =IF(25='Assumption Setting'!$D$208,'Assumption Setting'!$C$208/'Timeline and FX'!AC8,0) -> 0 | AD9: =IF(26='Assumption Setting'!$D$208,'Assumption Setting'!$C$208/'Timeline and FX'!AD8,0) -> 0 | AE9: =IF(27='Assumption Setting'!$D$208,'Assumption Setting'!$C$208/'Timeline and FX'!AE8,0) -> 0 | AF9: =IF(28='Assumption Setting'!$D$208,'Assumption Setting'!$C$208/'Timeline and FX'!AF8,0) -> 0 | AG9: =IF(29='Assumption Setting'!$D$208,'Assumption Setting'!$C$208/'Timeline and FX'!AG8,0) -> 0 | AH9: =IF(30='Assumption Setting'!$D$208,'Assumption Setting'!$C$208/'Timeline and FX'!AH8,0) -> 0 | AI9: =IF(31='Assumption Setting'!$D$208,'Assumption Setting'!$C$208/'Timeline and FX'!AI8,0) -> 0 | AJ9: =IF(32='Assumption Setting'!$D$208,'Assumption Setting'!$C$208/'Timeline and FX'!AJ8,0) -> 0 | AK9: =IF(33='Assumption Setting'!$D$208,'Assumption Setting'!$C$208/'Timeline and FX'!AK8,0) -> 0 | AL9: =IF(34='Assumption Setting'!$D$208,'Assumption Setting'!$C$208/'Timeline and FX'!AL8,0) -> 0 | AM9: =IF(35='Assumption Setting'!$D$208,'Assumption Setting'!$C$208/'Timeline and FX'!AM8,0) -> 0 | AN9: =IF(36='Assumption Setting'!$D$208,'Assumption Setting'!$C$208/'Timeline and FX'!AN8,0) -> 0 | AO9: =SUM(AP9:BA9) -> 0 | AP9: =IF(37='Assumption Setting'!$D$208,'Assumption Setting'!$C$208/'Timeline and FX'!AP8,0) -> 0 | AQ9: =IF(38='Assumption Setting'!$D$208,'Assumption Setting'!$C$208/'Timeline and FX'!AQ8,0) -> 0 | AR9: =IF(39='Assumption Setting'!$D$208,'Assumption Setting'!$C$208/'Timeline and FX'!AR8,0) -> 0 | AS9: =IF(40='Assumption Setting'!$D$208,'Assumption Setting'!$C$208/'Timeline and FX'!AS8,0) -> 0 | AT9: =IF(41='Assumption Setting'!$D$208,'Assumption Setting'!$C$208/'Timeline and FX'!AT8,0) -> 0 | AU9: =IF(42='Assumption Setting'!$D$208,'Assumption Setting'!$C$208/'Timeline and FX'!AU8,0) -> 0 | AV9: =IF(43='Assumption Setting'!$D$208,'Assumption Setting'!$C$208/'Timeline and FX'!AV8,0) -> 0 | AW9: =IF(44='Assumption Setting'!$D$208,'Assumption Setting'!$C$208/'Timeline and FX'!AW8,0) -> 0 | AX9: =IF(45='Assumption Setting'!$D$208,'Assumption Setting'!$C$208/'Timeline and FX'!AX8,0) -> 0 | AY9: =IF(46='Assumption Setting'!$D$208,'Assumption Setting'!$C$208/'Timeline and FX'!AY8,0) -> 0 | AZ9: =IF(47='Assumption Setting'!$D$208,'Assumption Setting'!$C$208/'Timeline and FX'!AZ8,0) -> 0 | BA9: =IF(48='Assumption Setting'!$D$208,'Assumption Setting'!$C$208/'Timeline and FX'!BA8,0) -> 0 | BB9: =SUM(BC9:BN9) -> 0 | BC9: =IF(49='Assumption Setting'!$D$208,'Assumption Setting'!$C$208/'Timeline and FX'!BC8,0) -> 0 | BD9: =IF(50='Assumption Setting'!$D$208,'Assumption Setting'!$C$208/'Timeline and FX'!BD8,0) -> 0 | BE9: =IF(51='Assumption Setting'!$D$208,'Assumption Setting'!$C$208/'Timeline and FX'!BE8,0) -> 0 | BF9: =IF(52='Assumption Setting'!$D$208,'Assumption Setting'!$C$208/'Timeline and FX'!BF8,0) -> 0 | BG9: =IF(53='Assumption Setting'!$D$208,'Assumption Setting'!$C$208/'Timeline and FX'!BG8,0) -> 0 | BH9: =IF(54='Assumption Setting'!$D$208,'Assumption Setting'!$C$208/'Timeline and FX'!BH8,0) -> 0 | BI9: =IF(55='Assumption Setting'!$D$208,'Assumption Setting'!$C$208/'Timeline and FX'!BI8,0) -> 0 | BJ9: =IF(56='Assumption Setting'!$D$208,'Assumption Setting'!$C$208/'Timeline and FX'!BJ8,0) -> 0 | BK9: =IF(57='Assumption Setting'!$D$208,'Assumption Setting'!$C$208/'Timeline and FX'!BK8,0) -> 0 | BL9: =IF(58='Assumption Setting'!$D$208,'Assumption Setting'!$C$208/'Timeline and FX'!BL8,0) -> 0 | BM9: =IF(59='Assumption Setting'!$D$208,'Assumption Setting'!$C$208/'Timeline and FX'!BM8,0) -> 0 | BN9: =IF(60='Assumption Setting'!$D$208,'Assumption Setting'!$C$208/'Timeline and FX'!BN8,0) -> 0
A10: Studio and content production kit | B10: =SUM(C10:N10) -> 1538.3853 | C10: =IF(1='Assumption Setting'!$D$209,'Assumption Setting'!$C$209/'Timeline and FX'!C8,0) -> 0 | D10: =IF(2='Assumption Setting'!$D$209,'Assumption Setting'!$C$209/'Timeline and FX'!D8,0) -> 0 | E10: =IF(3='Assumption Setting'!$D$209,'Assumption Setting'!$C$209/'Timeline and FX'!E8,0) -> 1538.3853 | F10: =IF(4='Assumption Setting'!$D$209,'Assumption Setting'!$C$209/'Timeline and FX'!F8,0) -> 0 | G10: =IF(5='Assumption Setting'!$D$209,'Assumption Setting'!$C$209/'Timeline and FX'!G8,0) -> 0 | H10: =IF(6='Assumption Setting'!$D$209,'Assumption Setting'!$C$209/'Timeline and FX'!H8,0) -> 0 | I10: =IF(7='Assumption Setting'!$D$209,'Assumption Setting'!$C$209/'Timeline and FX'!I8,0) -> 0 | J10: =IF(8='Assumption Setting'!$D$209,'Assumption Setting'!$C$209/'Timeline and FX'!J8,0) -> 0 | K10: =IF(9='Assumption Setting'!$D$209,'Assumption Setting'!$C$209/'Timeline and FX'!K8,0) -> 0 | L10: =IF(10='Assumption Setting'!$D$209,'Assumption Setting'!$C$209/'Timeline and FX'!L8,0) -> 0 | M10: =IF(11='Assumption Setting'!$D$209,'Assumption Setting'!$C$209/'Timeline and FX'!M8,0) -> 0 | N10: =IF(12='Assumption Setting'!$D$209,'Assumption Setting'!$C$209/'Timeline and FX'!N8,0) -> 0 | O10: =SUM(P10:AA10) -> 0 | P10: =IF(13='Assumption Setting'!$D$209,'Assumption Setting'!$C$209/'Timeline and FX'!P8,0) -> 0 | Q10: =IF(14='Assumption Setting'!$D$209,'Assumption Setting'!$C$209/'Timeline and FX'!Q8,0) -> 0 | R10: =IF(15='Assumption Setting'!$D$209,'Assumption Setting'!$C$209/'Timeline and FX'!R8,0) -> 0 | S10: =IF(16='Assumption Setting'!$D$209,'Assumption Setting'!$C$209/'Timeline and FX'!S8,0) -> 0 | T10: =IF(17='Assumption Setting'!$D$209,'Assumption Setting'!$C$209/'Timeline and FX'!T8,0) -> 0 | U10: =IF(18='Assumption Setting'!$D$209,'Assumption Setting'!$C$209/'Timeline and FX'!U8,0) -> 0 | V10: =IF(19='Assumption Setting'!$D$209,'Assumption Setting'!$C$209/'Timeline and FX'!V8,0) -> 0 | W10: =IF(20='Assumption Setting'!$D$209,'Assumption Setting'!$C$209/'Timeline and FX'!W8,0) -> 0 | X10: =IF(21='Assumption Setting'!$D$209,'Assumption Setting'!$C$209/'Timeline and FX'!X8,0) -> 0 | Y10: =IF(22='Assumption Setting'!$D$209,'Assumption Setting'!$C$209/'Timeline and FX'!Y8,0) -> 0 | Z10: =IF(23='Assumption Setting'!$D$209,'Assumption Setting'!$C$209/'Timeline and FX'!Z8,0) -> 0 | AA10: =IF(24='Assumption Setting'!$D$209,'Assumption Setting'!$C$209/'Timeline and FX'!AA8,0) -> 0 | AB10: =SUM(AC10:AN10) -> 0 | AC10: =IF(25='Assumption Setting'!$D$209,'Assumption Setting'!$C$209/'Timeline and FX'!AC8,0) -> 0 | AD10: =IF(26='Assumption Setting'!$D$209,'Assumption Setting'!$C$209/'Timeline and FX'!AD8,0) -> 0 | AE10: =IF(27='Assumption Setting'!$D$209,'Assumption Setting'!$C$209/'Timeline and FX'!AE8,0) -> 0 | AF10: =IF(28='Assumption Setting'!$D$209,'Assumption Setting'!$C$209/'Timeline and FX'!AF8,0) -> 0 | AG10: =IF(29='Assumption Setting'!$D$209,'Assumption Setting'!$C$209/'Timeline and FX'!AG8,0) -> 0 | AH10: =IF(30='Assumption Setting'!$D$209,'Assumption Setting'!$C$209/'Timeline and FX'!AH8,0) -> 0 | AI10: =IF(31='Assumption Setting'!$D$209,'Assumption Setting'!$C$209/'Timeline and FX'!AI8,0) -> 0 | AJ10: =IF(32='Assumption Setting'!$D$209,'Assumption Setting'!$C$209/'Timeline and FX'!AJ8,0) -> 0 | AK10: =IF(33='Assumption Setting'!$D$209,'Assumption Setting'!$C$209/'Timeline and FX'!AK8,0) -> 0 | AL10: =IF(34='Assumption Setting'!$D$209,'Assumption Setting'!$C$209/'Timeline and FX'!AL8,0) -> 0 | AM10: =IF(35='Assumption Setting'!$D$209,'Assumption Setting'!$C$209/'Timeline and FX'!AM8,0) -> 0 | AN10: =IF(36='Assumption Setting'!$D$209,'Assumption Setting'!$C$209/'Timeline and FX'!AN8,0) -> 0 | AO10: =SUM(AP10:BA10) -> 0 | AP10: =IF(37='Assumption Setting'!$D$209,'Assumption Setting'!$C$209/'Timeline and FX'!AP8,0) -> 0 | AQ10: =IF(38='Assumption Setting'!$D$209,'Assumption Setting'!$C$209/'Timeline and FX'!AQ8,0) -> 0 | AR10: =IF(39='Assumption Setting'!$D$209,'Assumption Setting'!$C$209/'Timeline and FX'!AR8,0) -> 0 | AS10: =IF(40='Assumption Setting'!$D$209,'Assumption Setting'!$C$209/'Timeline and FX'!AS8,0) -> 0 | AT10: =IF(41='Assumption Setting'!$D$209,'Assumption Setting'!$C$209/'Timeline and FX'!AT8,0) -> 0 | AU10: =IF(42='Assumption Setting'!$D$209,'Assumption Setting'!$C$209/'Timeline and FX'!AU8,0) -> 0 | AV10: =IF(43='Assumption Setting'!$D$209,'Assumption Setting'!$C$209/'Timeline and FX'!AV8,0) -> 0 | AW10: =IF(44='Assumption Setting'!$D$209,'Assumption Setting'!$C$209/'Timeline and FX'!AW8,0) -> 0 | AX10: =IF(45='Assumption Setting'!$D$209,'Assumption Setting'!$C$209/'Timeline and FX'!AX8,0) -> 0 | AY10: =IF(46='Assumption Setting'!$D$209,'Assumption Setting'!$C$209/'Timeline and FX'!AY8,0) -> 0 | AZ10: =IF(47='Assumption Setting'!$D$209,'Assumption Setting'!$C$209/'Timeline and FX'!AZ8,0) -> 0 | BA10: =IF(48='Assumption Setting'!$D$209,'Assumption Setting'!$C$209/'Timeline and FX'!BA8,0) -> 0 | BB10: =SUM(BC10:BN10) -> 0 | BC10: =IF(49='Assumption Setting'!$D$209,'Assumption Setting'!$C$209/'Timeline and FX'!BC8,0) -> 0 | BD10: =IF(50='Assumption Setting'!$D$209,'Assumption Setting'!$C$209/'Timeline and FX'!BD8,0) -> 0 | BE10: =IF(51='Assumption Setting'!$D$209,'Assumption Setting'!$C$209/'Timeline and FX'!BE8,0) -> 0 | BF10: =IF(52='Assumption Setting'!$D$209,'Assumption Setting'!$C$209/'Timeline and FX'!BF8,0) -> 0 | BG10: =IF(53='Assumption Setting'!$D$209,'Assumption Setting'!$C$209/'Timeline and FX'!BG8,0) -> 0 | BH10: =IF(54='Assumption Setting'!$D$209,'Assumption Setting'!$C$209/'Timeline and FX'!BH8,0) -> 0 | BI10: =IF(55='Assumption Setting'!$D$209,'Assumption Setting'!$C$209/'Timeline and FX'!BI8,0) -> 0 | BJ10: =IF(56='Assumption Setting'!$D$209,'Assumption Setting'!$C$209/'Timeline and FX'!BJ8,0) -> 0 | BK10: =IF(57='Assumption Setting'!$D$209,'Assumption Setting'!$C$209/'Timeline and FX'!BK8,0) -> 0 | BL10: =IF(58='Assumption Setting'!$D$209,'Assumption Setting'!$C$209/'Timeline and FX'!BL8,0) -> 0 | BM10: =IF(59='Assumption Setting'!$D$209,'Assumption Setting'!$C$209/'Timeline and FX'!BM8,0) -> 0 | BN10: =IF(60='Assumption Setting'!$D$209,'Assumption Setting'!$C$209/'Timeline and FX'!BN8,0) -> 0
A11: Second city office set up | B11: =SUM(C11:N11) -> 0 | C11: =IF(1='Assumption Setting'!$D$210,'Assumption Setting'!$C$210/'Timeline and FX'!C8,0) -> 0 | D11: =IF(2='Assumption Setting'!$D$210,'Assumption Setting'!$C$210/'Timeline and FX'!D8,0) -> 0 | E11: =IF(3='Assumption Setting'!$D$210,'Assumption Setting'!$C$210/'Timeline and FX'!E8,0) -> 0 | F11: =IF(4='Assumption Setting'!$D$210,'Assumption Setting'!$C$210/'Timeline and FX'!F8,0) -> 0 | G11: =IF(5='Assumption Setting'!$D$210,'Assumption Setting'!$C$210/'Timeline and FX'!G8,0) -> 0 | H11: =IF(6='Assumption Setting'!$D$210,'Assumption Setting'!$C$210/'Timeline and FX'!H8,0) -> 0 | I11: =IF(7='Assumption Setting'!$D$210,'Assumption Setting'!$C$210/'Timeline and FX'!I8,0) -> 0 | J11: =IF(8='Assumption Setting'!$D$210,'Assumption Setting'!$C$210/'Timeline and FX'!J8,0) -> 0 | K11: =IF(9='Assumption Setting'!$D$210,'Assumption Setting'!$C$210/'Timeline and FX'!K8,0) -> 0 | L11: =IF(10='Assumption Setting'!$D$210,'Assumption Setting'!$C$210/'Timeline and FX'!L8,0) -> 0 | M11: =IF(11='Assumption Setting'!$D$210,'Assumption Setting'!$C$210/'Timeline and FX'!M8,0) -> 0 | N11: =IF(12='Assumption Setting'!$D$210,'Assumption Setting'!$C$210/'Timeline and FX'!N8,0) -> 0 | O11: =SUM(P11:AA11) -> 2166.4152 | P11: =IF(13='Assumption Setting'!$D$210,'Assumption Setting'!$C$210/'Timeline and FX'!P8,0) -> 0 | Q11: =IF(14='Assumption Setting'!$D$210,'Assumption Setting'!$C$210/'Timeline and FX'!Q8,0) -> 0 | R11: =IF(15='Assumption Setting'!$D$210,'Assumption Setting'!$C$210/'Timeline and FX'!R8,0) -> 0 | S11: =IF(16='Assumption Setting'!$D$210,'Assumption Setting'!$C$210/'Timeline and FX'!S8,0) -> 2166.4152 | T11: =IF(17='Assumption Setting'!$D$210,'Assumption Setting'!$C$210/'Timeline and FX'!T8,0) -> 0 | U11: =IF(18='Assumption Setting'!$D$210,'Assumption Setting'!$C$210/'Timeline and FX'!U8,0) -> 0 | V11: =IF(19='Assumption Setting'!$D$210,'Assumption Setting'!$C$210/'Timeline and FX'!V8,0) -> 0 | W11: =IF(20='Assumption Setting'!$D$210,'Assumption Setting'!$C$210/'Timeline and FX'!W8,0) -> 0 | X11: =IF(21='Assumption Setting'!$D$210,'Assumption Setting'!$C$210/'Timeline and FX'!X8,0) -> 0 | Y11: =IF(22='Assumption Setting'!$D$210,'Assumption Setting'!$C$210/'Timeline and FX'!Y8,0) -> 0 | Z11: =IF(23='Assumption Setting'!$D$210,'Assumption Setting'!$C$210/'Timeline and FX'!Z8,0) -> 0 | AA11: =IF(24='Assumption Setting'!$D$210,'Assumption Setting'!$C$210/'Timeline and FX'!AA8,0) -> 0 | AB11: =SUM(AC11:AN11) -> 0 | AC11: =IF(25='Assumption Setting'!$D$210,'Assumption Setting'!$C$210/'Timeline and FX'!AC8,0) -> 0 | AD11: =IF(26='Assumption Setting'!$D$210,'Assumption Setting'!$C$210/'Timeline and FX'!AD8,0) -> 0 | AE11: =IF(27='Assumption Setting'!$D$210,'Assumption Setting'!$C$210/'Timeline and FX'!AE8,0) -> 0 | AF11: =IF(28='Assumption Setting'!$D$210,'Assumption Setting'!$C$210/'Timeline and FX'!AF8,0) -> 0 | AG11: =IF(29='Assumption Setting'!$D$210,'Assumption Setting'!$C$210/'Timeline and FX'!AG8,0) -> 0 | AH11: =IF(30='Assumption Setting'!$D$210,'Assumption Setting'!$C$210/'Timeline and FX'!AH8,0) -> 0 | AI11: =IF(31='Assumption Setting'!$D$210,'Assumption Setting'!$C$210/'Timeline and FX'!AI8,0) -> 0 | AJ11: =IF(32='Assumption Setting'!$D$210,'Assumption Setting'!$C$210/'Timeline and FX'!AJ8,0) -> 0 | AK11: =IF(33='Assumption Setting'!$D$210,'Assumption Setting'!$C$210/'Timeline and FX'!AK8,0) -> 0 | AL11: =IF(34='Assumption Setting'!$D$210,'Assumption Setting'!$C$210/'Timeline and FX'!AL8,0) -> 0 | AM11: =IF(35='Assumption Setting'!$D$210,'Assumption Setting'!$C$210/'Timeline and FX'!AM8,0) -> 0 | AN11: =IF(36='Assumption Setting'!$D$210,'Assumption Setting'!$C$210/'Timeline and FX'!AN8,0) -> 0 | AO11: =SUM(AP11:BA11) -> 0 | AP11: =IF(37='Assumption Setting'!$D$210,'Assumption Setting'!$C$210/'Timeline and FX'!AP8,0) -> 0 | AQ11: =IF(38='Assumption Setting'!$D$210,'Assumption Setting'!$C$210/'Timeline and FX'!AQ8,0) -> 0 | AR11: =IF(39='Assumption Setting'!$D$210,'Assumption Setting'!$C$210/'Timeline and FX'!AR8,0) -> 0 | AS11: =IF(40='Assumption Setting'!$D$210,'Assumption Setting'!$C$210/'Timeline and FX'!AS8,0) -> 0 | AT11: =IF(41='Assumption Setting'!$D$210,'Assumption Setting'!$C$210/'Timeline and FX'!AT8,0) -> 0 | AU11: =IF(42='Assumption Setting'!$D$210,'Assumption Setting'!$C$210/'Timeline and FX'!AU8,0) -> 0 | AV11: =IF(43='Assumption Setting'!$D$210,'Assumption Setting'!$C$210/'Timeline and FX'!AV8,0) -> 0 | AW11: =IF(44='Assumption Setting'!$D$210,'Assumption Setting'!$C$210/'Timeline and FX'!AW8,0) -> 0 | AX11: =IF(45='Assumption Setting'!$D$210,'Assumption Setting'!$C$210/'Timeline and FX'!AX8,0) -> 0 | AY11: =IF(46='Assumption Setting'!$D$210,'Assumption Setting'!$C$210/'Timeline and FX'!AY8,0) -> 0 | AZ11: =IF(47='Assumption Setting'!$D$210,'Assumption Setting'!$C$210/'Timeline and FX'!AZ8,0) -> 0 | BA11: =IF(48='Assumption Setting'!$D$210,'Assumption Setting'!$C$210/'Timeline and FX'!BA8,0) -> 0 | BB11: =SUM(BC11:BN11) -> 0 | BC11: =IF(49='Assumption Setting'!$D$210,'Assumption Setting'!$C$210/'Timeline and FX'!BC8,0) -> 0 | BD11: =IF(50='Assumption Setting'!$D$210,'Assumption Setting'!$C$210/'Timeline and FX'!BD8,0) -> 0 | BE11: =IF(51='Assumption Setting'!$D$210,'Assumption Setting'!$C$210/'Timeline and FX'!BE8,0) -> 0 | BF11: =IF(52='Assumption Setting'!$D$210,'Assumption Setting'!$C$210/'Timeline and FX'!BF8,0) -> 0 | BG11: =IF(53='Assumption Setting'!$D$210,'Assumption Setting'!$C$210/'Timeline and FX'!BG8,0) -> 0 | BH11: =IF(54='Assumption Setting'!$D$210,'Assumption Setting'!$C$210/'Timeline and FX'!BH8,0) -> 0 | BI11: =IF(55='Assumption Setting'!$D$210,'Assumption Setting'!$C$210/'Timeline and FX'!BI8,0) -> 0 | BJ11: =IF(56='Assumption Setting'!$D$210,'Assumption Setting'!$C$210/'Timeline and FX'!BJ8,0) -> 0 | BK11: =IF(57='Assumption Setting'!$D$210,'Assumption Setting'!$C$210/'Timeline and FX'!BK8,0) -> 0 | BL11: =IF(58='Assumption Setting'!$D$210,'Assumption Setting'!$C$210/'Timeline and FX'!BL8,0) -> 0 | BM11: =IF(59='Assumption Setting'!$D$210,'Assumption Setting'!$C$210/'Timeline and FX'!BM8,0) -> 0 | BN11: =IF(60='Assumption Setting'!$D$210,'Assumption Setting'!$C$210/'Timeline and FX'!BN8,0) -> 0
A12: Trademark, entity formation and IP registration | B12: =SUM(C12:N12) -> 1747.5728 | C12: =IF(1='Assumption Setting'!$D$207,'Assumption Setting'!$C$207/'Timeline and FX'!C8,0) -> 1747.5728 | D12: =IF(2='Assumption Setting'!$D$207,'Assumption Setting'!$C$207/'Timeline and FX'!D8,0) -> 0 | E12: =IF(3='Assumption Setting'!$D$207,'Assumption Setting'!$C$207/'Timeline and FX'!E8,0) -> 0 | F12: =IF(4='Assumption Setting'!$D$207,'Assumption Setting'!$C$207/'Timeline and FX'!F8,0) -> 0 | G12: =IF(5='Assumption Setting'!$D$207,'Assumption Setting'!$C$207/'Timeline and FX'!G8,0) -> 0 | H12: =IF(6='Assumption Setting'!$D$207,'Assumption Setting'!$C$207/'Timeline and FX'!H8,0) -> 0 | I12: =IF(7='Assumption Setting'!$D$207,'Assumption Setting'!$C$207/'Timeline and FX'!I8,0) -> 0 | J12: =IF(8='Assumption Setting'!$D$207,'Assumption Setting'!$C$207/'Timeline and FX'!J8,0) -> 0 | K12: =IF(9='Assumption Setting'!$D$207,'Assumption Setting'!$C$207/'Timeline and FX'!K8,0) -> 0 | L12: =IF(10='Assumption Setting'!$D$207,'Assumption Setting'!$C$207/'Timeline and FX'!L8,0) -> 0 | M12: =IF(11='Assumption Setting'!$D$207,'Assumption Setting'!$C$207/'Timeline and FX'!M8,0) -> 0 | N12: =IF(12='Assumption Setting'!$D$207,'Assumption Setting'!$C$207/'Timeline and FX'!N8,0) -> 0 | O12: =SUM(P12:AA12) -> 0 | P12: =IF(13='Assumption Setting'!$D$207,'Assumption Setting'!$C$207/'Timeline and FX'!P8,0) -> 0 | Q12: =IF(14='Assumption Setting'!$D$207,'Assumption Setting'!$C$207/'Timeline and FX'!Q8,0) -> 0 | R12: =IF(15='Assumption Setting'!$D$207,'Assumption Setting'!$C$207/'Timeline and FX'!R8,0) -> 0 | S12: =IF(16='Assumption Setting'!$D$207,'Assumption Setting'!$C$207/'Timeline and FX'!S8,0) -> 0 | T12: =IF(17='Assumption Setting'!$D$207,'Assumption Setting'!$C$207/'Timeline and FX'!T8,0) -> 0 | U12: =IF(18='Assumption Setting'!$D$207,'Assumption Setting'!$C$207/'Timeline and FX'!U8,0) -> 0 | V12: =IF(19='Assumption Setting'!$D$207,'Assumption Setting'!$C$207/'Timeline and FX'!V8,0) -> 0 | W12: =IF(20='Assumption Setting'!$D$207,'Assumption Setting'!$C$207/'Timeline and FX'!W8,0) -> 0 | X12: =IF(21='Assumption Setting'!$D$207,'Assumption Setting'!$C$207/'Timeline and FX'!X8,0) -> 0 | Y12: =IF(22='Assumption Setting'!$D$207,'Assumption Setting'!$C$207/'Timeline and FX'!Y8,0) -> 0 | Z12: =IF(23='Assumption Setting'!$D$207,'Assumption Setting'!$C$207/'Timeline and FX'!Z8,0) -> 0 | AA12: =IF(24='Assumption Setting'!$D$207,'Assumption Setting'!$C$207/'Timeline and FX'!AA8,0) -> 0 | AB12: =SUM(AC12:AN12) -> 0 | AC12: =IF(25='Assumption Setting'!$D$207,'Assumption Setting'!$C$207/'Timeline and FX'!AC8,0) -> 0 | AD12: =IF(26='Assumption Setting'!$D$207,'Assumption Setting'!$C$207/'Timeline and FX'!AD8,0) -> 0 | AE12: =IF(27='Assumption Setting'!$D$207,'Assumption Setting'!$C$207/'Timeline and FX'!AE8,0) -> 0 | AF12: =IF(28='Assumption Setting'!$D$207,'Assumption Setting'!$C$207/'Timeline and FX'!AF8,0) -> 0 | AG12: =IF(29='Assumption Setting'!$D$207,'Assumption Setting'!$C$207/'Timeline and FX'!AG8,0) -> 0 | AH12: =IF(30='Assumption Setting'!$D$207,'Assumption Setting'!$C$207/'Timeline and FX'!AH8,0) -> 0 | AI12: =IF(31='Assumption Setting'!$D$207,'Assumption Setting'!$C$207/'Timeline and FX'!AI8,0) -> 0 | AJ12: =IF(32='Assumption Setting'!$D$207,'Assumption Setting'!$C$207/'Timeline and FX'!AJ8,0) -> 0 | AK12: =IF(33='Assumption Setting'!$D$207,'Assumption Setting'!$C$207/'Timeline and FX'!AK8,0) -> 0 | AL12: =IF(34='Assumption Setting'!$D$207,'Assumption Setting'!$C$207/'Timeline and FX'!AL8,0) -> 0 | AM12: =IF(35='Assumption Setting'!$D$207,'Assumption Setting'!$C$207/'Timeline and FX'!AM8,0) -> 0 | AN12: =IF(36='Assumption Setting'!$D$207,'Assumption Setting'!$C$207/'Timeline and FX'!AN8,0) -> 0 | AO12: =SUM(AP12:BA12) -> 0 | AP12: =IF(37='Assumption Setting'!$D$207,'Assumption Setting'!$C$207/'Timeline and FX'!AP8,0) -> 0 | AQ12: =IF(38='Assumption Setting'!$D$207,'Assumption Setting'!$C$207/'Timeline and FX'!AQ8,0) -> 0 | AR12: =IF(39='Assumption Setting'!$D$207,'Assumption Setting'!$C$207/'Timeline and FX'!AR8,0) -> 0 | AS12: =IF(40='Assumption Setting'!$D$207,'Assumption Setting'!$C$207/'Timeline and FX'!AS8,0) -> 0 | AT12: =IF(41='Assumption Setting'!$D$207,'Assumption Setting'!$C$207/'Timeline and FX'!AT8,0) -> 0 | AU12: =IF(42='Assumption Setting'!$D$207,'Assumption Setting'!$C$207/'Timeline and FX'!AU8,0) -> 0 | AV12: =IF(43='Assumption Setting'!$D$207,'Assumption Setting'!$C$207/'Timeline and FX'!AV8,0) -> 0 | AW12: =IF(44='Assumption Setting'!$D$207,'Assumption Setting'!$C$207/'Timeline and FX'!AW8,0) -> 0 | AX12: =IF(45='Assumption Setting'!$D$207,'Assumption Setting'!$C$207/'Timeline and FX'!AX8,0) -> 0 | AY12: =IF(46='Assumption Setting'!$D$207,'Assumption Setting'!$C$207/'Timeline and FX'!AY8,0) -> 0 | AZ12: =IF(47='Assumption Setting'!$D$207,'Assumption Setting'!$C$207/'Timeline and FX'!AZ8,0) -> 0 | BA12: =IF(48='Assumption Setting'!$D$207,'Assumption Setting'!$C$207/'Timeline and FX'!BA8,0) -> 0 | BB12: =SUM(BC12:BN12) -> 0 | BC12: =IF(49='Assumption Setting'!$D$207,'Assumption Setting'!$C$207/'Timeline and FX'!BC8,0) -> 0 | BD12: =IF(50='Assumption Setting'!$D$207,'Assumption Setting'!$C$207/'Timeline and FX'!BD8,0) -> 0 | BE12: =IF(51='Assumption Setting'!$D$207,'Assumption Setting'!$C$207/'Timeline and FX'!BE8,0) -> 0 | BF12: =IF(52='Assumption Setting'!$D$207,'Assumption Setting'!$C$207/'Timeline and FX'!BF8,0) -> 0 | BG12: =IF(53='Assumption Setting'!$D$207,'Assumption Setting'!$C$207/'Timeline and FX'!BG8,0) -> 0 | BH12: =IF(54='Assumption Setting'!$D$207,'Assumption Setting'!$C$207/'Timeline and FX'!BH8,0) -> 0 | BI12: =IF(55='Assumption Setting'!$D$207,'Assumption Setting'!$C$207/'Timeline and FX'!BI8,0) -> 0 | BJ12: =IF(56='Assumption Setting'!$D$207,'Assumption Setting'!$C$207/'Timeline and FX'!BJ8,0) -> 0 | BK12: =IF(57='Assumption Setting'!$D$207,'Assumption Setting'!$C$207/'Timeline and FX'!BK8,0) -> 0 | BL12: =IF(58='Assumption Setting'!$D$207,'Assumption Setting'!$C$207/'Timeline and FX'!BL8,0) -> 0 | BM12: =IF(59='Assumption Setting'!$D$207,'Assumption Setting'!$C$207/'Timeline and FX'!BM8,0) -> 0 | BN12: =IF(60='Assumption Setting'!$D$207,'Assumption Setting'!$C$207/'Timeline and FX'!BN8,0) -> 0
A13: Total capital expenditure | B13: =SUM(C13:N13) -> 46179.162 | C13: =SUM(C6:C12) -> 44640.777 | D13: =SUM(D6:D12) -> 0 | E13: =SUM(E6:E12) -> 1538.3853 | F13: =SUM(F6:F12) -> 0 | G13: =SUM(G6:G12) -> 0 | H13: =SUM(H6:H12) -> 0 | I13: =SUM(I6:I12) -> 0 | J13: =SUM(J6:J12) -> 0 | ... N13: =SUM(N6:N12) -> 0 | O13: =SUM(P13:AA13) -> 18986.215 | P13: =SUM(P6:P12) -> 13218.538 | Q13: =SUM(Q6:Q12) -> 0 | R13: =SUM(R6:R12) -> 0 | S13: =SUM(S6:S12) -> 2166.4152 | T13: =SUM(T6:T12) -> 909.08006 | U13: =SUM(U6:U12) -> 0 | V13: =SUM(V6:V12) -> 1800.5886 | W13: =SUM(W6:W12) -> 0 | ... AA13: =SUM(AA6:AA12) -> 0 | AB13: =SUM(AC13:AN13) -> 20303.972 | AC13: =SUM(AC6:AC12) -> 15207.706 | AD13: =SUM(AD6:AD12) -> 0 | AE13: =SUM(AE6:AE12) -> 0 | AF13: =SUM(AF6:AF12) -> 861.79722 | AG13: =SUM(AG6:AG12) -> 857.6227 | AH13: =SUM(AH6:AH12) -> 0 | AI13: =SUM(AI6:AI12) -> 1698.6684 | AJ13: =SUM(AJ6:AJ12) -> 0 | ... AN13: =SUM(AN6:AN12) -> 0 | AO13: =SUM(AP13:BA13) -> 21889.776 | AP13: =SUM(AP6:AP12) -> 13055.672 | AQ13: =SUM(AQ6:AQ12) -> 820.95031 | AR13: =SUM(AR6:AR12) -> 816.97365 | AS13: =SUM(AS6:AS12) -> 813.01625 | AT13: =SUM(AT6:AT12) -> 809.07802 | AU13: =SUM(AU6:AU12) -> 805.15887 | AV13: =SUM(AV6:AV12) -> 1602.5174 | AW13: =SUM(AW6:AW12) -> 797.37743 | ... BA13: =SUM(BA6:BA12) -> 0 | BB13: =SUM(BC13:BN13) -> 26848.423 | BC13: =SUM(BC6:BC12) -> 13974.685 | BD13: =SUM(BD6:BD12) -> 1548.9628 | BE13: =SUM(BE6:BE12) -> 1541.4597 | BF13: =SUM(BF6:BF12) -> 0 | BG13: =SUM(BG6:BG12) -> 1526.5623 | BH13: =SUM(BH6:BH12) -> 1519.1677 | BI13: =SUM(BI6:BI12) -> 2267.7133 | BJ13: =SUM(BJ6:BJ12) -> 0 | ... BN13: =SUM(BN6:BN12) -> 0
A14: of which property and equipment | B14: =SUM(C14:N14) -> 44431.589 | C14: =SUM(C6:C11) -> 42893.204 | D14: =SUM(D6:D11) -> 0 | E14: =SUM(E6:E11) -> 1538.3853 | F14: =SUM(F6:F11) -> 0 | G14: =SUM(G6:G11) -> 0 | H14: =SUM(H6:H11) -> 0 | I14: =SUM(I6:I11) -> 0 | J14: =SUM(J6:J11) -> 0 | ... N14: =SUM(N6:N11) -> 0 | O14: =SUM(P14:AA14) -> 18986.215 | P14: =SUM(P6:P11) -> 13218.538 | Q14: =SUM(Q6:Q11) -> 0 | R14: =SUM(R6:R11) -> 0 | S14: =SUM(S6:S11) -> 2166.4152 | T14: =SUM(T6:T11) -> 909.08006 | U14: =SUM(U6:U11) -> 0 | V14: =SUM(V6:V11) -> 1800.5886 | W14: =SUM(W6:W11) -> 0 | ... AA14: =SUM(AA6:AA11) -> 0 | AB14: =SUM(AC14:AN14) -> 20303.972 | AC14: =SUM(AC6:AC11) -> 15207.706 | AD14: =SUM(AD6:AD11) -> 0 | AE14: =SUM(AE6:AE11) -> 0 | AF14: =SUM(AF6:AF11) -> 861.79722 | AG14: =SUM(AG6:AG11) -> 857.6227 | AH14: =SUM(AH6:AH11) -> 0 | AI14: =SUM(AI6:AI11) -> 1698.6684 | AJ14: =SUM(AJ6:AJ11) -> 0 | ... AN14: =SUM(AN6:AN11) -> 0 | AO14: =SUM(AP14:BA14) -> 21889.776 | AP14: =SUM(AP6:AP11) -> 13055.672 | AQ14: =SUM(AQ6:AQ11) -> 820.95031 | AR14: =SUM(AR6:AR11) -> 816.97365 | AS14: =SUM(AS6:AS11) -> 813.01625 | AT14: =SUM(AT6:AT11) -> 809.07802 | AU14: =SUM(AU6:AU11) -> 805.15887 | AV14: =SUM(AV6:AV11) -> 1602.5174 | AW14: =SUM(AW6:AW11) -> 797.37743 | ... BA14: =SUM(BA6:BA11) -> 0 | BB14: =SUM(BC14:BN14) -> 26848.423 | BC14: =SUM(BC6:BC11) -> 13974.685 | BD14: =SUM(BD6:BD11) -> 1548.9628 | BE14: =SUM(BE6:BE11) -> 1541.4597 | BF14: =SUM(BF6:BF11) -> 0 | BG14: =SUM(BG6:BG11) -> 1526.5623 | BH14: =SUM(BH6:BH11) -> 1519.1677 | BI14: =SUM(BI6:BI11) -> 2267.7133 | BJ14: =SUM(BJ6:BJ11) -> 0 | ... BN14: =SUM(BN6:BN11) -> 0
A15: of which intangible | B15: =SUM(C15:N15) -> 1747.5728 | C15: =C12 -> 1747.5728 | D15: =D12 -> 0 | E15: =E12 -> 0 | F15: =F12 -> 0 | G15: =G12 -> 0 | H15: =H12 -> 0 | I15: =I12 -> 0 | J15: =J12 -> 0 | ... N15: =N12 -> 0 | O15: =SUM(P15:AA15) -> 0 | P15: =P12 -> 0 | Q15: =Q12 -> 0 | R15: =R12 -> 0 | S15: =S12 -> 0 | T15: =T12 -> 0 | U15: =U12 -> 0 | V15: =V12 -> 0 | W15: =W12 -> 0 | ... AA15: =AA12 -> 0 | AB15: =SUM(AC15:AN15) -> 0 | AC15: =AC12 -> 0 | AD15: =AD12 -> 0 | AE15: =AE12 -> 0 | AF15: =AF12 -> 0 | AG15: =AG12 -> 0 | AH15: =AH12 -> 0 | AI15: =AI12 -> 0 | AJ15: =AJ12 -> 0 | ... AN15: =AN12 -> 0 | AO15: =SUM(AP15:BA15) -> 0 | AP15: =AP12 -> 0 | AQ15: =AQ12 -> 0 | AR15: =AR12 -> 0 | AS15: =AS12 -> 0 | AT15: =AT12 -> 0 | AU15: =AU12 -> 0 | AV15: =AV12 -> 0 | AW15: =AW12 -> 0 | ... BA15: =BA12 -> 0 | BB15: =SUM(BC15:BN15) -> 0 | BC15: =BC12 -> 0 | BD15: =BD12 -> 0 | BE15: =BE12 -> 0 | BF15: =BF12 -> 0 | BG15: =BG12 -> 0 | BH15: =BH12 -> 0 | BI15: =BI12 -> 0 | BJ15: =BJ12 -> 0 | ... BN15: =BN12 -> 0
A17: The founder investment already made in the product is not a purchase in this model. It sits as the opening intangible on the Depreciation and Amortization sheet.

Sheet Actuals
A1: Actuals
A2: The opening position and a grid to record each month. Type actuals into the yellow cells and the variance rows read against the model.
A3: Month number | B3: 9999 | C3: 1 | D3: 2 | E3: 3 | F3: 4 | G3: 5 | H3: 6 | I3: 7 | J3: 8 | K3: 9 | L3: 10 | M3: 11 | N3: 12 | O3: 9999 | P3: 13 | Q3: 14 | R3: 15 | S3: 16 | T3: 17 | U3: 18 | V3: 19 | W3: 20 | X3: 21 | Y3: 22 | Z3: 23 | AA3: 24 | AB3: 9999 | AC3: 25 | AD3: 26 | AE3: 27 | AF3: 28 | AG3: 29 | AH3: 30 | AI3: 31 | AJ3: 32 | AK3: 33 | AL3: 34 | AM3: 35 | AN3: 36 | AO3: 9999 | AP3: 37 | AQ3: 38 | AR3: 39 | AS3: 40 | AT3: 41 | AU3: 42 | AV3: 43 | AW3: 44 | AX3: 45 | AY3: 46 | AZ3: 47 | BA3: 48 | BB3: 9999 | BC3: 49 | BD3: 50 | BE3: 51 | BF3: 52 | BG3: 53 | BH3: 54 | BI3: 55 | BJ3: 56 | BK3: 57 | BL3: 58 | BM3: 59 | BN3: 60
A4: THE OPENING POSITION AT 31 DECEMBER 2026
A5: Active Launch (free) stores | B5: ='Assumption Setting'!$C$13 -> 0
A6: Paying Starter accounts | B6: ='Assumption Setting'!$C$14 -> 0
A7: Paying Pro accounts | B7: ='Assumption Setting'!$C$15 -> 0
A8: Paying Enterprise accounts | B8: ='Assumption Setting'!$C$16 -> 0
A9: Opening cash, USD | B9: ='Assumption Setting'!$C$17 -> 0
A10: Founder capital carried as an intangible, USD | B10: ='Assumption Setting'!$C$20 -> 58252.427
A12: ACTUALS AGAINST THE MODEL
A13: Line item | B13: Year 1 | C13: Jan 27 | D13: Feb 27 | E13: Mar 27 | F13: Apr 27 | G13: May 27 | H13: Jun 27 | I13: Jul 27 | J13: Aug 27 | K13: Sep 27 | L13: Oct 27 | M13: Nov 27 | N13: Dec 27 | O13: Year 2 | P13: Jan 28 | Q13: Feb 28 | R13: Mar 28 | S13: Apr 28 | T13: May 28 | U13: Jun 28 | V13: Jul 28 | W13: Aug 28 | X13: Sep 28 | Y13: Oct 28 | Z13: Nov 28 | AA13: Dec 28 | AB13: Year 3 | AC13: Jan 29 | AD13: Feb 29 | AE13: Mar 29 | AF13: Apr 29 | AG13: May 29 | AH13: Jun 29 | AI13: Jul 29 | AJ13: Aug 29 | AK13: Sep 29 | AL13: Oct 29 | AM13: Nov 29 | AN13: Dec 29 | AO13: Year 4 | AP13: Jan 30 | AQ13: Feb 30 | AR13: Mar 30 | AS13: Apr 30 | AT13: May 30 | AU13: Jun 30 | AV13: Jul 30 | AW13: Aug 30 | AX13: Sep 30 | AY13: Oct 30 | AZ13: Nov 30 | BA13: Dec 30 | BB13: Year 5 | BC13: Jan 31 | BD13: Feb 31 | BE13: Mar 31 | BF13: Apr 31 | BG13: May 31 | BH13: Jun 31 | BI13: Jul 31 | BJ13: Aug 31 | BK13: Sep 31 | BL13: Oct 31 | BM13: Nov 31 | BN13: Dec 31
A14: Model, Total revenue, USD | B14: =SUM(C14:N14) -> 68602.054 | C14: ='Total Revenue'!C18 -> 0 | D14: ='Total Revenue'!D18 -> 536.42548 | E14: ='Total Revenue'!E18 -> 1606.3055 | F14: ='Total Revenue'!F18 -> 2923.9978 | G14: ='Total Revenue'!G18 -> 4059.7813 | H14: ='Total Revenue'!H18 -> 5188.7 | I14: ='Total Revenue'!I18 -> 6309.2954 | J14: ='Total Revenue'!J18 -> 7420.238 | ... N14: ='Total Revenue'!N18 -> 11744.941 | O14: =SUM(P14:AA14) -> 391860.51 | P14: ='Total Revenue'!P18 -> 14243.139 | Q14: ='Total Revenue'!Q18 -> 16896.292 | R14: ='Total Revenue'!R18 -> 20131.007 | S14: ='Total Revenue'!S18 -> 23405.643 | T14: ='Total Revenue'!T18 -> 26713.929 | U14: ='Total Revenue'!U18 -> 30009.98 | V14: ='Total Revenue'!V18 -> 34948.656 | W14: ='Total Revenue'!W18 -> 38367.78 | ... AA14: ='Total Revenue'!AA18 -> 51778.747 | AB14: =SUM(AC14:AN14) -> 1221612.7 | AC14: ='Total Revenue'!AC18 -> 61799.016 | AD14: ='Total Revenue'!AD18 -> 68222.614 | AE14: ='Total Revenue'!AE18 -> 75648.419 | AF14: ='Total Revenue'!AF18 -> 83124.155 | AG14: ='Total Revenue'!AG18 -> 90639.845 | AH14: ='Total Revenue'!AH18 -> 98131.212 | AI14: ='Total Revenue'!AI18 -> 105592.37 | AJ14: ='Total Revenue'!AJ18 -> 113017.79 | ... AN14: ='Total Revenue'!AN18 -> 142264.01 | AO14: =SUM(AP14:BA14) -> 2763830.2 | AP14: ='Total Revenue'!AP18 -> 164411.15 | AQ14: ='Total Revenue'!AQ18 -> 175574.32 | AR14: ='Total Revenue'!AR18 -> 187823.61 | AS14: ='Total Revenue'!AS18 -> 200081.16 | AT14: ='Total Revenue'!AT18 -> 212336.03 | AU14: ='Total Revenue'!AU18 -> 224531.03 | AV14: ='Total Revenue'!AV18 -> 236658.93 | AW14: ='Total Revenue'!AW18 -> 248712.97 | ... BA14: ='Total Revenue'!BA18 -> 296069.4 | BB14: =SUM(BC14:BN14) -> 4998712.1 | BC14: ='Total Revenue'!BC18 -> 332663.94 | BD14: ='Total Revenue'!BD18 -> 347532.65 | BE14: ='Total Revenue'!BE18 -> 363059.64 | BF14: ='Total Revenue'!BF18 -> 378561.82 | BG14: ='Total Revenue'!BG18 -> 394028.49 | BH14: ='Total Revenue'!BH18 -> 409405.37 | BI14: ='Total Revenue'!BI18 -> 424685.22 | BJ14: ='Total Revenue'!BJ18 -> 439861.25 | ... BN14: ='Total Revenue'!BN18 -> 499405.4
A15: Actual, Total revenue, USD | B15: =SUM(C15:N15) -> 0 | O15: =SUM(P15:AA15) -> 0 | AB15: =SUM(AC15:AN15) -> 0 | AO15: =SUM(AP15:BA15) -> 0 | BB15: =SUM(BC15:BN15) -> 0
A16: Variance, actual less model | C16: =IF(ISNUMBER(C15),C15-C14,0) -> 0 | D16: =IF(ISNUMBER(D15),D15-D14,0) -> 0 | E16: =IF(ISNUMBER(E15),E15-E14,0) -> 0 | F16: =IF(ISNUMBER(F15),F15-F14,0) -> 0 | G16: =IF(ISNUMBER(G15),G15-G14,0) -> 0 | H16: =IF(ISNUMBER(H15),H15-H14,0) -> 0 | I16: =IF(ISNUMBER(I15),I15-I14,0) -> 0 | J16: =IF(ISNUMBER(J15),J15-J14,0) -> 0 | ... N16: =IF(ISNUMBER(N15),N15-N14,0) -> 0 | P16: =IF(ISNUMBER(P15),P15-P14,0) -> 0 | Q16: =IF(ISNUMBER(Q15),Q15-Q14,0) -> 0 | R16: =IF(ISNUMBER(R15),R15-R14,0) -> 0 | S16: =IF(ISNUMBER(S15),S15-S14,0) -> 0 | T16: =IF(ISNUMBER(T15),T15-T14,0) -> 0 | U16: =IF(ISNUMBER(U15),U15-U14,0) -> 0 | V16: =IF(ISNUMBER(V15),V15-V14,0) -> 0 | W16: =IF(ISNUMBER(W15),W15-W14,0) -> 0 | ... AA16: =IF(ISNUMBER(AA15),AA15-AA14,0) -> 0 | AC16: =IF(ISNUMBER(AC15),AC15-AC14,0) -> 0 | AD16: =IF(ISNUMBER(AD15),AD15-AD14,0) -> 0 | AE16: =IF(ISNUMBER(AE15),AE15-AE14,0) -> 0 | AF16: =IF(ISNUMBER(AF15),AF15-AF14,0) -> 0 | AG16: =IF(ISNUMBER(AG15),AG15-AG14,0) -> 0 | AH16: =IF(ISNUMBER(AH15),AH15-AH14,0) -> 0 | AI16: =IF(ISNUMBER(AI15),AI15-AI14,0) -> 0 | AJ16: =IF(ISNUMBER(AJ15),AJ15-AJ14,0) -> 0 | ... AN16: =IF(ISNUMBER(AN15),AN15-AN14,0) -> 0 | AP16: =IF(ISNUMBER(AP15),AP15-AP14,0) -> 0 | AQ16: =IF(ISNUMBER(AQ15),AQ15-AQ14,0) -> 0 | AR16: =IF(ISNUMBER(AR15),AR15-AR14,0) -> 0 | AS16: =IF(ISNUMBER(AS15),AS15-AS14,0) -> 0 | AT16: =IF(ISNUMBER(AT15),AT15-AT14,0) -> 0 | AU16: =IF(ISNUMBER(AU15),AU15-AU14,0) -> 0 | AV16: =IF(ISNUMBER(AV15),AV15-AV14,0) -> 0 | AW16: =IF(ISNUMBER(AW15),AW15-AW14,0) -> 0 | ... BA16: =IF(ISNUMBER(BA15),BA15-BA14,0) -> 0 | BC16: =IF(ISNUMBER(BC15),BC15-BC14,0) -> 0 | BD16: =IF(ISNUMBER(BD15),BD15-BD14,0) -> 0 | BE16: =IF(ISNUMBER(BE15),BE15-BE14,0) -> 0 | BF16: =IF(ISNUMBER(BF15),BF15-BF14,0) -> 0 | BG16: =IF(ISNUMBER(BG15),BG15-BG14,0) -> 0 | BH16: =IF(ISNUMBER(BH15),BH15-BH14,0) -> 0 | BI16: =IF(ISNUMBER(BI15),BI15-BI14,0) -> 0 | BJ16: =IF(ISNUMBER(BJ15),BJ15-BJ14,0) -> 0 | ... BN16: =IF(ISNUMBER(BN15),BN15-BN14,0) -> 0
A18: Model, Paying accounts at month end | B18: =N18 -> 319.89518 | C18: =Acquisitions!C124 -> 0 | D18: =Acquisitions!D124 -> 29.631629 | E18: =Acquisitions!E124 -> 59.232003 | F18: =Acquisitions!F124 -> 89.024873 | G18: =Acquisitions!G124 -> 118.6902 | H18: =Acquisitions!H124 -> 148.1884 | I18: =Acquisitions!I124 -> 177.48366 | J18: =Acquisitions!J124 -> 206.54371 | ... N18: =Acquisitions!N124 -> 319.89518 | O18: =AA18 -> 1234.8023 | P18: =Acquisitions!P124 -> 355.32366 | Q18: =Acquisitions!Q124 -> 436.33605 | R18: =Acquisitions!R124 -> 517.32602 | S18: =Acquisitions!S124 -> 598.55154 | T18: =Acquisitions!T124 -> 679.56772 | U18: =Acquisitions!U124 -> 760.29387 | V18: =Acquisitions!V124 -> 840.65574 | W18: =Acquisitions!W124 -> 920.58506 | ... AA18: =Acquisitions!AA124 -> 1234.8023 | AB18: =AN18 -> 3089.9291 | AC18: =Acquisitions!AC124 -> 1330.744 | AD18: =Acquisitions!AD124 -> 1492.9258 | AE18: =Acquisitions!AE124 -> 1654.9458 | AF18: =Acquisitions!AF124 -> 1817.1339 | AG18: =Acquisitions!AG124 -> 1978.8869 | AH18: =Acquisitions!AH124 -> 2140.0846 | AI18: =Acquisitions!AI124 -> 2300.6159 | AJ18: =Acquisitions!AJ124 -> 2460.3776 | ... AN18: =Acquisitions!AN124 -> 3089.9291 | AO18: =BA18 -> 6004.4174 | AP18: =Acquisitions!AP124 -> 3275.0844 | AQ18: =Acquisitions!AQ124 -> 3528.4799 | AR18: =Acquisitions!AR124 -> 3781.1594 | AS18: =Acquisitions!AS124 -> 4033.3658 | AT18: =Acquisitions!AT124 -> 4284.5567 | AU18: =Acquisitions!AU124 -> 4534.5992 | AV18: =Acquisitions!AV124 -> 4783.37 | AW18: =Acquisitions!AW124 -> 5030.7542 | ... BA18: =Acquisitions!BA124 -> 6004.4174 | BB18: =BN18 -> 9567.5154 | BC18: =Acquisitions!BC124 -> 6266.857 | BD18: =Acquisitions!BD124 -> 6573.2183 | BE18: =Acquisitions!BE124 -> 6878.6612 | BF18: =Acquisitions!BF124 -> 7183.4061 | BG18: =Acquisitions!BG124 -> 7486.9354 | BH18: =Acquisitions!BH124 -> 7789.1164 | BI18: =Acquisitions!BI124 -> 8089.8252 | BJ18: =Acquisitions!BJ124 -> 8388.9462 | ... BN18: =Acquisitions!BN124 -> 9567.5154
A19: Actual, Paying accounts at month end | B19: =N19 -> 0 | O19: =AA19 -> 0 | AB19: =AN19 -> 0 | AO19: =BA19 -> 0 | BB19: =BN19 -> 0
A20: Variance, actual less model | C20: =IF(ISNUMBER(C19),C19-C18,0) -> 0 | D20: =IF(ISNUMBER(D19),D19-D18,0) -> 0 | E20: =IF(ISNUMBER(E19),E19-E18,0) -> 0 | F20: =IF(ISNUMBER(F19),F19-F18,0) -> 0 | G20: =IF(ISNUMBER(G19),G19-G18,0) -> 0 | H20: =IF(ISNUMBER(H19),H19-H18,0) -> 0 | I20: =IF(ISNUMBER(I19),I19-I18,0) -> 0 | J20: =IF(ISNUMBER(J19),J19-J18,0) -> 0 | ... N20: =IF(ISNUMBER(N19),N19-N18,0) -> 0 | P20: =IF(ISNUMBER(P19),P19-P18,0) -> 0 | Q20: =IF(ISNUMBER(Q19),Q19-Q18,0) -> 0 | R20: =IF(ISNUMBER(R19),R19-R18,0) -> 0 | S20: =IF(ISNUMBER(S19),S19-S18,0) -> 0 | T20: =IF(ISNUMBER(T19),T19-T18,0) -> 0 | U20: =IF(ISNUMBER(U19),U19-U18,0) -> 0 | V20: =IF(ISNUMBER(V19),V19-V18,0) -> 0 | W20: =IF(ISNUMBER(W19),W19-W18,0) -> 0 | ... AA20: =IF(ISNUMBER(AA19),AA19-AA18,0) -> 0 | AC20: =IF(ISNUMBER(AC19),AC19-AC18,0) -> 0 | AD20: =IF(ISNUMBER(AD19),AD19-AD18,0) -> 0 | AE20: =IF(ISNUMBER(AE19),AE19-AE18,0) -> 0 | AF20: =IF(ISNUMBER(AF19),AF19-AF18,0) -> 0 | AG20: =IF(ISNUMBER(AG19),AG19-AG18,0) -> 0 | AH20: =IF(ISNUMBER(AH19),AH19-AH18,0) -> 0 | AI20: =IF(ISNUMBER(AI19),AI19-AI18,0) -> 0 | AJ20: =IF(ISNUMBER(AJ19),AJ19-AJ18,0) -> 0 | ... AN20: =IF(ISNUMBER(AN19),AN19-AN18,0) -> 0 | AP20: =IF(ISNUMBER(AP19),AP19-AP18,0) -> 0 | AQ20: =IF(ISNUMBER(AQ19),AQ19-AQ18,0) -> 0 | AR20: =IF(ISNUMBER(AR19),AR19-AR18,0) -> 0 | AS20: =IF(ISNUMBER(AS19),AS19-AS18,0) -> 0 | AT20: =IF(ISNUMBER(AT19),AT19-AT18,0) -> 0 | AU20: =IF(ISNUMBER(AU19),AU19-AU18,0) -> 0 | AV20: =IF(ISNUMBER(AV19),AV19-AV18,0) -> 0 | AW20: =IF(ISNUMBER(AW19),AW19-AW18,0) -> 0 | ... BA20: =IF(ISNUMBER(BA19),BA19-BA18,0) -> 0 | BC20: =IF(ISNUMBER(BC19),BC19-BC18,0) -> 0 | BD20: =IF(ISNUMBER(BD19),BD19-BD18,0) -> 0 | BE20: =IF(ISNUMBER(BE19),BE19-BE18,0) -> 0 | BF20: =IF(ISNUMBER(BF19),BF19-BF18,0) -> 0 | BG20: =IF(ISNUMBER(BG19),BG19-BG18,0) -> 0 | BH20: =IF(ISNUMBER(BH19),BH19-BH18,0) -> 0 | BI20: =IF(ISNUMBER(BI19),BI19-BI18,0) -> 0 | BJ20: =IF(ISNUMBER(BJ19),BJ19-BJ18,0) -> 0 | ... BN20: =IF(ISNUMBER(BN19),BN19-BN18,0) -> 0
A22: Model, Launch (free) stores at month end | B22: =N22 -> 4207.4483 | C22: =Acquisitions!C96 -> 396.15458 | D22: =Acquisitions!D96 -> 814.3538 | E22: =Acquisitions!E96 -> 1216.4942 | F22: =Acquisitions!F96 -> 1603.1924 | G22: =Acquisitions!G96 -> 1975.0413 | H22: =Acquisitions!H96 -> 2332.6113 | I22: =Acquisitions!I96 -> 2676.4506 | J22: =Acquisitions!J96 -> 3007.0865 | ... N22: =Acquisitions!N96 -> 4207.4483 | O22: =AA22 -> 12270 | P22: =Acquisitions!P96 -> 4964.5571 | Q22: =Acquisitions!Q96 -> 5749.3826 | R22: =Acquisitions!R96 -> 6507.524 | S22: =Acquisitions!S96 -> 7239.8886 | T22: =Acquisitions!T96 -> 7947.3528 | U22: =Acquisitions!U96 -> 8630.7632 | V22: =Acquisitions!V96 -> 9290.9377 | W22: =Acquisitions!W96 -> 9928.6662 | ... AA22: =Acquisitions!AA96 -> 12270 | AB22: =AN22 -> 24195.606 | AC22: =Acquisitions!AC96 -> 13381.989 | AD22: =Acquisitions!AD96 -> 14530.322 | AE22: =Acquisitions!AE96 -> 15642.368 | AF22: =Acquisitions!AF96 -> 16719.273 | AG22: =Acquisitions!AG96 -> 17762.147 | AH22: =Acquisitions!AH96 -> 18772.067 | AI22: =Acquisitions!AI96 -> 19750.074 | AJ22: =Acquisitions!AJ96 -> 20697.175 | ... AN22: =Acquisitions!AN96 -> 24195.606 | AO22: =BA22 -> 37855.297 | AP22: =Acquisitions!AP96 -> 25467.575 | AQ22: =Acquisitions!AQ96 -> 26774.191 | AR22: =Acquisitions!AR96 -> 28041.347 | AS22: =Acquisitions!AS96 -> 29270.234 | AT22: =Acquisitions!AT96 -> 30462.009 | AU22: =Acquisitions!AU96 -> 31617.793 | AV22: =Acquisitions!AV96 -> 32738.672 | AW22: =Acquisitions!AW96 -> 33825.701 | ... BA22: =Acquisitions!BA96 -> 37855.297 | BB22: =BN22 -> 52258.036 | BC22: =Acquisitions!BC96 -> 39220.996 | BD22: =Acquisitions!BD96 -> 40589.456 | BE22: =Acquisitions!BE96 -> 41917.957 | BF22: =Acquisitions!BF96 -> 43207.666 | BG22: =Acquisitions!BG96 -> 44459.715 | BH22: =Acquisitions!BH96 -> 45675.205 | BI22: =Acquisitions!BI96 -> 46855.202 | BJ22: =Acquisitions!BJ96 -> 48000.743 | ... BN22: =Acquisitions!BN96 -> 52258.036
A23: Actual, Launch (free) stores at month end | B23: =N23 -> 0 | O23: =AA23 -> 0 | AB23: =AN23 -> 0 | AO23: =BA23 -> 0 | BB23: =BN23 -> 0
A24: Variance, actual less model | C24: =IF(ISNUMBER(C23),C23-C22,0) -> 0 | D24: =IF(ISNUMBER(D23),D23-D22,0) -> 0 | E24: =IF(ISNUMBER(E23),E23-E22,0) -> 0 | F24: =IF(ISNUMBER(F23),F23-F22,0) -> 0 | G24: =IF(ISNUMBER(G23),G23-G22,0) -> 0 | H24: =IF(ISNUMBER(H23),H23-H22,0) -> 0 | I24: =IF(ISNUMBER(I23),I23-I22,0) -> 0 | J24: =IF(ISNUMBER(J23),J23-J22,0) -> 0 | ... N24: =IF(ISNUMBER(N23),N23-N22,0) -> 0 | P24: =IF(ISNUMBER(P23),P23-P22,0) -> 0 | Q24: =IF(ISNUMBER(Q23),Q23-Q22,0) -> 0 | R24: =IF(ISNUMBER(R23),R23-R22,0) -> 0 | S24: =IF(ISNUMBER(S23),S23-S22,0) -> 0 | T24: =IF(ISNUMBER(T23),T23-T22,0) -> 0 | U24: =IF(ISNUMBER(U23),U23-U22,0) -> 0 | V24: =IF(ISNUMBER(V23),V23-V22,0) -> 0 | W24: =IF(ISNUMBER(W23),W23-W22,0) -> 0 | ... AA24: =IF(ISNUMBER(AA23),AA23-AA22,0) -> 0 | AC24: =IF(ISNUMBER(AC23),AC23-AC22,0) -> 0 | AD24: =IF(ISNUMBER(AD23),AD23-AD22,0) -> 0 | AE24: =IF(ISNUMBER(AE23),AE23-AE22,0) -> 0 | AF24: =IF(ISNUMBER(AF23),AF23-AF22,0) -> 0 | AG24: =IF(ISNUMBER(AG23),AG23-AG22,0) -> 0 | AH24: =IF(ISNUMBER(AH23),AH23-AH22,0) -> 0 | AI24: =IF(ISNUMBER(AI23),AI23-AI22,0) -> 0 | AJ24: =IF(ISNUMBER(AJ23),AJ23-AJ22,0) -> 0 | ... AN24: =IF(ISNUMBER(AN23),AN23-AN22,0) -> 0 | AP24: =IF(ISNUMBER(AP23),AP23-AP22,0) -> 0 | AQ24: =IF(ISNUMBER(AQ23),AQ23-AQ22,0) -> 0 | AR24: =IF(ISNUMBER(AR23),AR23-AR22,0) -> 0 | AS24: =IF(ISNUMBER(AS23),AS23-AS22,0) -> 0 | AT24: =IF(ISNUMBER(AT23),AT23-AT22,0) -> 0 | AU24: =IF(ISNUMBER(AU23),AU23-AU22,0) -> 0 | AV24: =IF(ISNUMBER(AV23),AV23-AV22,0) -> 0 | AW24: =IF(ISNUMBER(AW23),AW23-AW22,0) -> 0 | ... BA24: =IF(ISNUMBER(BA23),BA23-BA22,0) -> 0 | BC24: =IF(ISNUMBER(BC23),BC23-BC22,0) -> 0 | BD24: =IF(ISNUMBER(BD23),BD23-BD22,0) -> 0 | BE24: =IF(ISNUMBER(BE23),BE23-BE22,0) -> 0 | BF24: =IF(ISNUMBER(BF23),BF23-BF22,0) -> 0 | BG24: =IF(ISNUMBER(BG23),BG23-BG22,0) -> 0 | BH24: =IF(ISNUMBER(BH23),BH23-BH22,0) -> 0 | BI24: =IF(ISNUMBER(BI23),BI23-BI22,0) -> 0 | BJ24: =IF(ISNUMBER(BJ23),BJ23-BJ22,0) -> 0 | ... BN24: =IF(ISNUMBER(BN23),BN23-BN22,0) -> 0
A26: Model, Cash at month end, USD | B26: =N26 -> 185235.3 | C26: ='Cash Flow Statement'!C34 -> 542291.82 | D26: ='Cash Flow Statement'!D34 -> 498317.68 | E26: ='Cash Flow Statement'!E34 -> 461394.87 | F26: ='Cash Flow Statement'!F34 -> 427091.9 | G26: ='Cash Flow Statement'!G34 -> 393706.65 | H26: ='Cash Flow Statement'!H34 -> 361235.1 | I26: ='Cash Flow Statement'!I34 -> 329672.09 | J26: ='Cash Flow Statement'!J34 -> 299011.42 | ... N26: ='Cash Flow Statement'!N34 -> 185235.3 | O26: =AA26 -> 237273.56 | P26: ='Cash Flow Statement'!P34 -> 593556.29 | Q26: ='Cash Flow Statement'!Q34 -> 545118.38 | R26: ='Cash Flow Statement'!R34 -> 503815.96 | S26: ='Cash Flow Statement'!S34 -> 462984.11 | T26: ='Cash Flow Statement'!T34 -> 425859.21 | U26: ='Cash Flow Statement'!U34 -> 391504.08 | V26: ='Cash Flow Statement'!V34 -> 358875.99 | W26: ='Cash Flow Statement'!W34 -> 329348.53 | ... AA26: ='Cash Flow Statement'!AA34 -> 237273.56 | AB26: =AN26 -> 188317.95 | AC26: ='Cash Flow Statement'!AC34 -> 217962.92 | AD26: ='Cash Flow Statement'!AD34 -> 182922.49 | AE26: ='Cash Flow Statement'!AE34 -> 159853.62 | AF26: ='Cash Flow Statement'!AF34 -> 141715.74 | AG26: ='Cash Flow Statement'!AG34 -> 128476.9 | AH26: ='Cash Flow Statement'!AH34 -> 121484.11 | AI26: ='Cash Flow Statement'!AI34 -> 118602.47 | AJ26: ='Cash Flow Statement'!AJ34 -> 121749.36 | ... AN26: ='Cash Flow Statement'!AN34 -> 188317.95 | AO26: =BA26 -> 1031867.6 | AP26: ='Cash Flow Statement'!AP34 -> 244212.67 | AQ26: ='Cash Flow Statement'!AQ34 -> 266467.64 | AR26: ='Cash Flow Statement'!AR34 -> 303517.29 | AS26: ='Cash Flow Statement'!AS34 -> 349577.46 | AT26: ='Cash Flow Statement'!AT34 -> 404613.42 | AU26: ='Cash Flow Statement'!AU34 -> 468526.47 | AV26: ='Cash Flow Statement'!AV34 -> 540341.75 | AW26: ='Cash Flow Statement'!AW34 -> 620865.81 | ... BA26: ='Cash Flow Statement'!BA34 -> 1031867.6 | BB26: =BN26 -> 3195853.7 | BC26: ='Cash Flow Statement'!BC34 -> 1209507 | BD26: ='Cash Flow Statement'!BD34 -> 1330089.9 | BE26: ='Cash Flow Statement'!BE34 -> 1466980.8 | BF26: ='Cash Flow Statement'!BF34 -> 1616787.1 | BG26: ='Cash Flow Statement'!BG34 -> 1777642.6 | BH26: ='Cash Flow Statement'!BH34 -> 1948267.7 | BI26: ='Cash Flow Statement'!BI34 -> 2128344.3 | BJ26: ='Cash Flow Statement'!BJ34 -> 2320844.5 | ... BN26: ='Cash Flow Statement'!BN34 -> 3195853.7
A27: Actual, Cash at month end, USD | B27: =N27 -> 0 | O27: =AA27 -> 0 | AB27: =AN27 -> 0 | AO27: =BA27 -> 0 | BB27: =BN27 -> 0
A28: Variance, actual less model | C28: =IF(ISNUMBER(C27),C27-C26,0) -> 0 | D28: =IF(ISNUMBER(D27),D27-D26,0) -> 0 | E28: =IF(ISNUMBER(E27),E27-E26,0) -> 0 | F28: =IF(ISNUMBER(F27),F27-F26,0) -> 0 | G28: =IF(ISNUMBER(G27),G27-G26,0) -> 0 | H28: =IF(ISNUMBER(H27),H27-H26,0) -> 0 | I28: =IF(ISNUMBER(I27),I27-I26,0) -> 0 | J28: =IF(ISNUMBER(J27),J27-J26,0) -> 0 | ... N28: =IF(ISNUMBER(N27),N27-N26,0) -> 0 | P28: =IF(ISNUMBER(P27),P27-P26,0) -> 0 | Q28: =IF(ISNUMBER(Q27),Q27-Q26,0) -> 0 | R28: =IF(ISNUMBER(R27),R27-R26,0) -> 0 | S28: =IF(ISNUMBER(S27),S27-S26,0) -> 0 | T28: =IF(ISNUMBER(T27),T27-T26,0) -> 0 | U28: =IF(ISNUMBER(U27),U27-U26,0) -> 0 | V28: =IF(ISNUMBER(V27),V27-V26,0) -> 0 | W28: =IF(ISNUMBER(W27),W27-W26,0) -> 0 | ... AA28: =IF(ISNUMBER(AA27),AA27-AA26,0) -> 0 | AC28: =IF(ISNUMBER(AC27),AC27-AC26,0) -> 0 | AD28: =IF(ISNUMBER(AD27),AD27-AD26,0) -> 0 | AE28: =IF(ISNUMBER(AE27),AE27-AE26,0) -> 0 | AF28: =IF(ISNUMBER(AF27),AF27-AF26,0) -> 0 | AG28: =IF(ISNUMBER(AG27),AG27-AG26,0) -> 0 | AH28: =IF(ISNUMBER(AH27),AH27-AH26,0) -> 0 | AI28: =IF(ISNUMBER(AI27),AI27-AI26,0) -> 0 | AJ28: =IF(ISNUMBER(AJ27),AJ27-AJ26,0) -> 0 | ... AN28: =IF(ISNUMBER(AN27),AN27-AN26,0) -> 0 | AP28: =IF(ISNUMBER(AP27),AP27-AP26,0) -> 0 | AQ28: =IF(ISNUMBER(AQ27),AQ27-AQ26,0) -> 0 | AR28: =IF(ISNUMBER(AR27),AR27-AR26,0) -> 0 | AS28: =IF(ISNUMBER(AS27),AS27-AS26,0) -> 0 | AT28: =IF(ISNUMBER(AT27),AT27-AT26,0) -> 0 | AU28: =IF(ISNUMBER(AU27),AU27-AU26,0) -> 0 | AV28: =IF(ISNUMBER(AV27),AV27-AV26,0) -> 0 | AW28: =IF(ISNUMBER(AW27),AW27-AW26,0) -> 0 | ... BA28: =IF(ISNUMBER(BA27),BA27-BA26,0) -> 0 | BC28: =IF(ISNUMBER(BC27),BC27-BC26,0) -> 0 | BD28: =IF(ISNUMBER(BD27),BD27-BD26,0) -> 0 | BE28: =IF(ISNUMBER(BE27),BE27-BE26,0) -> 0 | BF28: =IF(ISNUMBER(BF27),BF27-BF26,0) -> 0 | BG28: =IF(ISNUMBER(BG27),BG27-BG26,0) -> 0 | BH28: =IF(ISNUMBER(BH27),BH27-BH26,0) -> 0 | BI28: =IF(ISNUMBER(BI27),BI27-BI26,0) -> 0 | BJ28: =IF(ISNUMBER(BJ27),BJ27-BJ26,0) -> 0 | ... BN28: =IF(ISNUMBER(BN27),BN27-BN26,0) -> 0
A30: Model, Employees in post | B30: =N30 -> 24 | C30: =Payroll!C73 -> 24 | D30: =Payroll!D73 -> 24 | E30: =Payroll!E73 -> 24 | F30: =Payroll!F73 -> 24 | G30: =Payroll!G73 -> 24 | H30: =Payroll!H73 -> 24 | I30: =Payroll!I73 -> 24 | J30: =Payroll!J73 -> 24 | ... N30: =Payroll!N73 -> 24 | O30: =AA30 -> 40 | P30: =Payroll!P73 -> 36 | Q30: =Payroll!Q73 -> 36 | R30: =Payroll!R73 -> 36 | S30: =Payroll!S73 -> 36 | T30: =Payroll!T73 -> 37 | U30: =Payroll!U73 -> 37 | V30: =Payroll!V73 -> 39 | W30: =Payroll!W73 -> 39 | ... AA30: =Payroll!AA73 -> 40 | AB30: =AN30 -> 60 | AC30: =Payroll!AC73 -> 54 | AD30: =Payroll!AD73 -> 54 | AE30: =Payroll!AE73 -> 54 | AF30: =Payroll!AF73 -> 55 | AG30: =Payroll!AG73 -> 56 | AH30: =Payroll!AH73 -> 56 | AI30: =Payroll!AI73 -> 58 | AJ30: =Payroll!AJ73 -> 58 | ... AN30: =Payroll!AN73 -> 60 | AO30: =BA30 -> 84 | AP30: =Payroll!AP73 -> 73 | AQ30: =Payroll!AQ73 -> 74 | AR30: =Payroll!AR73 -> 75 | AS30: =Payroll!AS73 -> 76 | AT30: =Payroll!AT73 -> 77 | AU30: =Payroll!AU73 -> 78 | AV30: =Payroll!AV73 -> 80 | AW30: =Payroll!AW73 -> 81 | ... BA30: =Payroll!BA73 -> 84 | BB30: =BN30 -> 115 | BC30: =Payroll!BC73 -> 98 | BD30: =Payroll!BD73 -> 100 | BE30: =Payroll!BE73 -> 102 | BF30: =Payroll!BF73 -> 102 | BG30: =Payroll!BG73 -> 104 | BH30: =Payroll!BH73 -> 106 | BI30: =Payroll!BI73 -> 109 | BJ30: =Payroll!BJ73 -> 109 | ... BN30: =Payroll!BN73 -> 115
A31: Actual, Employees in post | B31: =N31 -> 0 | O31: =AA31 -> 0 | AB31: =AN31 -> 0 | AO31: =BA31 -> 0 | BB31: =BN31 -> 0
A32: Variance, actual less model | C32: =IF(ISNUMBER(C31),C31-C30,0) -> 0 | D32: =IF(ISNUMBER(D31),D31-D30,0) -> 0 | E32: =IF(ISNUMBER(E31),E31-E30,0) -> 0 | F32: =IF(ISNUMBER(F31),F31-F30,0) -> 0 | G32: =IF(ISNUMBER(G31),G31-G30,0) -> 0 | H32: =IF(ISNUMBER(H31),H31-H30,0) -> 0 | I32: =IF(ISNUMBER(I31),I31-I30,0) -> 0 | J32: =IF(ISNUMBER(J31),J31-J30,0) -> 0 | ... N32: =IF(ISNUMBER(N31),N31-N30,0) -> 0 | P32: =IF(ISNUMBER(P31),P31-P30,0) -> 0 | Q32: =IF(ISNUMBER(Q31),Q31-Q30,0) -> 0 | R32: =IF(ISNUMBER(R31),R31-R30,0) -> 0 | S32: =IF(ISNUMBER(S31),S31-S30,0) -> 0 | T32: =IF(ISNUMBER(T31),T31-T30,0) -> 0 | U32: =IF(ISNUMBER(U31),U31-U30,0) -> 0 | V32: =IF(ISNUMBER(V31),V31-V30,0) -> 0 | W32: =IF(ISNUMBER(W31),W31-W30,0) -> 0 | ... AA32: =IF(ISNUMBER(AA31),AA31-AA30,0) -> 0 | AC32: =IF(ISNUMBER(AC31),AC31-AC30,0) -> 0 | AD32: =IF(ISNUMBER(AD31),AD31-AD30,0) -> 0 | AE32: =IF(ISNUMBER(AE31),AE31-AE30,0) -> 0 | AF32: =IF(ISNUMBER(AF31),AF31-AF30,0) -> 0 | AG32: =IF(ISNUMBER(AG31),AG31-AG30,0) -> 0 | AH32: =IF(ISNUMBER(AH31),AH31-AH30,0) -> 0 | AI32: =IF(ISNUMBER(AI31),AI31-AI30,0) -> 0 | AJ32: =IF(ISNUMBER(AJ31),AJ31-AJ30,0) -> 0 | ... AN32: =IF(ISNUMBER(AN31),AN31-AN30,0) -> 0 | AP32: =IF(ISNUMBER(AP31),AP31-AP30,0) -> 0 | AQ32: =IF(ISNUMBER(AQ31),AQ31-AQ30,0) -> 0 | AR32: =IF(ISNUMBER(AR31),AR31-AR30,0) -> 0 | AS32: =IF(ISNUMBER(AS31),AS31-AS30,0) -> 0 | AT32: =IF(ISNUMBER(AT31),AT31-AT30,0) -> 0 | AU32: =IF(ISNUMBER(AU31),AU31-AU30,0) -> 0 | AV32: =IF(ISNUMBER(AV31),AV31-AV30,0) -> 0 | AW32: =IF(ISNUMBER(AW31),AW31-AW30,0) -> 0 | ... BA32: =IF(ISNUMBER(BA31),BA31-BA30,0) -> 0 | BC32: =IF(ISNUMBER(BC31),BC31-BC30,0) -> 0 | BD32: =IF(ISNUMBER(BD31),BD31-BD30,0) -> 0 | BE32: =IF(ISNUMBER(BE31),BE31-BE30,0) -> 0 | BF32: =IF(ISNUMBER(BF31),BF31-BF30,0) -> 0 | BG32: =IF(ISNUMBER(BG31),BG31-BG30,0) -> 0 | BH32: =IF(ISNUMBER(BH31),BH31-BH30,0) -> 0 | BI32: =IF(ISNUMBER(BI31),BI31-BI30,0) -> 0 | BJ32: =IF(ISNUMBER(BJ31),BJ31-BJ30,0) -> 0 | ... BN32: =IF(ISNUMBER(BN31),BN31-BN30,0) -> 0

Sheet Process>>
B2: Process
B5: Timeline and FX | C5: The calendar, the pound rate and the cost indices
B6: Acquisitions | C6: Spend to activity to signups to paying accounts, sixty months
B7: GTM Capacity and Timing | C7: Who runs the activity, whether there are enough of them, and how long a deal takes
B8: Revenue Streams | C8: Eight engines, every one of them an output of the account engine
B9: Total Revenue | C9: Gathered into four families
B10: Payroll | C10: Roles monthly, with heads set by year
B11: Depreciation and Amortization | C11: Straight line by asset class
B12: Expenses | C12: Direct cost, revenue share, operating cost, and the first twelve months in full

Sheet Timeline and FX
A1: Timeline and FX
A2: The calendar, the pound rate and the cost indices that every other sheet reads.
A3: Month number | B3: 9999 | C3: 1 | D3: 2 | E3: 3 | F3: 4 | G3: 5 | H3: 6 | I3: 7 | J3: 8 | K3: 9 | L3: 10 | M3: 11 | N3: 12 | O3: 9999 | P3: 13 | Q3: 14 | R3: 15 | S3: 16 | T3: 17 | U3: 18 | V3: 19 | W3: 20 | X3: 21 | Y3: 22 | Z3: 23 | AA3: 24 | AB3: 9999 | AC3: 25 | AD3: 26 | AE3: 27 | AF3: 28 | AG3: 29 | AH3: 30 | AI3: 31 | AJ3: 32 | AK3: 33 | AL3: 34 | AM3: 35 | AN3: 36 | AO3: 9999 | AP3: 37 | AQ3: 38 | AR3: 39 | AS3: 40 | AT3: 41 | AU3: 42 | AV3: 43 | AW3: 44 | AX3: 45 | AY3: 46 | AZ3: 47 | BA3: 48 | BB3: 9999 | BC3: 49 | BD3: 50 | BE3: 51 | BF3: 52 | BG3: 53 | BH3: 54 | BI3: 55 | BJ3: 56 | BK3: 57 | BL3: 58 | BM3: 59 | BN3: 60
A4: CALENDAR AND PRICE LEVELS
A5: Line item | B5: Year 1 | C5: Jan 27 | D5: Feb 27 | E5: Mar 27 | F5: Apr 27 | G5: May 27 | H5: Jun 27 | I5: Jul 27 | J5: Aug 27 | K5: Sep 27 | L5: Oct 27 | M5: Nov 27 | N5: Dec 27 | O5: Year 2 | P5: Jan 28 | Q5: Feb 28 | R5: Mar 28 | S5: Apr 28 | T5: May 28 | U5: Jun 28 | V5: Jul 28 | W5: Aug 28 | X5: Sep 28 | Y5: Oct 28 | Z5: Nov 28 | AA5: Dec 28 | AB5: Year 3 | AC5: Jan 29 | AD5: Feb 29 | AE5: Mar 29 | AF5: Apr 29 | AG5: May 29 | AH5: Jun 29 | AI5: Jul 29 | AJ5: Aug 29 | AK5: Sep 29 | AL5: Oct 29 | AM5: Nov 29 | AN5: Dec 29 | AO5: Year 4 | AP5: Jan 30 | AQ5: Feb 30 | AR5: Mar 30 | AS5: Apr 30 | AT5: May 30 | AU5: Jun 30 | AV5: Jul 30 | AW5: Aug 30 | AX5: Sep 30 | AY5: Oct 30 | AZ5: Nov 30 | BA5: Dec 30 | BB5: Year 5 | BC5: Jan 31 | BD5: Feb 31 | BE5: Mar 31 | BF5: Apr 31 | BG5: May 31 | BH5: Jun 31 | BI5: Jul 31 | BJ5: Aug 31 | BK5: Sep 31 | BL5: Oct 31 | BM5: Nov 31 | BN5: Dec 31
A6: Calendar month | C6: =EDATE('Assumption Setting'!$C$6,0) -> 46388 | D6: =EDATE('Assumption Setting'!$C$6,1) -> 46419 | E6: =EDATE('Assumption Setting'!$C$6,2) -> 46447 | F6: =EDATE('Assumption Setting'!$C$6,3) -> 46478 | G6: =EDATE('Assumption Setting'!$C$6,4) -> 46508 | H6: =EDATE('Assumption Setting'!$C$6,5) -> 46539 | I6: =EDATE('Assumption Setting'!$C$6,6) -> 46569 | J6: =EDATE('Assumption Setting'!$C$6,7) -> 46600 | K6: =EDATE('Assumption Setting'!$C$6,8) -> 46631 | L6: =EDATE('Assumption Setting'!$C$6,9) -> 46661 | M6: =EDATE('Assumption Setting'!$C$6,10) -> 46692 | N6: =EDATE('Assumption Setting'!$C$6,11) -> 46722 | P6: =EDATE('Assumption Setting'!$C$6,12) -> 46753 | Q6: =EDATE('Assumption Setting'!$C$6,13) -> 46784 | R6: =EDATE('Assumption Setting'!$C$6,14) -> 46813 | S6: =EDATE('Assumption Setting'!$C$6,15) -> 46844 | T6: =EDATE('Assumption Setting'!$C$6,16) -> 46874 | U6: =EDATE('Assumption Setting'!$C$6,17) -> 46905 | V6: =EDATE('Assumption Setting'!$C$6,18) -> 46935 | W6: =EDATE('Assumption Setting'!$C$6,19) -> 46966 | X6: =EDATE('Assumption Setting'!$C$6,20) -> 46997 | Y6: =EDATE('Assumption Setting'!$C$6,21) -> 47027 | Z6: =EDATE('Assumption Setting'!$C$6,22) -> 47058 | AA6: =EDATE('Assumption Setting'!$C$6,23) -> 47088 | AC6: =EDATE('Assumption Setting'!$C$6,24) -> 47119 | AD6: =EDATE('Assumption Setting'!$C$6,25) -> 47150 | AE6: =EDATE('Assumption Setting'!$C$6,26) -> 47178 | AF6: =EDATE('Assumption Setting'!$C$6,27) -> 47209 | AG6: =EDATE('Assumption Setting'!$C$6,28) -> 47239 | AH6: =EDATE('Assumption Setting'!$C$6,29) -> 47270 | AI6: =EDATE('Assumption Setting'!$C$6,30) -> 47300 | AJ6: =EDATE('Assumption Setting'!$C$6,31) -> 47331 | AK6: =EDATE('Assumption Setting'!$C$6,32) -> 47362 | AL6: =EDATE('Assumption Setting'!$C$6,33) -> 47392 | AM6: =EDATE('Assumption Setting'!$C$6,34) -> 47423 | AN6: =EDATE('Assumption Setting'!$C$6,35) -> 47453 | AP6: =EDATE('Assumption Setting'!$C$6,36) -> 47484 | AQ6: =EDATE('Assumption Setting'!$C$6,37) -> 47515 | AR6: =EDATE('Assumption Setting'!$C$6,38) -> 47543 | AS6: =EDATE('Assumption Setting'!$C$6,39) -> 47574 | AT6: =EDATE('Assumption Setting'!$C$6,40) -> 47604 | AU6: =EDATE('Assumption Setting'!$C$6,41) -> 47635 | AV6: =EDATE('Assumption Setting'!$C$6,42) -> 47665 | AW6: =EDATE('Assumption Setting'!$C$6,43) -> 47696 | AX6: =EDATE('Assumption Setting'!$C$6,44) -> 47727 | AY6: =EDATE('Assumption Setting'!$C$6,45) -> 47757 | AZ6: =EDATE('Assumption Setting'!$C$6,46) -> 47788 | BA6: =EDATE('Assumption Setting'!$C$6,47) -> 47818 | BC6: =EDATE('Assumption Setting'!$C$6,48) -> 47849 | BD6: =EDATE('Assumption Setting'!$C$6,49) -> 47880 | BE6: =EDATE('Assumption Setting'!$C$6,50) -> 47908 | BF6: =EDATE('Assumption Setting'!$C$6,51) -> 47939 | BG6: =EDATE('Assumption Setting'!$C$6,52) -> 47969 | BH6: =EDATE('Assumption Setting'!$C$6,53) -> 48000 | BI6: =EDATE('Assumption Setting'!$C$6,54) -> 48030 | BJ6: =EDATE('Assumption Setting'!$C$6,55) -> 48061 | BK6: =EDATE('Assumption Setting'!$C$6,56) -> 48092 | BL6: =EDATE('Assumption Setting'!$C$6,57) -> 48122 | BM6: =EDATE('Assumption Setting'!$C$6,58) -> 48153 | BN6: =EDATE('Assumption Setting'!$C$6,59) -> 48183
A7: Model year | C7: 1 | D7: 1 | E7: 1 | F7: 1 | G7: 1 | H7: 1 | I7: 1 | J7: 1 | K7: 1 | L7: 1 | M7: 1 | N7: 1 | P7: 2 | Q7: 2 | R7: 2 | S7: 2 | T7: 2 | U7: 2 | V7: 2 | W7: 2 | X7: 2 | Y7: 2 | Z7: 2 | AA7: 2 | AC7: 3 | AD7: 3 | AE7: 3 | AF7: 3 | AG7: 3 | AH7: 3 | AI7: 3 | AJ7: 3 | AK7: 3 | AL7: 3 | AM7: 3 | AN7: 3 | AP7: 4 | AQ7: 4 | AR7: 4 | AS7: 4 | AT7: 4 | AU7: 4 | AV7: 4 | AW7: 4 | AX7: 4 | AY7: 4 | AZ7: 4 | BA7: 4 | BC7: 5 | BD7: 5 | BE7: 5 | BF7: 5 | BG7: 5 | BH7: 5 | BI7: 5 | BJ7: 5 | BK7: 5 | BL7: 5 | BM7: 5 | BN7: 5
A8: Egyptian pounds to the dollar | B8: =IFERROR(AVERAGE(C8:N8),0) -> 52.901351 | C8: ='Assumption Setting'!$C$7*(1+'Assumption Setting'!$C$8)^((1-1)/12) -> 51.5 | D8: ='Assumption Setting'!$C$7*(1+'Assumption Setting'!$C$8)^((2-1)/12) -> 51.750679 | E8: ='Assumption Setting'!$C$7*(1+'Assumption Setting'!$C$8)^((3-1)/12) -> 52.002578 | F8: ='Assumption Setting'!$C$7*(1+'Assumption Setting'!$C$8)^((4-1)/12) -> 52.255703 | G8: ='Assumption Setting'!$C$7*(1+'Assumption Setting'!$C$8)^((5-1)/12) -> 52.51006 | H8: ='Assumption Setting'!$C$7*(1+'Assumption Setting'!$C$8)^((6-1)/12) -> 52.765656 | I8: ='Assumption Setting'!$C$7*(1+'Assumption Setting'!$C$8)^((7-1)/12) -> 53.022495 | J8: ='Assumption Setting'!$C$7*(1+'Assumption Setting'!$C$8)^((8-1)/12) -> 53.280585 | K8: ='Assumption Setting'!$C$7*(1+'Assumption Setting'!$C$8)^((9-1)/12) -> 53.539931 | L8: ='Assumption Setting'!$C$7*(1+'Assumption Setting'!$C$8)^((10-1)/12) -> 53.800539 | M8: ='Assumption Setting'!$C$7*(1+'Assumption Setting'!$C$8)^((11-1)/12) -> 54.062416 | N8: ='Assumption Setting'!$C$7*(1+'Assumption Setting'!$C$8)^((12-1)/12) -> 54.325568 | O8: =IFERROR(AVERAGE(P8:AA8),0) -> 56.075432 | P8: ='Assumption Setting'!$C$7*(1+'Assumption Setting'!$C$8)^((13-1)/12) -> 54.59 | Q8: ='Assumption Setting'!$C$7*(1+'Assumption Setting'!$C$8)^((14-1)/12) -> 54.85572 | R8: ='Assumption Setting'!$C$7*(1+'Assumption Setting'!$C$8)^((15-1)/12) -> 55.122733 | S8: ='Assumption Setting'!$C$7*(1+'Assumption Setting'!$C$8)^((16-1)/12) -> 55.391045 | T8: ='Assumption Setting'!$C$7*(1+'Assumption Setting'!$C$8)^((17-1)/12) -> 55.660664 | U8: ='Assumption Setting'!$C$7*(1+'Assumption Setting'!$C$8)^((18-1)/12) -> 55.931595 | V8: ='Assumption Setting'!$C$7*(1+'Assumption Setting'!$C$8)^((19-1)/12) -> 56.203845 | W8: ='Assumption Setting'!$C$7*(1+'Assumption Setting'!$C$8)^((20-1)/12) -> 56.47742 | X8: ='Assumption Setting'!$C$7*(1+'Assumption Setting'!$C$8)^((21-1)/12) -> 56.752327 | Y8: ='Assumption Setting'!$C$7*(1+'Assumption Setting'!$C$8)^((22-1)/12) -> 57.028572 | Z8: ='Assumption Setting'!$C$7*(1+'Assumption Setting'!$C$8)^((23-1)/12) -> 57.306161 | AA8: ='Assumption Setting'!$C$7*(1+'Assumption Setting'!$C$8)^((24-1)/12) -> 57.585102 | AB8: =IFERROR(AVERAGE(AC8:AN8),0) -> 59.439958 | AC8: ='Assumption Setting'!$C$7*(1+'Assumption Setting'!$C$8)^((25-1)/12) -> 57.8654 | AD8: ='Assumption Setting'!$C$7*(1+'Assumption Setting'!$C$8)^((26-1)/12) -> 58.147063 | AE8: ='Assumption Setting'!$C$7*(1+'Assumption Setting'!$C$8)^((27-1)/12) -> 58.430097 | AF8: ='Assumption Setting'!$C$7*(1+'Assumption Setting'!$C$8)^((28-1)/12) -> 58.714508 | AG8: ='Assumption Setting'!$C$7*(1+'Assumption Setting'!$C$8)^((29-1)/12) -> 59.000304 | AH8: ='Assumption Setting'!$C$7*(1+'Assumption Setting'!$C$8)^((30-1)/12) -> 59.287491 | AI8: ='Assumption Setting'!$C$7*(1+'Assumption Setting'!$C$8)^((31-1)/12) -> 59.576076 | AJ8: ='Assumption Setting'!$C$7*(1+'Assumption Setting'!$C$8)^((32-1)/12) -> 59.866065 | AK8: ='Assumption Setting'!$C$7*(1+'Assumption Setting'!$C$8)^((33-1)/12) -> 60.157466 | AL8: ='Assumption Setting'!$C$7*(1+'Assumption Setting'!$C$8)^((34-1)/12) -> 60.450286 | AM8: ='Assumption Setting'!$C$7*(1+'Assumption Setting'!$C$8)^((35-1)/12) -> 60.744531 | AN8: ='Assumption Setting'!$C$7*(1+'Assumption Setting'!$C$8)^((36-1)/12) -> 61.040208 | AO8: =IFERROR(AVERAGE(AP8:BA8),0) -> 63.006355 | AP8: ='Assumption Setting'!$C$7*(1+'Assumption Setting'!$C$8)^((37-1)/12) -> 61.337324 | AQ8: ='Assumption Setting'!$C$7*(1+'Assumption Setting'!$C$8)^((38-1)/12) -> 61.635887 | AR8: ='Assumption Setting'!$C$7*(1+'Assumption Setting'!$C$8)^((39-1)/12) -> 61.935902 | AS8: ='Assumption Setting'!$C$7*(1+'Assumption Setting'!$C$8)^((40-1)/12) -> 62.237378 | AT8: ='Assumption Setting'!$C$7*(1+'Assumption Setting'!$C$8)^((41-1)/12) -> 62.540322 | AU8: ='Assumption Setting'!$C$7*(1+'Assumption Setting'!$C$8)^((42-1)/12) -> 62.84474 | AV8: ='Assumption Setting'!$C$7*(1+'Assumption Setting'!$C$8)^((43-1)/12) -> 63.15064 | AW8: ='Assumption Setting'!$C$7*(1+'Assumption Setting'!$C$8)^((44-1)/12) -> 63.458029 | AX8: ='Assumption Setting'!$C$7*(1+'Assumption Setting'!$C$8)^((45-1)/12) -> 63.766914 | AY8: ='Assumption Setting'!$C$7*(1+'Assumption Setting'!$C$8)^((46-1)/12) -> 64.077303 | AZ8: ='Assumption Setting'!$C$7*(1+'Assumption Setting'!$C$8)^((47-1)/12) -> 64.389202 | BA8: ='Assumption Setting'!$C$7*(1+'Assumption Setting'!$C$8)^((48-1)/12) -> 64.70262 | BB8: =IFERROR(AVERAGE(BC8:BN8),0) -> 66.786737 | BC8: ='Assumption Setting'!$C$7*(1+'Assumption Setting'!$C$8)^((49-1)/12) -> 65.017563 | BD8: ='Assumption Setting'!$C$7*(1+'Assumption Setting'!$C$8)^((50-1)/12) -> 65.33404 | BE8: ='Assumption Setting'!$C$7*(1+'Assumption Setting'!$C$8)^((51-1)/12) -> 65.652056 | BF8: ='Assumption Setting'!$C$7*(1+'Assumption Setting'!$C$8)^((52-1)/12) -> 65.971621 | BG8: ='Assumption Setting'!$C$7*(1+'Assumption Setting'!$C$8)^((53-1)/12) -> 66.292741 | BH8: ='Assumption Setting'!$C$7*(1+'Assumption Setting'!$C$8)^((54-1)/12) -> 66.615425 | BI8: ='Assumption Setting'!$C$7*(1+'Assumption Setting'!$C$8)^((55-1)/12) -> 66.939679 | BJ8: ='Assumption Setting'!$C$7*(1+'Assumption Setting'!$C$8)^((56-1)/12) -> 67.265511 | BK8: ='Assumption Setting'!$C$7*(1+'Assumption Setting'!$C$8)^((57-1)/12) -> 67.592929 | BL8: ='Assumption Setting'!$C$7*(1+'Assumption Setting'!$C$8)^((58-1)/12) -> 67.921941 | BM8: ='Assumption Setting'!$C$7*(1+'Assumption Setting'!$C$8)^((59-1)/12) -> 68.252555 | BN8: ='Assumption Setting'!$C$7*(1+'Assumption Setting'!$C$8)^((60-1)/12) -> 68.584777
A9: Price index on list prices | B9: =N9 -> 1 | C9: ='Assumption Setting'!$C$96 -> 1 | D9: ='Assumption Setting'!$C$96 -> 1 | E9: ='Assumption Setting'!$C$96 -> 1 | F9: ='Assumption Setting'!$C$96 -> 1 | G9: ='Assumption Setting'!$C$96 -> 1 | H9: ='Assumption Setting'!$C$96 -> 1 | I9: ='Assumption Setting'!$C$96 -> 1 | J9: ='Assumption Setting'!$C$96 -> 1 | ... N9: ='Assumption Setting'!$C$96 -> 1 | O9: =AA9 -> 1.08 | P9: ='Assumption Setting'!$D$96 -> 1.08 | Q9: ='Assumption Setting'!$D$96 -> 1.08 | R9: ='Assumption Setting'!$D$96 -> 1.08 | S9: ='Assumption Setting'!$D$96 -> 1.08 | T9: ='Assumption Setting'!$D$96 -> 1.08 | U9: ='Assumption Setting'!$D$96 -> 1.08 | V9: ='Assumption Setting'!$D$96 -> 1.08 | W9: ='Assumption Setting'!$D$96 -> 1.08 | ... AA9: ='Assumption Setting'!$D$96 -> 1.08 | AB9: =AN9 -> 1.1664 | AC9: ='Assumption Setting'!$E$96 -> 1.1664 | AD9: ='Assumption Setting'!$E$96 -> 1.1664 | AE9: ='Assumption Setting'!$E$96 -> 1.1664 | AF9: ='Assumption Setting'!$E$96 -> 1.1664 | AG9: ='Assumption Setting'!$E$96 -> 1.1664 | AH9: ='Assumption Setting'!$E$96 -> 1.1664 | AI9: ='Assumption Setting'!$E$96 -> 1.1664 | AJ9: ='Assumption Setting'!$E$96 -> 1.1664 | ... AN9: ='Assumption Setting'!$E$96 -> 1.1664 | AO9: =BA9 -> 1.248048 | AP9: ='Assumption Setting'!$F$96 -> 1.248048 | AQ9: ='Assumption Setting'!$F$96 -> 1.248048 | AR9: ='Assumption Setting'!$F$96 -> 1.248048 | AS9: ='Assumption Setting'!$F$96 -> 1.248048 | AT9: ='Assumption Setting'!$F$96 -> 1.248048 | AU9: ='Assumption Setting'!$F$96 -> 1.248048 | AV9: ='Assumption Setting'!$F$96 -> 1.248048 | AW9: ='Assumption Setting'!$F$96 -> 1.248048 | ... BA9: ='Assumption Setting'!$F$96 -> 1.248048 | BB9: =BN9 -> 1.3229309 | BC9: ='Assumption Setting'!$G$96 -> 1.3229309 | BD9: ='Assumption Setting'!$G$96 -> 1.3229309 | BE9: ='Assumption Setting'!$G$96 -> 1.3229309 | BF9: ='Assumption Setting'!$G$96 -> 1.3229309 | BG9: ='Assumption Setting'!$G$96 -> 1.3229309 | BH9: ='Assumption Setting'!$G$96 -> 1.3229309 | BI9: ='Assumption Setting'!$G$96 -> 1.3229309 | BJ9: ='Assumption Setting'!$G$96 -> 1.3229309 | ... BN9: ='Assumption Setting'!$G$96 -> 1.3229309
A10: Payment value index per account | B10: =N10 -> 1 | C10: ='Assumption Setting'!$C$112 -> 1 | D10: ='Assumption Setting'!$C$112 -> 1 | E10: ='Assumption Setting'!$C$112 -> 1 | F10: ='Assumption Setting'!$C$112 -> 1 | G10: ='Assumption Setting'!$C$112 -> 1 | H10: ='Assumption Setting'!$C$112 -> 1 | I10: ='Assumption Setting'!$C$112 -> 1 | J10: ='Assumption Setting'!$C$112 -> 1 | ... N10: ='Assumption Setting'!$C$112 -> 1 | O10: =AA10 -> 1.12 | P10: ='Assumption Setting'!$D$112 -> 1.12 | Q10: ='Assumption Setting'!$D$112 -> 1.12 | R10: ='Assumption Setting'!$D$112 -> 1.12 | S10: ='Assumption Setting'!$D$112 -> 1.12 | T10: ='Assumption Setting'!$D$112 -> 1.12 | U10: ='Assumption Setting'!$D$112 -> 1.12 | V10: ='Assumption Setting'!$D$112 -> 1.12 | W10: ='Assumption Setting'!$D$112 -> 1.12 | ... AA10: ='Assumption Setting'!$D$112 -> 1.12 | AB10: =AN10 -> 1.2544 | AC10: ='Assumption Setting'!$E$112 -> 1.2544 | AD10: ='Assumption Setting'!$E$112 -> 1.2544 | AE10: ='Assumption Setting'!$E$112 -> 1.2544 | AF10: ='Assumption Setting'!$E$112 -> 1.2544 | AG10: ='Assumption Setting'!$E$112 -> 1.2544 | AH10: ='Assumption Setting'!$E$112 -> 1.2544 | AI10: ='Assumption Setting'!$E$112 -> 1.2544 | AJ10: ='Assumption Setting'!$E$112 -> 1.2544 | ... AN10: ='Assumption Setting'!$E$112 -> 1.2544 | AO10: =BA10 -> 1.392384 | AP10: ='Assumption Setting'!$F$112 -> 1.392384 | AQ10: ='Assumption Setting'!$F$112 -> 1.392384 | AR10: ='Assumption Setting'!$F$112 -> 1.392384 | AS10: ='Assumption Setting'!$F$112 -> 1.392384 | AT10: ='Assumption Setting'!$F$112 -> 1.392384 | AU10: ='Assumption Setting'!$F$112 -> 1.392384 | AV10: ='Assumption Setting'!$F$112 -> 1.392384 | AW10: ='Assumption Setting'!$F$112 -> 1.392384 | ... BA10: ='Assumption Setting'!$F$112 -> 1.392384 | BB10: =BN10 -> 1.5316224 | BC10: ='Assumption Setting'!$G$112 -> 1.5316224 | BD10: ='Assumption Setting'!$G$112 -> 1.5316224 | BE10: ='Assumption Setting'!$G$112 -> 1.5316224 | BF10: ='Assumption Setting'!$G$112 -> 1.5316224 | BG10: ='Assumption Setting'!$G$112 -> 1.5316224 | BH10: ='Assumption Setting'!$G$112 -> 1.5316224 | BI10: ='Assumption Setting'!$G$112 -> 1.5316224 | BJ10: ='Assumption Setting'!$G$112 -> 1.5316224 | ... BN10: ='Assumption Setting'!$G$112 -> 1.5316224
A11: Operating cost index, dollar costs | B11: =N11 -> 1 | C11: ='Assumption Setting'!$C$161 -> 1 | D11: ='Assumption Setting'!$C$161 -> 1 | E11: ='Assumption Setting'!$C$161 -> 1 | F11: ='Assumption Setting'!$C$161 -> 1 | G11: ='Assumption Setting'!$C$161 -> 1 | H11: ='Assumption Setting'!$C$161 -> 1 | I11: ='Assumption Setting'!$C$161 -> 1 | J11: ='Assumption Setting'!$C$161 -> 1 | ... N11: ='Assumption Setting'!$C$161 -> 1 | O11: =AA11 -> 1.08 | P11: ='Assumption Setting'!$D$161 -> 1.08 | Q11: ='Assumption Setting'!$D$161 -> 1.08 | R11: ='Assumption Setting'!$D$161 -> 1.08 | S11: ='Assumption Setting'!$D$161 -> 1.08 | T11: ='Assumption Setting'!$D$161 -> 1.08 | U11: ='Assumption Setting'!$D$161 -> 1.08 | V11: ='Assumption Setting'!$D$161 -> 1.08 | W11: ='Assumption Setting'!$D$161 -> 1.08 | ... AA11: ='Assumption Setting'!$D$161 -> 1.08 | AB11: =AN11 -> 1.1664 | AC11: ='Assumption Setting'!$E$161 -> 1.1664 | AD11: ='Assumption Setting'!$E$161 -> 1.1664 | AE11: ='Assumption Setting'!$E$161 -> 1.1664 | AF11: ='Assumption Setting'!$E$161 -> 1.1664 | AG11: ='Assumption Setting'!$E$161 -> 1.1664 | AH11: ='Assumption Setting'!$E$161 -> 1.1664 | AI11: ='Assumption Setting'!$E$161 -> 1.1664 | AJ11: ='Assumption Setting'!$E$161 -> 1.1664 | ... AN11: ='Assumption Setting'!$E$161 -> 1.1664 | AO11: =BA11 -> 1.248048 | AP11: ='Assumption Setting'!$F$161 -> 1.248048 | AQ11: ='Assumption Setting'!$F$161 -> 1.248048 | AR11: ='Assumption Setting'!$F$161 -> 1.248048 | AS11: ='Assumption Setting'!$F$161 -> 1.248048 | AT11: ='Assumption Setting'!$F$161 -> 1.248048 | AU11: ='Assumption Setting'!$F$161 -> 1.248048 | AV11: ='Assumption Setting'!$F$161 -> 1.248048 | AW11: ='Assumption Setting'!$F$161 -> 1.248048 | ... BA11: ='Assumption Setting'!$F$161 -> 1.248048 | BB11: =BN11 -> 1.3229309 | BC11: ='Assumption Setting'!$G$161 -> 1.3229309 | BD11: ='Assumption Setting'!$G$161 -> 1.3229309 | BE11: ='Assumption Setting'!$G$161 -> 1.3229309 | BF11: ='Assumption Setting'!$G$161 -> 1.3229309 | BG11: ='Assumption Setting'!$G$161 -> 1.3229309 | BH11: ='Assumption Setting'!$G$161 -> 1.3229309 | BI11: ='Assumption Setting'!$G$161 -> 1.3229309 | BJ11: ='Assumption Setting'!$G$161 -> 1.3229309 | ... BN11: ='Assumption Setting'!$G$161 -> 1.3229309
A12: Salary index | B12: =N12 -> 1 | C12: =(1+Payroll!$C$37)^0 -> 1 | D12: =(1+Payroll!$C$37)^0 -> 1 | E12: =(1+Payroll!$C$37)^0 -> 1 | F12: =(1+Payroll!$C$37)^0 -> 1 | G12: =(1+Payroll!$C$37)^0 -> 1 | H12: =(1+Payroll!$C$37)^0 -> 1 | I12: =(1+Payroll!$C$37)^0 -> 1 | J12: =(1+Payroll!$C$37)^0 -> 1 | ... N12: =(1+Payroll!$C$37)^0 -> 1 | O12: =AA12 -> 1.12 | P12: =(1+Payroll!$C$37)^1 -> 1.12 | Q12: =(1+Payroll!$C$37)^1 -> 1.12 | R12: =(1+Payroll!$C$37)^1 -> 1.12 | S12: =(1+Payroll!$C$37)^1 -> 1.12 | T12: =(1+Payroll!$C$37)^1 -> 1.12 | U12: =(1+Payroll!$C$37)^1 -> 1.12 | V12: =(1+Payroll!$C$37)^1 -> 1.12 | W12: =(1+Payroll!$C$37)^1 -> 1.12 | ... AA12: =(1+Payroll!$C$37)^1 -> 1.12 | AB12: =AN12 -> 1.2544 | AC12: =(1+Payroll!$C$37)^2 -> 1.2544 | AD12: =(1+Payroll!$C$37)^2 -> 1.2544 | AE12: =(1+Payroll!$C$37)^2 -> 1.2544 | AF12: =(1+Payroll!$C$37)^2 -> 1.2544 | AG12: =(1+Payroll!$C$37)^2 -> 1.2544 | AH12: =(1+Payroll!$C$37)^2 -> 1.2544 | AI12: =(1+Payroll!$C$37)^2 -> 1.2544 | AJ12: =(1+Payroll!$C$37)^2 -> 1.2544 | ... AN12: =(1+Payroll!$C$37)^2 -> 1.2544 | AO12: =BA12 -> 1.404928 | AP12: =(1+Payroll!$C$37)^3 -> 1.404928 | AQ12: =(1+Payroll!$C$37)^3 -> 1.404928 | AR12: =(1+Payroll!$C$37)^3 -> 1.404928 | AS12: =(1+Payroll!$C$37)^3 -> 1.404928 | AT12: =(1+Payroll!$C$37)^3 -> 1.404928 | AU12: =(1+Payroll!$C$37)^3 -> 1.404928 | AV12: =(1+Payroll!$C$37)^3 -> 1.404928 | AW12: =(1+Payroll!$C$37)^3 -> 1.404928 | ... BA12: =(1+Payroll!$C$37)^3 -> 1.404928 | BB12: =BN12 -> 1.5735194 | BC12: =(1+Payroll!$C$37)^4 -> 1.5735194 | BD12: =(1+Payroll!$C$37)^4 -> 1.5735194 | BE12: =(1+Payroll!$C$37)^4 -> 1.5735194 | BF12: =(1+Payroll!$C$37)^4 -> 1.5735194 | BG12: =(1+Payroll!$C$37)^4 -> 1.5735194 | BH12: =(1+Payroll!$C$37)^4 -> 1.5735194 | BI12: =(1+Payroll!$C$37)^4 -> 1.5735194 | BJ12: =(1+Payroll!$C$37)^4 -> 1.5735194 | ... BN12: =(1+Payroll!$C$37)^4 -> 1.5735194
A13: Insurable wage ceiling per month, EGP | B13: =N13 -> 19300 | C13: =Payroll!$C$38*(1+Payroll!$C$40)^0 -> 19300 | D13: =Payroll!$C$38*(1+Payroll!$C$40)^0 -> 19300 | E13: =Payroll!$C$38*(1+Payroll!$C$40)^0 -> 19300 | F13: =Payroll!$C$38*(1+Payroll!$C$40)^0 -> 19300 | G13: =Payroll!$C$38*(1+Payroll!$C$40)^0 -> 19300 | H13: =Payroll!$C$38*(1+Payroll!$C$40)^0 -> 19300 | I13: =Payroll!$C$38*(1+Payroll!$C$40)^0 -> 19300 | J13: =Payroll!$C$38*(1+Payroll!$C$40)^0 -> 19300 | ... N13: =Payroll!$C$38*(1+Payroll!$C$40)^0 -> 19300 | O13: =AA13 -> 22195 | P13: =Payroll!$C$38*(1+Payroll!$C$40)^1 -> 22195 | Q13: =Payroll!$C$38*(1+Payroll!$C$40)^1 -> 22195 | R13: =Payroll!$C$38*(1+Payroll!$C$40)^1 -> 22195 | S13: =Payroll!$C$38*(1+Payroll!$C$40)^1 -> 22195 | T13: =Payroll!$C$38*(1+Payroll!$C$40)^1 -> 22195 | U13: =Payroll!$C$38*(1+Payroll!$C$40)^1 -> 22195 | V13: =Payroll!$C$38*(1+Payroll!$C$40)^1 -> 22195 | W13: =Payroll!$C$38*(1+Payroll!$C$40)^1 -> 22195 | ... AA13: =Payroll!$C$38*(1+Payroll!$C$40)^1 -> 22195 | AB13: =AN13 -> 25524.25 | AC13: =Payroll!$C$38*(1+Payroll!$C$40)^2 -> 25524.25 | AD13: =Payroll!$C$38*(1+Payroll!$C$40)^2 -> 25524.25 | AE13: =Payroll!$C$38*(1+Payroll!$C$40)^2 -> 25524.25 | AF13: =Payroll!$C$38*(1+Payroll!$C$40)^2 -> 25524.25 | AG13: =Payroll!$C$38*(1+Payroll!$C$40)^2 -> 25524.25 | AH13: =Payroll!$C$38*(1+Payroll!$C$40)^2 -> 25524.25 | AI13: =Payroll!$C$38*(1+Payroll!$C$40)^2 -> 25524.25 | AJ13: =Payroll!$C$38*(1+Payroll!$C$40)^2 -> 25524.25 | ... AN13: =Payroll!$C$38*(1+Payroll!$C$40)^2 -> 25524.25 | AO13: =BA13 -> 29352.888 | AP13: =Payroll!$C$38*(1+Payroll!$C$40)^3 -> 29352.888 | AQ13: =Payroll!$C$38*(1+Payroll!$C$40)^3 -> 29352.888 | AR13: =Payroll!$C$38*(1+Payroll!$C$40)^3 -> 29352.888 | AS13: =Payroll!$C$38*(1+Payroll!$C$40)^3 -> 29352.888 | AT13: =Payroll!$C$38*(1+Payroll!$C$40)^3 -> 29352.888 | AU13: =Payroll!$C$38*(1+Payroll!$C$40)^3 -> 29352.888 | AV13: =Payroll!$C$38*(1+Payroll!$C$40)^3 -> 29352.888 | AW13: =Payroll!$C$38*(1+Payroll!$C$40)^3 -> 29352.888 | ... BA13: =Payroll!$C$38*(1+Payroll!$C$40)^3 -> 29352.888 | BB13: =BN13 -> 33755.821 | BC13: =Payroll!$C$38*(1+Payroll!$C$40)^4 -> 33755.821 | BD13: =Payroll!$C$38*(1+Payroll!$C$40)^4 -> 33755.821 | BE13: =Payroll!$C$38*(1+Payroll!$C$40)^4 -> 33755.821 | BF13: =Payroll!$C$38*(1+Payroll!$C$40)^4 -> 33755.821 | BG13: =Payroll!$C$38*(1+Payroll!$C$40)^4 -> 33755.821 | BH13: =Payroll!$C$38*(1+Payroll!$C$40)^4 -> 33755.821 | BI13: =Payroll!$C$38*(1+Payroll!$C$40)^4 -> 33755.821 | BJ13: =Payroll!$C$38*(1+Payroll!$C$40)^4 -> 33755.821 | ... BN13: =Payroll!$C$38*(1+Payroll!$C$40)^4 -> 33755.821
A14: Insurable wage floor per month, EGP | B14: =N14 -> 3200 | C14: =Payroll!$C$39*(1+Payroll!$C$40)^0 -> 3200 | D14: =Payroll!$C$39*(1+Payroll!$C$40)^0 -> 3200 | E14: =Payroll!$C$39*(1+Payroll!$C$40)^0 -> 3200 | F14: =Payroll!$C$39*(1+Payroll!$C$40)^0 -> 3200 | G14: =Payroll!$C$39*(1+Payroll!$C$40)^0 -> 3200 | H14: =Payroll!$C$39*(1+Payroll!$C$40)^0 -> 3200 | I14: =Payroll!$C$39*(1+Payroll!$C$40)^0 -> 3200 | J14: =Payroll!$C$39*(1+Payroll!$C$40)^0 -> 3200 | ... N14: =Payroll!$C$39*(1+Payroll!$C$40)^0 -> 3200 | O14: =AA14 -> 3680 | P14: =Payroll!$C$39*(1+Payroll!$C$40)^1 -> 3680 | Q14: =Payroll!$C$39*(1+Payroll!$C$40)^1 -> 3680 | R14: =Payroll!$C$39*(1+Payroll!$C$40)^1 -> 3680 | S14: =Payroll!$C$39*(1+Payroll!$C$40)^1 -> 3680 | T14: =Payroll!$C$39*(1+Payroll!$C$40)^1 -> 3680 | U14: =Payroll!$C$39*(1+Payroll!$C$40)^1 -> 3680 | V14: =Payroll!$C$39*(1+Payroll!$C$40)^1 -> 3680 | W14: =Payroll!$C$39*(1+Payroll!$C$40)^1 -> 3680 | ... AA14: =Payroll!$C$39*(1+Payroll!$C$40)^1 -> 3680 | AB14: =AN14 -> 4232 | AC14: =Payroll!$C$39*(1+Payroll!$C$40)^2 -> 4232 | AD14: =Payroll!$C$39*(1+Payroll!$C$40)^2 -> 4232 | AE14: =Payroll!$C$39*(1+Payroll!$C$40)^2 -> 4232 | AF14: =Payroll!$C$39*(1+Payroll!$C$40)^2 -> 4232 | AG14: =Payroll!$C$39*(1+Payroll!$C$40)^2 -> 4232 | AH14: =Payroll!$C$39*(1+Payroll!$C$40)^2 -> 4232 | AI14: =Payroll!$C$39*(1+Payroll!$C$40)^2 -> 4232 | AJ14: =Payroll!$C$39*(1+Payroll!$C$40)^2 -> 4232 | ... AN14: =Payroll!$C$39*(1+Payroll!$C$40)^2 -> 4232 | AO14: =BA14 -> 4866.8 | AP14: =Payroll!$C$39*(1+Payroll!$C$40)^3 -> 4866.8 | AQ14: =Payroll!$C$39*(1+Payroll!$C$40)^3 -> 4866.8 | AR14: =Payroll!$C$39*(1+Payroll!$C$40)^3 -> 4866.8 | AS14: =Payroll!$C$39*(1+Payroll!$C$40)^3 -> 4866.8 | AT14: =Payroll!$C$39*(1+Payroll!$C$40)^3 -> 4866.8 | AU14: =Payroll!$C$39*(1+Payroll!$C$40)^3 -> 4866.8 | AV14: =Payroll!$C$39*(1+Payroll!$C$40)^3 -> 4866.8 | AW14: =Payroll!$C$39*(1+Payroll!$C$40)^3 -> 4866.8 | ... BA14: =Payroll!$C$39*(1+Payroll!$C$40)^3 -> 4866.8 | BB14: =BN14 -> 5596.82 | BC14: =Payroll!$C$39*(1+Payroll!$C$40)^4 -> 5596.82 | BD14: =Payroll!$C$39*(1+Payroll!$C$40)^4 -> 5596.82 | BE14: =Payroll!$C$39*(1+Payroll!$C$40)^4 -> 5596.82 | BF14: =Payroll!$C$39*(1+Payroll!$C$40)^4 -> 5596.82 | BG14: =Payroll!$C$39*(1+Payroll!$C$40)^4 -> 5596.82 | BH14: =Payroll!$C$39*(1+Payroll!$C$40)^4 -> 5596.82 | BI14: =Payroll!$C$39*(1+Payroll!$C$40)^4 -> 5596.82 | BJ14: =Payroll!$C$39*(1+Payroll!$C$40)^4 -> 5596.82 | ... BN14: =Payroll!$C$39*(1+Payroll!$C$40)^4 -> 5596.82

Sheet Acquisitions
A1: Acquisitions
A2: Spend to activity to signups to paying accounts, sixty months. No account count is typed: every one is produced here from the assumptions.
A3: Month number | B3: 9999 | C3: 1 | D3: 2 | E3: 3 | F3: 4 | G3: 5 | H3: 6 | I3: 7 | J3: 8 | K3: 9 | L3: 10 | M3: 11 | N3: 12 | O3: 9999 | P3: 13 | Q3: 14 | R3: 15 | S3: 16 | T3: 17 | U3: 18 | V3: 19 | W3: 20 | X3: 21 | Y3: 22 | Z3: 23 | AA3: 24 | AB3: 9999 | AC3: 25 | AD3: 26 | AE3: 27 | AF3: 28 | AG3: 29 | AH3: 30 | AI3: 31 | AJ3: 32 | AK3: 33 | AL3: 34 | AM3: 35 | AN3: 36 | AO3: 9999 | AP3: 37 | AQ3: 38 | AR3: 39 | AS3: 40 | AT3: 41 | AU3: 42 | AV3: 43 | AW3: 44 | AX3: 45 | AY3: 46 | AZ3: 47 | BA3: 48 | BB3: 9999 | BC3: 49 | BD3: 50 | BE3: 51 | BF3: 52 | BG3: 53 | BH3: 54 | BI3: 55 | BJ3: 56 | BK3: 57 | BL3: 58 | BM3: 59 | BN3: 60
A4: 1. ONLINE CHANNELS, MONTHLY BUDGET, USD
A5: Line item | B5: Year 1 | C5: Jan 27 | D5: Feb 27 | E5: Mar 27 | F5: Apr 27 | G5: May 27 | H5: Jun 27 | I5: Jul 27 | J5: Aug 27 | K5: Sep 27 | L5: Oct 27 | M5: Nov 27 | N5: Dec 27 | O5: Year 2 | P5: Jan 28 | Q5: Feb 28 | R5: Mar 28 | S5: Apr 28 | T5: May 28 | U5: Jun 28 | V5: Jul 28 | W5: Aug 28 | X5: Sep 28 | Y5: Oct 28 | Z5: Nov 28 | AA5: Dec 28 | AB5: Year 3 | AC5: Jan 29 | AD5: Feb 29 | AE5: Mar 29 | AF5: Apr 29 | AG5: May 29 | AH5: Jun 29 | AI5: Jul 29 | AJ5: Aug 29 | AK5: Sep 29 | AL5: Oct 29 | AM5: Nov 29 | AN5: Dec 29 | AO5: Year 4 | AP5: Jan 30 | AQ5: Feb 30 | AR5: Mar 30 | AS5: Apr 30 | AT5: May 30 | AU5: Jun 30 | AV5: Jul 30 | AW5: Aug 30 | AX5: Sep 30 | AY5: Oct 30 | AZ5: Nov 30 | BA5: Dec 30 | BB5: Year 5 | BC5: Jan 31 | BD5: Feb 31 | BE5: Mar 31 | BF5: Apr 31 | BG5: May 31 | BH5: Jun 31 | BI5: Jul 31 | BJ5: Aug 31 | BK5: Sep 31 | BL5: Oct 31 | BM5: Nov 31 | BN5: Dec 31
A6: Meta and Instagram ads, merchants | B6: =SUM(C6:N6) -> 9600 | C6: ='Assumption Setting'!$C$25 -> 800 | D6: ='Assumption Setting'!$C$25 -> 800 | E6: ='Assumption Setting'!$C$25 -> 800 | F6: ='Assumption Setting'!$C$25 -> 800 | G6: ='Assumption Setting'!$C$25 -> 800 | H6: ='Assumption Setting'!$C$25 -> 800 | I6: ='Assumption Setting'!$C$25 -> 800 | J6: ='Assumption Setting'!$C$25 -> 800 | ... N6: ='Assumption Setting'!$C$25 -> 800 | O6: =SUM(P6:AA6) -> 24000 | P6: ='Assumption Setting'!$D$25 -> 2000 | Q6: ='Assumption Setting'!$D$25 -> 2000 | R6: ='Assumption Setting'!$D$25 -> 2000 | S6: ='Assumption Setting'!$D$25 -> 2000 | T6: ='Assumption Setting'!$D$25 -> 2000 | U6: ='Assumption Setting'!$D$25 -> 2000 | V6: ='Assumption Setting'!$D$25 -> 2000 | W6: ='Assumption Setting'!$D$25 -> 2000 | ... AA6: ='Assumption Setting'!$D$25 -> 2000 | AB6: =SUM(AC6:AN6) -> 43200 | AC6: ='Assumption Setting'!$E$25 -> 3600 | AD6: ='Assumption Setting'!$E$25 -> 3600 | AE6: ='Assumption Setting'!$E$25 -> 3600 | AF6: ='Assumption Setting'!$E$25 -> 3600 | AG6: ='Assumption Setting'!$E$25 -> 3600 | AH6: ='Assumption Setting'!$E$25 -> 3600 | AI6: ='Assumption Setting'!$E$25 -> 3600 | AJ6: ='Assumption Setting'!$E$25 -> 3600 | ... AN6: ='Assumption Setting'!$E$25 -> 3600 | AO6: =SUM(AP6:BA6) -> 62400 | AP6: ='Assumption Setting'!$F$25 -> 5200 | AQ6: ='Assumption Setting'!$F$25 -> 5200 | AR6: ='Assumption Setting'!$F$25 -> 5200 | AS6: ='Assumption Setting'!$F$25 -> 5200 | AT6: ='Assumption Setting'!$F$25 -> 5200 | AU6: ='Assumption Setting'!$F$25 -> 5200 | AV6: ='Assumption Setting'!$F$25 -> 5200 | AW6: ='Assumption Setting'!$F$25 -> 5200 | ... BA6: ='Assumption Setting'!$F$25 -> 5200 | BB6: =SUM(BC6:BN6) -> 81600 | BC6: ='Assumption Setting'!$G$25 -> 6800 | BD6: ='Assumption Setting'!$G$25 -> 6800 | BE6: ='Assumption Setting'!$G$25 -> 6800 | BF6: ='Assumption Setting'!$G$25 -> 6800 | BG6: ='Assumption Setting'!$G$25 -> 6800 | BH6: ='Assumption Setting'!$G$25 -> 6800 | BI6: ='Assumption Setting'!$G$25 -> 6800 | BJ6: ='Assumption Setting'!$G$25 -> 6800 | ... BN6: ='Assumption Setting'!$G$25 -> 6800
A7: Google Search, store builder and POS intent | B7: =SUM(C7:N7) -> 6000 | C7: ='Assumption Setting'!$C$26 -> 500 | D7: ='Assumption Setting'!$C$26 -> 500 | E7: ='Assumption Setting'!$C$26 -> 500 | F7: ='Assumption Setting'!$C$26 -> 500 | G7: ='Assumption Setting'!$C$26 -> 500 | H7: ='Assumption Setting'!$C$26 -> 500 | I7: ='Assumption Setting'!$C$26 -> 500 | J7: ='Assumption Setting'!$C$26 -> 500 | ... N7: ='Assumption Setting'!$C$26 -> 500 | O7: =SUM(P7:AA7) -> 15600 | P7: ='Assumption Setting'!$D$26 -> 1300 | Q7: ='Assumption Setting'!$D$26 -> 1300 | R7: ='Assumption Setting'!$D$26 -> 1300 | S7: ='Assumption Setting'!$D$26 -> 1300 | T7: ='Assumption Setting'!$D$26 -> 1300 | U7: ='Assumption Setting'!$D$26 -> 1300 | V7: ='Assumption Setting'!$D$26 -> 1300 | W7: ='Assumption Setting'!$D$26 -> 1300 | ... AA7: ='Assumption Setting'!$D$26 -> 1300 | AB7: =SUM(AC7:AN7) -> 27600 | AC7: ='Assumption Setting'!$E$26 -> 2300 | AD7: ='Assumption Setting'!$E$26 -> 2300 | AE7: ='Assumption Setting'!$E$26 -> 2300 | AF7: ='Assumption Setting'!$E$26 -> 2300 | AG7: ='Assumption Setting'!$E$26 -> 2300 | AH7: ='Assumption Setting'!$E$26 -> 2300 | AI7: ='Assumption Setting'!$E$26 -> 2300 | AJ7: ='Assumption Setting'!$E$26 -> 2300 | ... AN7: ='Assumption Setting'!$E$26 -> 2300 | AO7: =SUM(AP7:BA7) -> 39600 | AP7: ='Assumption Setting'!$F$26 -> 3300 | AQ7: ='Assumption Setting'!$F$26 -> 3300 | AR7: ='Assumption Setting'!$F$26 -> 3300 | AS7: ='Assumption Setting'!$F$26 -> 3300 | AT7: ='Assumption Setting'!$F$26 -> 3300 | AU7: ='Assumption Setting'!$F$26 -> 3300 | AV7: ='Assumption Setting'!$F$26 -> 3300 | AW7: ='Assumption Setting'!$F$26 -> 3300 | ... BA7: ='Assumption Setting'!$F$26 -> 3300 | BB7: =SUM(BC7:BN7) -> 51600 | BC7: ='Assumption Setting'!$G$26 -> 4300 | BD7: ='Assumption Setting'!$G$26 -> 4300 | BE7: ='Assumption Setting'!$G$26 -> 4300 | BF7: ='Assumption Setting'!$G$26 -> 4300 | BG7: ='Assumption Setting'!$G$26 -> 4300 | BH7: ='Assumption Setting'!$G$26 -> 4300 | BI7: ='Assumption Setting'!$G$26 -> 4300 | BJ7: ='Assumption Setting'!$G$26 -> 4300 | ... BN7: ='Assumption Setting'!$G$26 -> 4300
A8: TikTok and short video, sellers | B8: =SUM(C8:N8) -> 3600 | C8: ='Assumption Setting'!$C$27 -> 300 | D8: ='Assumption Setting'!$C$27 -> 300 | E8: ='Assumption Setting'!$C$27 -> 300 | F8: ='Assumption Setting'!$C$27 -> 300 | G8: ='Assumption Setting'!$C$27 -> 300 | H8: ='Assumption Setting'!$C$27 -> 300 | I8: ='Assumption Setting'!$C$27 -> 300 | J8: ='Assumption Setting'!$C$27 -> 300 | ... N8: ='Assumption Setting'!$C$27 -> 300 | O8: =SUM(P8:AA8) -> 8400 | P8: ='Assumption Setting'!$D$27 -> 700 | Q8: ='Assumption Setting'!$D$27 -> 700 | R8: ='Assumption Setting'!$D$27 -> 700 | S8: ='Assumption Setting'!$D$27 -> 700 | T8: ='Assumption Setting'!$D$27 -> 700 | U8: ='Assumption Setting'!$D$27 -> 700 | V8: ='Assumption Setting'!$D$27 -> 700 | W8: ='Assumption Setting'!$D$27 -> 700 | ... AA8: ='Assumption Setting'!$D$27 -> 700 | AB8: =SUM(AC8:AN8) -> 15600 | AC8: ='Assumption Setting'!$E$27 -> 1300 | AD8: ='Assumption Setting'!$E$27 -> 1300 | AE8: ='Assumption Setting'!$E$27 -> 1300 | AF8: ='Assumption Setting'!$E$27 -> 1300 | AG8: ='Assumption Setting'!$E$27 -> 1300 | AH8: ='Assumption Setting'!$E$27 -> 1300 | AI8: ='Assumption Setting'!$E$27 -> 1300 | AJ8: ='Assumption Setting'!$E$27 -> 1300 | ... AN8: ='Assumption Setting'!$E$27 -> 1300 | AO8: =SUM(AP8:BA8) -> 22800 | AP8: ='Assumption Setting'!$F$27 -> 1900 | AQ8: ='Assumption Setting'!$F$27 -> 1900 | AR8: ='Assumption Setting'!$F$27 -> 1900 | AS8: ='Assumption Setting'!$F$27 -> 1900 | AT8: ='Assumption Setting'!$F$27 -> 1900 | AU8: ='Assumption Setting'!$F$27 -> 1900 | AV8: ='Assumption Setting'!$F$27 -> 1900 | AW8: ='Assumption Setting'!$F$27 -> 1900 | ... BA8: ='Assumption Setting'!$F$27 -> 1900 | BB8: =SUM(BC8:BN8) -> 28800 | BC8: ='Assumption Setting'!$G$27 -> 2400 | BD8: ='Assumption Setting'!$G$27 -> 2400 | BE8: ='Assumption Setting'!$G$27 -> 2400 | BF8: ='Assumption Setting'!$G$27 -> 2400 | BG8: ='Assumption Setting'!$G$27 -> 2400 | BH8: ='Assumption Setting'!$G$27 -> 2400 | BI8: ='Assumption Setting'!$G$27 -> 2400 | BJ8: ='Assumption Setting'!$G$27 -> 2400 | ... BN8: ='Assumption Setting'!$G$27 -> 2400
A9: Retargeting, trial starters | B9: =SUM(C9:N9) -> 2400 | C9: ='Assumption Setting'!$C$28 -> 200 | D9: ='Assumption Setting'!$C$28 -> 200 | E9: ='Assumption Setting'!$C$28 -> 200 | F9: ='Assumption Setting'!$C$28 -> 200 | G9: ='Assumption Setting'!$C$28 -> 200 | H9: ='Assumption Setting'!$C$28 -> 200 | I9: ='Assumption Setting'!$C$28 -> 200 | J9: ='Assumption Setting'!$C$28 -> 200 | ... N9: ='Assumption Setting'!$C$28 -> 200 | O9: =SUM(P9:AA9) -> 5400 | P9: ='Assumption Setting'!$D$28 -> 450 | Q9: ='Assumption Setting'!$D$28 -> 450 | R9: ='Assumption Setting'!$D$28 -> 450 | S9: ='Assumption Setting'!$D$28 -> 450 | T9: ='Assumption Setting'!$D$28 -> 450 | U9: ='Assumption Setting'!$D$28 -> 450 | V9: ='Assumption Setting'!$D$28 -> 450 | W9: ='Assumption Setting'!$D$28 -> 450 | ... AA9: ='Assumption Setting'!$D$28 -> 450 | AB9: =SUM(AC9:AN9) -> 9600 | AC9: ='Assumption Setting'!$E$28 -> 800 | AD9: ='Assumption Setting'!$E$28 -> 800 | AE9: ='Assumption Setting'!$E$28 -> 800 | AF9: ='Assumption Setting'!$E$28 -> 800 | AG9: ='Assumption Setting'!$E$28 -> 800 | AH9: ='Assumption Setting'!$E$28 -> 800 | AI9: ='Assumption Setting'!$E$28 -> 800 | AJ9: ='Assumption Setting'!$E$28 -> 800 | ... AN9: ='Assumption Setting'!$E$28 -> 800 | AO9: =SUM(AP9:BA9) -> 13200 | AP9: ='Assumption Setting'!$F$28 -> 1100 | AQ9: ='Assumption Setting'!$F$28 -> 1100 | AR9: ='Assumption Setting'!$F$28 -> 1100 | AS9: ='Assumption Setting'!$F$28 -> 1100 | AT9: ='Assumption Setting'!$F$28 -> 1100 | AU9: ='Assumption Setting'!$F$28 -> 1100 | AV9: ='Assumption Setting'!$F$28 -> 1100 | AW9: ='Assumption Setting'!$F$28 -> 1100 | ... BA9: ='Assumption Setting'!$F$28 -> 1100 | BB9: =SUM(BC9:BN9) -> 16800 | BC9: ='Assumption Setting'!$G$28 -> 1400 | BD9: ='Assumption Setting'!$G$28 -> 1400 | BE9: ='Assumption Setting'!$G$28 -> 1400 | BF9: ='Assumption Setting'!$G$28 -> 1400 | BG9: ='Assumption Setting'!$G$28 -> 1400 | BH9: ='Assumption Setting'!$G$28 -> 1400 | BI9: ='Assumption Setting'!$G$28 -> 1400 | BJ9: ='Assumption Setting'!$G$28 -> 1400 | ... BN9: ='Assumption Setting'!$G$28 -> 1400
A10: Content and SEO, Arabic commerce guides | B10: =SUM(C10:N10) -> 9996 | C10: ='Assumption Setting'!$C$29 -> 833 | D10: ='Assumption Setting'!$C$29 -> 833 | E10: ='Assumption Setting'!$C$29 -> 833 | F10: ='Assumption Setting'!$C$29 -> 833 | G10: ='Assumption Setting'!$C$29 -> 833 | H10: ='Assumption Setting'!$C$29 -> 833 | I10: ='Assumption Setting'!$C$29 -> 833 | J10: ='Assumption Setting'!$C$29 -> 833 | ... N10: ='Assumption Setting'!$C$29 -> 833 | O10: =SUM(P10:AA10) -> 18000 | P10: ='Assumption Setting'!$D$29 -> 1500 | Q10: ='Assumption Setting'!$D$29 -> 1500 | R10: ='Assumption Setting'!$D$29 -> 1500 | S10: ='Assumption Setting'!$D$29 -> 1500 | T10: ='Assumption Setting'!$D$29 -> 1500 | U10: ='Assumption Setting'!$D$29 -> 1500 | V10: ='Assumption Setting'!$D$29 -> 1500 | W10: ='Assumption Setting'!$D$29 -> 1500 | ... AA10: ='Assumption Setting'!$D$29 -> 1500 | AB10: =SUM(AC10:AN10) -> 28800 | AC10: ='Assumption Setting'!$E$29 -> 2400 | AD10: ='Assumption Setting'!$E$29 -> 2400 | AE10: ='Assumption Setting'!$E$29 -> 2400 | AF10: ='Assumption Setting'!$E$29 -> 2400 | AG10: ='Assumption Setting'!$E$29 -> 2400 | AH10: ='Assumption Setting'!$E$29 -> 2400 | AI10: ='Assumption Setting'!$E$29 -> 2400 | AJ10: ='Assumption Setting'!$E$29 -> 2400 | ... AN10: ='Assumption Setting'!$E$29 -> 2400 | AO10: =SUM(AP10:BA10) -> 38400 | AP10: ='Assumption Setting'!$F$29 -> 3200 | AQ10: ='Assumption Setting'!$F$29 -> 3200 | AR10: ='Assumption Setting'!$F$29 -> 3200 | AS10: ='Assumption Setting'!$F$29 -> 3200 | AT10: ='Assumption Setting'!$F$29 -> 3200 | AU10: ='Assumption Setting'!$F$29 -> 3200 | AV10: ='Assumption Setting'!$F$29 -> 3200 | AW10: ='Assumption Setting'!$F$29 -> 3200 | ... BA10: ='Assumption Setting'!$F$29 -> 3200 | BB10: =SUM(BC10:BN10) -> 48000 | BC10: ='Assumption Setting'!$G$29 -> 4000 | BD10: ='Assumption Setting'!$G$29 -> 4000 | BE10: ='Assumption Setting'!$G$29 -> 4000 | BF10: ='Assumption Setting'!$G$29 -> 4000 | BG10: ='Assumption Setting'!$G$29 -> 4000 | BH10: ='Assumption Setting'!$G$29 -> 4000 | BI10: ='Assumption Setting'!$G$29 -> 4000 | BJ10: ='Assumption Setting'!$G$29 -> 4000 | ... BN10: ='Assumption Setting'!$G$29 -> 4000
A11: Merchant referral program credits | B11: =SUM(C11:N11) -> 5004 | C11: ='Assumption Setting'!$C$30 -> 417 | D11: ='Assumption Setting'!$C$30 -> 417 | E11: ='Assumption Setting'!$C$30 -> 417 | F11: ='Assumption Setting'!$C$30 -> 417 | G11: ='Assumption Setting'!$C$30 -> 417 | H11: ='Assumption Setting'!$C$30 -> 417 | I11: ='Assumption Setting'!$C$30 -> 417 | J11: ='Assumption Setting'!$C$30 -> 417 | ... N11: ='Assumption Setting'!$C$30 -> 417 | O11: =SUM(P11:AA11) -> 10800 | P11: ='Assumption Setting'!$D$30 -> 900 | Q11: ='Assumption Setting'!$D$30 -> 900 | R11: ='Assumption Setting'!$D$30 -> 900 | S11: ='Assumption Setting'!$D$30 -> 900 | T11: ='Assumption Setting'!$D$30 -> 900 | U11: ='Assumption Setting'!$D$30 -> 900 | V11: ='Assumption Setting'!$D$30 -> 900 | W11: ='Assumption Setting'!$D$30 -> 900 | ... AA11: ='Assumption Setting'!$D$30 -> 900 | AB11: =SUM(AC11:AN11) -> 18000 | AC11: ='Assumption Setting'!$E$30 -> 1500 | AD11: ='Assumption Setting'!$E$30 -> 1500 | AE11: ='Assumption Setting'!$E$30 -> 1500 | AF11: ='Assumption Setting'!$E$30 -> 1500 | AG11: ='Assumption Setting'!$E$30 -> 1500 | AH11: ='Assumption Setting'!$E$30 -> 1500 | AI11: ='Assumption Setting'!$E$30 -> 1500 | AJ11: ='Assumption Setting'!$E$30 -> 1500 | ... AN11: ='Assumption Setting'!$E$30 -> 1500 | AO11: =SUM(AP11:BA11) -> 25200 | AP11: ='Assumption Setting'!$F$30 -> 2100 | AQ11: ='Assumption Setting'!$F$30 -> 2100 | AR11: ='Assumption Setting'!$F$30 -> 2100 | AS11: ='Assumption Setting'!$F$30 -> 2100 | AT11: ='Assumption Setting'!$F$30 -> 2100 | AU11: ='Assumption Setting'!$F$30 -> 2100 | AV11: ='Assumption Setting'!$F$30 -> 2100 | AW11: ='Assumption Setting'!$F$30 -> 2100 | ... BA11: ='Assumption Setting'!$F$30 -> 2100 | BB11: =SUM(BC11:BN11) -> 32400 | BC11: ='Assumption Setting'!$G$30 -> 2700 | BD11: ='Assumption Setting'!$G$30 -> 2700 | BE11: ='Assumption Setting'!$G$30 -> 2700 | BF11: ='Assumption Setting'!$G$30 -> 2700 | BG11: ='Assumption Setting'!$G$30 -> 2700 | BH11: ='Assumption Setting'!$G$30 -> 2700 | BI11: ='Assumption Setting'!$G$30 -> 2700 | BJ11: ='Assumption Setting'!$G$30 -> 2700 | ... BN11: ='Assumption Setting'!$G$30 -> 2700
A12: Seller communities and social groups | B12: =SUM(C12:N12) -> 3600 | C12: ='Assumption Setting'!$C$31 -> 300 | D12: ='Assumption Setting'!$C$31 -> 300 | E12: ='Assumption Setting'!$C$31 -> 300 | F12: ='Assumption Setting'!$C$31 -> 300 | G12: ='Assumption Setting'!$C$31 -> 300 | H12: ='Assumption Setting'!$C$31 -> 300 | I12: ='Assumption Setting'!$C$31 -> 300 | J12: ='Assumption Setting'!$C$31 -> 300 | ... N12: ='Assumption Setting'!$C$31 -> 300 | O12: =SUM(P12:AA12) -> 7800 | P12: ='Assumption Setting'!$D$31 -> 650 | Q12: ='Assumption Setting'!$D$31 -> 650 | R12: ='Assumption Setting'!$D$31 -> 650 | S12: ='Assumption Setting'!$D$31 -> 650 | T12: ='Assumption Setting'!$D$31 -> 650 | U12: ='Assumption Setting'!$D$31 -> 650 | V12: ='Assumption Setting'!$D$31 -> 650 | W12: ='Assumption Setting'!$D$31 -> 650 | ... AA12: ='Assumption Setting'!$D$31 -> 650 | AB12: =SUM(AC12:AN12) -> 13200 | AC12: ='Assumption Setting'!$E$31 -> 1100 | AD12: ='Assumption Setting'!$E$31 -> 1100 | AE12: ='Assumption Setting'!$E$31 -> 1100 | AF12: ='Assumption Setting'!$E$31 -> 1100 | AG12: ='Assumption Setting'!$E$31 -> 1100 | AH12: ='Assumption Setting'!$E$31 -> 1100 | AI12: ='Assumption Setting'!$E$31 -> 1100 | AJ12: ='Assumption Setting'!$E$31 -> 1100 | ... AN12: ='Assumption Setting'!$E$31 -> 1100 | AO12: =SUM(AP12:BA12) -> 18000 | AP12: ='Assumption Setting'!$F$31 -> 1500 | AQ12: ='Assumption Setting'!$F$31 -> 1500 | AR12: ='Assumption Setting'!$F$31 -> 1500 | AS12: ='Assumption Setting'!$F$31 -> 1500 | AT12: ='Assumption Setting'!$F$31 -> 1500 | AU12: ='Assumption Setting'!$F$31 -> 1500 | AV12: ='Assumption Setting'!$F$31 -> 1500 | AW12: ='Assumption Setting'!$F$31 -> 1500 | ... BA12: ='Assumption Setting'!$F$31 -> 1500 | BB12: =SUM(BC12:BN12) -> 22800 | BC12: ='Assumption Setting'!$G$31 -> 1900 | BD12: ='Assumption Setting'!$G$31 -> 1900 | BE12: ='Assumption Setting'!$G$31 -> 1900 | BF12: ='Assumption Setting'!$G$31 -> 1900 | BG12: ='Assumption Setting'!$G$31 -> 1900 | BH12: ='Assumption Setting'!$G$31 -> 1900 | BI12: ='Assumption Setting'!$G$31 -> 1900 | BJ12: ='Assumption Setting'!$G$31 -> 1900 | ... BN12: ='Assumption Setting'!$G$31 -> 1900
A13: Total online budget | B13: =SUM(C13:N13) -> 40200 | C13: =SUM(C6:C12) -> 3350 | D13: =SUM(D6:D12) -> 3350 | E13: =SUM(E6:E12) -> 3350 | F13: =SUM(F6:F12) -> 3350 | G13: =SUM(G6:G12) -> 3350 | H13: =SUM(H6:H12) -> 3350 | I13: =SUM(I6:I12) -> 3350 | J13: =SUM(J6:J12) -> 3350 | ... N13: =SUM(N6:N12) -> 3350 | O13: =SUM(P13:AA13) -> 90000 | P13: =SUM(P6:P12) -> 7500 | Q13: =SUM(Q6:Q12) -> 7500 | R13: =SUM(R6:R12) -> 7500 | S13: =SUM(S6:S12) -> 7500 | T13: =SUM(T6:T12) -> 7500 | U13: =SUM(U6:U12) -> 7500 | V13: =SUM(V6:V12) -> 7500 | W13: =SUM(W6:W12) -> 7500 | ... AA13: =SUM(AA6:AA12) -> 7500 | AB13: =SUM(AC13:AN13) -> 156000 | AC13: =SUM(AC6:AC12) -> 13000 | AD13: =SUM(AD6:AD12) -> 13000 | AE13: =SUM(AE6:AE12) -> 13000 | AF13: =SUM(AF6:AF12) -> 13000 | AG13: =SUM(AG6:AG12) -> 13000 | AH13: =SUM(AH6:AH12) -> 13000 | AI13: =SUM(AI6:AI12) -> 13000 | AJ13: =SUM(AJ6:AJ12) -> 13000 | ... AN13: =SUM(AN6:AN12) -> 13000 | AO13: =SUM(AP13:BA13) -> 219600 | AP13: =SUM(AP6:AP12) -> 18300 | AQ13: =SUM(AQ6:AQ12) -> 18300 | AR13: =SUM(AR6:AR12) -> 18300 | AS13: =SUM(AS6:AS12) -> 18300 | AT13: =SUM(AT6:AT12) -> 18300 | AU13: =SUM(AU6:AU12) -> 18300 | AV13: =SUM(AV6:AV12) -> 18300 | AW13: =SUM(AW6:AW12) -> 18300 | ... BA13: =SUM(BA6:BA12) -> 18300 | BB13: =SUM(BC13:BN13) -> 282000 | BC13: =SUM(BC6:BC12) -> 23500 | BD13: =SUM(BD6:BD12) -> 23500 | BE13: =SUM(BE6:BE12) -> 23500 | BF13: =SUM(BF6:BF12) -> 23500 | BG13: =SUM(BG6:BG12) -> 23500 | BH13: =SUM(BH6:BH12) -> 23500 | BI13: =SUM(BI6:BI12) -> 23500 | BJ13: =SUM(BJ6:BJ12) -> 23500 | ... BN13: =SUM(BN6:BN12) -> 23500
A15: 2. PAID CLICKS, BUDGET DIVIDED BY COST PER CLICK
A16: Line item | B16: Year 1 | C16: Jan 27 | D16: Feb 27 | E16: Mar 27 | F16: Apr 27 | G16: May 27 | H16: Jun 27 | I16: Jul 27 | J16: Aug 27 | K16: Sep 27 | L16: Oct 27 | M16: Nov 27 | N16: Dec 27 | O16: Year 2 | P16: Jan 28 | Q16: Feb 28 | R16: Mar 28 | S16: Apr 28 | T16: May 28 | U16: Jun 28 | V16: Jul 28 | W16: Aug 28 | X16: Sep 28 | Y16: Oct 28 | Z16: Nov 28 | AA16: Dec 28 | AB16: Year 3 | AC16: Jan 29 | AD16: Feb 29 | AE16: Mar 29 | AF16: Apr 29 | AG16: May 29 | AH16: Jun 29 | AI16: Jul 29 | AJ16: Aug 29 | AK16: Sep 29 | AL16: Oct 29 | AM16: Nov 29 | AN16: Dec 29 | AO16: Year 4 | AP16: Jan 30 | AQ16: Feb 30 | AR16: Mar 30 | AS16: Apr 30 | AT16: May 30 | AU16: Jun 30 | AV16: Jul 30 | AW16: Aug 30 | AX16: Sep 30 | AY16: Oct 30 | AZ16: Nov 30 | BA16: Dec 30 | BB16: Year 5 | BC16: Jan 31 | BD16: Feb 31 | BE16: Mar 31 | BF16: Apr 31 | BG16: May 31 | BH16: Jun 31 | BI16: Jul 31 | BJ16: Aug 31 | BK16: Sep 31 | BL16: Oct 31 | BM16: Nov 31 | BN16: Dec 31
A17: Meta and Instagram ads, merchants | B17: =SUM(C17:N17) -> 96000 | C17: =C6/('Assumption Setting'!$H$25*'Assumption Setting'!$C$35) -> 8000 | D17: =D6/('Assumption Setting'!$H$25*'Assumption Setting'!$C$35) -> 8000 | E17: =E6/('Assumption Setting'!$H$25*'Assumption Setting'!$C$35) -> 8000 | F17: =F6/('Assumption Setting'!$H$25*'Assumption Setting'!$C$35) -> 8000 | G17: =G6/('Assumption Setting'!$H$25*'Assumption Setting'!$C$35) -> 8000 | H17: =H6/('Assumption Setting'!$H$25*'Assumption Setting'!$C$35) -> 8000 | I17: =I6/('Assumption Setting'!$H$25*'Assumption Setting'!$C$35) -> 8000 | J17: =J6/('Assumption Setting'!$H$25*'Assumption Setting'!$C$35) -> 8000 | ... N17: =N6/('Assumption Setting'!$H$25*'Assumption Setting'!$C$35) -> 8000 | O17: =SUM(P17:AA17) -> 218181.82 | P17: =P6/('Assumption Setting'!$H$25*'Assumption Setting'!$D$35) -> 18181.818 | Q17: =Q6/('Assumption Setting'!$H$25*'Assumption Setting'!$D$35) -> 18181.818 | R17: =R6/('Assumption Setting'!$H$25*'Assumption Setting'!$D$35) -> 18181.818 | S17: =S6/('Assumption Setting'!$H$25*'Assumption Setting'!$D$35) -> 18181.818 | T17: =T6/('Assumption Setting'!$H$25*'Assumption Setting'!$D$35) -> 18181.818 | U17: =U6/('Assumption Setting'!$H$25*'Assumption Setting'!$D$35) -> 18181.818 | V17: =V6/('Assumption Setting'!$H$25*'Assumption Setting'!$D$35) -> 18181.818 | W17: =W6/('Assumption Setting'!$H$25*'Assumption Setting'!$D$35) -> 18181.818 | ... AA17: =AA6/('Assumption Setting'!$H$25*'Assumption Setting'!$D$35) -> 18181.818 | AB17: =SUM(AC17:AN17) -> 357024.79 | AC17: =AC6/('Assumption Setting'!$H$25*'Assumption Setting'!$E$35) -> 29752.066 | AD17: =AD6/('Assumption Setting'!$H$25*'Assumption Setting'!$E$35) -> 29752.066 | AE17: =AE6/('Assumption Setting'!$H$25*'Assumption Setting'!$E$35) -> 29752.066 | AF17: =AF6/('Assumption Setting'!$H$25*'Assumption Setting'!$E$35) -> 29752.066 | AG17: =AG6/('Assumption Setting'!$H$25*'Assumption Setting'!$E$35) -> 29752.066 | AH17: =AH6/('Assumption Setting'!$H$25*'Assumption Setting'!$E$35) -> 29752.066 | AI17: =AI6/('Assumption Setting'!$H$25*'Assumption Setting'!$E$35) -> 29752.066 | AJ17: =AJ6/('Assumption Setting'!$H$25*'Assumption Setting'!$E$35) -> 29752.066 | ... AN17: =AN6/('Assumption Setting'!$H$25*'Assumption Setting'!$E$35) -> 29752.066 | AO17: =SUM(AP17:BA17) -> 468820.44 | AP17: =AP6/('Assumption Setting'!$H$25*'Assumption Setting'!$F$35) -> 39068.37 | AQ17: =AQ6/('Assumption Setting'!$H$25*'Assumption Setting'!$F$35) -> 39068.37 | AR17: =AR6/('Assumption Setting'!$H$25*'Assumption Setting'!$F$35) -> 39068.37 | AS17: =AS6/('Assumption Setting'!$H$25*'Assumption Setting'!$F$35) -> 39068.37 | AT17: =AT6/('Assumption Setting'!$H$25*'Assumption Setting'!$F$35) -> 39068.37 | AU17: =AU6/('Assumption Setting'!$H$25*'Assumption Setting'!$F$35) -> 39068.37 | AV17: =AV6/('Assumption Setting'!$H$25*'Assumption Setting'!$F$35) -> 39068.37 | AW17: =AW6/('Assumption Setting'!$H$25*'Assumption Setting'!$F$35) -> 39068.37 | ... BA17: =BA6/('Assumption Setting'!$H$25*'Assumption Setting'!$F$35) -> 39068.37 | BB17: =SUM(BC17:BN17) -> 557338.98 | BC17: =BC6/('Assumption Setting'!$H$25*'Assumption Setting'!$G$35) -> 46444.915 | BD17: =BD6/('Assumption Setting'!$H$25*'Assumption Setting'!$G$35) -> 46444.915 | BE17: =BE6/('Assumption Setting'!$H$25*'Assumption Setting'!$G$35) -> 46444.915 | BF17: =BF6/('Assumption Setting'!$H$25*'Assumption Setting'!$G$35) -> 46444.915 | BG17: =BG6/('Assumption Setting'!$H$25*'Assumption Setting'!$G$35) -> 46444.915 | BH17: =BH6/('Assumption Setting'!$H$25*'Assumption Setting'!$G$35) -> 46444.915 | BI17: =BI6/('Assumption Setting'!$H$25*'Assumption Setting'!$G$35) -> 46444.915 | BJ17: =BJ6/('Assumption Setting'!$H$25*'Assumption Setting'!$G$35) -> 46444.915 | ... BN17: =BN6/('Assumption Setting'!$H$25*'Assumption Setting'!$G$35) -> 46444.915
A18: Google Search, store builder and POS intent | B18: =SUM(C18:N18) -> 27272.727 | C18: =C7/('Assumption Setting'!$H$26*'Assumption Setting'!$C$35) -> 2272.7273 | D18: =D7/('Assumption Setting'!$H$26*'Assumption Setting'!$C$35) -> 2272.7273 | E18: =E7/('Assumption Setting'!$H$26*'Assumption Setting'!$C$35) -> 2272.7273 | F18: =F7/('Assumption Setting'!$H$26*'Assumption Setting'!$C$35) -> 2272.7273 | G18: =G7/('Assumption Setting'!$H$26*'Assumption Setting'!$C$35) -> 2272.7273 | H18: =H7/('Assumption Setting'!$H$26*'Assumption Setting'!$C$35) -> 2272.7273 | I18: =I7/('Assumption Setting'!$H$26*'Assumption Setting'!$C$35) -> 2272.7273 | J18: =J7/('Assumption Setting'!$H$26*'Assumption Setting'!$C$35) -> 2272.7273 | ... N18: =N7/('Assumption Setting'!$H$26*'Assumption Setting'!$C$35) -> 2272.7273 | O18: =SUM(P18:AA18) -> 64462.81 | P18: =P7/('Assumption Setting'!$H$26*'Assumption Setting'!$D$35) -> 5371.9008 | Q18: =Q7/('Assumption Setting'!$H$26*'Assumption Setting'!$D$35) -> 5371.9008 | R18: =R7/('Assumption Setting'!$H$26*'Assumption Setting'!$D$35) -> 5371.9008 | S18: =S7/('Assumption Setting'!$H$26*'Assumption Setting'!$D$35) -> 5371.9008 | T18: =T7/('Assumption Setting'!$H$26*'Assumption Setting'!$D$35) -> 5371.9008 | U18: =U7/('Assumption Setting'!$H$26*'Assumption Setting'!$D$35) -> 5371.9008 | V18: =V7/('Assumption Setting'!$H$26*'Assumption Setting'!$D$35) -> 5371.9008 | W18: =W7/('Assumption Setting'!$H$26*'Assumption Setting'!$D$35) -> 5371.9008 | ... AA18: =AA7/('Assumption Setting'!$H$26*'Assumption Setting'!$D$35) -> 5371.9008 | AB18: =SUM(AC18:AN18) -> 103681.44 | AC18: =AC7/('Assumption Setting'!$H$26*'Assumption Setting'!$E$35) -> 8640.1202 | AD18: =AD7/('Assumption Setting'!$H$26*'Assumption Setting'!$E$35) -> 8640.1202 | AE18: =AE7/('Assumption Setting'!$H$26*'Assumption Setting'!$E$35) -> 8640.1202 | AF18: =AF7/('Assumption Setting'!$H$26*'Assumption Setting'!$E$35) -> 8640.1202 | AG18: =AG7/('Assumption Setting'!$H$26*'Assumption Setting'!$E$35) -> 8640.1202 | AH18: =AH7/('Assumption Setting'!$H$26*'Assumption Setting'!$E$35) -> 8640.1202 | AI18: =AI7/('Assumption Setting'!$H$26*'Assumption Setting'!$E$35) -> 8640.1202 | AJ18: =AJ7/('Assumption Setting'!$H$26*'Assumption Setting'!$E$35) -> 8640.1202 | ... AN18: =AN7/('Assumption Setting'!$H$26*'Assumption Setting'!$E$35) -> 8640.1202 | AO18: =SUM(AP18:BA18) -> 135236.66 | AP18: =AP7/('Assumption Setting'!$H$26*'Assumption Setting'!$F$35) -> 11269.722 | AQ18: =AQ7/('Assumption Setting'!$H$26*'Assumption Setting'!$F$35) -> 11269.722 | AR18: =AR7/('Assumption Setting'!$H$26*'Assumption Setting'!$F$35) -> 11269.722 | AS18: =AS7/('Assumption Setting'!$H$26*'Assumption Setting'!$F$35) -> 11269.722 | AT18: =AT7/('Assumption Setting'!$H$26*'Assumption Setting'!$F$35) -> 11269.722 | AU18: =AU7/('Assumption Setting'!$H$26*'Assumption Setting'!$F$35) -> 11269.722 | AV18: =AV7/('Assumption Setting'!$H$26*'Assumption Setting'!$F$35) -> 11269.722 | AW18: =AW7/('Assumption Setting'!$H$26*'Assumption Setting'!$F$35) -> 11269.722 | ... BA18: =BA7/('Assumption Setting'!$H$26*'Assumption Setting'!$F$35) -> 11269.722 | BB18: =SUM(BC18:BN18) -> 160197.7 | BC18: =BC7/('Assumption Setting'!$H$26*'Assumption Setting'!$G$35) -> 13349.808 | BD18: =BD7/('Assumption Setting'!$H$26*'Assumption Setting'!$G$35) -> 13349.808 | BE18: =BE7/('Assumption Setting'!$H$26*'Assumption Setting'!$G$35) -> 13349.808 | BF18: =BF7/('Assumption Setting'!$H$26*'Assumption Setting'!$G$35) -> 13349.808 | BG18: =BG7/('Assumption Setting'!$H$26*'Assumption Setting'!$G$35) -> 13349.808 | BH18: =BH7/('Assumption Setting'!$H$26*'Assumption Setting'!$G$35) -> 13349.808 | BI18: =BI7/('Assumption Setting'!$H$26*'Assumption Setting'!$G$35) -> 13349.808 | BJ18: =BJ7/('Assumption Setting'!$H$26*'Assumption Setting'!$G$35) -> 13349.808 | ... BN18: =BN7/('Assumption Setting'!$H$26*'Assumption Setting'!$G$35) -> 13349.808
A19: TikTok and short video, sellers | B19: =SUM(C19:N19) -> 60000 | C19: =C8/('Assumption Setting'!$H$27*'Assumption Setting'!$C$35) -> 5000 | D19: =D8/('Assumption Setting'!$H$27*'Assumption Setting'!$C$35) -> 5000 | E19: =E8/('Assumption Setting'!$H$27*'Assumption Setting'!$C$35) -> 5000 | F19: =F8/('Assumption Setting'!$H$27*'Assumption Setting'!$C$35) -> 5000 | G19: =G8/('Assumption Setting'!$H$27*'Assumption Setting'!$C$35) -> 5000 | H19: =H8/('Assumption Setting'!$H$27*'Assumption Setting'!$C$35) -> 5000 | I19: =I8/('Assumption Setting'!$H$27*'Assumption Setting'!$C$35) -> 5000 | J19: =J8/('Assumption Setting'!$H$27*'Assumption Setting'!$C$35) -> 5000 | ... N19: =N8/('Assumption Setting'!$H$27*'Assumption Setting'!$C$35) -> 5000 | O19: =SUM(P19:AA19) -> 127272.73 | P19: =P8/('Assumption Setting'!$H$27*'Assumption Setting'!$D$35) -> 10606.061 | Q19: =Q8/('Assumption Setting'!$H$27*'Assumption Setting'!$D$35) -> 10606.061 | R19: =R8/('Assumption Setting'!$H$27*'Assumption Setting'!$D$35) -> 10606.061 | S19: =S8/('Assumption Setting'!$H$27*'Assumption Setting'!$D$35) -> 10606.061 | T19: =T8/('Assumption Setting'!$H$27*'Assumption Setting'!$D$35) -> 10606.061 | U19: =U8/('Assumption Setting'!$H$27*'Assumption Setting'!$D$35) -> 10606.061 | V19: =V8/('Assumption Setting'!$H$27*'Assumption Setting'!$D$35) -> 10606.061 | W19: =W8/('Assumption Setting'!$H$27*'Assumption Setting'!$D$35) -> 10606.061 | ... AA19: =AA8/('Assumption Setting'!$H$27*'Assumption Setting'!$D$35) -> 10606.061 | AB19: =SUM(AC19:AN19) -> 214876.03 | AC19: =AC8/('Assumption Setting'!$H$27*'Assumption Setting'!$E$35) -> 17906.336 | AD19: =AD8/('Assumption Setting'!$H$27*'Assumption Setting'!$E$35) -> 17906.336 | AE19: =AE8/('Assumption Setting'!$H$27*'Assumption Setting'!$E$35) -> 17906.336 | AF19: =AF8/('Assumption Setting'!$H$27*'Assumption Setting'!$E$35) -> 17906.336 | AG19: =AG8/('Assumption Setting'!$H$27*'Assumption Setting'!$E$35) -> 17906.336 | AH19: =AH8/('Assumption Setting'!$H$27*'Assumption Setting'!$E$35) -> 17906.336 | AI19: =AI8/('Assumption Setting'!$H$27*'Assumption Setting'!$E$35) -> 17906.336 | AJ19: =AJ8/('Assumption Setting'!$H$27*'Assumption Setting'!$E$35) -> 17906.336 | ... AN19: =AN8/('Assumption Setting'!$H$27*'Assumption Setting'!$E$35) -> 17906.336 | AO19: =SUM(AP19:BA19) -> 285499.62 | AP19: =AP8/('Assumption Setting'!$H$27*'Assumption Setting'!$F$35) -> 23791.635 | AQ19: =AQ8/('Assumption Setting'!$H$27*'Assumption Setting'!$F$35) -> 23791.635 | AR19: =AR8/('Assumption Setting'!$H$27*'Assumption Setting'!$F$35) -> 23791.635 | AS19: =AS8/('Assumption Setting'!$H$27*'Assumption Setting'!$F$35) -> 23791.635 | AT19: =AT8/('Assumption Setting'!$H$27*'Assumption Setting'!$F$35) -> 23791.635 | AU19: =AU8/('Assumption Setting'!$H$27*'Assumption Setting'!$F$35) -> 23791.635 | AV19: =AV8/('Assumption Setting'!$H$27*'Assumption Setting'!$F$35) -> 23791.635 | AW19: =AW8/('Assumption Setting'!$H$27*'Assumption Setting'!$F$35) -> 23791.635 | ... BA19: =BA8/('Assumption Setting'!$H$27*'Assumption Setting'!$F$35) -> 23791.635 | BB19: =SUM(BC19:BN19) -> 327846.46 | BC19: =BC8/('Assumption Setting'!$H$27*'Assumption Setting'!$G$35) -> 27320.538 | BD19: =BD8/('Assumption Setting'!$H$27*'Assumption Setting'!$G$35) -> 27320.538 | BE19: =BE8/('Assumption Setting'!$H$27*'Assumption Setting'!$G$35) -> 27320.538 | BF19: =BF8/('Assumption Setting'!$H$27*'Assumption Setting'!$G$35) -> 27320.538 | BG19: =BG8/('Assumption Setting'!$H$27*'Assumption Setting'!$G$35) -> 27320.538 | BH19: =BH8/('Assumption Setting'!$H$27*'Assumption Setting'!$G$35) -> 27320.538 | BI19: =BI8/('Assumption Setting'!$H$27*'Assumption Setting'!$G$35) -> 27320.538 | BJ19: =BJ8/('Assumption Setting'!$H$27*'Assumption Setting'!$G$35) -> 27320.538 | ... BN19: =BN8/('Assumption Setting'!$H$27*'Assumption Setting'!$G$35) -> 27320.538
A20: Retargeting, trial starters | B20: =SUM(C20:N20) -> 17142.857 | C20: =C9/('Assumption Setting'!$H$28*'Assumption Setting'!$C$35) -> 1428.5714 | D20: =D9/('Assumption Setting'!$H$28*'Assumption Setting'!$C$35) -> 1428.5714 | E20: =E9/('Assumption Setting'!$H$28*'Assumption Setting'!$C$35) -> 1428.5714 | F20: =F9/('Assumption Setting'!$H$28*'Assumption Setting'!$C$35) -> 1428.5714 | G20: =G9/('Assumption Setting'!$H$28*'Assumption Setting'!$C$35) -> 1428.5714 | H20: =H9/('Assumption Setting'!$H$28*'Assumption Setting'!$C$35) -> 1428.5714 | I20: =I9/('Assumption Setting'!$H$28*'Assumption Setting'!$C$35) -> 1428.5714 | J20: =J9/('Assumption Setting'!$H$28*'Assumption Setting'!$C$35) -> 1428.5714 | ... N20: =N9/('Assumption Setting'!$H$28*'Assumption Setting'!$C$35) -> 1428.5714 | O20: =SUM(P20:AA20) -> 35064.935 | P20: =P9/('Assumption Setting'!$H$28*'Assumption Setting'!$D$35) -> 2922.0779 | Q20: =Q9/('Assumption Setting'!$H$28*'Assumption Setting'!$D$35) -> 2922.0779 | R20: =R9/('Assumption Setting'!$H$28*'Assumption Setting'!$D$35) -> 2922.0779 | S20: =S9/('Assumption Setting'!$H$28*'Assumption Setting'!$D$35) -> 2922.0779 | T20: =T9/('Assumption Setting'!$H$28*'Assumption Setting'!$D$35) -> 2922.0779 | U20: =U9/('Assumption Setting'!$H$28*'Assumption Setting'!$D$35) -> 2922.0779 | V20: =V9/('Assumption Setting'!$H$28*'Assumption Setting'!$D$35) -> 2922.0779 | W20: =W9/('Assumption Setting'!$H$28*'Assumption Setting'!$D$35) -> 2922.0779 | ... AA20: =AA9/('Assumption Setting'!$H$28*'Assumption Setting'!$D$35) -> 2922.0779 | AB20: =SUM(AC20:AN20) -> 56670.602 | AC20: =AC9/('Assumption Setting'!$H$28*'Assumption Setting'!$E$35) -> 4722.5502 | AD20: =AD9/('Assumption Setting'!$H$28*'Assumption Setting'!$E$35) -> 4722.5502 | AE20: =AE9/('Assumption Setting'!$H$28*'Assumption Setting'!$E$35) -> 4722.5502 | AF20: =AF9/('Assumption Setting'!$H$28*'Assumption Setting'!$E$35) -> 4722.5502 | AG20: =AG9/('Assumption Setting'!$H$28*'Assumption Setting'!$E$35) -> 4722.5502 | AH20: =AH9/('Assumption Setting'!$H$28*'Assumption Setting'!$E$35) -> 4722.5502 | AI20: =AI9/('Assumption Setting'!$H$28*'Assumption Setting'!$E$35) -> 4722.5502 | AJ20: =AJ9/('Assumption Setting'!$H$28*'Assumption Setting'!$E$35) -> 4722.5502 | ... AN20: =AN9/('Assumption Setting'!$H$28*'Assumption Setting'!$E$35) -> 4722.5502 | AO20: =SUM(AP20:BA20) -> 70838.253 | AP20: =AP9/('Assumption Setting'!$H$28*'Assumption Setting'!$F$35) -> 5903.1877 | AQ20: =AQ9/('Assumption Setting'!$H$28*'Assumption Setting'!$F$35) -> 5903.1877 | AR20: =AR9/('Assumption Setting'!$H$28*'Assumption Setting'!$F$35) -> 5903.1877 | AS20: =AS9/('Assumption Setting'!$H$28*'Assumption Setting'!$F$35) -> 5903.1877 | AT20: =AT9/('Assumption Setting'!$H$28*'Assumption Setting'!$F$35) -> 5903.1877 | AU20: =AU9/('Assumption Setting'!$H$28*'Assumption Setting'!$F$35) -> 5903.1877 | AV20: =AV9/('Assumption Setting'!$H$28*'Assumption Setting'!$F$35) -> 5903.1877 | AW20: =AW9/('Assumption Setting'!$H$28*'Assumption Setting'!$F$35) -> 5903.1877 | ... BA20: =BA9/('Assumption Setting'!$H$28*'Assumption Setting'!$F$35) -> 5903.1877 | BB20: =SUM(BC20:BN20) -> 81961.615 | BC20: =BC9/('Assumption Setting'!$H$28*'Assumption Setting'!$G$35) -> 6830.1346 | BD20: =BD9/('Assumption Setting'!$H$28*'Assumption Setting'!$G$35) -> 6830.1346 | BE20: =BE9/('Assumption Setting'!$H$28*'Assumption Setting'!$G$35) -> 6830.1346 | BF20: =BF9/('Assumption Setting'!$H$28*'Assumption Setting'!$G$35) -> 6830.1346 | BG20: =BG9/('Assumption Setting'!$H$28*'Assumption Setting'!$G$35) -> 6830.1346 | BH20: =BH9/('Assumption Setting'!$H$28*'Assumption Setting'!$G$35) -> 6830.1346 | BI20: =BI9/('Assumption Setting'!$H$28*'Assumption Setting'!$G$35) -> 6830.1346 | BJ20: =BJ9/('Assumption Setting'!$H$28*'Assumption Setting'!$G$35) -> 6830.1346 | ... BN20: =BN9/('Assumption Setting'!$H$28*'Assumption Setting'!$G$35) -> 6830.1346
A21: Content and SEO, Arabic commerce guides | B21: =SUM(C21:N21) -> 33320 | C21: =C10/('Assumption Setting'!$H$29*'Assumption Setting'!$C$35) -> 2776.6667 | D21: =D10/('Assumption Setting'!$H$29*'Assumption Setting'!$C$35) -> 2776.6667 | E21: =E10/('Assumption Setting'!$H$29*'Assumption Setting'!$C$35) -> 2776.6667 | F21: =F10/('Assumption Setting'!$H$29*'Assumption Setting'!$C$35) -> 2776.6667 | G21: =G10/('Assumption Setting'!$H$29*'Assumption Setting'!$C$35) -> 2776.6667 | H21: =H10/('Assumption Setting'!$H$29*'Assumption Setting'!$C$35) -> 2776.6667 | I21: =I10/('Assumption Setting'!$H$29*'Assumption Setting'!$C$35) -> 2776.6667 | J21: =J10/('Assumption Setting'!$H$29*'Assumption Setting'!$C$35) -> 2776.6667 | ... N21: =N10/('Assumption Setting'!$H$29*'Assumption Setting'!$C$35) -> 2776.6667 | O21: =SUM(P21:AA21) -> 54545.455 | P21: =P10/('Assumption Setting'!$H$29*'Assumption Setting'!$D$35) -> 4545.4545 | Q21: =Q10/('Assumption Setting'!$H$29*'Assumption Setting'!$D$35) -> 4545.4545 | R21: =R10/('Assumption Setting'!$H$29*'Assumption Setting'!$D$35) -> 4545.4545 | S21: =S10/('Assumption Setting'!$H$29*'Assumption Setting'!$D$35) -> 4545.4545 | T21: =T10/('Assumption Setting'!$H$29*'Assumption Setting'!$D$35) -> 4545.4545 | U21: =U10/('Assumption Setting'!$H$29*'Assumption Setting'!$D$35) -> 4545.4545 | V21: =V10/('Assumption Setting'!$H$29*'Assumption Setting'!$D$35) -> 4545.4545 | W21: =W10/('Assumption Setting'!$H$29*'Assumption Setting'!$D$35) -> 4545.4545 | ... AA21: =AA10/('Assumption Setting'!$H$29*'Assumption Setting'!$D$35) -> 4545.4545 | AB21: =SUM(AC21:AN21) -> 79338.843 | AC21: =AC10/('Assumption Setting'!$H$29*'Assumption Setting'!$E$35) -> 6611.5702 | AD21: =AD10/('Assumption Setting'!$H$29*'Assumption Setting'!$E$35) -> 6611.5702 | AE21: =AE10/('Assumption Setting'!$H$29*'Assumption Setting'!$E$35) -> 6611.5702 | AF21: =AF10/('Assumption Setting'!$H$29*'Assumption Setting'!$E$35) -> 6611.5702 | AG21: =AG10/('Assumption Setting'!$H$29*'Assumption Setting'!$E$35) -> 6611.5702 | AH21: =AH10/('Assumption Setting'!$H$29*'Assumption Setting'!$E$35) -> 6611.5702 | AI21: =AI10/('Assumption Setting'!$H$29*'Assumption Setting'!$E$35) -> 6611.5702 | AJ21: =AJ10/('Assumption Setting'!$H$29*'Assumption Setting'!$E$35) -> 6611.5702 | ... AN21: =AN10/('Assumption Setting'!$H$29*'Assumption Setting'!$E$35) -> 6611.5702 | AO21: =SUM(AP21:BA21) -> 96168.295 | AP21: =AP10/('Assumption Setting'!$H$29*'Assumption Setting'!$F$35) -> 8014.0245 | AQ21: =AQ10/('Assumption Setting'!$H$29*'Assumption Setting'!$F$35) -> 8014.0245 | AR21: =AR10/('Assumption Setting'!$H$29*'Assumption Setting'!$F$35) -> 8014.0245 | AS21: =AS10/('Assumption Setting'!$H$29*'Assumption Setting'!$F$35) -> 8014.0245 | AT21: =AT10/('Assumption Setting'!$H$29*'Assumption Setting'!$F$35) -> 8014.0245 | AU21: =AU10/('Assumption Setting'!$H$29*'Assumption Setting'!$F$35) -> 8014.0245 | AV21: =AV10/('Assumption Setting'!$H$29*'Assumption Setting'!$F$35) -> 8014.0245 | AW21: =AW10/('Assumption Setting'!$H$29*'Assumption Setting'!$F$35) -> 8014.0245 | ... BA21: =BA10/('Assumption Setting'!$H$29*'Assumption Setting'!$F$35) -> 8014.0245 | BB21: =SUM(BC21:BN21) -> 109282.15 | BC21: =BC10/('Assumption Setting'!$H$29*'Assumption Setting'!$G$35) -> 9106.8461 | BD21: =BD10/('Assumption Setting'!$H$29*'Assumption Setting'!$G$35) -> 9106.8461 | BE21: =BE10/('Assumption Setting'!$H$29*'Assumption Setting'!$G$35) -> 9106.8461 | BF21: =BF10/('Assumption Setting'!$H$29*'Assumption Setting'!$G$35) -> 9106.8461 | BG21: =BG10/('Assumption Setting'!$H$29*'Assumption Setting'!$G$35) -> 9106.8461 | BH21: =BH10/('Assumption Setting'!$H$29*'Assumption Setting'!$G$35) -> 9106.8461 | BI21: =BI10/('Assumption Setting'!$H$29*'Assumption Setting'!$G$35) -> 9106.8461 | BJ21: =BJ10/('Assumption Setting'!$H$29*'Assumption Setting'!$G$35) -> 9106.8461 | ... BN21: =BN10/('Assumption Setting'!$H$29*'Assumption Setting'!$G$35) -> 9106.8461
A22: Merchant referral program credits | B22: =SUM(C22:N22) -> 11120 | C22: =C11/('Assumption Setting'!$H$30*'Assumption Setting'!$C$35) -> 926.66667 | D22: =D11/('Assumption Setting'!$H$30*'Assumption Setting'!$C$35) -> 926.66667 | E22: =E11/('Assumption Setting'!$H$30*'Assumption Setting'!$C$35) -> 926.66667 | F22: =F11/('Assumption Setting'!$H$30*'Assumption Setting'!$C$35) -> 926.66667 | G22: =G11/('Assumption Setting'!$H$30*'Assumption Setting'!$C$35) -> 926.66667 | H22: =H11/('Assumption Setting'!$H$30*'Assumption Setting'!$C$35) -> 926.66667 | I22: =I11/('Assumption Setting'!$H$30*'Assumption Setting'!$C$35) -> 926.66667 | J22: =J11/('Assumption Setting'!$H$30*'Assumption Setting'!$C$35) -> 926.66667 | ... N22: =N11/('Assumption Setting'!$H$30*'Assumption Setting'!$C$35) -> 926.66667 | O22: =SUM(P22:AA22) -> 21818.182 | P22: =P11/('Assumption Setting'!$H$30*'Assumption Setting'!$D$35) -> 1818.1818 | Q22: =Q11/('Assumption Setting'!$H$30*'Assumption Setting'!$D$35) -> 1818.1818 | R22: =R11/('Assumption Setting'!$H$30*'Assumption Setting'!$D$35) -> 1818.1818 | S22: =S11/('Assumption Setting'!$H$30*'Assumption Setting'!$D$35) -> 1818.1818 | T22: =T11/('Assumption Setting'!$H$30*'Assumption Setting'!$D$35) -> 1818.1818 | U22: =U11/('Assumption Setting'!$H$30*'Assumption Setting'!$D$35) -> 1818.1818 | V22: =V11/('Assumption Setting'!$H$30*'Assumption Setting'!$D$35) -> 1818.1818 | W22: =W11/('Assumption Setting'!$H$30*'Assumption Setting'!$D$35) -> 1818.1818 | ... AA22: =AA11/('Assumption Setting'!$H$30*'Assumption Setting'!$D$35) -> 1818.1818 | AB22: =SUM(AC22:AN22) -> 33057.851 | AC22: =AC11/('Assumption Setting'!$H$30*'Assumption Setting'!$E$35) -> 2754.8209 | AD22: =AD11/('Assumption Setting'!$H$30*'Assumption Setting'!$E$35) -> 2754.8209 | AE22: =AE11/('Assumption Setting'!$H$30*'Assumption Setting'!$E$35) -> 2754.8209 | AF22: =AF11/('Assumption Setting'!$H$30*'Assumption Setting'!$E$35) -> 2754.8209 | AG22: =AG11/('Assumption Setting'!$H$30*'Assumption Setting'!$E$35) -> 2754.8209 | AH22: =AH11/('Assumption Setting'!$H$30*'Assumption Setting'!$E$35) -> 2754.8209 | AI22: =AI11/('Assumption Setting'!$H$30*'Assumption Setting'!$E$35) -> 2754.8209 | AJ22: =AJ11/('Assumption Setting'!$H$30*'Assumption Setting'!$E$35) -> 2754.8209 | ... AN22: =AN11/('Assumption Setting'!$H$30*'Assumption Setting'!$E$35) -> 2754.8209 | AO22: =SUM(AP22:BA22) -> 42073.629 | AP22: =AP11/('Assumption Setting'!$H$30*'Assumption Setting'!$F$35) -> 3506.1357 | AQ22: =AQ11/('Assumption Setting'!$H$30*'Assumption Setting'!$F$35) -> 3506.1357 | AR22: =AR11/('Assumption Setting'!$H$30*'Assumption Setting'!$F$35) -> 3506.1357 | AS22: =AS11/('Assumption Setting'!$H$30*'Assumption Setting'!$F$35) -> 3506.1357 | AT22: =AT11/('Assumption Setting'!$H$30*'Assumption Setting'!$F$35) -> 3506.1357 | AU22: =AU11/('Assumption Setting'!$H$30*'Assumption Setting'!$F$35) -> 3506.1357 | AV22: =AV11/('Assumption Setting'!$H$30*'Assumption Setting'!$F$35) -> 3506.1357 | AW22: =AW11/('Assumption Setting'!$H$30*'Assumption Setting'!$F$35) -> 3506.1357 | ... BA22: =BA11/('Assumption Setting'!$H$30*'Assumption Setting'!$F$35) -> 3506.1357 | BB22: =SUM(BC22:BN22) -> 49176.969 | BC22: =BC11/('Assumption Setting'!$H$30*'Assumption Setting'!$G$35) -> 4098.0807 | BD22: =BD11/('Assumption Setting'!$H$30*'Assumption Setting'!$G$35) -> 4098.0807 | BE22: =BE11/('Assumption Setting'!$H$30*'Assumption Setting'!$G$35) -> 4098.0807 | BF22: =BF11/('Assumption Setting'!$H$30*'Assumption Setting'!$G$35) -> 4098.0807 | BG22: =BG11/('Assumption Setting'!$H$30*'Assumption Setting'!$G$35) -> 4098.0807 | BH22: =BH11/('Assumption Setting'!$H$30*'Assumption Setting'!$G$35) -> 4098.0807 | BI22: =BI11/('Assumption Setting'!$H$30*'Assumption Setting'!$G$35) -> 4098.0807 | BJ22: =BJ11/('Assumption Setting'!$H$30*'Assumption Setting'!$G$35) -> 4098.0807 | ... BN22: =BN11/('Assumption Setting'!$H$30*'Assumption Setting'!$G$35) -> 4098.0807
A23: Seller communities and social groups | B23: =SUM(C23:N23) -> 30000 | C23: =C12/('Assumption Setting'!$H$31*'Assumption Setting'!$C$35) -> 2500 | D23: =D12/('Assumption Setting'!$H$31*'Assumption Setting'!$C$35) -> 2500 | E23: =E12/('Assumption Setting'!$H$31*'Assumption Setting'!$C$35) -> 2500 | F23: =F12/('Assumption Setting'!$H$31*'Assumption Setting'!$C$35) -> 2500 | G23: =G12/('Assumption Setting'!$H$31*'Assumption Setting'!$C$35) -> 2500 | H23: =H12/('Assumption Setting'!$H$31*'Assumption Setting'!$C$35) -> 2500 | I23: =I12/('Assumption Setting'!$H$31*'Assumption Setting'!$C$35) -> 2500 | J23: =J12/('Assumption Setting'!$H$31*'Assumption Setting'!$C$35) -> 2500 | ... N23: =N12/('Assumption Setting'!$H$31*'Assumption Setting'!$C$35) -> 2500 | O23: =SUM(P23:AA23) -> 59090.909 | P23: =P12/('Assumption Setting'!$H$31*'Assumption Setting'!$D$35) -> 4924.2424 | Q23: =Q12/('Assumption Setting'!$H$31*'Assumption Setting'!$D$35) -> 4924.2424 | R23: =R12/('Assumption Setting'!$H$31*'Assumption Setting'!$D$35) -> 4924.2424 | S23: =S12/('Assumption Setting'!$H$31*'Assumption Setting'!$D$35) -> 4924.2424 | T23: =T12/('Assumption Setting'!$H$31*'Assumption Setting'!$D$35) -> 4924.2424 | U23: =U12/('Assumption Setting'!$H$31*'Assumption Setting'!$D$35) -> 4924.2424 | V23: =V12/('Assumption Setting'!$H$31*'Assumption Setting'!$D$35) -> 4924.2424 | W23: =W12/('Assumption Setting'!$H$31*'Assumption Setting'!$D$35) -> 4924.2424 | ... AA23: =AA12/('Assumption Setting'!$H$31*'Assumption Setting'!$D$35) -> 4924.2424 | AB23: =SUM(AC23:AN23) -> 90909.091 | AC23: =AC12/('Assumption Setting'!$H$31*'Assumption Setting'!$E$35) -> 7575.7576 | AD23: =AD12/('Assumption Setting'!$H$31*'Assumption Setting'!$E$35) -> 7575.7576 | AE23: =AE12/('Assumption Setting'!$H$31*'Assumption Setting'!$E$35) -> 7575.7576 | AF23: =AF12/('Assumption Setting'!$H$31*'Assumption Setting'!$E$35) -> 7575.7576 | AG23: =AG12/('Assumption Setting'!$H$31*'Assumption Setting'!$E$35) -> 7575.7576 | AH23: =AH12/('Assumption Setting'!$H$31*'Assumption Setting'!$E$35) -> 7575.7576 | AI23: =AI12/('Assumption Setting'!$H$31*'Assumption Setting'!$E$35) -> 7575.7576 | AJ23: =AJ12/('Assumption Setting'!$H$31*'Assumption Setting'!$E$35) -> 7575.7576 | ... AN23: =AN12/('Assumption Setting'!$H$31*'Assumption Setting'!$E$35) -> 7575.7576 | AO23: =SUM(AP23:BA23) -> 112697.22 | AP23: =AP12/('Assumption Setting'!$H$31*'Assumption Setting'!$F$35) -> 9391.435 | AQ23: =AQ12/('Assumption Setting'!$H$31*'Assumption Setting'!$F$35) -> 9391.435 | AR23: =AR12/('Assumption Setting'!$H$31*'Assumption Setting'!$F$35) -> 9391.435 | AS23: =AS12/('Assumption Setting'!$H$31*'Assumption Setting'!$F$35) -> 9391.435 | AT23: =AT12/('Assumption Setting'!$H$31*'Assumption Setting'!$F$35) -> 9391.435 | AU23: =AU12/('Assumption Setting'!$H$31*'Assumption Setting'!$F$35) -> 9391.435 | AV23: =AV12/('Assumption Setting'!$H$31*'Assumption Setting'!$F$35) -> 9391.435 | AW23: =AW12/('Assumption Setting'!$H$31*'Assumption Setting'!$F$35) -> 9391.435 | ... BA23: =BA12/('Assumption Setting'!$H$31*'Assumption Setting'!$F$35) -> 9391.435 | BB23: =SUM(BC23:BN23) -> 129772.56 | BC23: =BC12/('Assumption Setting'!$H$31*'Assumption Setting'!$G$35) -> 10814.38 | BD23: =BD12/('Assumption Setting'!$H$31*'Assumption Setting'!$G$35) -> 10814.38 | BE23: =BE12/('Assumption Setting'!$H$31*'Assumption Setting'!$G$35) -> 10814.38 | BF23: =BF12/('Assumption Setting'!$H$31*'Assumption Setting'!$G$35) -> 10814.38 | BG23: =BG12/('Assumption Setting'!$H$31*'Assumption Setting'!$G$35) -> 10814.38 | BH23: =BH12/('Assumption Setting'!$H$31*'Assumption Setting'!$G$35) -> 10814.38 | BI23: =BI12/('Assumption Setting'!$H$31*'Assumption Setting'!$G$35) -> 10814.38 | BJ23: =BJ12/('Assumption Setting'!$H$31*'Assumption Setting'!$G$35) -> 10814.38 | ... BN23: =BN12/('Assumption Setting'!$H$31*'Assumption Setting'!$G$35) -> 10814.38
A24: Total paid clicks | B24: =SUM(C24:N24) -> 274855.58 | C24: =SUM(C17:C23) -> 22904.632 | D24: =SUM(D17:D23) -> 22904.632 | E24: =SUM(E17:E23) -> 22904.632 | F24: =SUM(F17:F23) -> 22904.632 | G24: =SUM(G17:G23) -> 22904.632 | H24: =SUM(H17:H23) -> 22904.632 | I24: =SUM(I17:I23) -> 22904.632 | J24: =SUM(J17:J23) -> 22904.632 | ... N24: =SUM(N17:N23) -> 22904.632 | O24: =SUM(P24:AA24) -> 580436.84 | P24: =SUM(P17:P23) -> 48369.736 | Q24: =SUM(Q17:Q23) -> 48369.736 | R24: =SUM(R17:R23) -> 48369.736 | S24: =SUM(S17:S23) -> 48369.736 | T24: =SUM(T17:T23) -> 48369.736 | U24: =SUM(U17:U23) -> 48369.736 | V24: =SUM(V17:V23) -> 48369.736 | W24: =SUM(W17:W23) -> 48369.736 | ... AA24: =SUM(AA17:AA23) -> 48369.736 | AB24: =SUM(AC24:AN24) -> 935558.66 | AC24: =SUM(AC17:AC23) -> 77963.221 | AD24: =SUM(AD17:AD23) -> 77963.221 | AE24: =SUM(AE17:AE23) -> 77963.221 | AF24: =SUM(AF17:AF23) -> 77963.221 | AG24: =SUM(AG17:AG23) -> 77963.221 | AH24: =SUM(AH17:AH23) -> 77963.221 | AI24: =SUM(AI17:AI23) -> 77963.221 | AJ24: =SUM(AJ17:AJ23) -> 77963.221 | ... AN24: =SUM(AN17:AN23) -> 77963.221 | AO24: =SUM(AP24:BA24) -> 1211334.1 | AP24: =SUM(AP17:AP23) -> 100944.51 | AQ24: =SUM(AQ17:AQ23) -> 100944.51 | AR24: =SUM(AR17:AR23) -> 100944.51 | AS24: =SUM(AS17:AS23) -> 100944.51 | AT24: =SUM(AT17:AT23) -> 100944.51 | AU24: =SUM(AU17:AU23) -> 100944.51 | AV24: =SUM(AV17:AV23) -> 100944.51 | AW24: =SUM(AW17:AW23) -> 100944.51 | ... BA24: =SUM(BA17:BA23) -> 100944.51 | BB24: =SUM(BC24:BN24) -> 1415576.4 | BC24: =SUM(BC17:BC23) -> 117964.7 | BD24: =SUM(BD17:BD23) -> 117964.7 | BE24: =SUM(BE17:BE23) -> 117964.7 | BF24: =SUM(BF17:BF23) -> 117964.7 | BG24: =SUM(BG17:BG23) -> 117964.7 | BH24: =SUM(BH17:BH23) -> 117964.7 | BI24: =SUM(BI17:BI23) -> 117964.7 | BJ24: =SUM(BJ17:BJ23) -> 117964.7 | ... BN24: =SUM(BN17:BN23) -> 117964.7
A26: 3. VISITS, PAID PLUS ORGANIC AND REFERRAL
A27: Line item | B27: Year 1 | C27: Jan 27 | D27: Feb 27 | E27: Mar 27 | F27: Apr 27 | G27: May 27 | H27: Jun 27 | I27: Jul 27 | J27: Aug 27 | K27: Sep 27 | L27: Oct 27 | M27: Nov 27 | N27: Dec 27 | O27: Year 2 | P27: Jan 28 | Q27: Feb 28 | R27: Mar 28 | S27: Apr 28 | T27: May 28 | U27: Jun 28 | V27: Jul 28 | W27: Aug 28 | X27: Sep 28 | Y27: Oct 28 | Z27: Nov 28 | AA27: Dec 28 | AB27: Year 3 | AC27: Jan 29 | AD27: Feb 29 | AE27: Mar 29 | AF27: Apr 29 | AG27: May 29 | AH27: Jun 29 | AI27: Jul 29 | AJ27: Aug 29 | AK27: Sep 29 | AL27: Oct 29 | AM27: Nov 29 | AN27: Dec 29 | AO27: Year 4 | AP27: Jan 30 | AQ27: Feb 30 | AR27: Mar 30 | AS27: Apr 30 | AT27: May 30 | AU27: Jun 30 | AV27: Jul 30 | AW27: Aug 30 | AX27: Sep 30 | AY27: Oct 30 | AZ27: Nov 30 | BA27: Dec 30 | BB27: Year 5 | BC27: Jan 31 | BD27: Feb 31 | BE27: Mar 31 | BF27: Apr 31 | BG27: May 31 | BH27: Jun 31 | BI27: Jul 31 | BJ27: Aug 31 | BK27: Sep 31 | BL27: Oct 31 | BM27: Nov 31 | BN27: Dec 31
A28: Meta and Instagram ads, merchants | B28: =SUM(C28:N28) -> 123840 | C28: =C17*(1+'Assumption Setting'!$I$25+'Assumption Setting'!$J$25) -> 10320 | D28: =D17*(1+'Assumption Setting'!$I$25+'Assumption Setting'!$J$25) -> 10320 | E28: =E17*(1+'Assumption Setting'!$I$25+'Assumption Setting'!$J$25) -> 10320 | F28: =F17*(1+'Assumption Setting'!$I$25+'Assumption Setting'!$J$25) -> 10320 | G28: =G17*(1+'Assumption Setting'!$I$25+'Assumption Setting'!$J$25) -> 10320 | H28: =H17*(1+'Assumption Setting'!$I$25+'Assumption Setting'!$J$25) -> 10320 | I28: =I17*(1+'Assumption Setting'!$I$25+'Assumption Setting'!$J$25) -> 10320 | J28: =J17*(1+'Assumption Setting'!$I$25+'Assumption Setting'!$J$25) -> 10320 | ... N28: =N17*(1+'Assumption Setting'!$I$25+'Assumption Setting'!$J$25) -> 10320 | O28: =SUM(P28:AA28) -> 281454.55 | P28: =P17*(1+'Assumption Setting'!$I$25+'Assumption Setting'!$J$25) -> 23454.545 | Q28: =Q17*(1+'Assumption Setting'!$I$25+'Assumption Setting'!$J$25) -> 23454.545 | R28: =R17*(1+'Assumption Setting'!$I$25+'Assumption Setting'!$J$25) -> 23454.545 | S28: =S17*(1+'Assumption Setting'!$I$25+'Assumption Setting'!$J$25) -> 23454.545 | T28: =T17*(1+'Assumption Setting'!$I$25+'Assumption Setting'!$J$25) -> 23454.545 | U28: =U17*(1+'Assumption Setting'!$I$25+'Assumption Setting'!$J$25) -> 23454.545 | V28: =V17*(1+'Assumption Setting'!$I$25+'Assumption Setting'!$J$25) -> 23454.545 | W28: =W17*(1+'Assumption Setting'!$I$25+'Assumption Setting'!$J$25) -> 23454.545 | ... AA28: =AA17*(1+'Assumption Setting'!$I$25+'Assumption Setting'!$J$25) -> 23454.545 | AB28: =SUM(AC28:AN28) -> 460561.98 | AC28: =AC17*(1+'Assumption Setting'!$I$25+'Assumption Setting'!$J$25) -> 38380.165 | AD28: =AD17*(1+'Assumption Setting'!$I$25+'Assumption Setting'!$J$25) -> 38380.165 | AE28: =AE17*(1+'Assumption Setting'!$I$25+'Assumption Setting'!$J$25) -> 38380.165 | AF28: =AF17*(1+'Assumption Setting'!$I$25+'Assumption Setting'!$J$25) -> 38380.165 | AG28: =AG17*(1+'Assumption Setting'!$I$25+'Assumption Setting'!$J$25) -> 38380.165 | AH28: =AH17*(1+'Assumption Setting'!$I$25+'Assumption Setting'!$J$25) -> 38380.165 | AI28: =AI17*(1+'Assumption Setting'!$I$25+'Assumption Setting'!$J$25) -> 38380.165 | AJ28: =AJ17*(1+'Assumption Setting'!$I$25+'Assumption Setting'!$J$25) -> 38380.165 | ... AN28: =AN17*(1+'Assumption Setting'!$I$25+'Assumption Setting'!$J$25) -> 38380.165 | AO28: =SUM(AP28:BA28) -> 604778.36 | AP28: =AP17*(1+'Assumption Setting'!$I$25+'Assumption Setting'!$J$25) -> 50398.197 | AQ28: =AQ17*(1+'Assumption Setting'!$I$25+'Assumption Setting'!$J$25) -> 50398.197 | AR28: =AR17*(1+'Assumption Setting'!$I$25+'Assumption Setting'!$J$25) -> 50398.197 | AS28: =AS17*(1+'Assumption Setting'!$I$25+'Assumption Setting'!$J$25) -> 50398.197 | AT28: =AT17*(1+'Assumption Setting'!$I$25+'Assumption Setting'!$J$25) -> 50398.197 | AU28: =AU17*(1+'Assumption Setting'!$I$25+'Assumption Setting'!$J$25) -> 50398.197 | AV28: =AV17*(1+'Assumption Setting'!$I$25+'Assumption Setting'!$J$25) -> 50398.197 | AW28: =AW17*(1+'Assumption Setting'!$I$25+'Assumption Setting'!$J$25) -> 50398.197 | ... BA28: =BA17*(1+'Assumption Setting'!$I$25+'Assumption Setting'!$J$25) -> 50398.197 | BB28: =SUM(BC28:BN28) -> 718967.28 | BC28: =BC17*(1+'Assumption Setting'!$I$25+'Assumption Setting'!$J$25) -> 59913.94 | BD28: =BD17*(1+'Assumption Setting'!$I$25+'Assumption Setting'!$J$25) -> 59913.94 | BE28: =BE17*(1+'Assumption Setting'!$I$25+'Assumption Setting'!$J$25) -> 59913.94 | BF28: =BF17*(1+'Assumption Setting'!$I$25+'Assumption Setting'!$J$25) -> 59913.94 | BG28: =BG17*(1+'Assumption Setting'!$I$25+'Assumption Setting'!$J$25) -> 59913.94 | BH28: =BH17*(1+'Assumption Setting'!$I$25+'Assumption Setting'!$J$25) -> 59913.94 | BI28: =BI17*(1+'Assumption Setting'!$I$25+'Assumption Setting'!$J$25) -> 59913.94 | BJ28: =BJ17*(1+'Assumption Setting'!$I$25+'Assumption Setting'!$J$25) -> 59913.94 | ... BN28: =BN17*(1+'Assumption Setting'!$I$25+'Assumption Setting'!$J$25) -> 59913.94
A29: Google Search, store builder and POS intent | B29: =SUM(C29:N29) -> 30818.182 | C29: =C18*(1+'Assumption Setting'!$I$26+'Assumption Setting'!$J$26) -> 2568.1818 | D29: =D18*(1+'Assumption Setting'!$I$26+'Assumption Setting'!$J$26) -> 2568.1818 | E29: =E18*(1+'Assumption Setting'!$I$26+'Assumption Setting'!$J$26) -> 2568.1818 | F29: =F18*(1+'Assumption Setting'!$I$26+'Assumption Setting'!$J$26) -> 2568.1818 | G29: =G18*(1+'Assumption Setting'!$I$26+'Assumption Setting'!$J$26) -> 2568.1818 | H29: =H18*(1+'Assumption Setting'!$I$26+'Assumption Setting'!$J$26) -> 2568.1818 | I29: =I18*(1+'Assumption Setting'!$I$26+'Assumption Setting'!$J$26) -> 2568.1818 | J29: =J18*(1+'Assumption Setting'!$I$26+'Assumption Setting'!$J$26) -> 2568.1818 | ... N29: =N18*(1+'Assumption Setting'!$I$26+'Assumption Setting'!$J$26) -> 2568.1818 | O29: =SUM(P29:AA29) -> 72842.975 | P29: =P18*(1+'Assumption Setting'!$I$26+'Assumption Setting'!$J$26) -> 6070.2479 | Q29: =Q18*(1+'Assumption Setting'!$I$26+'Assumption Setting'!$J$26) -> 6070.2479 | R29: =R18*(1+'Assumption Setting'!$I$26+'Assumption Setting'!$J$26) -> 6070.2479 | S29: =S18*(1+'Assumption Setting'!$I$26+'Assumption Setting'!$J$26) -> 6070.2479 | T29: =T18*(1+'Assumption Setting'!$I$26+'Assumption Setting'!$J$26) -> 6070.2479 | U29: =U18*(1+'Assumption Setting'!$I$26+'Assumption Setting'!$J$26) -> 6070.2479 | V29: =V18*(1+'Assumption Setting'!$I$26+'Assumption Setting'!$J$26) -> 6070.2479 | W29: =W18*(1+'Assumption Setting'!$I$26+'Assumption Setting'!$J$26) -> 6070.2479 | ... AA29: =AA18*(1+'Assumption Setting'!$I$26+'Assumption Setting'!$J$26) -> 6070.2479 | AB29: =SUM(AC29:AN29) -> 117160.03 | AC29: =AC18*(1+'Assumption Setting'!$I$26+'Assumption Setting'!$J$26) -> 9763.3358 | AD29: =AD18*(1+'Assumption Setting'!$I$26+'Assumption Setting'!$J$26) -> 9763.3358 | AE29: =AE18*(1+'Assumption Setting'!$I$26+'Assumption Setting'!$J$26) -> 9763.3358 | AF29: =AF18*(1+'Assumption Setting'!$I$26+'Assumption Setting'!$J$26) -> 9763.3358 | AG29: =AG18*(1+'Assumption Setting'!$I$26+'Assumption Setting'!$J$26) -> 9763.3358 | AH29: =AH18*(1+'Assumption Setting'!$I$26+'Assumption Setting'!$J$26) -> 9763.3358 | AI29: =AI18*(1+'Assumption Setting'!$I$26+'Assumption Setting'!$J$26) -> 9763.3358 | AJ29: =AJ18*(1+'Assumption Setting'!$I$26+'Assumption Setting'!$J$26) -> 9763.3358 | ... AN29: =AN18*(1+'Assumption Setting'!$I$26+'Assumption Setting'!$J$26) -> 9763.3358 | AO29: =SUM(AP29:BA29) -> 152817.43 | AP29: =AP18*(1+'Assumption Setting'!$I$26+'Assumption Setting'!$J$26) -> 12734.786 | AQ29: =AQ18*(1+'Assumption Setting'!$I$26+'Assumption Setting'!$J$26) -> 12734.786 | AR29: =AR18*(1+'Assumption Setting'!$I$26+'Assumption Setting'!$J$26) -> 12734.786 | AS29: =AS18*(1+'Assumption Setting'!$I$26+'Assumption Setting'!$J$26) -> 12734.786 | AT29: =AT18*(1+'Assumption Setting'!$I$26+'Assumption Setting'!$J$26) -> 12734.786 | AU29: =AU18*(1+'Assumption Setting'!$I$26+'Assumption Setting'!$J$26) -> 12734.786 | AV29: =AV18*(1+'Assumption Setting'!$I$26+'Assumption Setting'!$J$26) -> 12734.786 | AW29: =AW18*(1+'Assumption Setting'!$I$26+'Assumption Setting'!$J$26) -> 12734.786 | ... BA29: =BA18*(1+'Assumption Setting'!$I$26+'Assumption Setting'!$J$26) -> 12734.786 | BB29: =SUM(BC29:BN29) -> 181023.4 | BC29: =BC18*(1+'Assumption Setting'!$I$26+'Assumption Setting'!$J$26) -> 15085.284 | BD29: =BD18*(1+'Assumption Setting'!$I$26+'Assumption Setting'!$J$26) -> 15085.284 | BE29: =BE18*(1+'Assumption Setting'!$I$26+'Assumption Setting'!$J$26) -> 15085.284 | BF29: =BF18*(1+'Assumption Setting'!$I$26+'Assumption Setting'!$J$26) -> 15085.284 | BG29: =BG18*(1+'Assumption Setting'!$I$26+'Assumption Setting'!$J$26) -> 15085.284 | BH29: =BH18*(1+'Assumption Setting'!$I$26+'Assumption Setting'!$J$26) -> 15085.284 | BI29: =BI18*(1+'Assumption Setting'!$I$26+'Assumption Setting'!$J$26) -> 15085.284 | BJ29: =BJ18*(1+'Assumption Setting'!$I$26+'Assumption Setting'!$J$26) -> 15085.284 | ... BN29: =BN18*(1+'Assumption Setting'!$I$26+'Assumption Setting'!$J$26) -> 15085.284
A30: TikTok and short video, sellers | B30: =SUM(C30:N30) -> 83400 | C30: =C19*(1+'Assumption Setting'!$I$27+'Assumption Setting'!$J$27) -> 6950 | D30: =D19*(1+'Assumption Setting'!$I$27+'Assumption Setting'!$J$27) -> 6950 | E30: =E19*(1+'Assumption Setting'!$I$27+'Assumption Setting'!$J$27) -> 6950 | F30: =F19*(1+'Assumption Setting'!$I$27+'Assumption Setting'!$J$27) -> 6950 | G30: =G19*(1+'Assumption Setting'!$I$27+'Assumption Setting'!$J$27) -> 6950 | H30: =H19*(1+'Assumption Setting'!$I$27+'Assumption Setting'!$J$27) -> 6950 | I30: =I19*(1+'Assumption Setting'!$I$27+'Assumption Setting'!$J$27) -> 6950 | J30: =J19*(1+'Assumption Setting'!$I$27+'Assumption Setting'!$J$27) -> 6950 | ... N30: =N19*(1+'Assumption Setting'!$I$27+'Assumption Setting'!$J$27) -> 6950 | O30: =SUM(P30:AA30) -> 176909.09 | P30: =P19*(1+'Assumption Setting'!$I$27+'Assumption Setting'!$J$27) -> 14742.424 | Q30: =Q19*(1+'Assumption Setting'!$I$27+'Assumption Setting'!$J$27) -> 14742.424 | R30: =R19*(1+'Assumption Setting'!$I$27+'Assumption Setting'!$J$27) -> 14742.424 | S30: =S19*(1+'Assumption Setting'!$I$27+'Assumption Setting'!$J$27) -> 14742.424 | T30: =T19*(1+'Assumption Setting'!$I$27+'Assumption Setting'!$J$27) -> 14742.424 | U30: =U19*(1+'Assumption Setting'!$I$27+'Assumption Setting'!$J$27) -> 14742.424 | V30: =V19*(1+'Assumption Setting'!$I$27+'Assumption Setting'!$J$27) -> 14742.424 | W30: =W19*(1+'Assumption Setting'!$I$27+'Assumption Setting'!$J$27) -> 14742.424 | ... AA30: =AA19*(1+'Assumption Setting'!$I$27+'Assumption Setting'!$J$27) -> 14742.424 | AB30: =SUM(AC30:AN30) -> 298677.69 | AC30: =AC19*(1+'Assumption Setting'!$I$27+'Assumption Setting'!$J$27) -> 24889.807 | AD30: =AD19*(1+'Assumption Setting'!$I$27+'Assumption Setting'!$J$27) -> 24889.807 | AE30: =AE19*(1+'Assumption Setting'!$I$27+'Assumption Setting'!$J$27) -> 24889.807 | AF30: =AF19*(1+'Assumption Setting'!$I$27+'Assumption Setting'!$J$27) -> 24889.807 | AG30: =AG19*(1+'Assumption Setting'!$I$27+'Assumption Setting'!$J$27) -> 24889.807 | AH30: =AH19*(1+'Assumption Setting'!$I$27+'Assumption Setting'!$J$27) -> 24889.807 | AI30: =AI19*(1+'Assumption Setting'!$I$27+'Assumption Setting'!$J$27) -> 24889.807 | AJ30: =AJ19*(1+'Assumption Setting'!$I$27+'Assumption Setting'!$J$27) -> 24889.807 | ... AN30: =AN19*(1+'Assumption Setting'!$I$27+'Assumption Setting'!$J$27) -> 24889.807 | AO30: =SUM(AP30:BA30) -> 396844.48 | AP30: =AP19*(1+'Assumption Setting'!$I$27+'Assumption Setting'!$J$27) -> 33070.373 | AQ30: =AQ19*(1+'Assumption Setting'!$I$27+'Assumption Setting'!$J$27) -> 33070.373 | AR30: =AR19*(1+'Assumption Setting'!$I$27+'Assumption Setting'!$J$27) -> 33070.373 | AS30: =AS19*(1+'Assumption Setting'!$I$27+'Assumption Setting'!$J$27) -> 33070.373 | AT30: =AT19*(1+'Assumption Setting'!$I$27+'Assumption Setting'!$J$27) -> 33070.373 | AU30: =AU19*(1+'Assumption Setting'!$I$27+'Assumption Setting'!$J$27) -> 33070.373 | AV30: =AV19*(1+'Assumption Setting'!$I$27+'Assumption Setting'!$J$27) -> 33070.373 | AW30: =AW19*(1+'Assumption Setting'!$I$27+'Assumption Setting'!$J$27) -> 33070.373 | ... BA30: =BA19*(1+'Assumption Setting'!$I$27+'Assumption Setting'!$J$27) -> 33070.373 | BB30: =SUM(BC30:BN30) -> 455706.58 | BC30: =BC19*(1+'Assumption Setting'!$I$27+'Assumption Setting'!$J$27) -> 37975.548 | BD30: =BD19*(1+'Assumption Setting'!$I$27+'Assumption Setting'!$J$27) -> 37975.548 | BE30: =BE19*(1+'Assumption Setting'!$I$27+'Assumption Setting'!$J$27) -> 37975.548 | BF30: =BF19*(1+'Assumption Setting'!$I$27+'Assumption Setting'!$J$27) -> 37975.548 | BG30: =BG19*(1+'Assumption Setting'!$I$27+'Assumption Setting'!$J$27) -> 37975.548 | BH30: =BH19*(1+'Assumption Setting'!$I$27+'Assumption Setting'!$J$27) -> 37975.548 | BI30: =BI19*(1+'Assumption Setting'!$I$27+'Assumption Setting'!$J$27) -> 37975.548 | BJ30: =BJ19*(1+'Assumption Setting'!$I$27+'Assumption Setting'!$J$27) -> 37975.548 | ... BN30: =BN19*(1+'Assumption Setting'!$I$27+'Assumption Setting'!$J$27) -> 37975.548
A31: Retargeting, trial starters | B31: =SUM(C31:N31) -> 18171.429 | C31: =C20*(1+'Assumption Setting'!$I$28+'Assumption Setting'!$J$28) -> 1514.2857 | D31: =D20*(1+'Assumption Setting'!$I$28+'Assumption Setting'!$J$28) -> 1514.2857 | E31: =E20*(1+'Assumption Setting'!$I$28+'Assumption Setting'!$J$28) -> 1514.2857 | F31: =F20*(1+'Assumption Setting'!$I$28+'Assumption Setting'!$J$28) -> 1514.2857 | G31: =G20*(1+'Assumption Setting'!$I$28+'Assumption Setting'!$J$28) -> 1514.2857 | H31: =H20*(1+'Assumption Setting'!$I$28+'Assumption Setting'!$J$28) -> 1514.2857 | I31: =I20*(1+'Assumption Setting'!$I$28+'Assumption Setting'!$J$28) -> 1514.2857 | J31: =J20*(1+'Assumption Setting'!$I$28+'Assumption Setting'!$J$28) -> 1514.2857 | ... N31: =N20*(1+'Assumption Setting'!$I$28+'Assumption Setting'!$J$28) -> 1514.2857 | O31: =SUM(P31:AA31) -> 37168.831 | P31: =P20*(1+'Assumption Setting'!$I$28+'Assumption Setting'!$J$28) -> 3097.4026 | Q31: =Q20*(1+'Assumption Setting'!$I$28+'Assumption Setting'!$J$28) -> 3097.4026 | R31: =R20*(1+'Assumption Setting'!$I$28+'Assumption Setting'!$J$28) -> 3097.4026 | S31: =S20*(1+'Assumption Setting'!$I$28+'Assumption Setting'!$J$28) -> 3097.4026 | T31: =T20*(1+'Assumption Setting'!$I$28+'Assumption Setting'!$J$28) -> 3097.4026 | U31: =U20*(1+'Assumption Setting'!$I$28+'Assumption Setting'!$J$28) -> 3097.4026 | V31: =V20*(1+'Assumption Setting'!$I$28+'Assumption Setting'!$J$28) -> 3097.4026 | W31: =W20*(1+'Assumption Setting'!$I$28+'Assumption Setting'!$J$28) -> 3097.4026 | ... AA31: =AA20*(1+'Assumption Setting'!$I$28+'Assumption Setting'!$J$28) -> 3097.4026 | AB31: =SUM(AC31:AN31) -> 60070.838 | AC31: =AC20*(1+'Assumption Setting'!$I$28+'Assumption Setting'!$J$28) -> 5005.9032 | AD31: =AD20*(1+'Assumption Setting'!$I$28+'Assumption Setting'!$J$28) -> 5005.9032 | AE31: =AE20*(1+'Assumption Setting'!$I$28+'Assumption Setting'!$J$28) -> 5005.9032 | AF31: =AF20*(1+'Assumption Setting'!$I$28+'Assumption Setting'!$J$28) -> 5005.9032 | AG31: =AG20*(1+'Assumption Setting'!$I$28+'Assumption Setting'!$J$28) -> 5005.9032 | AH31: =AH20*(1+'Assumption Setting'!$I$28+'Assumption Setting'!$J$28) -> 5005.9032 | AI31: =AI20*(1+'Assumption Setting'!$I$28+'Assumption Setting'!$J$28) -> 5005.9032 | AJ31: =AJ20*(1+'Assumption Setting'!$I$28+'Assumption Setting'!$J$28) -> 5005.9032 | ... AN31: =AN20*(1+'Assumption Setting'!$I$28+'Assumption Setting'!$J$28) -> 5005.9032 | AO31: =SUM(AP31:BA31) -> 75088.548 | AP31: =AP20*(1+'Assumption Setting'!$I$28+'Assumption Setting'!$J$28) -> 6257.379 | AQ31: =AQ20*(1+'Assumption Setting'!$I$28+'Assumption Setting'!$J$28) -> 6257.379 | AR31: =AR20*(1+'Assumption Setting'!$I$28+'Assumption Setting'!$J$28) -> 6257.379 | AS31: =AS20*(1+'Assumption Setting'!$I$28+'Assumption Setting'!$J$28) -> 6257.379 | AT31: =AT20*(1+'Assumption Setting'!$I$28+'Assumption Setting'!$J$28) -> 6257.379 | AU31: =AU20*(1+'Assumption Setting'!$I$28+'Assumption Setting'!$J$28) -> 6257.379 | AV31: =AV20*(1+'Assumption Setting'!$I$28+'Assumption Setting'!$J$28) -> 6257.379 | AW31: =AW20*(1+'Assumption Setting'!$I$28+'Assumption Setting'!$J$28) -> 6257.379 | ... BA31: =BA20*(1+'Assumption Setting'!$I$28+'Assumption Setting'!$J$28) -> 6257.379 | BB31: =SUM(BC31:BN31) -> 86879.312 | BC31: =BC20*(1+'Assumption Setting'!$I$28+'Assumption Setting'!$J$28) -> 7239.9426 | BD31: =BD20*(1+'Assumption Setting'!$I$28+'Assumption Setting'!$J$28) -> 7239.9426 | BE31: =BE20*(1+'Assumption Setting'!$I$28+'Assumption Setting'!$J$28) -> 7239.9426 | BF31: =BF20*(1+'Assumption Setting'!$I$28+'Assumption Setting'!$J$28) -> 7239.9426 | BG31: =BG20*(1+'Assumption Setting'!$I$28+'Assumption Setting'!$J$28) -> 7239.9426 | BH31: =BH20*(1+'Assumption Setting'!$I$28+'Assumption Setting'!$J$28) -> 7239.9426 | BI31: =BI20*(1+'Assumption Setting'!$I$28+'Assumption Setting'!$J$28) -> 7239.9426 | BJ31: =BJ20*(1+'Assumption Setting'!$I$28+'Assumption Setting'!$J$28) -> 7239.9426 | ... BN31: =BN20*(1+'Assumption Setting'!$I$28+'Assumption Setting'!$J$28) -> 7239.9426
A32: Content and SEO, Arabic commerce guides | B32: =SUM(C32:N32) -> 44982 | C32: =C21*(1+'Assumption Setting'!$I$29+'Assumption Setting'!$J$29) -> 3748.5 | D32: =D21*(1+'Assumption Setting'!$I$29+'Assumption Setting'!$J$29) -> 3748.5 | E32: =E21*(1+'Assumption Setting'!$I$29+'Assumption Setting'!$J$29) -> 3748.5 | F32: =F21*(1+'Assumption Setting'!$I$29+'Assumption Setting'!$J$29) -> 3748.5 | G32: =G21*(1+'Assumption Setting'!$I$29+'Assumption Setting'!$J$29) -> 3748.5 | H32: =H21*(1+'Assumption Setting'!$I$29+'Assumption Setting'!$J$29) -> 3748.5 | I32: =I21*(1+'Assumption Setting'!$I$29+'Assumption Setting'!$J$29) -> 3748.5 | J32: =J21*(1+'Assumption Setting'!$I$29+'Assumption Setting'!$J$29) -> 3748.5 | ... N32: =N21*(1+'Assumption Setting'!$I$29+'Assumption Setting'!$J$29) -> 3748.5 | O32: =SUM(P32:AA32) -> 73636.364 | P32: =P21*(1+'Assumption Setting'!$I$29+'Assumption Setting'!$J$29) -> 6136.3636 | Q32: =Q21*(1+'Assumption Setting'!$I$29+'Assumption Setting'!$J$29) -> 6136.3636 | R32: =R21*(1+'Assumption Setting'!$I$29+'Assumption Setting'!$J$29) -> 6136.3636 | S32: =S21*(1+'Assumption Setting'!$I$29+'Assumption Setting'!$J$29) -> 6136.3636 | T32: =T21*(1+'Assumption Setting'!$I$29+'Assumption Setting'!$J$29) -> 6136.3636 | U32: =U21*(1+'Assumption Setting'!$I$29+'Assumption Setting'!$J$29) -> 6136.3636 | V32: =V21*(1+'Assumption Setting'!$I$29+'Assumption Setting'!$J$29) -> 6136.3636 | W32: =W21*(1+'Assumption Setting'!$I$29+'Assumption Setting'!$J$29) -> 6136.3636 | ... AA32: =AA21*(1+'Assumption Setting'!$I$29+'Assumption Setting'!$J$29) -> 6136.3636 | AB32: =SUM(AC32:AN32) -> 107107.44 | AC32: =AC21*(1+'Assumption Setting'!$I$29+'Assumption Setting'!$J$29) -> 8925.6198 | AD32: =AD21*(1+'Assumption Setting'!$I$29+'Assumption Setting'!$J$29) -> 8925.6198 | AE32: =AE21*(1+'Assumption Setting'!$I$29+'Assumption Setting'!$J$29) -> 8925.6198 | AF32: =AF21*(1+'Assumption Setting'!$I$29+'Assumption Setting'!$J$29) -> 8925.6198 | AG32: =AG21*(1+'Assumption Setting'!$I$29+'Assumption Setting'!$J$29) -> 8925.6198 | AH32: =AH21*(1+'Assumption Setting'!$I$29+'Assumption Setting'!$J$29) -> 8925.6198 | AI32: =AI21*(1+'Assumption Setting'!$I$29+'Assumption Setting'!$J$29) -> 8925.6198 | AJ32: =AJ21*(1+'Assumption Setting'!$I$29+'Assumption Setting'!$J$29) -> 8925.6198 | ... AN32: =AN21*(1+'Assumption Setting'!$I$29+'Assumption Setting'!$J$29) -> 8925.6198 | AO32: =SUM(AP32:BA32) -> 129827.2 | AP32: =AP21*(1+'Assumption Setting'!$I$29+'Assumption Setting'!$J$29) -> 10818.933 | AQ32: =AQ21*(1+'Assumption Setting'!$I$29+'Assumption Setting'!$J$29) -> 10818.933 | AR32: =AR21*(1+'Assumption Setting'!$I$29+'Assumption Setting'!$J$29) -> 10818.933 | AS32: =AS21*(1+'Assumption Setting'!$I$29+'Assumption Setting'!$J$29) -> 10818.933 | AT32: =AT21*(1+'Assumption Setting'!$I$29+'Assumption Setting'!$J$29) -> 10818.933 | AU32: =AU21*(1+'Assumption Setting'!$I$29+'Assumption Setting'!$J$29) -> 10818.933 | AV32: =AV21*(1+'Assumption Setting'!$I$29+'Assumption Setting'!$J$29) -> 10818.933 | AW32: =AW21*(1+'Assumption Setting'!$I$29+'Assumption Setting'!$J$29) -> 10818.933 | ... BA32: =BA21*(1+'Assumption Setting'!$I$29+'Assumption Setting'!$J$29) -> 10818.933 | BB32: =SUM(BC32:BN32) -> 147530.91 | BC32: =BC21*(1+'Assumption Setting'!$I$29+'Assumption Setting'!$J$29) -> 12294.242 | BD32: =BD21*(1+'Assumption Setting'!$I$29+'Assumption Setting'!$J$29) -> 12294.242 | BE32: =BE21*(1+'Assumption Setting'!$I$29+'Assumption Setting'!$J$29) -> 12294.242 | BF32: =BF21*(1+'Assumption Setting'!$I$29+'Assumption Setting'!$J$29) -> 12294.242 | BG32: =BG21*(1+'Assumption Setting'!$I$29+'Assumption Setting'!$J$29) -> 12294.242 | BH32: =BH21*(1+'Assumption Setting'!$I$29+'Assumption Setting'!$J$29) -> 12294.242 | BI32: =BI21*(1+'Assumption Setting'!$I$29+'Assumption Setting'!$J$29) -> 12294.242 | BJ32: =BJ21*(1+'Assumption Setting'!$I$29+'Assumption Setting'!$J$29) -> 12294.242 | ... BN32: =BN21*(1+'Assumption Setting'!$I$29+'Assumption Setting'!$J$29) -> 12294.242
